Workbook

Sheet Valuation
B2: ='2. Basics'!D2 -> Docty Health Care India Private Limited
B3: Valuation Of the company without Corporate Wellness & Market Place
B6: Year | C6: 1 | D6: =C6+1 -> 2 | E6: =D6+1 -> 3 | F6: =E6+1 -> 4 | G6: =F6+1 -> 5 | H6: =G6+1 -> 6
B7: Particulars | C7: ='1. P&L (Only CR)'!B7 -> 2025 | D7: ='1. P&L (Only CR)'!C7 -> 2026 | E7: ='1. P&L (Only CR)'!D7 -> 2027 | F7: ='1. P&L (Only CR)'!E7 -> 2028 | G7: ='1. P&L (Only CR)'!F7 -> 2029 | H7: ='1. P&L (Only CR)'!G7 -> 2030
B8: EAT | C8: ='1. P&L (Only CR)'!B41 -> #VALUE! | D8: ='1. P&L (Only CR)'!C41 -> #VALUE! | E8: ='1. P&L (Only CR)'!D41 -> #VALUE! | F8: ='1. P&L (Only CR)'!E41 -> #VALUE! | G8: ='1. P&L (Only CR)'!F41 -> #VALUE! | H8: ='1. P&L (Only CR)'!G41 -> #VALUE!
B9: Add: Depreciation | C9: ='1. P&L (Only CR)'!B36 -> 3531770 | D9: ='1. P&L (Only CR)'!C36 -> 12069046 | E9: ='1. P&L (Only CR)'!D36 -> 9437782.2 | F9: ='1. P&L (Only CR)'!E36 -> 7425803.1 | G9: ='1. P&L (Only CR)'!F36 -> 5884008.2 | H9: ='1. P&L (Only CR)'!G36 -> 4699586.8
B10: Cash from operations | C10: =C8+C9 -> #VALUE! | D10: =D8+D9 -> #VALUE! | E10: =E8+E9 -> #VALUE! | F10: =F8+F9 -> #VALUE! | G10: =G8+G9 -> #VALUE! | H10: =H8+H9 -> #VALUE!
B11: Less: Capex | C11: ='FA Schedule'!D17 -> 77650000 | D11: ='FA Schedule'!H17 -> 0 | E11: ='FA Schedule'!K17 -> 0 | F11: ='FA Schedule'!N17 -> 0 | G11: ='FA Schedule'!Q17 -> 0 | H11: ='FA Schedule'!T17 -> 0
B12: Net Operating Cash | C12: =C10-C11 -> #VALUE! | D12: =D10-D11 -> #VALUE! | E12: =E10-E11 -> #VALUE! | F12: =F10-F11 -> #VALUE! | G12: =G10-G11 -> #VALUE! | H12: =H10-H11 -> #VALUE!
B14: Discounting rate | C14: 0.15
B15: Discounting Factor | C15: =(1+$C$14)^C6 -> 1.15 | D15: =(1+$C$14)^D6 -> 1.3225 | E15: =(1+$C$14)^E6 -> 1.520875 | F15: =(1+$C$14)^F6 -> 1.7490062 | G15: =(1+$C$14)^G6 -> 2.0113572 | H15: =(1+$C$14)^H6 -> 2.3130608
B16: Present value of Cash Flows | C16: =C12/C15 -> #VALUE! | D16: =D12/D15 -> #VALUE! | E16: =E12/E15 -> #VALUE! | F16: =F12/F15 -> #VALUE! | G16: =G12/G15 -> #VALUE! | H16: =H12/H15 -> #VALUE!
B17: Growth Rate | C17: 0.05
B18: Terminal value | C18: =H16*(1+C17)/(C14-C17) -> #VALUE!
B19: Company Value | C19: =SUM(C16:H16)+C18 -> #VALUE!
B22: Total Company Value | C22: =SUM(C19:C21) -> #VALUE!
B25: =B2 -> Docty Health Care India Private Limited
B26: Valuation Of the company with Corporate Wellness & Market Place
B28: Year | C28: 1 | D28: =C28+1 -> 2 | E28: =D28+1 -> 3 | F28: =E28+1 -> 4 | G28: =F28+1 -> 5 | H28: =G28+1 -> 6
B29: Particulars | C29: =C7 -> 2025 | D29: =D7 -> 2026 | E29: =E7 -> 2027 | F29: =F7 -> 2028 | G29: =G7 -> 2029 | H29: =H7 -> 2030
B30: EAT | C30: ='1. P&L'!B43 -> #VALUE! | D30: ='1. P&L'!C43 -> #VALUE! | E30: ='1. P&L'!D43 -> #VALUE! | F30: ='1. P&L'!E43 -> #VALUE! | G30: ='1. P&L'!F43 -> #VALUE! | H30: ='1. P&L'!G43 -> #VALUE!
B31: Add: Depreciation | C31: ='1. P&L'!B38 -> 3531770 | D31: ='1. P&L'!C38 -> 12069046 | E31: ='1. P&L'!D38 -> 9437782.2 | F31: ='1. P&L'!E38 -> 7425803.1 | G31: ='1. P&L'!F38 -> 5884008.2 | H31: ='1. P&L'!G38 -> 4699586.8
B32: Cash from operations | C32: =C30+C31 -> #VALUE! | D32: =D30+D31 -> #VALUE! | E32: =E30+E31 -> #VALUE! | F32: =F30+F31 -> #VALUE! | G32: =G30+G31 -> #VALUE! | H32: =H30+H31 -> #VALUE!
B33: Less: Capex | C33: =C11 -> 77650000 | D33: =D11 -> 0 | E33: =E11 -> 0 | F33: =F11 -> 0 | G33: =G11 -> 0 | H33: =H11 -> 0
B34: Net Operating Cash | C34: =C32-C33 -> #VALUE! | D34: =D32-D33 -> #VALUE! | E34: =E32-E33 -> #VALUE! | F34: =F32-F33 -> #VALUE! | G34: =G32-G33 -> #VALUE! | H34: =H32-H33 -> #VALUE!
B36: Discounting rate | C36: =C14 -> 0.15
B37: Discounting Factor | C37: =(1+$C$36)^C28 -> 1.15 | D37: =(1+$C$36)^D28 -> 1.3225 | E37: =(1+$C$36)^E28 -> 1.520875 | F37: =(1+$C$36)^F28 -> 1.7490062 | G37: =(1+$C$36)^G28 -> 2.0113572 | H37: =(1+$C$36)^H28 -> 2.3130608
B38: Present value of Cash Flows | C38: =C34/C37 -> #VALUE! | D38: =D34/D37 -> #VALUE! | E38: =E34/E37 -> #VALUE! | F38: =F34/F37 -> #VALUE! | G38: =G34/G37 -> #VALUE! | H38: =H34/H37 -> #VALUE!
B39: Growth Rate | C39: =C17 -> 0.05
B40: Terminal value | C40: =H38*(1+C39)/(C36-C39) -> #VALUE!
B41: Company Value | C41: =SUM(C38:H38)+C40 -> #VALUE!
B42: No. of Equity shares | C42: =10000 -> 10000
B43: Fair value per Equity share | C43: =C41/C42 -> #VALUE!
B46: Total Company Value | C46: =C41 -> #VALUE!
B48: Computation of cost of capital
B49: Beta | C49: 1
B50: Risk free rate | C50: =D50/100 -> 0.0657 | D50: 6.57 | E50: 10 yr bond rate as on 30th Sep 2025
B51: Return of market | C51: =+C68 -> 0.1489
C52: 0.15
B53: Add: Company specific risk premium | C53: -
B54: Ke | C54: 0.15
B56: Computation of Weighted Avg Cost of Capital (WACC)
B57: Equity | C57: 1 | F57: Equity | G57: 1
B58: Ke | C58: 0.15 | F58: Debt | G58: -
B59: Debt | C59: - | F59: Total | G59: 1
B60: Kd | C60: - | F60: Weight of Equity | G60: 1
B61: Tax Rate | C61: 0.25 | F61: Weight of Debt | G61: -
B62: WACC | C62: 0.15
B64: Sensex Data
B65: 28917 | C65: 124.2 | E65: 28917
B66: 30/09/2025 | C66: 80267.62 | E66: 30/09/25
B67: No.of Yrs. | C67: 46.61 | E67: =(E66-E65)/365 -> #VALUE!
B68: Rm | C68: 0.1489
B69: [Source: BSE]

Sheet 1. P&L (Only CR)
A2: ='2. Basics'!D4 -> Docty Health Care India Private Limited
A4: ='2. Basics'!D6 -> Block C, Flat No.003, My Home, Hightech City, Sy No.83/1, Gachibowli, K.V.Rangareddy, Seri Lingampally, Telangana, India, 500032
A6: PROFIT & LOSS ACCOUNT FOR THE PERIOD
A7: Particulars | B7: 2025 | C7: 2026 | D7: 2027 | E7: 2028 | F7: 2029 | G7: 2030
A9: Gross Receipts
A10: Phase I
A11: ='A.I Revenue Streams - P1'!D9 -> Clinical Revenue | B11: ='B.I Sales - P1 (2)'!KK68 -> #VALUE! | C11: ='B.I Sales - P1 (2)'!KO68 -> #VALUE! | D11: ='B.I Sales - P1 (2)'!KS68 -> #VALUE! | E11: ='B.I Sales - P1 (2)'!KW68 -> #VALUE! | F11: ='B.I Sales - P1 (2)'!LA68 -> #VALUE! | G11: ='B.I Sales - P1 (2)'!LE68 -> #VALUE!
A12: ='A.I Revenue Streams - P1'!D69 -> Docty Pharma | B12: ='B.I Sales - P1 (2)'!KK78 -> 966831 | C12: ='B.I Sales - P1 (2)'!KO78 -> 42563338 | D12: ='B.I Sales - P1 (2)'!KS78 -> 2.8016689e+08 | E12: ='B.I Sales - P1 (2)'!KW78 -> 1.6641202e+09 | F12: ='B.I Sales - P1 (2)'!LA78 -> 9.7938055e+09 | G12: ='B.I Sales - P1 (2)'!LE78 -> 5.9970885e+10
A13: ='A.I Revenue Streams - P1'!D79 -> Lab & Diagnostics | B13: ='B.I Sales - P1 (2)'!KK175 -> 2123277.6 | C13: ='B.I Sales - P1 (2)'!KO175 -> 93474227 | D13: ='B.I Sales - P1 (2)'!KS175 -> 6.1528031e+08 | E13: ='B.I Sales - P1 (2)'!KW175 -> 3.6546089e+09 | F13: ='B.I Sales - P1 (2)'!LA175 -> 2.1508379e+10 | G13: ='B.I Sales - P1 (2)'!LE175 -> 1.317033e+11
A14: ='A.I Revenue Streams - P1'!D182 -> Other Services | B14: ='B.I Sales - P1 (2)'!KK192 -> 1027574.4 | C14: ='B.I Sales - P1 (2)'!KO192 -> 40514961 | D14: ='B.I Sales - P1 (2)'!KS192 -> 2.5169632e+08 | E14: ='B.I Sales - P1 (2)'!KW192 -> 1.4586208e+09 | F14: ='B.I Sales - P1 (2)'!LA192 -> 8.5250276e+09 | G14: ='B.I Sales - P1 (2)'!LE72 -> 2.5849519e+10
B15: =SUM(B11:B14) -> #VALUE! | C15: =SUM(C11:C14) -> #VALUE! | D15: =SUM(D11:D14) -> #VALUE! | E15: =SUM(E11:E14) -> #VALUE! | F15: =SUM(F11:F14) -> #VALUE! | G15: =SUM(G11:G14) -> #VALUE!
A17: Expenditure
A18: Phase - I
A19: =A.IIOPEX!D10 -> Utilities | B19: ='B.II OPEX - P1'!KJ17 -> 3590000 | C19: ='B.II OPEX - P1'!KN17 -> 40567000 | D19: ='B.II OPEX - P1'!KR17 -> 43080000 | E19: ='B.II OPEX - P1'!KV17 -> 43080000 | F19: ='B.II OPEX - P1'!KZ17 -> 43080000 | G19: ='B.II OPEX - P1'!LD17 -> 43080000
A20: =A.IIOPEX!D21 -> Salaries | B20: ='B.II OPEX - P1'!KJ28 -> 5750000 | C20: ='B.II OPEX - P1'!KN28 -> 64975000 | D20: ='B.II OPEX - P1'!KR28 -> 69000000 | E20: ='B.II OPEX - P1'!KV28 -> 69000000 | F20: ='B.II OPEX - P1'!KZ28 -> 69000000 | G20: ='B.II OPEX - P1'!LD28 -> 69000000
A21: =A.IIOPEX!D30 -> Vendor Payments | B21: ='B.II OPEX - P1'!KJ38 -> 6535178.8 | C21: ='B.II OPEX - P1'!KN38 -> 91641203 | D21: ='B.II OPEX - P1'!KR38 -> 4.4203633e+08 | E21: ='B.II OPEX - P1'!KV38 -> 2.4598324e+09 | F21: ='B.II OPEX - P1'!KZ38 -> 1.4335118e+10 | G21: ='B.II OPEX - P1'!LD38 -> 8.341874e+10
A22: =A.IIOPEX!D40 -> Supplies | B22: ='B.II OPEX - P1'!KJ47 -> 825000 | C22: ='B.II OPEX - P1'!KN47 -> 8475000 | D22: ='B.II OPEX - P1'!KR47 -> 9000000 | E22: ='B.II OPEX - P1'!KV47 -> 9000000 | F22: ='B.II OPEX - P1'!KZ47 -> 9000000 | G22: ='B.II OPEX - P1'!LD47 -> 9000000
A23: =A.IIOPEX!D49 -> Payouts | B23: ='B.II OPEX - P1'!KJ55 -> 6534000 | C23: ='B.II OPEX - P1'!KN55 -> 67122000 | D23: ='B.II OPEX - P1'!KR55 -> 71280000 | E23: ='B.II OPEX - P1'!KV55 -> 71280000 | F23: ='B.II OPEX - P1'!KZ55 -> 71280000 | G23: ='B.II OPEX - P1'!LD55 -> 71280000
A24: =A.IIOPEX!D57 -> Marketing & Promotions | B24: ='B.II OPEX - P1'!KJ63 -> 1650000 | C24: ='B.II OPEX - P1'!KN63 -> 16950000 | D24: ='B.II OPEX - P1'!KR63 -> 18000000 | E24: ='B.II OPEX - P1'!KV63 -> 18000000 | F24: ='B.II OPEX - P1'!KZ63 -> 18000000 | G24: ='B.II OPEX - P1'!LD63 -> 18000000
A25: =A.IIOPEX!D65 -> Licenses and Registration | B25: ='B.II OPEX - P1'!KJ76 -> 242000 | C25: ='B.II OPEX - P1'!KN76 -> 2486000 | D25: ='B.II OPEX - P1'!KR76 -> 2640000 | E25: ='B.II OPEX - P1'!KV76 -> 2640000 | F25: ='B.II OPEX - P1'!KZ76 -> 2640000 | G25: ='B.II OPEX - P1'!LD76 -> 2640000
A26: =A.IIOPEX!D79 -> Supplies | B26: ='B.II OPEX - P1'!KJ87 -> 0 | C26: ='B.II OPEX - P1'!KN87 -> 0 | D26: ='B.II OPEX - P1'!KR87 -> 0 | E26: ='B.II OPEX - P1'!KV87 -> 0 | F26: ='B.II OPEX - P1'!KZ87 -> 0 | G26: ='B.II OPEX - P1'!LD87 -> 0
B28: =SUM(B19:B27) -> 25126179 | C28: =SUM(C19:C27) -> 2.922162e+08 | D28: =SUM(D19:D27) -> 6.5503633e+08 | E28: =SUM(E19:E27) -> 2.6728324e+09 | F28: =SUM(F19:F27) -> 1.4548118e+10 | G28: =SUM(G19:G27) -> 8.363174e+10
A31: EBIDTA | B31: =B15-B28 -> #VALUE! | C31: =C15-C28 -> #VALUE! | D31: =D15-D28 -> #VALUE! | E31: =E15-E28 -> #VALUE! | F31: =F15-F28 -> #VALUE! | G31: =G15-G28 -> #VALUE!
B32: =B31/B15 -> #VALUE! | C32: =C31/C15 -> #VALUE! | D32: =D31/D15 -> #VALUE! | E32: =E31/E15 -> #VALUE! | F32: =F31/F15 -> #VALUE! | G32: =G31/G15 -> #VALUE!
A34: Net Profit Before Depreciation and Tax | B34: =B31-SUM(B33:B33) -> #VALUE! | C34: =C31-SUM(C33:C33) -> #VALUE! | D34: =D31-SUM(D33:D33) -> #VALUE! | E34: =E31-SUM(E33:E33) -> #VALUE! | F34: =F31-SUM(F33:F33) -> #VALUE! | G34: =G31-SUM(G33:G33) -> #VALUE!
A35: Net Profit (Before Depreciation) Ratio | B35: =B32 -> #VALUE! | C35: =C32 -> #VALUE! | D35: =D32 -> #VALUE! | E35: =E32 -> #VALUE! | F35: =F32 -> #VALUE! | G35: =G32 -> #VALUE!
A36: Depreciation | B36: ='FA Schedule'!F17 -> 3531770 | C36: ='FA Schedule'!I17 -> 12069046 | D36: ='FA Schedule'!L17 -> 9437782.2 | E36: ='FA Schedule'!O17 -> 7425803.1 | F36: ='FA Schedule'!R17 -> 5884008.2 | G36: ='FA Schedule'!U17 -> 4699586.8
A37: Net Profit After Depreciation Before Tax | B37: =B34-B36 -> #VALUE! | C37: =C34-C36 -> #VALUE! | D37: =D34-D36 -> #VALUE! | E37: =E34-E36 -> #VALUE! | F37: =F34-F36 -> #VALUE! | G37: =G34-G36 -> #VALUE!
A39: Net Profit (After Depreciation) Ratio | B39: =B$37/B15 -> #VALUE! | C39: =C$37/C15 -> #VALUE! | D39: =D$37/D15 -> #VALUE! | E39: =E$37/E15 -> #VALUE! | F39: =F$37/F15 -> #VALUE! | G39: =G$37/G15 -> #VALUE!
A40: Provision For Tax | B40: =IF(B37>0,B37*25.17%,0) -> #VALUE! | C40: =IF(C37>0,C37*25.17%,0) -> #VALUE! | D40: =IF(D37>0,D37*25.17%,0) -> #VALUE! | E40: =IF(E37>0,E37*25.17%,0) -> #VALUE! | F40: =IF(F37>0,F37*25.17%,0) -> #VALUE! | G40: =IF(G37>0,G37*25.17%,0) -> #VALUE!
A41: Net Profit After Tax | B41: =B37-B40 -> #VALUE! | C41: =C37-C40 -> #VALUE! | D41: =D37-D40 -> #VALUE! | E41: =E37-E40 -> #VALUE! | F41: =F37-F40 -> #VALUE! | G41: =G37-G40 -> #VALUE!
A48: Average Yearly turnover for the last four years | B48: =SUM(C15:G15)/COUNT(C15:G15) -> #VALUE!

Sheet 1. P&L
A2: ='2. Basics'!D4 -> Docty Health Care India Private Limited
A4: ='2. Basics'!D6 -> Block C, Flat No.003, My Home, Hightech City, Sy No.83/1, Gachibowli, K.V.Rangareddy, Seri Lingampally, Telangana, India, 500032
A6: PROFIT & LOSS ACCOUNT FOR THE PERIOD
A7: Particulars | B7: 2025 | C7: 2026 | D7: 2027 | E7: 2028 | F7: 2029 | G7: 2030
A9: Gross Receipts
A10: Phase I
A11: ='A.I Revenue Streams - P1'!D9 -> Clinical Revenue | B11: ='B.I Sales - P1 (2)'!KK68 -> #VALUE! | C11: ='B.I Sales - P1 (2)'!KO68 -> #VALUE! | D11: ='B.I Sales - P1 (2)'!KS68 -> #VALUE! | E11: ='B.I Sales - P1 (2)'!KW68 -> #VALUE! | F11: ='B.I Sales - P1 (2)'!LA68 -> #VALUE! | G11: ='B.I Sales - P1 (2)'!LE68 -> #VALUE!
A12: ='A.I Revenue Streams - P1'!D69 -> Docty Pharma | B12: ='B.I Sales - P1 (2)'!KK78 -> 966831 | C12: ='B.I Sales - P1 (2)'!KO78 -> 42563338 | D12: ='B.I Sales - P1 (2)'!KS78 -> 2.8016689e+08 | E12: ='B.I Sales - P1 (2)'!KW78 -> 1.6641202e+09 | F12: ='B.I Sales - P1 (2)'!LA78 -> 9.7938055e+09 | G12: ='B.I Sales - P1 (2)'!LE78 -> 5.9970885e+10
A13: ='A.I Revenue Streams - P1'!D79 -> Lab & Diagnostics | B13: ='B.I Sales - P1 (2)'!KK175 -> 2123277.6 | C13: ='B.I Sales - P1 (2)'!KO175 -> 93474227 | D13: ='B.I Sales - P1 (2)'!KS175 -> 6.1528031e+08 | E13: ='B.I Sales - P1 (2)'!KW175 -> 3.6546089e+09 | F13: ='B.I Sales - P1 (2)'!LA175 -> 2.1508379e+10 | G13: ='B.I Sales - P1 (2)'!LE175 -> 1.317033e+11
A14: ='A.I Revenue Streams - P1'!D176 -> Workplace Wellness | B14: ='B.I Sales - P1 (2)'!KK182 -> 0 | C14: ='B.I Sales - P1 (2)'!KO182 -> 9860267.5 | D14: ='B.I Sales - P1 (2)'!KS182 -> 21240815 | E14: ='B.I Sales - P1 (2)'!KW182 -> 31968588 | F14: ='B.I Sales - P1 (2)'!LA182 -> 42644534 | G14: ='B.I Sales - P1 (2)'!LE182 -> 34948679
A15: ='A.I Revenue Streams - P1'!D182 -> Other Services | B15: ='B.I Sales - P1 (2)'!KK192 -> 1027574.4 | C15: ='B.I Sales - P1 (2)'!KO192 -> 40514961 | D15: ='B.I Sales - P1 (2)'!KS192 -> 2.5169632e+08 | E15: ='B.I Sales - P1 (2)'!KW192 -> 1.4586208e+09 | F15: ='B.I Sales - P1 (2)'!LA192 -> 8.5250276e+09 | G15: ='B.I Sales - P1 (2)'!LE72 -> 2.5849519e+10
A16: Marketplace | B16: ='B.I Sales - P1 (2)'!KK205 -> 0 | C16: ='B.I Sales - P1 (2)'!KO205 -> 26613382 | D16: ='B.I Sales - P1 (2)'!KS205 -> 44210637 | E16: ='B.I Sales - P1 (2)'!KW205 -> 55306195 | F16: ='B.I Sales - P1 (2)'!LA205 -> 66008875 | G16: ='B.I Sales - P1 (2)'!LE73 -> 1.2407769e+10
B17: =SUM(B11:B16) -> #VALUE! | C17: =SUM(C11:C16) -> #VALUE! | D17: =SUM(D11:D16) -> #VALUE! | E17: =SUM(E11:E16) -> #VALUE! | F17: =SUM(F11:F16) -> #VALUE! | G17: =SUM(G11:G16) -> #VALUE!
D18: =D17/C17-1 -> #VALUE! | E18: =E17/D17-1 -> #VALUE! | F18: =F17/E17-1 -> #VALUE! | G18: =G17/F17-1 -> #VALUE!
A19: Expenditure
A20: Phase - I
A21: =A.IIOPEX!D10 -> Utilities | B21: ='B.II OPEX - P1'!KJ17 -> 3590000 | C21: ='B.II OPEX - P1'!KN17 -> 40567000 | D21: ='B.II OPEX - P1'!KR17 -> 43080000 | E21: ='B.II OPEX - P1'!KV17 -> 43080000 | F21: ='B.II OPEX - P1'!KZ17 -> 43080000 | G21: ='B.II OPEX - P1'!LD17 -> 43080000
A22: =A.IIOPEX!D21 -> Salaries | B22: ='B.II OPEX - P1'!KJ28 -> 5750000 | C22: ='B.II OPEX - P1'!KN28 -> 64975000 | D22: ='B.II OPEX - P1'!KR28 -> 69000000 | E22: ='B.II OPEX - P1'!KV28 -> 69000000 | F22: ='B.II OPEX - P1'!KZ28 -> 69000000 | G22: ='B.II OPEX - P1'!LD28 -> 69000000
A23: =A.IIOPEX!D30 -> Vendor Payments | B23: ='B.II OPEX - P1'!KJ38 -> 6535178.8 | C23: ='B.II OPEX - P1'!KN38 -> 91641203 | D23: ='B.II OPEX - P1'!KR38 -> 4.4203633e+08 | E23: ='B.II OPEX - P1'!KV38 -> 2.4598324e+09 | F23: ='B.II OPEX - P1'!KZ38 -> 1.4335118e+10 | G23: ='B.II OPEX - P1'!LD38 -> 8.341874e+10
A24: =A.IIOPEX!D40 -> Supplies | B24: ='B.II OPEX - P1'!KJ47 -> 825000 | C24: ='B.II OPEX - P1'!KN47 -> 8475000 | D24: ='B.II OPEX - P1'!KR47 -> 9000000 | E24: ='B.II OPEX - P1'!KV47 -> 9000000 | F24: ='B.II OPEX - P1'!KZ47 -> 9000000 | G24: ='B.II OPEX - P1'!LD47 -> 9000000
A25: =A.IIOPEX!D49 -> Payouts | B25: ='B.II OPEX - P1'!KJ55 -> 6534000 | C25: ='B.II OPEX - P1'!KN55 -> 67122000 | D25: ='B.II OPEX - P1'!KR55 -> 71280000 | E25: ='B.II OPEX - P1'!KV55 -> 71280000 | F25: ='B.II OPEX - P1'!KZ55 -> 71280000 | G25: ='B.II OPEX - P1'!LD55 -> 71280000
A26: =A.IIOPEX!D57 -> Marketing & Promotions | B26: ='B.II OPEX - P1'!KJ63 -> 1650000 | C26: ='B.II OPEX - P1'!KN63 -> 16950000 | D26: ='B.II OPEX - P1'!KR63 -> 18000000 | E26: ='B.II OPEX - P1'!KV63 -> 18000000 | F26: ='B.II OPEX - P1'!KZ63 -> 18000000 | G26: ='B.II OPEX - P1'!LD63 -> 18000000
A27: =A.IIOPEX!D65 -> Licenses and Registration | B27: ='B.II OPEX - P1'!KJ76 -> 242000 | C27: ='B.II OPEX - P1'!KN76 -> 2486000 | D27: ='B.II OPEX - P1'!KR76 -> 2640000 | E27: ='B.II OPEX - P1'!KV76 -> 2640000 | F27: ='B.II OPEX - P1'!KZ76 -> 2640000 | G27: ='B.II OPEX - P1'!LD76 -> 2640000
A28: =A.IIOPEX!D79 -> Supplies | B28: ='B.II OPEX - P1'!KJ87 -> 0 | C28: ='B.II OPEX - P1'!KN87 -> 0 | D28: ='B.II OPEX - P1'!KR87 -> 0 | E28: ='B.II OPEX - P1'!KV87 -> 0 | F28: ='B.II OPEX - P1'!KZ87 -> 0 | G28: ='B.II OPEX - P1'!LD87 -> 0
B30: =SUM(B21:B29) -> 25126179 | C30: =SUM(C21:C29) -> 2.922162e+08 | D30: =SUM(D21:D29) -> 6.5503633e+08 | E30: =SUM(E21:E29) -> 2.6728324e+09 | F30: =SUM(F21:F29) -> 1.4548118e+10 | G30: =SUM(G21:G29) -> 8.363174e+10
A33: EBIDTA | B33: =B17-B30 -> #VALUE! | C33: =C17-C30 -> #VALUE! | D33: =D17-D30 -> #VALUE! | E33: =E17-E30 -> #VALUE! | F33: =F17-F30 -> #VALUE! | G33: =G17-G30 -> #VALUE! | H33: =SUM(C33:G33)/5 -> #VALUE!
B34: =B33/B17 -> #VALUE! | C34: =C33/C17 -> #VALUE! | D34: =D33/D17 -> #VALUE! | E34: =E33/E17 -> #VALUE! | F34: =F33/F17 -> #VALUE! | G34: =G33/G17 -> #VALUE!
A36: Net Profit Before Depreciation and Tax | B36: =B33-SUM(B35:B35) -> #VALUE! | C36: =C33-SUM(C35:C35) -> #VALUE! | D36: =D33-SUM(D35:D35) -> #VALUE! | E36: =E33-SUM(E35:E35) -> #VALUE! | F36: =F33-SUM(F35:F35) -> #VALUE! | G36: =G33-SUM(G35:G35) -> #VALUE!
A37: Net Profit (Before Depreciation) Ratio | B37: =B34 -> #VALUE! | C37: =C34 -> #VALUE! | D37: =D34 -> #VALUE! | E37: =E34 -> #VALUE! | F37: =F34 -> #VALUE! | G37: =G34 -> #VALUE!
A38: Depreciation | B38: ='FA Schedule'!F17 -> 3531770 | C38: ='FA Schedule'!I17 -> 12069046 | D38: ='FA Schedule'!L17 -> 9437782.2 | E38: ='FA Schedule'!O17 -> 7425803.1 | F38: ='FA Schedule'!R17 -> 5884008.2 | G38: ='FA Schedule'!U17 -> 4699586.8
A39: Net Profit After Depreciation Before Tax | B39: =B36-B38 -> #VALUE! | C39: =C36-C38 -> #VALUE! | D39: =D36-D38 -> #VALUE! | E39: =E36-E38 -> #VALUE! | F39: =F36-F38 -> #VALUE! | G39: =G36-G38 -> #VALUE!
A41: Net Profit (After Depreciation) Ratio | B41: =B$39/B17 -> #VALUE! | C41: =C$39/C17 -> #VALUE! | D41: =D$39/D17 -> #VALUE! | E41: =E$39/E17 -> #VALUE! | F41: =F$39/F17 -> #VALUE! | G41: =G$39/G17 -> #VALUE!
A42: Provision For Tax | B42: =IF(B39>0,B39*25.17%,0) -> #VALUE! | C42: =IF(C39>0,C39*25.17%,0) -> #VALUE! | D42: =IF(D39>0,D39*25.17%,0) -> #VALUE! | E42: =IF(E39>0,E39*25.17%,0) -> #VALUE! | F42: =IF(F39>0,F39*25.17%,0) -> #VALUE! | G42: =IF(G39>0,G39*25.17%,0) -> #VALUE!
A43: Net Profit After Tax | B43: =B39-B42 -> #VALUE! | C43: =C39-C42 -> #VALUE! | D43: =D39-D42 -> #VALUE! | E43: =E39-E42 -> #VALUE! | F43: =F39-F42 -> #VALUE! | G43: =G39-G42 -> #VALUE!
D44: =D43/D17*100 -> #VALUE! | E44: =E43/E17*100 -> #VALUE! | F44: =F43/F17*100 -> #VALUE! | G44: =G43/G17*100 -> #VALUE!
A50: Average Yearly turnover for the last four years | B50: =SUM(C17:G17)/COUNT(C17:G17) -> #VALUE!

Sheet 2. Basics
B2: 1 | C2: Legal Name of the Business | D2: Docty Health Care India Private Limited
B4: 2 | C4: Trade Name of the Business | D4: =D2 -> Docty Health Care India Private Limited
B6: 3 | C6: Registered Office Address | D6: Block C, Flat No.003, My Home, Hightech City, Sy No.83/1, Gachibowli, K.V.Rangareddy, Seri Lingampally, Telangana, India, 500032
B8: 4 | C8: Official Email Id | D8: lakshman@docty.ai
B10: 5 | C10: Official Contact Number | D10: 7305961978
B12: 6 | C12: Details of the Promoter | D12: Bennebathula Varhala Babu, Venkataratnam Kamala Bai
B14: 6.a | C14: Total number of Promoters | D14: 2
B16: 7 | C16: Tentative Start Date of the project Phase 1 | D16: 45870 | E16: DD/MM/YYYY
B18: 8 | C18: Company Description | D18: Docty positions itself as the India arm of the global telehealth and digital healthcare platform Docty Healthcare, which was incorporated in 2020. The company describes its offering as a “360-degree digital healthcare solution.” It is developing an online platform that enables users to consult doctors via telemedicine, order medicines online, book home lab tests, and more. In addition, Docty offers corporate wellness packages designed to support employee health and well-being.
B20: 9 | C20: No. of Equity Share of the Company | D20: 10000
B22: 10 | C22: Face value of equity shares | D22: 10
B24: 11 | C24: Paid up Share Capital | D24: 100000

Sheet A.I Revenue Streams - P1
C2: Revenue Streams
C3: This Sheet assists us in getting the data related to Sales
C5: PHASE - 1 | F5: ='2. Basics'!D16 -> 45870 | L5: Y2
H6: No. of branches | L6: 2026-27 | N6: 2027-28 | P6: 2028-29 | R6: 2029-30 | T6: 2030-31 | V6: 2031-32
H7: 1
D8: Revenue Streams | E8: Sub Stream | F8: Products | H8: Number of Products sold per month | J8: Sale Price of each product | L8: Monthly Growth Rate in Y2 | N8: Yearly Growth Rate from Y2 to Y3 | P8: Yearly Growth Rate from Y3 to Y4 | R8: Yearly Growth Rate from Y4 to Y5 | T8: Yearly Growth Rate from Y5 to Y6 | V8: Yearly Growth Rate from Y6 to Y7 | AI8: =AE8+IF(AI3='A.I Revenue Streams - P1'!H9
C9: 1 | D9: Clinical Revenue | E9: Dental
C10: 1a | F10: Root Canal | H10: =2*4*H7 -> 8 | J10: Q | L10: 0.25 | N10: 0.2 | P10: 0.1 | R10: 0.1 | T10: 0.15 | V10: 0.01
C11: 1b | F11: Teeth Extraction | H11: =2*4*H7 -> 8 | J11: 1500 | L11: 0.25 | N11: 0.2 | P11: 0.1 | R11: 0.1 | T11: 0.15 | V11: 0.01
C12: 1c | F12: Wisdom tooth Removal | H12: =1*4*H7 -> 4 | J12: 5500 | L12: 0.25 | N12: 0.2 | P12: 0.1 | R12: 0.1 | T12: 0.15 | V12: 0.01
C13: 1d | F13: Implant | H13: =2*H7 -> 2 | J13: 22000 | L13: 0.25 | N13: 0.2 | P13: 0.1 | R13: 0.1 | T13: 0.15 | V13: 0.01
F14: X Ray | H14: =10*30*H7 -> 300 | J14: 300 | L14: 0.25 | N14: 0.2 | P14: 0.1 | R14: 0.1 | T14: 0.15 | V14: 0.01
F15: Scaling | H15: =2*4*H7 -> 8 | J15: 1800 | L15: 0.25 | N15: 0.2 | P15: 0.1 | R15: 0.1 | T15: 0.15 | V15: 0.01
F16: Flap Surgery | H16: =1*H7 -> 1 | J16: 33000 | L16: 0.25 | N16: 0.2 | P16: 0.1 | R16: 0.1 | T16: 0.15 | V16: 0.01
F17: Curetta (2-3 teeth) | H17: =4*H7 -> 4 | J17: 3700 | L17: 0.25 | N17: 0.2 | P17: 0.1 | R17: 0.1 | T17: 0.15 | V17: 0.01
F18: Complete Denture | H18: =0.5*H7 -> 0.5 | J18: 30000 | L18: 0.25 | N18: 0.2 | P18: 0.1 | R18: 0.1 | T18: 0.15 | V18: 0.01
F19: Comple Denture (BPS Denture) | H19: =0.5*H7 -> 0.5 | J19: 47000 | L19: 0.25 | N19: 0.2 | P19: 0.1 | R19: 0.1 | T19: 0.15 | V19: 0.01
F20: Removable Partial Denture | H20: =2*H7 -> 2 | J20: 1500 | L20: 0.25 | N20: 0.2 | P20: 0.1 | R20: 0.1 | T20: 0.15 | V20: 0.01
F21: Filling | H21: =2*30*H7 -> 60 | J21: 1500 | L21: 0.25 | N21: 0.2 | P21: 0.1 | R21: 0.1 | T21: 0.15 | V21: 0.01
F22: Crowns | H22: =4*H7 -> 4 | J22: 5000 | L22: 0.25 | N22: 0.2 | P22: 0.1 | R22: 0.1 | T22: 0.15 | V22: 0.01
F23: Crowns Zircornia | H23: =4*H7 -> 4 | J23: 10000 | L23: 0.25 | N23: 0.2 | P23: 0.1 | R23: 0.1 | T23: 0.15 | V23: 0.01
F24: Bruxzir (Lifetime) | H24: =1*H7 -> 1 | J24: 20000 | L24: 0.25 | N24: 0.2 | P24: 0.1 | R24: 0.1 | T24: 0.15 | V24: 0.01
F25: Metal Braces | H25: =0.25*H7 -> 0.25 | J25: 30000 | L25: 0.25 | N25: 0.2 | P25: 0.1 | R25: 0.1 | T25: 0.15 | V25: 0.01
F26: Ceramics Braces | H26: =0.25*H7 -> 0.25 | J26: 45000 | L26: 0.25 | N26: 0.2 | P26: 0.1 | R26: 0.1 | T26: 0.15 | V26: 0.01
F27: Metal Braces(Self Ligating) | H27: =0.25*H7 -> 0.25 | J27: 55000 | L27: 0.25 | N27: 0.2 | P27: 0.1 | R27: 0.1 | T27: 0.15 | V27: 0.01
F28: Ceramics Braces (Self Ligating) | H28: =0.25*H7 -> 0.25 | J28: 65000 | L28: 0.25 | N28: 0.2 | P28: 0.1 | R28: 0.1 | T28: 0.15 | V28: 0.01
L29: 0.25 | N29: 0.2 | P29: 0.1 | R29: 0.1 | T29: 0.15 | V29: 0.01
E30: General Physician | L30: 0.25 | N30: 0.2 | P30: 0.1 | R30: 0.1 | T30: 0.15 | V30: 0.01
F31: Consultation | H31: =20*30*H7 -> 600 | J31: 500 | L31: 0.25 | N31: 0.2 | P31: 0.1 | R31: 0.1 | T31: 0.15 | V31: 0.01
F32: Medical Certificate | H32: =30*H7 -> 30 | J32: 300 | L32: 0.25 | N32: 0.2 | P32: 0.1 | R32: 0.1 | T32: 0.15 | V32: 0.01
F33: Fit to Fly Certificate | H33: =2*H7 -> 2 | J33: 300 | L33: 0.25 | N33: 0.2 | P33: 0.1 | R33: 0.1 | T33: 0.15 | V33: 0.01
L34: 0.25 | N34: 0.2 | P34: 0.1 | R34: 0.1 | T34: 0.15 | V34: 0.01
E35: Physio | L35: 0.25 | N35: 0.2 | P35: 0.1 | R35: 0.1 | T35: 0.15 | V35: 0.01
F36: Excercises | H36: =1*30*H7 -> 30 | J36: 500 | L36: 0.25 | N36: 0.2 | P36: 0.1 | R36: 0.1 | T36: 0.15 | V36: 0.01
F37: Interferentail Therapy(IFT)-Single | H37: =30*H7 -> 30 | J37: 700 | L37: 0.25 | N37: 0.2 | P37: 0.1 | R37: 0.1 | T37: 0.15 | V37: 0.01
F38: Interferentail Therapy(IFT)-Standard package | H38: =2*4*H7 -> 8 | J38: 3000 | L38: 0.25 | N38: 0.2 | P38: 0.1 | R38: 0.1 | T38: 0.15 | V38: 0.01
F39: Interferentail Therapy(IFT)-Advance package | H39: =2*4*H7 -> 8 | J39: 5500 | L39: 0.25 | N39: 0.2 | P39: 0.1 | R39: 0.1 | T39: 0.15 | V39: 0.01
F40: Ultrasound Therapy (UST) - Single | H40: =30*H7 -> 30 | J40: 600 | L40: 0.25 | N40: 0.2 | P40: 0.1 | R40: 0.1 | T40: 0.15 | V40: 0.01
F41: Ultrasound Therapy (UST) - Standard Package | H41: =2*4*H7 -> 8 | J41: 3000 | L41: 0.25 | N41: 0.2 | P41: 0.1 | R41: 0.1 | T41: 0.15 | V41: 0.01
F42: Ultrasound Therapy (UST) - Advance Package | H42: =2*4*H7 -> 8 | J42: 5500 | L42: 0.25 | N42: 0.2 | P42: 0.1 | R42: 0.1 | T42: 0.15 | V42: 0.01
F43: Muscle Stimulation -Single | H43: =30*H7 -> 30 | J43: 800 | L43: 0.25 | N43: 0.2 | P43: 0.1 | R43: 0.1 | T43: 0.15 | V43: 0.01
F44: Muscle Stimulation -Standard Package | H44: =2*4*H7 -> 8 | J44: 3000 | L44: 0.25 | N44: 0.2 | P44: 0.1 | R44: 0.1 | T44: 0.15 | V44: 0.01
F45: Muscle Stimulation -Advance Package | H45: =2*4*H7 -> 8 | J45: 5500 | L45: 0.25 | N45: 0.2 | P45: 0.1 | R45: 0.1 | T45: 0.15 | V45: 0.01
F46: IFT+UST-Single | H46: =8*H7 -> 8 | J46: 1200 | L46: 0.25 | N46: 0.2 | P46: 0.1 | R46: 0.1 | T46: 0.15 | V46: 0.01
F47: IFT+UST-Standard | H47: =2*H7 -> 2 | J47: 5000 | L47: 0.25 | N47: 0.2 | P47: 0.1 | R47: 0.1 | T47: 0.15 | V47: 0.01
F48: IFT+UST-Advance | H48: =2*H7 -> 2 | J48: 9000 | L48: 0.25 | N48: 0.2 | P48: 0.1 | R48: 0.1 | T48: 0.15 | V48: 0.01
F49: IFT+UST+Exercises-Single | H49: =8*H7 -> 8 | J49: 1300 | L49: 0.25 | N49: 0.2 | P49: 0.1 | R49: 0.1 | T49: 0.15 | V49: 0.01
F50: IFT+UST+Exercises-Standard | H50: =2*H7 -> 2 | J50: 5500 | L50: 0.25 | N50: 0.2 | P50: 0.1 | R50: 0.1 | T50: 0.15 | V50: 0.01
F51: IFT+UST+Exercises-Advance | H51: =2*H7 -> 2 | J51: 9500 | L51: 0.25 | N51: 0.2 | P51: 0.1 | R51: 0.1 | T51: 0.15 | V51: 0.01
F52: IFT+Exercises-Single | H52: =8*H7 -> 8 | J52: 800 | L52: 0.25 | N52: 0.2 | P52: 0.1 | R52: 0.1 | T52: 0.15 | V52: 0.01
F53: IFT+Exercises-Standard | H53: =2*H7 -> 2 | J53: 3500 | L53: 0.25 | N53: 0.2 | P53: 0.1 | R53: 0.1 | T53: 0.15 | V53: 0.01
F54: IFT+Exercises-Advance | H54: =2*H7 -> 2 | J54: 6000 | L54: 0.25 | N54: 0.2 | P54: 0.1 | R54: 0.1 | T54: 0.15 | V54: 0.01
F55: UST+Exercises-Single | H55: =8*H7 -> 8 | J55: 700 | L55: 0.25 | N55: 0.2 | P55: 0.1 | R55: 0.1 | T55: 0.15 | V55: 0.01
F56: UST+Exercises-Standard | H56: =2*H7 -> 2 | J56: 3000 | L56: 0.25 | N56: 0.2 | P56: 0.1 | R56: 0.1 | T56: 0.15 | V56: 0.01
F57: UST+Exercises-Advance | H57: =2*H7 -> 2 | J57: 5000 | L57: 0.25 | N57: 0.2 | P57: 0.1 | R57: 0.1 | T57: 0.15 | V57: 0.01
L58: 0.25 | N58: 0.2 | P58: 0.1 | R58: 0.1 | T58: 0.15 | V58: 0.01
E59: DayCare | L59: 0.25 | N59: 0.2 | P59: 0.1 | R59: 0.1 | T59: 0.15 | V59: 0.01
F60: IV fluid therapy | H60: =30*H7 -> 30 | J60: 250 | L60: 0.25 | N60: 0.2 | P60: 0.1 | R60: 0.1 | T60: 0.15 | V60: 0.01
F61: IM/IV Injection | H61: =10*30*H7 -> 300 | J61: 100 | L61: 0.25 | N61: 0.2 | P61: 0.1 | R61: 0.1 | T61: 0.15 | V61: 0.01
F62: GRBS checking | L62: 0.25 | N62: 0.2 | P62: 0.1 | R62: 0.1 | T62: 0.15 | V62: 0.01
F63: Foleys Catheterization | H63: =5*H7 -> 5 | J63: 500 | L63: 0.25 | N63: 0.2 | P63: 0.1 | R63: 0.1 | T63: 0.15 | V63: 0.01
F64: Wound Dressing | H64: =10*4*H7 -> 40 | J64: 100 | L64: 0.25 | N64: 0.2 | P64: 0.1 | R64: 0.1 | T64: 0.15 | V64: 0.01
F65: IV Cannulaization | H65: =20*H7 -> 20 | J65: 150 | L65: 0.25 | N65: 0.2 | P65: 0.1 | R65: 0.1 | T65: 0.15 | V65: 0.01
C66: Grand Total | L66: 0.25 | N66: 0.2 | P66: 0.1 | R66: 0.1 | T66: 0.15 | V66: 0.01
L67: 0.25 | N67: 0.2 | P67: 0.1 | R67: 0.1 | T67: 0.15 | V67: 0.01
L68: 0.25 | N68: 0.2 | P68: 0.1 | R68: 0.1 | T68: 0.15 | V68: 0.01
C69: 2 | D69: Docty Pharma | L69: 0.25 | N69: 0.2 | P69: 0.1 | R69: 0.1 | T69: 0.15 | V69: 0.01
C70: 2a | F70: Ethical drugs | H70: =30*30*H7 -> 900 | J70: 500 | L70: 0.25 | N70: 0.2 | P70: 0.1 | R70: 0.1 | T70: 0.15 | V70: 0.01
C71: 2b | F71: Generic drugs | H71: =50*30*H7 -> 1500 | J71: 200 | L71: 0.25 | N71: 0.2 | P71: 0.1 | R71: 0.1 | T71: 0.15 | V71: 0.01
C72: 2c | F72: Nurtraceuticals | H72: =10*50*H7 -> 500 | J72: 700 | L72: 0.25 | N72: 0.2 | P72: 0.1 | R72: 0.1 | T72: 0.15 | V72: 0.01
C73: 2d | F73: FMCG | H73: =20*30*H7 -> 600 | J73: 300 | L73: 0.25 | N73: 0.2 | P73: 0.1 | R73: 0.1 | T73: 0.15 | V73: 0.01
C74: 2e | F74: Surgicals | H74: =10*30*H7 -> 300 | J74: 500 | L74: 0.25 | N74: 0.2 | P74: 0.1 | R74: 0.1 | T74: 0.15 | V74: 0.01
L75: 0.25 | N75: 0.2 | P75: 0.1 | R75: 0.1 | T75: 0.15 | V75: 0.01
C76: Grand Total | L76: 0.25 | N76: 0.2 | P76: 0.1 | R76: 0.1 | T76: 0.15 | V76: 0.01
L77: 0.25 | N77: 0.2 | P77: 0.1 | R77: 0.1 | T77: 0.15 | V77: 0.01
L78: 0.25 | N78: 0.2 | P78: 0.1 | R78: 0.1 | T78: 0.15 | V78: 0.01
C79: 3 | D79: Lab & Diagnostics | E79: Serology & Immunology | L79: 0.25 | N79: 0.2 | P79: 0.1 | R79: 0.1 | T79: 0.15 | V79: 0.01
C80: 3a | F80: =E79 -> Serology & Immunology | H80: =3*30*H7 -> 90 | J80: 1000 | L80: 0.25 | N80: 0.2 | P80: 0.1 | R80: 0.1 | T80: 0.15 | V80: 0.01
E81: Molecular Biology | L81: 0.25 | N81: 0.2 | P81: 0.1 | R81: 0.1 | T81: 0.15 | V81: 0.01
F82: =E81 -> Molecular Biology | H82: =4*H7 -> 4 | J82: 4500 | L82: 0.25 | N82: 0.2 | P82: 0.1 | R82: 0.1 | T82: 0.15 | V82: 0.01
E83: Micro Biology | L83: 0.25 | N83: 0.2 | P83: 0.1 | R83: 0.1 | T83: 0.15 | V83: 0.01
F84: =E83 -> Micro Biology | H84: =30/12*H7 -> 2.5 | J84: 1200 | L84: 0.25 | N84: 0.2 | P84: 0.1 | R84: 0.1 | T84: 0.15 | V84: 0.01
E85: Histopathology | L85: 0.25 | N85: 0.2 | P85: 0.1 | R85: 0.1 | T85: 0.15 | V85: 0.01
F86: =E85 -> Histopathology | H86: =30/12*H7 -> 2.5 | J86: 1500 | L86: 0.25 | N86: 0.2 | P86: 0.1 | R86: 0.1 | T86: 0.15 | V86: 0.01
E87: Packages | L87: 0.25 | N87: 0.2 | P87: 0.1 | R87: 0.1 | T87: 0.15 | V87: 0.01
F88: Minor-Surgical Profile | H88: =3*30*H7 -> 90 | J88: 1500 | L88: 0.25 | N88: 0.2 | P88: 0.1 | R88: 0.1 | T88: 0.15 | V88: 0.01
F89: Fever Profile | L89: 0.25 | N89: 0.2 | P89: 0.1 | R89: 0.1 | T89: 0.15 | V89: 0.01
F90: Cardiac Profile | L90: 0.25 | N90: 0.2 | P90: 0.1 | R90: 0.1 | T90: 0.15 | V90: 0.01
F91: Diabetic Proflie | L91: 0.25 | N91: 0.2 | P91: 0.1 | R91: 0.1 | T91: 0.15 | V91: 0.01
F92: General Health Check-Basic | L92: 0.25 | N92: 0.2 | P92: 0.1 | R92: 0.1 | T92: 0.15 | V92: 0.01
F93: General Health Check-Basic Plus | L93: 0.25 | N93: 0.2 | P93: 0.1 | R93: 0.1 | T93: 0.15 | V93: 0.01
F94: Master Health Checkup | L94: 0.25 | N94: 0.2 | P94: 0.1 | R94: 0.1 | T94: 0.15 | V94: 0.01
F95: Master Health Checkup Plus | L95: 0.25 | N95: 0.2 | P95: 0.1 | R95: 0.1 | T95: 0.15 | V95: 0.01
F96: Monsoon Checkups Basic | L96: 0.25 | N96: 0.2 | P96: 0.1 | R96: 0.1 | T96: 0.15 | V96: 0.01
F97: Monsoon Checkups Advanced | L97: 0.25 | N97: 0.2 | P97: 0.1 | R97: 0.1 | T97: 0.15 | V97: 0.01
F98: Women Checkup-Basic | L98: 0.25 | N98: 0.2 | P98: 0.1 | R98: 0.1 | T98: 0.15 | V98: 0.01
F99: Women Checkup-Basic Plus | L99: 0.25 | N99: 0.2 | P99: 0.1 | R99: 0.1 | T99: 0.15 | V99: 0.01
F100: Women Checkup-Comprehensive | L100: 0.25 | N100: 0.2 | P100: 0.1 | R100: 0.1 | T100: 0.15 | V100: 0.01
... F102: Women Checkup-Advanced | L102: 0.25 | N102: 0.2 | P102: 0.1 | R102: 0.1 | T102: 0.15 | V102: 0.01
E103: Diagnostics | L103: 0.25 | N103: 0.2 | P103: 0.1 | R103: 0.1 | T103: 0.15 | V103: 0.01
...

Sheet Branch
B2: Sl. No. | C2: Year | D2: Month | E2: Number of Branches | F2: Growth | G2: Addition of branches | J2: Subscriptions Market Place | K2: Subscriptions Retail | L2: Subscriptions Corporate | M2: Cummulative Market Place | N2: Cummulative Subs Retail | O2: Cummulative Subs Corporate
B3: Start Date | C3: =IF(MONTH(D3)<=3,TEXT(D3,"yyyy")-1 & "-" & TEXT(D3,"yy"),IF(MONTH(D3)>3,TEXT(D3,"yyyy") & "-" & TEXT(D3,"yy")+1)) -> 2025-26 | D3: =EOMONTH('2. Basics'!$D$16,1) -> 45930 | G3: 1
B4: 1 | C4: =IF(MONTH(D4)<=3,TEXT(D4,"yyyy")-1 & "-" & TEXT(D4,"yy"),IF(MONTH(D4)>3,TEXT(D4,"yyyy") & "-" & TEXT(D4,"yy")+1)) -> 2025-26 | D4: =EOMONTH($D$3,B4) -> 45961 | E4: 3 | F4: 0.15 | G4: 2 | H4: 0.15 | K4: 60 | N4: =K4 -> 60
B5: 2 | C5: =IF(MONTH(D5)<=3,TEXT(D5,"yyyy")-1 & "-" & TEXT(D5,"yy"),IF(MONTH(D5)>3,TEXT(D5,"yyyy") & "-" & TEXT(D5,"yy")+1)) -> 2025-26 | D5: =EOMONTH($D$3,B5) -> 45991 | E5: 3 | F5: 0.15 | G5: =E5-E4 -> 0 | H5: 0.1 | K5: 75 | N5: =K5 -> 75
B6: 3 | C6: =IF(MONTH(D6)<=3,TEXT(D6,"yyyy")-1 & "-" & TEXT(D6,"yy"),IF(MONTH(D6)>3,TEXT(D6,"yyyy") & "-" & TEXT(D6,"yy")+1)) -> 2025-26 | D6: =EOMONTH($D$3,B6) -> 46022 | E6: 4 | F6: 0.15 | G6: =E6-E5 -> 1 | H6: 0.15 | K6: 100 | N6: =K6 -> 100
B7: 4 | C7: =IF(MONTH(D7)<=3,TEXT(D7,"yyyy")-1 & "-" & TEXT(D7,"yy"),IF(MONTH(D7)>3,TEXT(D7,"yyyy") & "-" & TEXT(D7,"yy")+1)) -> 2025-26 | D7: =EOMONTH($D$3,B7) -> 46053 | E7: 5 | F7: 0.15 | G7: =E7-E6 -> 1 | H7: 0 | J7: 50 | K7: 130 | L7: 1000 | M7: =J7 -> 50 | N7: =K7 -> 130 | O7: =L7 -> 1000
B8: 5 | C8: =IF(MONTH(D8)<=3,TEXT(D8,"yyyy")-1 & "-" & TEXT(D8,"yy"),IF(MONTH(D8)>3,TEXT(D8,"yyyy") & "-" & TEXT(D8,"yy")+1)) -> 2025-26 | D8: =EOMONTH($D$3,B8) -> 46081 | E8: 8 | F8: 0.15 | G8: =E8-E7 -> 3 | H8: 0 | J8: 80 | K8: 180 | L8: 1000 | M8: =J8 -> 80 | N8: =K8 -> 180 | O8: =L8 -> 1000
B9: 6 | C9: =IF(MONTH(D9)<=3,TEXT(D9,"yyyy")-1 & "-" & TEXT(D9,"yy"),IF(MONTH(D9)>3,TEXT(D9,"yyyy") & "-" & TEXT(D9,"yy")+1)) -> 2025-26 | D9: =EOMONTH($D$3,B9) -> 46112 | E9: 10 | F9: 0.15 | G9: =E9-E8 -> 2 | H9: 0 | J9: 100 | K9: 230 | L9: 1000 | M9: =J9 -> 100 | N9: =K9 -> 230 | O9: =L9 -> 1000
B10: 7 | C10: =IF(MONTH(D10)<=3,TEXT(D10,"yyyy")-1 & "-" & TEXT(D10,"yy"),IF(MONTH(D10)>3,TEXT(D10,"yyyy") & "-" & TEXT(D10,"yy")+1)) -> 2026-27 | D10: =EOMONTH($D$3,B10) -> 46142 | E10: 10 | F10: 0.15 | G10: =E10-E9 -> 0 | H10: 0 | J10: 150 | K10: 300 | L10: 1200 | M10: =J10 -> 150 | N10: =K10 -> 300 | O10: =L10 -> 1200
B11: 8 | C11: =IF(MONTH(D11)<=3,TEXT(D11,"yyyy")-1 & "-" & TEXT(D11,"yy"),IF(MONTH(D11)>3,TEXT(D11,"yyyy") & "-" & TEXT(D11,"yy")+1)) -> 2026-27 | D11: =EOMONTH($D$3,B11) -> 46173 | E11: 10 | F11: 0.15 | G11: =E11-E10 -> 0 | H11: 0 | J11: 200 | K11: 340 | L11: 1200 | M11: =J11 -> 200 | N11: =K11 -> 340 | O11: =L11 -> 1200
B12: 9 | C12: =IF(MONTH(D12)<=3,TEXT(D12,"yyyy")-1 & "-" & TEXT(D12,"yy"),IF(MONTH(D12)>3,TEXT(D12,"yyyy") & "-" & TEXT(D12,"yy")+1)) -> 2026-27 | D12: =EOMONTH($D$3,B12) -> 46203 | E12: 10 | F12: 0.15 | G12: =E12-E11 -> 0 | H12: 0 | J12: 250 | K12: 385 | L12: 1200 | M12: =J12 -> 250 | N12: =K12 -> 385 | O12: =L12 -> 1200
B13: 10 | C13: =IF(MONTH(D13)<=3,TEXT(D13,"yyyy")-1 & "-" & TEXT(D13,"yy"),IF(MONTH(D13)>3,TEXT(D13,"yyyy") & "-" & TEXT(D13,"yy")+1)) -> 2026-27 | D13: =EOMONTH($D$3,B13) -> 46234 | E13: 10 | F13: 0.15 | G13: =E13-E12 -> 0 | H13: 0 | J13: 300 | K13: 420 | L13: 1500 | M13: =J13 -> 300 | N13: =K13 -> 420 | O13: =L13 -> 1500
B14: 11 | C14: =IF(MONTH(D14)<=3,TEXT(D14,"yyyy")-1 & "-" & TEXT(D14,"yy"),IF(MONTH(D14)>3,TEXT(D14,"yyyy") & "-" & TEXT(D14,"yy")+1)) -> 2026-27 | D14: =EOMONTH($D$3,B14) -> 46265 | E14: 10 | F14: 0.15 | G14: =E14-E13 -> 0 | H14: 0 | J14: 350 | K14: 450 | L14: 1500 | M14: =J14 -> 350 | N14: =K14 -> 450 | O14: =L14 -> 1500
B15: 12 | C15: =IF(MONTH(D15)<=3,TEXT(D15,"yyyy")-1 & "-" & TEXT(D15,"yy"),IF(MONTH(D15)>3,TEXT(D15,"yyyy") & "-" & TEXT(D15,"yy")+1)) -> 2026-27 | D15: =EOMONTH($D$3,B15) -> 46295 | E15: 10 | F15: 0.15 | G15: =E15-E14 -> 0 | H15: 0 | J15: 400 | K15: 500 | L15: 1500 | M15: =J15 -> 400 | N15: =K15 -> 500 | O15: =L15 -> 1500
B16: 13 | C16: =IF(MONTH(D16)<=3,TEXT(D16,"yyyy")-1 & "-" & TEXT(D16,"yy"),IF(MONTH(D16)>3,TEXT(D16,"yyyy") & "-" & TEXT(D16,"yy")+1)) -> 2026-27 | D16: =EOMONTH($D$3,B16) -> 46326 | E16: 10 | F16: 0.15 | G16: =E16-E15 -> 0 | H16: 0 | J16: 450 | K16: 500 | L16: 1800 | M16: =J16 -> 450 | N16: =K16 -> 500 | O16: =L16 -> 1800
B17: 14 | C17: =IF(MONTH(D17)<=3,TEXT(D17,"yyyy")-1 & "-" & TEXT(D17,"yy"),IF(MONTH(D17)>3,TEXT(D17,"yyyy") & "-" & TEXT(D17,"yy")+1)) -> 2026-27 | D17: =EOMONTH($D$3,B17) -> 46356 | E17: 10 | F17: 0.15 | G17: =E17-E16 -> 0 | H17: 0 | J17: 500 | K17: 500 | L17: 1800 | M17: =J17 -> 500 | N17: =K17 -> 500 | O17: =L17 -> 1800
B18: 15 | C18: =IF(MONTH(D18)<=3,TEXT(D18,"yyyy")-1 & "-" & TEXT(D18,"yy"),IF(MONTH(D18)>3,TEXT(D18,"yyyy") & "-" & TEXT(D18,"yy")+1)) -> 2026-27 | D18: =EOMONTH($D$3,B18) -> 46387 | E18: 10 | F18: 0.15 | G18: =E18-E17 -> 0 | H18: 0 | J18: 500 | K18: 500 | L18: 1800 | M18: =J18 -> 500 | N18: =K18 -> 500 | O18: =L18 -> 1800
B19: 16 | C19: =IF(MONTH(D19)<=3,TEXT(D19,"yyyy")-1 & "-" & TEXT(D19,"yy"),IF(MONTH(D19)>3,TEXT(D19,"yyyy") & "-" & TEXT(D19,"yy")+1)) -> 2026-27 | D19: =EOMONTH($D$3,B19) -> 46418 | E19: 10 | F19: 0.15 | G19: =E19-E18 -> 0 | H19: 0 | J19: 500 | K19: 500 | L19: 2100 | M19: =J19+J7 -> 550 | N19: =K19+K7 -> 630 | O19: =(L19+L7) -> 3100
B20: 17 | C20: =IF(MONTH(D20)<=3,TEXT(D20,"yyyy")-1 & "-" & TEXT(D20,"yy"),IF(MONTH(D20)>3,TEXT(D20,"yyyy") & "-" & TEXT(D20,"yy")+1)) -> 2026-27 | D20: =EOMONTH($D$3,B20) -> 46446 | E20: 10 | F20: 0.15 | G20: =E20-E19 -> 0 | H20: 0 | J20: 500 | K20: 500 | L20: 2100 | M20: =J20+J8 -> 580 | N20: =K20+K8 -> 680 | O20: =(L20+L8) -> 3100
B21: 18 | C21: =IF(MONTH(D21)<=3,TEXT(D21,"yyyy")-1 & "-" & TEXT(D21,"yy"),IF(MONTH(D21)>3,TEXT(D21,"yyyy") & "-" & TEXT(D21,"yy")+1)) -> 2026-27 | D21: =EOMONTH($D$3,B21) -> 46477 | E21: 10 | F21: 0.15 | G21: =E21-E20 -> 0 | H21: 0 | J21: 500 | K21: 500 | L21: 2100 | M21: =J21+J9 -> 600 | N21: =K21+K9 -> 730 | O21: =(L21+L9) -> 3100
B22: 19 | C22: =IF(MONTH(D22)<=3,TEXT(D22,"yyyy")-1 & "-" & TEXT(D22,"yy"),IF(MONTH(D22)>3,TEXT(D22,"yyyy") & "-" & TEXT(D22,"yy")+1)) -> 2027-28 | D22: =EOMONTH($D$3,B22) -> 46507 | E22: 10 | F22: 0.15 | G22: =E22-E21 -> 0 | H22: 0 | J22: 500 | K22: 500 | L22: 2100 | M22: =J22+J10 -> 650 | N22: =K22+K10 -> 800 | O22: =(L22+L10) -> 3300
B23: 20 | C23: =IF(MONTH(D23)<=3,TEXT(D23,"yyyy")-1 & "-" & TEXT(D23,"yy"),IF(MONTH(D23)>3,TEXT(D23,"yyyy") & "-" & TEXT(D23,"yy")+1)) -> 2027-28 | D23: =EOMONTH($D$3,B23) -> 46538 | E23: 10 | F23: 0.15 | G23: =E23-E22 -> 0 | H23: 0 | J23: 500 | K23: 500 | L23: 2100 | M23: =J23+J11 -> 700 | N23: =K23+K11 -> 840 | O23: =(L23+L11) -> 3300
B24: 21 | C24: =IF(MONTH(D24)<=3,TEXT(D24,"yyyy")-1 & "-" & TEXT(D24,"yy"),IF(MONTH(D24)>3,TEXT(D24,"yyyy") & "-" & TEXT(D24,"yy")+1)) -> 2027-28 | D24: =EOMONTH($D$3,B24) -> 46568 | E24: 10 | F24: 0.15 | G24: =E24-E23 -> 0 | H24: 0 | J24: 500 | K24: 500 | L24: 2100 | M24: =J24+J12 -> 750 | N24: =K24+K12 -> 885 | O24: =(L24+L12) -> 3300
B25: 22 | C25: =IF(MONTH(D25)<=3,TEXT(D25,"yyyy")-1 & "-" & TEXT(D25,"yy"),IF(MONTH(D25)>3,TEXT(D25,"yyyy") & "-" & TEXT(D25,"yy")+1)) -> 2027-28 | D25: =EOMONTH($D$3,B25) -> 46599 | E25: 10 | F25: 0.15 | G25: =E25-E24 -> 0 | H25: 0 | J25: 500 | K25: 500 | L25: 2100 | M25: =J25+J13 -> 800 | N25: =K25+K13 -> 920 | O25: =(L25+L13) -> 3600
B26: 23 | C26: =IF(MONTH(D26)<=3,TEXT(D26,"yyyy")-1 & "-" & TEXT(D26,"yy"),IF(MONTH(D26)>3,TEXT(D26,"yyyy") & "-" & TEXT(D26,"yy")+1)) -> 2027-28 | D26: =EOMONTH($D$3,B26) -> 46630 | E26: 10 | F26: 0.15 | G26: =E26-E25 -> 0 | H26: 0 | J26: 500 | K26: 500 | L26: 2100 | M26: =J26+J14 -> 850 | N26: =K26+K14 -> 950 | O26: =(L26+L14) -> 3600
B27: 24 | C27: =IF(MONTH(D27)<=3,TEXT(D27,"yyyy")-1 & "-" & TEXT(D27,"yy"),IF(MONTH(D27)>3,TEXT(D27,"yyyy") & "-" & TEXT(D27,"yy")+1)) -> 2027-28 | D27: =EOMONTH($D$3,B27) -> 46660 | E27: 10 | F27: 0.15 | G27: =E27-E26 -> 0 | H27: 0 | J27: 500 | K27: 500 | L27: 2100 | M27: =J27+J15 -> 900 | N27: =K27+K15 -> 1000 | O27: =(L27+L15) -> 3600
B28: 25 | C28: =IF(MONTH(D28)<=3,TEXT(D28,"yyyy")-1 & "-" & TEXT(D28,"yy"),IF(MONTH(D28)>3,TEXT(D28,"yyyy") & "-" & TEXT(D28,"yy")+1)) -> 2027-28 | D28: =EOMONTH($D$3,B28) -> 46691 | E28: 10 | F28: 0.15 | G28: =E28-E27 -> 0 | H28: 0 | J28: 500 | K28: 500 | L28: 2100 | M28: =J28+J16 -> 950 | N28: =K28+K16 -> 1000 | O28: =(L28+L16) -> 3900
B29: 26 | C29: =IF(MONTH(D29)<=3,TEXT(D29,"yyyy")-1 & "-" & TEXT(D29,"yy"),IF(MONTH(D29)>3,TEXT(D29,"yyyy") & "-" & TEXT(D29,"yy")+1)) -> 2027-28 | D29: =EOMONTH($D$3,B29) -> 46721 | E29: 10 | F29: 0.15 | G29: =E29-E28 -> 0 | H29: 0 | J29: 500 | K29: 500 | L29: 2100 | M29: =J29+J17 -> 1000 | N29: =K29+K17 -> 1000 | O29: =(L29+L17) -> 3900
B30: 27 | C30: =IF(MONTH(D30)<=3,TEXT(D30,"yyyy")-1 & "-" & TEXT(D30,"yy"),IF(MONTH(D30)>3,TEXT(D30,"yyyy") & "-" & TEXT(D30,"yy")+1)) -> 2027-28 | D30: =EOMONTH($D$3,B30) -> 46752 | E30: 10 | F30: 0.15 | G30: =E30-E29 -> 0 | H30: 0 | J30: 500 | K30: 500 | L30: 2100 | M30: =J30+J18 -> 1000 | N30: =K30+K18 -> 1000 | O30: =(L30+L18) -> 3900
B31: 28 | C31: =IF(MONTH(D31)<=3,TEXT(D31,"yyyy")-1 & "-" & TEXT(D31,"yy"),IF(MONTH(D31)>3,TEXT(D31,"yyyy") & "-" & TEXT(D31,"yy")+1)) -> 2027-28 | D31: =EOMONTH($D$3,B31) -> 46783 | E31: 10 | F31: 0.15 | G31: =E31-E30 -> 0 | H31: 0 | J31: 500 | K31: 500 | L31: 2100 | M31: =J31+J19+J7 -> 1050 | N31: =K31+K19+K7 -> 1130 | O31: =L31+L19+L7 -> 5200
B32: 29 | C32: =IF(MONTH(D32)<=3,TEXT(D32,"yyyy")-1 & "-" & TEXT(D32,"yy"),IF(MONTH(D32)>3,TEXT(D32,"yyyy") & "-" & TEXT(D32,"yy")+1)) -> 2027-28 | D32: =EOMONTH($D$3,B32) -> 46812 | E32: 10 | F32: 0.15 | G32: =E32-E31 -> 0 | H32: 0 | J32: 500 | K32: 500 | L32: 2100 | M32: =J32+J20+J8 -> 1080 | N32: =K32+K20+K8 -> 1180 | O32: =L32+L20+L8 -> 5200
B33: 30 | C33: =IF(MONTH(D33)<=3,TEXT(D33,"yyyy")-1 & "-" & TEXT(D33,"yy"),IF(MONTH(D33)>3,TEXT(D33,"yyyy") & "-" & TEXT(D33,"yy")+1)) -> 2027-28 | D33: =EOMONTH($D$3,B33) -> 46843 | E33: 10 | F33: 0.15 | G33: =E33-E32 -> 0 | H33: 0 | J33: 500 | K33: 500 | L33: 2100 | M33: =J33+J21+J9 -> 1100 | N33: =K33+K21+K9 -> 1230 | O33: =L33+L21+L9 -> 5200
B34: 31 | C34: =IF(MONTH(D34)<=3,TEXT(D34,"yyyy")-1 & "-" & TEXT(D34,"yy"),IF(MONTH(D34)>3,TEXT(D34,"yyyy") & "-" & TEXT(D34,"yy")+1)) -> 2028-29 | D34: =EOMONTH($D$3,B34) -> 46873 | E34: 10 | F34: 0.15 | G34: =E34-E33 -> 0 | H34: 0 | J34: 500 | K34: 500 | L34: 2100 | M34: =J34+J22+J10 -> 1150 | N34: =K34+K22+K10 -> 1300 | O34: =L34+L22+L10 -> 5400
B35: 32 | C35: =IF(MONTH(D35)<=3,TEXT(D35,"yyyy")-1 & "-" & TEXT(D35,"yy"),IF(MONTH(D35)>3,TEXT(D35,"yyyy") & "-" & TEXT(D35,"yy")+1)) -> 2028-29 | D35: =EOMONTH($D$3,B35) -> 46904 | E35: 10 | F35: 0.15 | G35: =E35-E34 -> 0 | H35: 0 | J35: 500 | K35: 500 | L35: 2100 | M35: =J35+J23+J11 -> 1200 | N35: =K35+K23+K11 -> 1340 | O35: =L35+L23+L11 -> 5400
B36: 33 | C36: =IF(MONTH(D36)<=3,TEXT(D36,"yyyy")-1 & "-" & TEXT(D36,"yy"),IF(MONTH(D36)>3,TEXT(D36,"yyyy") & "-" & TEXT(D36,"yy")+1)) -> 2028-29 | D36: =EOMONTH($D$3,B36) -> 46934 | E36: 10 | F36: 0.15 | G36: =E36-E35 -> 0 | H36: 0 | J36: 500 | K36: 500 | L36: 2100 | M36: =J36+J24+J12 -> 1250 | N36: =K36+K24+K12 -> 1385 | O36: =L36+L24+L12 -> 5400
B37: 34 | C37: =IF(MONTH(D37)<=3,TEXT(D37,"yyyy")-1 & "-" & TEXT(D37,"yy"),IF(MONTH(D37)>3,TEXT(D37,"yyyy") & "-" & TEXT(D37,"yy")+1)) -> 2028-29 | D37: =EOMONTH($D$3,B37) -> 46965 | E37: 10 | F37: 0.15 | G37: =E37-E36 -> 0 | H37: 0 | J37: 500 | K37: 500 | L37: 2100 | M37: =J37+J25+J13 -> 1300 | N37: =K37+K25+K13 -> 1420 | O37: =L37+L25+L13 -> 5700
B38: 35 | C38: =IF(MONTH(D38)<=3,TEXT(D38,"yyyy")-1 & "-" & TEXT(D38,"yy"),IF(MONTH(D38)>3,TEXT(D38,"yyyy") & "-" & TEXT(D38,"yy")+1)) -> 2028-29 | D38: =EOMONTH($D$3,B38) -> 46996 | E38: 10 | F38: 0.15 | G38: =E38-E37 -> 0 | H38: 0 | J38: 500 | K38: 500 | L38: 2100 | M38: =J38+J26+J14 -> 1350 | N38: =K38+K26+K14 -> 1450 | O38: =L38+L26+L14 -> 5700
B39: 36 | C39: =IF(MONTH(D39)<=3,TEXT(D39,"yyyy")-1 & "-" & TEXT(D39,"yy"),IF(MONTH(D39)>3,TEXT(D39,"yyyy") & "-" & TEXT(D39,"yy")+1)) -> 2028-29 | D39: =EOMONTH($D$3,B39) -> 47026 | E39: 10 | F39: 0.15 | G39: =E39-E38 -> 0 | H39: 0 | J39: 500 | K39: 500 | L39: 2100 | M39: =J39+J27+J15 -> 1400 | N39: =K39+K27+K15 -> 1500 | O39: =L39+L27+L15 -> 5700
B40: 37 | C40: =IF(MONTH(D40)<=3,TEXT(D40,"yyyy")-1 & "-" & TEXT(D40,"yy"),IF(MONTH(D40)>3,TEXT(D40,"yyyy") & "-" & TEXT(D40,"yy")+1)) -> 2028-29 | D40: =EOMONTH($D$3,B40) -> 47057 | E40: 10 | F40: 0.15 | G40: =E40-E39 -> 0 | H40: 0 | J40: 500 | K40: 500 | L40: 2100 | M40: =J40+J28+J16 -> 1450 | N40: =K40+K28+K16 -> 1500 | O40: =L40+L28+L16 -> 6000
B41: 38 | C41: =IF(MONTH(D41)<=3,TEXT(D41,"yyyy")-1 & "-" & TEXT(D41,"yy"),IF(MONTH(D41)>3,TEXT(D41,"yyyy") & "-" & TEXT(D41,"yy")+1)) -> 2028-29 | D41: =EOMONTH($D$3,B41) -> 47087 | E41: 10 | F41: 0.15 | G41: =E41-E40 -> 0 | H41: 0 | J41: 500 | K41: 500 | L41: 2100 | M41: =J41+J29+J17 -> 1500 | N41: =K41+K29+K17 -> 1500 | O41: =L41+L29+L17 -> 6000
B42: 39 | C42: =IF(MONTH(D42)<=3,TEXT(D42,"yyyy")-1 & "-" & TEXT(D42,"yy"),IF(MONTH(D42)>3,TEXT(D42,"yyyy") & "-" & TEXT(D42,"yy")+1)) -> 2028-29 | D42: =EOMONTH($D$3,B42) -> 47118 | E42: 10 | F42: 0.15 | G42: =E42-E41 -> 0 | H42: 0 | J42: 500 | K42: 500 | L42: 2100 | M42: =J42+J30+J18 -> 1500 | N42: =K42+K30+K18 -> 1500 | O42: =L42+L30+L18 -> 6000
B43: 40 | C43: =IF(MONTH(D43)<=3,TEXT(D43,"yyyy")-1 & "-" & TEXT(D43,"yy"),IF(MONTH(D43)>3,TEXT(D43,"yyyy") & "-" & TEXT(D43,"yy")+1)) -> 2028-29 | D43: =EOMONTH($D$3,B43) -> 47149 | E43: 10 | F43: 0.15 | G43: =E43-E42 -> 0 | H43: 0 | J43: 500 | K43: 500 | L43: 2100 | M43: =J43+J31+J19+J7 -> 1550 | N43: =K43+K31+K19+K7 -> 1630 | O43: =L43+L31+L19+L7 -> 7300
B44: 41 | C44: =IF(MONTH(D44)<=3,TEXT(D44,"yyyy")-1 & "-" & TEXT(D44,"yy"),IF(MONTH(D44)>3,TEXT(D44,"yyyy") & "-" & TEXT(D44,"yy")+1)) -> 2028-29 | D44: =EOMONTH($D$3,B44) -> 47177 | E44: 10 | F44: 0.15 | G44: =E44-E43 -> 0 | H44: 0 | J44: 500 | K44: 500 | L44: 2100 | M44: =J44+J32+J20+J8 -> 1580 | N44: =K44+K32+K20+K8 -> 1680 | O44: =L44+L32+L20+L8 -> 7300
B45: 42 | C45: =IF(MONTH(D45)<=3,TEXT(D45,"yyyy")-1 & "-" & TEXT(D45,"yy"),IF(MONTH(D45)>3,TEXT(D45,"yyyy") & "-" & TEXT(D45,"yy")+1)) -> 2028-29 | D45: =EOMONTH($D$3,B45) -> 47208 | E45: 10 | F45: 0.15 | G45: =E45-E44 -> 0 | H45: 0 | J45: 500 | K45: 500 | L45: 2100 | M45: =J45+J33+J21+J9 -> 1600 | N45: =K45+K33+K21+K9 -> 1730 | O45: =L45+L33+L21+L9 -> 7300
B46: 43 | C46: =IF(MONTH(D46)<=3,TEXT(D46,"yyyy")-1 & "-" & TEXT(D46,"yy"),IF(MONTH(D46)>3,TEXT(D46,"yyyy") & "-" & TEXT(D46,"yy")+1)) -> 2029-30 | D46: =EOMONTH($D$3,B46) -> 47238 | E46: 10 | F46: 0.15 | G46: =E46-E45 -> 0 | H46: 0 | J46: 500 | K46: 500 | L46: 2100 | M46: =J46+J34+J22+J10 -> 1650 | N46: =K46+K34+K22+K10 -> 1800 | O46: =L46+L34+L22+L10 -> 7500
B47: 44 | C47: =IF(MONTH(D47)<=3,TEXT(D47,"yyyy")-1 & "-" & TEXT(D47,"yy"),IF(MONTH(D47)>3,TEXT(D47,"yyyy") & "-" & TEXT(D47,"yy")+1)) -> 2029-30 | D47: =EOMONTH($D$3,B47) -> 47269 | E47: 10 | F47: 0.15 | G47: =E47-E46 -> 0 | H47: 0 | J47: 500 | K47: 500 | L47: 2100 | M47: =J47+J35+J23+J11 -> 1700 | N47: =K47+K35+K23+K11 -> 1840 | O47: =L47+L35+L23+L11 -> 7500
B48: 45 | C48: =IF(MONTH(D48)<=3,TEXT(D48,"yyyy")-1 & "-" & TEXT(D48,"yy"),IF(MONTH(D48)>3,TEXT(D48,"yyyy") & "-" & TEXT(D48,"yy")+1)) -> 2029-30 | D48: =EOMONTH($D$3,B48) -> 47299 | E48: 10 | F48: 0.15 | G48: =E48-E47 -> 0 | H48: 0 | J48: 500 | K48: 500 | L48: 2100 | M48: =J48+J36+J24+J12 -> 1750 | N48: =K48+K36+K24+K12 -> 1885 | O48: =L48+L36+L24+L12 -> 7500
B49: 46 | C49: =IF(MONTH(D49)<=3,TEXT(D49,"yyyy")-1 & "-" & TEXT(D49,"yy"),IF(MONTH(D49)>3,TEXT(D49,"yyyy") & "-" & TEXT(D49,"yy")+1)) -> 2029-30 | D49: =EOMONTH($D$3,B49) -> 47330 | E49: 10 | F49: 0.15 | G49: =E49-E48 -> 0 | H49: 0 | J49: 500 | K49: 500 | L49: 2100 | M49: =J49+J37+J25+J13 -> 1800 | N49: =K49+K37+K25+K13 -> 1920 | O49: =L49+L37+L25+L13 -> 7800
B50: 47 | C50: =IF(MONTH(D50)<=3,TEXT(D50,"yyyy")-1 & "-" & TEXT(D50,"yy"),IF(MONTH(D50)>3,TEXT(D50,"yyyy") & "-" & TEXT(D50,"yy")+1)) -> 2029-30 | D50: =EOMONTH($D$3,B50) -> 47361 | E50: 10 | F50: 0.15 | G50: =E50-E49 -> 0 | H50: 0 | J50: 500 | K50: 500 | L50: 2100 | M50: =J50+J38+J26+J14 -> 1850 | N50: =K50+K38+K26+K14 -> 1950 | O50: =L50+L38+L26+L14 -> 7800
B51: 48 | C51: =IF(MONTH(D51)<=3,TEXT(D51,"yyyy")-1 & "-" & TEXT(D51,"yy"),IF(MONTH(D51)>3,TEXT(D51,"yyyy") & "-" & TEXT(D51,"yy")+1)) -> 2029-30 | D51: =EOMONTH($D$3,B51) -> 47391 | E51: 10 | F51: 0.15 | G51: =E51-E50 -> 0 | H51: 0 | J51: 500 | K51: 500 | L51: 2100 | M51: =J51+J39+J27+J15 -> 1900 | N51: =K51+K39+K27+K15 -> 2000 | O51: =L51+L39+L27+L15 -> 7800
B52: 49 | C52: =IF(MONTH(D52)<=3,TEXT(D52,"yyyy")-1 & "-" & TEXT(D52,"yy"),IF(MONTH(D52)>3,TEXT(D52,"yyyy") & "-" & TEXT(D52,"yy")+1)) -> 2029-30 | D52: =EOMONTH($D$3,B52) -> 47422 | E52: 10 | F52: 0.15 | G52: =E52-E51 -> 0 | H52: 0 | J52: 500 | K52: 500 | L52: 2100 | M52: =J52+J40+J28+J16 -> 1950 | N52: =K52+K40+K28+K16 -> 2000 | O52: =L52+L40+L28+L16 -> 8100
B53: 50 | C53: =IF(MONTH(D53)<=3,TEXT(D53,"yyyy")-1 & "-" & TEXT(D53,"yy"),IF(MONTH(D53)>3,TEXT(D53,"yyyy") & "-" & TEXT(D53,"yy")+1)) -> 2029-30 | D53: =EOMONTH($D$3,B53) -> 47452 | E53: 10 | F53: 0.15 | G53: =E53-E52 -> 0 | H53: 0 | J53: 500 | K53: 500 | L53: 2100 | M53: =J53+J41+J29+J17 -> 2000 | N53: =K53+K41+K29+K17 -> 2000 | O53: =L53+L41+L29+L17 -> 8100
B54: 51 | C54: =IF(MONTH(D54)<=3,TEXT(D54,"yyyy")-1 & "-" & TEXT(D54,"yy"),IF(MONTH(D54)>3,TEXT(D54,"yyyy") & "-" & TEXT(D54,"yy")+1)) -> 2029-30 | D54: =EOMONTH($D$3,B54) -> 47483 | E54: 10 | F54: 0.15 | G54: =E54-E53 -> 0 | H54: 0 | J54: 500 | K54: 500 | L54: 2100 | M54: =J54+J42+J30+J18 -> 2000 | N54: =K54+K42+K30+K18 -> 2000 | O54: =L54+L42+L30+L18 -> 8100
B55: 52 | C55: =IF(MONTH(D55)<=3,TEXT(D55,"yyyy")-1 & "-" & TEXT(D55,"yy"),IF(MONTH(D55)>3,TEXT(D55,"yyyy") & "-" & TEXT(D55,"yy")+1)) -> 2029-30 | D55: =EOMONTH($D$3,B55) -> 47514 | E55: 10 | F55: 0.15 | G55: =E55-E54 -> 0 | H55: 0 | J55: 500 | K55: 500 | L55: 2100 | M55: =J55+J43+J31+J19+J7 -> 2050 | N55: =K55+K43+K31+K19+K7 -> 2130 | O55: =L55+L43+L31+L19+L7 -> 9400
B56: 53 | C56: =IF(MONTH(D56)<=3,TEXT(D56,"yyyy")-1 & "-" & TEXT(D56,"yy"),IF(MONTH(D56)>3,TEXT(D56,"yyyy") & "-" & TEXT(D56,"yy")+1)) -> 2029-30 | D56: =EOMONTH($D$3,B56) -> 47542 | E56: 10 | F56: 0.15 | G56: =E56-E55 -> 0 | H56: 0 | J56: 500 | K56: 500 | L56: 2100 | M56: =J56+J44+J32+J20+J8 -> 2080 | N56: =K56+K44+K32+K20+K8 -> 2180 | O56: =L56+L44+L32+L20+L8 -> 9400
B57: 54 | C57: =IF(MONTH(D57)<=3,TEXT(D57,"yyyy")-1 & "-" & TEXT(D57,"yy"),IF(MONTH(D57)>3,TEXT(D57,"yyyy") & "-" & TEXT(D57,"yy")+1)) -> 2029-30 | D57: =EOMONTH($D$3,B57) -> 47573 | E57: 10 | F57: 0.15 | G57: =E57-E56 -> 0 | H57: 0 | J57: 500 | K57: 500 | L57: 2100 | M57: =J57+J45+J33+J21+J9 -> 2100 | N57: =K57+K45+K33+K21+K9 -> 2230 | O57: =L57+L45+L33+L21+L9 -> 9400
B58: 55 | C58: =IF(MONTH(D58)<=3,TEXT(D58,"yyyy")-1 & "-" & TEXT(D58,"yy"),IF(MONTH(D58)>3,TEXT(D58,"yyyy") & "-" & TEXT(D58,"yy")+1)) -> 2030-31 | D58: =EOMONTH($D$3,B58) -> 47603 | E58: 10 | F58: 0.15 | G58: =E58-E57 -> 0 | H58: 0 | J58: 500 | K58: 500 | L58: 2100 | M58: =J58+J46+J34+J22+J10 -> 2150 | N58: =K58+K46+K34+K22+K10 -> 2300 | O58: =L58+L46+L34+L22+L10 -> 9600
B59: 56 | C59: =IF(MONTH(D59)<=3,TEXT(D59,"yyyy")-1 & "-" & TEXT(D59,"yy"),IF(MONTH(D59)>3,TEXT(D59,"yyyy") & "-" & TEXT(D59,"yy")+1)) -> 2030-31 | D59: =EOMONTH($D$3,B59) -> 47634 | E59: 10 | F59: 0.15 | G59: =E59-E58 -> 0 | H59: 0 | J59: 500 | K59: 500 | L59: 2100 | M59: =J59+J47+J35+J23+J11 -> 2200 | N59: =K59+K47+K35+K23+K11 -> 2340 | O59: =L59+L47+L35+L23+L11 -> 9600
B60: 57 | C60: =IF(MONTH(D60)<=3,TEXT(D60,"yyyy")-1 & "-" & TEXT(D60,"yy"),IF(MONTH(D60)>3,TEXT(D60,"yyyy") & "-" & TEXT(D60,"yy")+1)) -> 2030-31 | D60: =EOMONTH($D$3,B60) -> 47664 | E60: 10 | F60: 0.15 | G60: =E60-E59 -> 0 | H60: 0 | J60: 500 | K60: 500 | L60: 2100 | M60: =J60+J48+J36+J24+J12 -> 2250 | N60: =K60+K48+K36+K24+K12 -> 2385 | O60: =L60+L48+L36+L24+L12 -> 9600
B61: 58 | C61: =IF(MONTH(D61)<=3,TEXT(D61,"yyyy")-1 & "-" & TEXT(D61,"yy"),IF(MONTH(D61)>3,TEXT(D61,"yyyy") & "-" & TEXT(D61,"yy")+1)) -> 2030-31 | D61: =EOMONTH($D$3,B61) -> 47695 | E61: 10 | F61: 0.15 | G61: =E61-E60 -> 0 | H61: 0 | J61: 500 | K61: 500 | L61: 2100 | M61: =J61+J49+J37+J25+J13 -> 2300 | N61: =K61+K49+K37+K25+K13 -> 2420 | O61: =L61+L49+L37+L25+L13 -> 9900
B62: 59 | C62: =IF(MONTH(D62)<=3,TEXT(D62,"yyyy")-1 & "-" & TEXT(D62,"yy"),IF(MONTH(D62)>3,TEXT(D62,"yyyy") & "-" & TEXT(D62,"yy")+1)) -> 2030-31 | D62: =EOMONTH($D$3,B62) -> 47726 | E62: 10 | F62: 0.15 | G62: =E62-E61 -> 0 | H62: 0 | J62: 500 | K62: 500 | L62: 2100 | M62: =J62+J50+J38+J26+J14 -> 2350 | N62: =K62+K50+K38+K26+K14 -> 2450 | O62: =L62+L50+L38+L26+L14 -> 9900
B63: 60 | C63: =IF(MONTH(D63)<=3,TEXT(D63,"yyyy")-1 & "-" & TEXT(D63,"yy"),IF(MONTH(D63)>3,TEXT(D63,"yyyy") & "-" & TEXT(D63,"yy")+1)) -> 2030-31 | D63: =EOMONTH($D$3,B63) -> 47756 | E63: 10 | F63: 0.15 | G63: =E63-E62 -> 0 | H63: 0 | J63: 500 | K63: 500 | L63: 2100 | M63: =J63+J51+J39+J27+J15 -> 2400 | N63: =K63+K51+K39+K27+K15 -> 2500 | O63: =L63+L51+L39+L27+L15 -> 9900
B64: 61 | C64: =IF(MONTH(D64)<=3,TEXT(D64,"yyyy")-1 & "-" & TEXT(D64,"yy"),IF(MONTH(D64)>3,TEXT(D64,"yyyy") & "-" & TEXT(D64,"yy")+1)) -> 2030-31 | D64: =EOMONTH($D$3,B64) -> 47787 | E64: 10 | F64: 0.15 | G64: =E64-E63 -> 0 | H64: 0 | J64: 500 | K64: 500 | L64: 2100 | M64: =J64+J52+J40+J28+J16 -> 2450 | N64: =K64+K52+K40+K28+K16 -> 2500 | O64: =L64+L52+L40+L28+L16 -> 10200
B65: 62 | C65: =IF(MONTH(D65)<=3,TEXT(D65,"yyyy")-1 & "-" & TEXT(D65,"yy"),IF(MONTH(D65)>3,TEXT(D65,"yyyy") & "-" & TEXT(D65,"yy")+1)) -> 2030-31 | D65: =EOMONTH($D$3,B65) -> 47817 | E65: 10 | F65: 0.15 | G65: =E65-E64 -> 0 | H65: 0 | J65: 500 | K65: 500 | L65: 2100 | M65: =J65+J53+J41+J29+J17 -> 2500 | N65: =K65+K53+K41+K29+K17 -> 2500 | O65: =L65+L53+L41+L29+L17 -> 10200
B66: 63 | C66: =IF(MONTH(D66)<=3,TEXT(D66,"yyyy")-1 & "-" & TEXT(D66,"yy"),IF(MONTH(D66)>3,TEXT(D66,"yyyy") & "-" & TEXT(D66,"yy")+1)) -> 2030-31 | D66: =EOMONTH($D$3,B66) -> 47848 | E66: 10 | F66: 0.15 | G66: =E66-E65 -> 0 | H66: 0 | J66: 500 | K66: 500 | L66: 2100 | M66: =J66+J54+J42+J30+J18 -> 2500 | N66: =K66+K54+K42+K30+K18 -> 2500 | O66: =L66+L54+L42+L30+L18 -> 10200
B67: 64 | C67: =IF(MONTH(D67)<=3,TEXT(D67,"yyyy")-1 & "-" & TEXT(D67,"yy"),IF(MONTH(D67)>3,TEXT(D67,"yyyy") & "-" & TEXT(D67,"yy")+1)) -> 2030-31 | D67: =EOMONTH($D$3,B67) -> 47879 | E67: 10 | F67: 0.15 | G67: =E67-E66 -> 0 | H67: 0 | J67: 500 | K67: 500 | L67: 2100 | M67: =J67+J55+J43+J31+J19+J7 -> 2550 | N67: =K67+K55+K43+K31+K19+K7 -> 2630 | O67: =L67+L55+L43+L31+L19+L7 -> 11500
B68: 65 | C68: =IF(MONTH(D68)<=3,TEXT(D68,"yyyy")-1 & "-" & TEXT(D68,"yy"),IF(MONTH(D68)>3,TEXT(D68,"yyyy") & "-" & TEXT(D68,"yy")+1)) -> 2030-31 | D68: =EOMONTH($D$3,B68) -> 47907 | E68: 10 | F68: 0.15 | G68: =E68-E67 -> 0 | H68: 0 | J68: 500 | K68: 500 | L68: 2100 | M68: =J68+J56+J44+J32+J20+J8 -> 2580 | N68: =K68+K56+K44+K32+K20+K8 -> 2680 | O68: =L68+L56+L44+L32+L20+L8 -> 11500
B69: 66 | C69: =IF(MONTH(D69)<=3,TEXT(D69,"yyyy")-1 & "-" & TEXT(D69,"yy"),IF(MONTH(D69)>3,TEXT(D69,"yyyy") & "-" & TEXT(D69,"yy")+1)) -> 2030-31 | D69: =EOMONTH($D$3,B69) -> 47938 | E69: 10 | F69: 0.15 | G69: =E69-E68 -> 0 | H69: 0 | J69: 500 | K69: 500 | L69: 2100 | M69: =J69+J57+J45+J33+J21+J9 -> 2600 | N69: =K69+K57+K45+K33+K21+K9 -> 2730 | O69: =L69+L57+L45+L33+L21+L9 -> 11500
B70: 67 | C70: =IF(MONTH(D70)<=3,TEXT(D70,"yyyy")-1 & "-" & TEXT(D70,"yy"),IF(MONTH(D70)>3,TEXT(D70,"yyyy") & "-" & TEXT(D70,"yy")+1)) -> 2031-32 | D70: =EOMONTH($D$3,B70) -> 47968 | E70: 10 | F70: 0.15 | G70: =E70-E69 -> 0 | H70: 0 | J70: 500 | K70: 500 | L70: 2100 | M70: =J70+J58+J46+J34+J22+J10 -> 2650 | N70: =K70+K58+K46+K34+K22+K10 -> 2800 | O70: =L70+L58+L46+L34+L22+L10 -> 11700
B71: 68 | C71: =IF(MONTH(D71)<=3,TEXT(D71,"yyyy")-1 & "-" & TEXT(D71,"yy"),IF(MONTH(D71)>3,TEXT(D71,"yyyy") & "-" & TEXT(D71,"yy")+1)) -> 2031-32 | D71: =EOMONTH($D$3,B71) -> 47999 | E71: 10 | F71: 0.15 | G71: =E71-E70 -> 0 | H71: 0 | J71: 500 | K71: 500 | L71: 2100 | M71: =J71+J59+J47+J35+J23+J11 -> 2700 | N71: =K71+K59+K47+K35+K23+K11 -> 2840 | O71: =L71+L59+L47+L35+L23+L11 -> 11700
B72: 69 | C72: =IF(MONTH(D72)<=3,TEXT(D72,"yyyy")-1 & "-" & TEXT(D72,"yy"),IF(MONTH(D72)>3,TEXT(D72,"yyyy") & "-" & TEXT(D72,"yy")+1)) -> 2031-32 | D72: =EOMONTH($D$3,B72) -> 48029 | E72: 10 | F72: 0.15 | G72: =E72-E71 -> 0 | H72: 0 | J72: 500 | K72: 500 | L72: 2100 | M72: =J72+J60+J48+J36+J24+J12 -> 2750 | N72: =K72+K60+K48+K36+K24+K12 -> 2885 | O72: =L72+L60+L48+L36+L24+L12 -> 11700
B73: 70 | C73: =IF(MONTH(D73)<=3,TEXT(D73,"yyyy")-1 & "-" & TEXT(D73,"yy"),IF(MONTH(D73)>3,TEXT(D73,"yyyy") & "-" & TEXT(D73,"yy")+1)) -> 2031-32 | D73: =EOMONTH($D$3,B73) -> 48060 | E73: 10 | F73: 0.15 | G73: =E73-E72 -> 0 | H73: 0 | J73: 500 | K73: 500 | L73: 2100 | M73: =J73+J61+J49+J37+J25+J13 -> 2800 | N73: =K73+K61+K49+K37+K25+K13 -> 2920 | O73: =L73+L61+L49+L37+L25+L13 -> 12000
B74: 71 | C74: =IF(MONTH(D74)<=3,TEXT(D74,"yyyy")-1 & "-" & TEXT(D74,"yy"),IF(MONTH(D74)>3,TEXT(D74,"yyyy") & "-" & TEXT(D74,"yy")+1)) -> 2031-32 | D74: =EOMONTH($D$3,B74) -> 48091 | E74: 10 | F74: 0.15 | G74: =E74-E73 -> 0 | H74: 0 | J74: 500 | K74: 500 | L74: 2100 | M74: =J74+J62+J50+J38+J26+J14 -> 2850 | N74: =K74+K62+K50+K38+K26+K14 -> 2950 | O74: =L74+L62+L50+L38+L26+L14 -> 12000

Sheet A. Data Needed
C2: Major heads of the data needed for the business plan
D3: Hyperlink to open
B4: I | C4: We need to clearly define the Revenue Streams | D4: Nature of services. click here for the link to enter the revenue streams
B7: II | C7: Sales price per revenue streams | D7: Click
B9: III | C9: Costing headers | D9: =A.IIOPEX!C2 -> Opex, Click on the link to refer to OPEX
B11: IIV | C11: Capex Information | D11: Capex Click on the link to refer to Capex
B13: V | C13: Other Information

Sheet A.IIOPEX
C2: Opex, Click on the link to refer to OPEX
K3: No of Branches
C4: Write down all the major and nimor headers for the costing and list them here | I4: Quarter 3 | K4: 10
C5: Beside the header you will be able to write the quantity and the price | I5: Quarter 4 | K5: 20 | M5: 48 | O5: 35 | Q5: 35 | S5: 35 | U5: 35
I6: Total | K6: =K4+K5 -> 30 | M6: =K6+M5+M4 -> 78 | O6: =M6+O5+O4 -> 113 | Q6: =O6+Q5+Q4 -> 148 | S6: =Q6+S5+S4 -> 183 | U6: =S6+U5+U4 -> 218
K7: 2025-26 | M7: 2026-27 | O7: 2027-28 | Q7: 2028-29 | S7: 2029-30 | U7: 2030-31
I8: 1
D9: Major Header | E9: Sub Services | G9: Monthly | I9: Cost per month per branch | K9: Monthly Growth Rate in Y1 | M9: Yearly Growth Rate from Y1 to Y2 | O9: Yearly Growth Rate from Y2 to Y3 | Q9: Yearly Growth Rate from Y3 to Y4 | S9: Yearly Growth Rate from Y4 to Y5 | U9: Yearly Growth Rate from Y5 to Y6
C10: 1 | D10: Utilities
C11: 1a | E11: Rent | I11: =295000*I8 -> 295000 | K11: 1 | M11: 0.01 | O11: 0.01 | Q11: 0.01 | S11: 0.01 | U11: 0.01
C12: 1b | E12: Electricity | I12: 40000 | K12: 1 | M12: 0.01 | O12: 0.01 | Q12: 0.01 | S12: 0.01 | U12: 0.01
C13: 1c | E13: Internet & Telephone | I13: 4000 | K13: 1 | M13: 0.01 | O13: 0.01 | Q13: 0.01 | S13: 0.01 | U13: 0.01
C14: 1d | E14: Maintenance & Repairs | I14: 10000 | K14: 1 | M14: 0.01 | O14: 0.01 | Q14: 0.01 | S14: 0.01 | U14: 0.01
C15: 1e | E15: Petty cash expense | I15: 10000 | K15: 1 | M15: 0.01 | O15: 0.01 | Q15: 0.01 | S15: 0.01 | U15: 0.01
K16: 1 | M16: 0.01 | O16: 0.01 | Q16: 0.01 | S16: 0.01 | U16: 0.01
K17: 1 | M17: 0.01 | O17: 0.01 | Q17: 0.01 | S17: 0.01 | U17: 0.01
C18: Grand Total
C21: 2 | D21: Salaries
C22: 2a | E22: Management | I22: =200000*I8 -> 200000 | K22: 1 | M22: 0.01 | O22: 0.01 | Q22: 0.01 | S22: 0.01 | U22: 0.01
C23: 2b | E23: Doctors | I23: =150000*I8 -> 150000 | K23: 1 | M23: 0.01 | O23: 0.01 | Q23: 0.01 | S23: 0.01 | U23: 0.01
C24: 2c | E24: Clinical Staff | I24: 125000 | K24: 1 | M24: 0.01 | O24: 0.01 | Q24: 0.01 | S24: 0.01 | U24: 0.01
E25: Admin & Accounting | I25: 50000 | K25: 1 | M25: 0.01 | O25: 0.01 | Q25: 0.01 | S25: 0.01 | U25: 0.01
E26: Other Salaries | I26: 50000 | K26: 1 | M26: 0.01 | O26: 0.01 | Q26: 0.01 | S26: 0.01 | U26: 0.01
C27: Grand Total
C30: 3 | D30: Vendor Payments
C31: 3a | E31: Housekeeping | I31: =30000*I8 -> 30000 | K31: 1 | M31: 0.01 | O31: 0.01 | Q31: 0.01 | S31: 0.01 | U31: 0.01
C32: 3b | E32: Pest Control | I32: =10000*I8 -> 10000 | K32: 1 | M32: 0.01 | O32: 0.01 | Q32: 0.01 | S32: 0.01 | U32: 0.01
C33: 3c | E33: Biomedical Waste Disposal | I33: =20000/12*I8 -> 1666.6667 | K33: 1 | M33: 0.01 | O33: 0.01 | Q33: 0.01 | S33: 0.01 | U33: 0.01
C34: 3d | E34: Lab Aggregators | I34: =200000*I8 -> 200000 | K34: 1 | M34: 0.01 | O34: 0.01 | Q34: 0.01 | S34: 0.01 | U34: 0.01
G35: 5 | K35: 1 | M35: 0.01 | O35: 0.01 | Q35: 0.01 | S35: 0.01 | U35: 0.01
K36: 1 | M36: 0.01 | O36: 0.01 | Q36: 0.01 | S36: 0.01 | U36: 0.01
C37: Grand Total
C40: 4 | D40: Supplies
C41: 4a | E41: Housekeeping | I41: =10000*I8 -> 10000 | K41: 1 | M41: 0.01 | O41: 0.01 | Q41: 0.01 | S41: 0.01 | U41: 0.01
C42: 4b | E42: Clinical | I42: =50000*I8 -> 50000 | K42: 1 | M42: 0.01 | O42: 0.01 | Q42: 0.01 | S42: 0.01 | U42: 0.01
C43: 4c | E43: Pantry | I43: =10000*I8 -> 10000 | K43: 1 | M43: 0.01 | O43: 0.01 | Q43: 0.01 | S43: 0.01 | U43: 0.01
C44: 4d | E44: Admin & Office | I44: =5000*I8 -> 5000 | K44: 1 | M44: 0.01 | O44: 0.01 | Q44: 0.01 | S44: 0.01 | U44: 0.01
K45: 1 | M45: 0.01 | O45: 0.01 | Q45: 0.01 | S45: 0.01 | U45: 0.01
C46: Grand Total
C49: 5 | D49: Payouts
C50: 5a | E50: Management Fee | I50: =200000*I8 -> 200000 | K50: 1 | M50: 0.01 | O50: 0.01 | P50: 0.01 | Q50: 0.01 | R50: 0.01 | S50: 0.01 | U50: 0.01
C51: 5b | E51: Franchisee Payout | I51: =250000*I8 -> 250000 | K51: 1 | M51: 0.01 | O51: 0.01 | P51: 0.01 | Q51: 0.01 | R51: 0.01 | S51: 0.01 | U51: 0.01
C52: 5c | E52: Consulting Doctors | I52: =144000*I8 -> 144000 | K52: 1 | M52: 0.01 | O52: 0.01 | P52: 0.01 | Q52: 0.01 | R52: 0.01 | S52: 0.01 | U52: 0.01
C53: 5d | O53: 0.01 | P53: 0.01 | Q53: 0.01 | R53: 0.01 | S53: 0.01 | U53: 0.01
C54: Grand Total
C57: 6 | D57: Marketing & Promotions
C58: 6a | E58: Leaflet Distribution | I58: =25000*I8 -> 25000 | K58: 1 | M58: 0.01 | O58: 0.45 | Q58: 0.4 | S58: 0.25 | U58: 0.15
C59: 6b | E59: Camps/Events | I59: =80000*I8 -> 80000 | K59: 1 | M59: 0.01 | O59: 0.45 | Q59: 0.4 | S59: 0.25 | U59: 0.15
C60: 6c | E60: Promotions | I60: =20000*I8 -> 20000 | K60: 1 | M60: 0.01 | O60: 0.45 | Q60: 0.4 | S60: 0.25 | U60: 0.15
C61: 6d | E61: Other Media | I61: =25000*I8 -> 25000 | K61: 1 | M61: 0.01 | O61: 0.45 | Q61: 0.4 | S61: 0.25 | U61: 0.15
C62: Grand Total
C65: 7 | D65: Licenses and Registration
C66: 7a | E66: Lease Deed Registration | I66: =130000/12 -> 10833.333 | K66: 1 | M66: 0.75 | O66: 0.45 | Q66: 0.4 | S66: 0.25 | U66: 0.15
C67: 7b | E67: Drug Licenses | I67: =145000/12/5 -> 2416.6667 | K67: 1 | M67: 0.75 | O67: 0.45 | Q67: 0.4 | S67: 0.25 | U67: 0.15
C68: 7c | E68: Clinical Establishment Licenses | I68: =135000/12/5 -> 2250 | K68: 1 | M68: 0.75 | O68: 0.45 | Q68: 0.4 | S68: 0.25 | U68: 0.15
E69: Trade License | I69: =20000/12 -> 1666.6667 | K69: 1 | M69: 0.75 | O69: 0.45 | Q69: 0.4 | S69: 0.25 | U69: 0.15
E70: Labour License | I70: =15000/12 -> 1250 | K70: 1 | M70: 0.75 | O70: 0.45 | Q70: 0.4 | S70: 0.25 | U70: 0.15
E71: FSSAI License | I71: =13000/12 -> 1083.3333 | K71: 1 | M71: 0.75 | O71: 0.45 | Q71: 0.4 | S71: 0.25 | U71: 0.15
E72: Biomedical Waste Certificate | I72: =20000/12 -> 1666.6667 | K72: 1 | M72: 0.75 | O72: 0.45 | Q72: 0.4 | S72: 0.25 | U72: 0.15
E73: PCB Certificate | I73: =5000/12 -> 416.66667 | K73: 1 | M73: 0.75 | O73: 0.45 | Q73: 0.4 | S73: 0.25 | U73: 0.15
E74: Firesafety Certificate | I74: =5000/12 -> 416.66667 | K74: 1 | M74: 0.75 | O74: 0.45 | Q74: 0.4 | S74: 0.25 | U74: 0.15
C76: Grand Total
C79: 8 | D79: Supplies
C80: 8a | E80: Pharmacy | K80: 1 | M80: 0.75 | O80: 0.45 | Q80: 0.4 | S80: 0.25 | U80: 0.15
C81: 8b | E81: Clinical Surgicals | K81: 1 | M81: 0.75 | O81: 0.45 | Q81: 0.4 | S81: 0.25 | U81: 0.15
C82: 8c | E82: Housekeeping | K82: 1 | M82: 0.75 | O82: 0.45 | Q82: 0.4 | S82: 0.25 | U82: 0.15
C83: 8d | K83: 1 | M83: 0.75 | O83: 0.45 | Q83: 0.4 | S83: 0.25 | U83: 0.15
C84: 8e | K84: 1 | M84: 0.75 | O84: 0.45 | Q84: 0.4 | S84: 0.25 | U84: 0.15
C85: 8f | K85: 1 | M85: 0.75 | O85: 0.45 | Q85: 0.4 | S85: 0.25 | U85: 0.15
C86: 8g | K86: 1 | M86: 0.75 | O86: 0.45 | Q86: 0.4 | S86: 0.25 | U86: 0.15

Sheet A.I Revenue Streams - P2
C2: Revenue Streams
C3: This Sheet assists us in getting the data related to Sales
C5: PHASE - 2 | E5: ='2. Basics'!D24 -> 100000
D8: Major Header | E8: Minor Header | G8: Number of Products sold per Day | I8: Sale Price of each product | K8: Monthly Growth Rate in Y1 | M8: Yearly Growth Rate from Y1 to Y2 | O8: Yearly Growth Rate from Y2 to Y3 | Q8: Yearly Growth Rate from Y3 to Y4 | S8: Yearly Growth Rate from Y4 to Y5 | U8: Yearly Growth Rate from Y5 to Y6
C9: 1 | D9: Cakes
C10: 1a | E10: Cup Cakes | G10: 5 | I10: 20 | K10: 0.1 | M10: 0.1 | O10: 0.1 | Q10: 0.1 | S10: 0.1 | U10: 0.1
C11: 1b | E11: Customised Cakes | G11: 4 | I11: 20 | K11: =$K$10 -> 0.1 | M11: =$M$10 -> 0.1 | O11: =$O$10 -> 0.1 | Q11: =$Q$10 -> 0.1 | S11: =$S$10 -> 0.1 | U11: =$U$10 -> 0.1
C12: 1c | E12: Standard Cake | G12: 3 | I12: 20 | K12: =$K$10 -> 0.1 | M12: =$M$10 -> 0.1 | O12: =$O$10 -> 0.1 | Q12: =$Q$10 -> 0.1 | S12: =$S$10 -> 0.1 | U12: =$U$10 -> 0.1
C13: 1d | E13: Cake Slices | G13: 2 | I13: 20 | K13: =$K$10 -> 0.1 | M13: =$M$10 -> 0.1 | O13: =$O$10 -> 0.1 | Q13: =$Q$10 -> 0.1 | S13: =$S$10 -> 0.1 | U13: =$U$10 -> 0.1
C14: 1e | E14: 0 | G14: 1 | I14: 20 | K14: =$K$10 -> 0.1 | M14: =$M$10 -> 0.1 | O14: =$O$10 -> 0.1 | Q14: =$Q$10 -> 0.1 | S14: =$S$10 -> 0.1 | U14: =$U$10 -> 0.1
C15: Grand Total
C18: 2 | D18: Confectionary
C19: 2a | E19: Burgers | G19: 5 | I19: 20 | K19: 0.1 | M19: 0.1 | O19: 0.1 | Q19: 0.1 | S19: 0.1 | U19: 0.1
C20: 2b | E20: Pizza | G20: 4 | I20: 20 | K20: =$K$19 -> 0.1 | M20: =$M$19 -> 0.1 | O20: =$O$19 -> 0.1 | Q20: =$Q$19 -> 0.1 | S20: =$S$19 -> 0.1 | U20: =$U$19 -> 0.1
C21: 2c | E21: Puffs | G21: 3 | I21: 20 | K21: =$K$19 -> 0.1 | M21: =$M$19 -> 0.1 | O21: =$O$19 -> 0.1 | Q21: =$Q$19 -> 0.1 | S21: =$S$19 -> 0.1 | U21: =$U$19 -> 0.1
C22: 2d | E22: Other 1 | G22: 2 | I22: 20 | K22: =$K$19 -> 0.1 | M22: =$M$19 -> 0.1 | O22: =$O$19 -> 0.1 | Q22: =$Q$19 -> 0.1 | S22: =$S$19 -> 0.1 | U22: =$U$19 -> 0.1
C23: 2e | E23: 0 | G23: 1 | I23: 20 | K23: =$K$19 -> 0.1 | M23: =$M$19 -> 0.1 | O23: =$O$19 -> 0.1 | Q23: =$Q$19 -> 0.1 | S23: =$S$19 -> 0.1 | U23: =$U$19 -> 0.1
C24: Grand Total
C27: 3 | D27: Accessorries
C28: 3a | E28: Poppers | G28: 5 | I28: 20 | K28: 0.1 | M28: 0.1 | O28: 0.1 | Q28: 0.1 | S28: 0.1 | U28: 0.1
C29: 3b | E29: Builders | G29: 4 | I29: 20 | K29: =$K$28 -> 0.1 | M29: =$M$28 -> 0.1 | O29: =$O$28 -> 0.1 | Q29: =$Q$28 -> 0.1 | S29: =$S$28 -> 0.1 | U29: =$U$28 -> 0.1
C30: 3c | E30: Blasters | G30: 3 | I30: 20 | K30: =$K$28 -> 0.1 | M30: =$M$28 -> 0.1 | O30: =$O$28 -> 0.1 | Q30: =$Q$28 -> 0.1 | S30: =$S$28 -> 0.1 | U30: =$U$28 -> 0.1
C31: 3d | E31: Decor | G31: 2 | I31: 20 | K31: =$K$28 -> 0.1 | M31: =$M$28 -> 0.1 | O31: =$O$28 -> 0.1 | Q31: =$Q$28 -> 0.1 | S31: =$S$28 -> 0.1 | U31: =$U$28 -> 0.1
C32: 3e | E32: Others | G32: 1 | I32: 20 | K32: =$K$28 -> 0.1 | M32: =$M$28 -> 0.1 | O32: =$O$28 -> 0.1 | Q32: =$Q$28 -> 0.1 | S32: =$S$28 -> 0.1 | U32: =$U$28 -> 0.1
C33: Grand Total
C36: 4 | D36: Others
C37: 4a | E37: Others 1 | G37: 5 | I37: 20 | K37: 0.1 | M37: 0.1 | O37: 0.1 | Q37: 0.1 | S37: 0.1 | U37: 0.1
C38: 4b | E38: Others 2 | G38: 4 | I38: 20 | K38: =$K$37 -> 0.1 | M38: =$M$37 -> 0.1 | O38: =$O$37 -> 0.1 | Q38: =$Q$37 -> 0.1 | S38: =$S$37 -> 0.1 | U38: =$U$37 -> 0.1
C39: 4c | E39: Others 3 | G39: 3 | I39: 20 | K39: =$K$37 -> 0.1 | M39: =$M$37 -> 0.1 | O39: =$O$37 -> 0.1 | Q39: =$Q$37 -> 0.1 | S39: =$S$37 -> 0.1 | U39: =$U$37 -> 0.1
C40: 4d | E40: Others 4 | G40: 2 | I40: 20 | K40: =$K$37 -> 0.1 | M40: =$M$37 -> 0.1 | O40: =$O$37 -> 0.1 | Q40: =$Q$37 -> 0.1 | S40: =$S$37 -> 0.1 | U40: =$U$37 -> 0.1
C41: 4e | E41: Others 5 | G41: 1 | I41: 20 | K41: =$K$37 -> 0.1 | M41: =$M$37 -> 0.1 | O41: =$O$37 -> 0.1 | Q41: =$Q$37 -> 0.1 | S41: =$S$37 -> 0.1 | U41: =$U$37 -> 0.1
C42: Grand Total
C45: 5 | D45: Others
C46: 5a | E46: Others 1 | G46: 5 | I46: 20 | K46: 0.1 | M46: 0.1 | O46: 0.1 | Q46: 0.1 | S46: 0.1 | U46: 0.1
C47: 5b | E47: Others 2 | G47: 4 | I47: 20 | K47: =$K$46 -> 0.1 | M47: =$M$46 -> 0.1 | O47: =$O$46 -> 0.1 | Q47: =$Q$46 -> 0.1 | S47: =$S$46 -> 0.1 | U47: =$U$46 -> 0.1
C48: 5c | E48: Others 3 | G48: 3 | I48: 20 | K48: =$K$46 -> 0.1 | M48: =$M$46 -> 0.1 | O48: =$O$46 -> 0.1 | Q48: =$Q$46 -> 0.1 | S48: =$S$46 -> 0.1 | U48: =$U$46 -> 0.1
C49: 5d | E49: Others 4 | G49: 2 | I49: 20 | K49: =$K$46 -> 0.1 | M49: =$M$46 -> 0.1 | O49: =$O$46 -> 0.1 | Q49: =$Q$46 -> 0.1 | S49: =$S$46 -> 0.1 | U49: =$U$46 -> 0.1
C50: 5e | E50: Others 5 | G50: 1 | I50: 20 | K50: =$K$46 -> 0.1 | M50: =$M$46 -> 0.1 | O50: =$O$46 -> 0.1 | Q50: =$Q$46 -> 0.1 | S50: =$S$46 -> 0.1 | U50: =$U$46 -> 0.1

Sheet A.III CAPEX
B2: S No | C2: Nature of the Expense | D2: Total Amount of the Project | E2: Cost for the Period Ending
E3: Year 1 Ending | G3: Year 2 Ending | H3: Year 3 Ending | I3: Year 4 Ending | J3: Year 5 Ending
E4: 31/03/2025 | F4: Year 1 Total | G4: 31/03/2027 | H4: 31/03/2028 | I4: 31/03/2029 | J4: 31/03/2030
B7: 1 | C7: Office Expenses | D7: =SUM(F7:J7) -> 0 | F7: =SUM(E7:E7) -> 0
C8: Laptop | D8: =SUM(F8:J8) -> 0 | F8: =SUM(E8:E8) -> 0
C9: Mobile | D9: =SUM(F9:J9) -> 0 | F9: =SUM(E9:E9) -> 0
C10: Monitor
C11: Tab
C12: Printer
B14: 2
D15: =SUM(F15:J15) -> 0 | F15: =SUM(E15:E15) -> 0
D16: =SUM(F16:J16) -> 0 | F16: =SUM(E16:E16) -> 0
B18: 3 | D18: 0 | F18: 0
D19: 0
D20: 0
D21: 0
B24: 4
D25: 0 | F25: 0
B27: 5 | D27: 0 | F27: 0
B32: 6 | D32: =SUM(F32:J32) -> 0 | F32: =SUM(E32:E32) -> 0
B35: Total Amount | D35: 510000000 | E35: =SUM(E7:E34) -> 0 | F35: =SUM(F7:F34) -> 0 | G35: =SUM(G7:G34) -> 0 | H35: 430000000 | I35: =SUM(I7:I34) -> 0 | J35: =SUM(J7:J34) -> 0
C41: 40 Cr is Equipment
C42: Civil

Sheet B.I Sales - P1 (2)
L1: =Branch!D4 -> 45961 | P1: =EOMONTH(L1,1) -> 45991 | T1: =EOMONTH(P1,1) -> 46022 | X1: =EOMONTH(T1,1) -> 46053 | AB1: =EOMONTH(X1,1) -> 46081 | AF1: =EOMONTH(AB1,1) -> 46112 | AJ1: =EOMONTH(AF1,1) -> 46142 | AN1: =EOMONTH(AJ1,1) -> 46173 | AR1: =EOMONTH(AN1,1) -> 46203 | AV1: =EOMONTH(AR1,1) -> 46234 | AZ1: =EOMONTH(AV1,1) -> 46265 | BD1: =EOMONTH(AZ1,1) -> 46295 | BH1: =EOMONTH(BD1,1) -> 46326 | BL1: =EOMONTH(BH1,1) -> 46356 | BP1: =EOMONTH(BL1,1) -> 46387 | BT1: =EOMONTH(BP1,1) -> 46418 | BX1: =EOMONTH(BT1,1) -> 46446 | CB1: =EOMONTH(BX1,1) -> 46477 | CF1: =EOMONTH(CB1,1) -> 46507 | CJ1: =EOMONTH(CF1,1) -> 46538 | CN1: =EOMONTH(CJ1,1) -> 46568 | CR1: =EOMONTH(CN1,1) -> 46599 | CV1: =EOMONTH(CR1,1) -> 46630 | CZ1: =EOMONTH(CV1,1) -> 46660 | DD1: =EOMONTH(CZ1,1) -> 46691 | DH1: =EOMONTH(DD1,1) -> 46721 | DL1: =EOMONTH(DH1,1) -> 46752 | DP1: =EOMONTH(DL1,1) -> 46783 | DT1: =EOMONTH(DP1,1) -> 46812 | DX1: =EOMONTH(DT1,1) -> 46843 | EB1: =EOMONTH(DX1,1) -> 46873 | EF1: =EOMONTH(EB1,1) -> 46904 | EJ1: =EOMONTH(EF1,1) -> 46934 | EN1: =EOMONTH(EJ1,1) -> 46965 | ER1: =EOMONTH(EN1,1) -> 46996 | EV1: =EOMONTH(ER1,1) -> 47026 | EZ1: =EOMONTH(EV1,1) -> 47057 | FD1: =EOMONTH(EZ1,1) -> 47087 | FH1: =EOMONTH(FD1,1) -> 47118 | FL1: =EOMONTH(FH1,1) -> 47149 | FP1: =EOMONTH(FL1,1) -> 47177 | FT1: =EOMONTH(FP1,1) -> 47208 | FX1: =EOMONTH(FT1,1) -> 47238 | GB1: =EOMONTH(FX1,1) -> 47269 | GF1: =EOMONTH(GB1,1) -> 47299 | GJ1: =EOMONTH(GF1,1) -> 47330 | GN1: =EOMONTH(GJ1,1) -> 47361 | GR1: =EOMONTH(GN1,1) -> 47391 | GV1: =EOMONTH(GR1,1) -> 47422 | GZ1: =EOMONTH(GV1,1) -> 47452 | HD1: =EOMONTH(GZ1,1) -> 47483 | HH1: =EOMONTH(HD1,1) -> 47514 | HL1: =EOMONTH(HH1,1) -> 47542 | HP1: =EOMONTH(HL1,1) -> 47573 | HT1: =EOMONTH(HP1,1) -> 47603 | HX1: =EOMONTH(HT1,1) -> 47634 | IB1: =EOMONTH(HX1,1) -> 47664 | IF1: =EOMONTH(IB1,1) -> 47695 | IJ1: =EOMONTH(IF1,1) -> 47726 | IN1: =EOMONTH(IJ1,1) -> 47756 | IR1: =EOMONTH(IN1,1) -> 47787 | IV1: =EOMONTH(IR1,1) -> 47817 | IZ1: =EOMONTH(IV1,1) -> 47848 | JD1: =EOMONTH(IZ1,1) -> 47879 | JH1: =EOMONTH(JD1,1) -> 47907 | JL1: =EOMONTH(JH1,1) -> 47938 | JP1: =EOMONTH(JL1,1) -> 47968 | JT1: =EOMONTH(JP1,1) -> 47999 | JX1: =EOMONTH(JT1,1) -> 48029 | KB1: =EOMONTH(JX1,1) -> 48060 | KF1: =EOMONTH(KB1,1) -> 48091
B2: A | C2: Do not enter any data in this sheet | E2: Number of branches | G2: Number of branches | K2: 3 | L2: =Branch!F4 -> 0.15 | O2: =VLOOKUP(O5,Branch!$D$4:$E$74,2,0) -> 3 | P2: =1+(L2*45%) -> 1.0675 | S2: =VLOOKUP(S5,Branch!$D$4:$E$74,2,0) -> 4 | T2: =1+Branch!F6 -> 1.15 | W2: =VLOOKUP(W5,Branch!$D$4:$E$74,2,0) -> 5 | X2: =1+Branch!F7 -> 1.15 | AA2: =VLOOKUP(AA5,Branch!$D$4:$E$74,2,0) -> 8 | AB2: =1+Branch!F8 -> 1.15 | AE2: =VLOOKUP(AE5,Branch!$D$4:$E$74,2,0) -> 10 | AF2: =1+Branch!F9 -> 1.15 | AI2: =VLOOKUP(AI5,Branch!$D$4:$E$74,2,0) -> 10 | AJ2: =1+Branch!F10 -> 1.15 | AM2: =VLOOKUP(AM5,Branch!$D$4:$E$74,2,0) -> 10 | AN2: =1+Branch!F11 -> 1.15 | AQ2: =VLOOKUP(AQ5,Branch!$D$4:$E$74,2,0) -> 10 | AR2: =1+Branch!F12 -> 1.15 | AU2: =VLOOKUP(AU5,Branch!$D$4:$E$74,2,0) -> 10 | AV2: =1+Branch!F13 -> 1.15 | AY2: =VLOOKUP(AY5,Branch!$D$4:$E$74,2,0) -> 10 | AZ2: =1+Branch!F14 -> 1.15 | BC2: =VLOOKUP(BC5,Branch!$D$4:$E$74,2,0) -> 10 | BD2: =1+Branch!F15 -> 1.15 | BG2: =VLOOKUP(BG5,Branch!$D$4:$E$74,2,0) -> 10 | BH2: =1+Branch!F16 -> 1.15 | BK2: =VLOOKUP(BK5,Branch!$D$4:$E$74,2,0) -> 10 | BL2: =1+Branch!F17 -> 1.15 | BO2: =VLOOKUP(BO5,Branch!$D$4:$E$74,2,0) -> 10 | BP2: =1+Branch!F18 -> 1.15 | BS2: =VLOOKUP(BS5,Branch!$D$4:$E$74,2,0) -> 10 | BT2: =1+Branch!F19 -> 1.15 | BW2: =VLOOKUP(BW5,Branch!$D$4:$E$74,2,0) -> 10 | BX2: =1+Branch!F20 -> 1.15 | CA2: =VLOOKUP(CA5,Branch!$D$4:$E$74,2,0) -> 10 | CB2: =1+Branch!F21 -> 1.15 | CE2: =VLOOKUP(CE5,Branch!$D$4:$E$74,2,0) -> 10 | CF2: =1+Branch!F22 -> 1.15 | CI2: =VLOOKUP(CI5,Branch!$D$4:$E$74,2,0) -> 10 | CJ2: =1+Branch!F23 -> 1.15 | CM2: =VLOOKUP(CM5,Branch!$D$4:$E$74,2,0) -> 10 | CN2: =1+Branch!F24 -> 1.15 | CQ2: =VLOOKUP(CQ5,Branch!$D$4:$E$74,2,0) -> 10 | CR2: =1+Branch!F25 -> 1.15 | CU2: =VLOOKUP(CU5,Branch!$D$4:$E$74,2,0) -> 10 | CV2: =1+Branch!F26 -> 1.15 | CY2: =VLOOKUP(CY5,Branch!$D$4:$E$74,2,0) -> 10 | CZ2: =1+Branch!F27 -> 1.15 | DC2: =VLOOKUP(DC5,Branch!$D$4:$E$74,2,0) -> 10 | DD2: =1+Branch!F28 -> 1.15 | DG2: =VLOOKUP(DG5,Branch!$D$4:$E$74,2,0) -> 10 | DH2: =1+Branch!F29 -> 1.15 | DK2: =VLOOKUP(DK5,Branch!$D$4:$E$74,2,0) -> 10 | DL2: =1+Branch!F30 -> 1.15 | DO2: =VLOOKUP(DO5,Branch!$D$4:$E$74,2,0) -> 10 | DP2: =1+Branch!F31 -> 1.15 | DS2: =VLOOKUP(DS5,Branch!$D$4:$E$74,2,0) -> 10 | DT2: =1+Branch!F32 -> 1.15 | DW2: =VLOOKUP(DW5,Branch!$D$4:$E$74,2,0) -> 10 | DX2: =1+Branch!F33 -> 1.15 | EA2: =VLOOKUP(EA5,Branch!$D$4:$E$74,2,0) -> 10 | EB2: =1+Branch!F34 -> 1.15 | EE2: =VLOOKUP(EE5,Branch!$D$4:$E$74,2,0) -> 10 | EF2: =1+Branch!F35 -> 1.15 | EI2: =VLOOKUP(EI5,Branch!$D$4:$E$74,2,0) -> 10 | EJ2: =1+Branch!F36 -> 1.15 | EM2: =VLOOKUP(EM5,Branch!$D$4:$E$74,2,0) -> 10 | EN2: =1+Branch!F37 -> 1.15 | EQ2: =VLOOKUP(EQ5,Branch!$D$4:$E$74,2,0) -> 10 | ER2: =1+Branch!F38 -> 1.15 | EU2: =VLOOKUP(EU5,Branch!$D$4:$E$74,2,0) -> 10 | EV2: =1+Branch!F39 -> 1.15 | EY2: =VLOOKUP(EY5,Branch!$D$4:$E$74,2,0) -> 10 | EZ2: =1+Branch!F40 -> 1.15 | FC2: =VLOOKUP(FC5,Branch!$D$4:$E$74,2,0) -> 10 | FD2: =1+Branch!F41 -> 1.15 | FG2: =VLOOKUP(FG5,Branch!$D$4:$E$74,2,0) -> 10 | FH2: =1+Branch!F42 -> 1.15 | FK2: =VLOOKUP(FK5,Branch!$D$4:$E$74,2,0) -> 10 | FL2: =1+Branch!F43 -> 1.15 | FO2: =VLOOKUP(FO5,Branch!$D$4:$E$74,2,0) -> 10 | FP2: =1+Branch!F44 -> 1.15 | FS2: =VLOOKUP(FS5,Branch!$D$4:$E$74,2,0) -> 10 | FT2: =1+Branch!F45 -> 1.15 | FW2: =VLOOKUP(FW5,Branch!$D$4:$E$74,2,0) -> 10 | FX2: =1+Branch!F46 -> 1.15 | GA2: =VLOOKUP(GA5,Branch!$D$4:$E$74,2,0) -> 10 | GB2: =1+Branch!F47 -> 1.15 | GE2: =VLOOKUP(GE5,Branch!$D$4:$E$74,2,0) -> 10 | GF2: =1+Branch!F48 -> 1.15 | GI2: =VLOOKUP(GI5,Branch!$D$4:$E$74,2,0) -> 10 | GJ2: =1+Branch!F49 -> 1.15 | GM2: =VLOOKUP(GM5,Branch!$D$4:$E$74,2,0) -> 10 | GN2: =1+Branch!F50 -> 1.15 | GQ2: =VLOOKUP(GQ5,Branch!$D$4:$E$74,2,0) -> 10 | GR2: =1+Branch!F51 -> 1.15 | GU2: =VLOOKUP(GU5,Branch!$D$4:$E$74,2,0) -> 10 | GV2: =1+Branch!F52 -> 1.15 | GY2: =VLOOKUP(GY5,Branch!$D$4:$E$74,2,0) -> 10 | GZ2: =1+Branch!F53 -> 1.15 | HC2: =VLOOKUP(HC5,Branch!$D$4:$E$74,2,0) -> 10 | HD2: =1+Branch!F54 -> 1.15 | HG2: =VLOOKUP(HG5,Branch!$D$4:$E$74,2,0) -> 10 | HH2: =1+Branch!F55 -> 1.15 | HK2: =VLOOKUP(HK5,Branch!$D$4:$E$74,2,0) -> 10 | HL2: =1+Branch!F56 -> 1.15 | HO2: =VLOOKUP(HO5,Branch!$D$4:$E$74,2,0) -> 10 | HP2: =1+Branch!F57 -> 1.15 | HS2: =VLOOKUP(HS5,Branch!$D$4:$E$74,2,0) -> 10 | HT2: =1+Branch!F58 -> 1.15 | HW2: =VLOOKUP(HW5,Branch!$D$4:$E$74,2,0) -> 10 | HX2: =1+Branch!F59 -> 1.15 | IA2: =VLOOKUP(IA5,Branch!$D$4:$E$74,2,0) -> 10 | IB2: =1+Branch!F60 -> 1.15 | IE2: =VLOOKUP(IE5,Branch!$D$4:$E$74,2,0) -> 10 | IF2: =1+Branch!F61 -> 1.15 | II2: =VLOOKUP(II5,Branch!$D$4:$E$74,2,0) -> 10 | IJ2: =1+Branch!F62 -> 1.15 | IM2: =VLOOKUP(IM5,Branch!$D$4:$E$74,2,0) -> 10 | IN2: =1+Branch!F63 -> 1.15 | IQ2: =VLOOKUP(IQ5,Branch!$D$4:$E$74,2,0) -> 10 | IR2: =1+Branch!F64 -> 1.15 | IU2: =VLOOKUP(IU5,Branch!$D$4:$E$74,2,0) -> 10 | IV2: =1+Branch!F65 -> 1.15 | IY2: =VLOOKUP(IY5,Branch!$D$4:$E$74,2,0) -> 10 | IZ2: =1+Branch!F66 -> 1.15 | JC2: =VLOOKUP(JC5,Branch!$D$4:$E$74,2,0) -> 10 | JD2: =1+Branch!F67 -> 1.15 | JG2: =VLOOKUP(JG5,Branch!$D$4:$E$74,2,0) -> 10 | JH2: =1+Branch!F68 -> 1.15 | JK2: =VLOOKUP(JK5,Branch!$D$4:$E$74,2,0) -> 10 | JL2: =1+Branch!F69 -> 1.15 | JO2: =VLOOKUP(JO5,Branch!$D$4:$E$74,2,0) -> 10 | JP2: =1+Branch!F70 -> 1.15 | JS2: =VLOOKUP(JS5,Branch!$D$4:$E$74,2,0) -> 10 | JT2: =1+Branch!F71 -> 1.15 | JW2: =VLOOKUP(JW5,Branch!$D$4:$E$74,2,0) -> 10 | JX2: =1+Branch!F72 -> 1.15 | KA2: =VLOOKUP(KA5,Branch!$D$4:$E$74,2,0) -> 10 | KB2: =1+Branch!F73 -> 1.15 | KE2: =VLOOKUP(KE5,Branch!$D$4:$E$74,2,0) -> 10 | KF2: =1+Branch!F74 -> 1.15
G3: =I3 -> 2025 | I3: =IF(MONTH(G5)<=3,TEXT(G5,"yyyy")-1&"-"&TEXT(G5,"yy"),IF(MONTH(G5)>3,TEXT(G5,"yyyy"))) -> 2025 | K3: =M3 -> 2025 | M3: =IF(MONTH(K5)<=3,TEXT(K5,"yyyy")-1&"-"&TEXT(K5,"yy"),IF(MONTH(K5)>3,TEXT(K5,"yyyy"))) -> 2025 | O3: =Q3 -> 2025 | Q3: =IF(MONTH(O5)<=3,TEXT(O5,"yyyy")-1&"-"&TEXT(O5,"yy"),IF(MONTH(O5)>3,TEXT(O5,"yyyy"))) -> 2025 | S3: =U3 -> 2025 | U3: =IF(MONTH(S5)<=3,TEXT(S5,"yyyy")-1&"-"&TEXT(S5,"yy"),IF(MONTH(S5)>3,TEXT(S5,"yyyy"))) -> 2025 | W3: =Y3 -> 2026 | Y3: =IF(MONTH(W5)<=3,TEXT(W5,"yyyy"),IF(MONTH(W5)>3,TEXT(W5,"yyyy"))) -> 2026 | AA3: =AC3 -> 2026 | AC3: =IF(MONTH(AA5)<=3,TEXT(AA5,"yyyy"),IF(MONTH(AA5)>3,TEXT(AA5,"yyyy"))) -> 2026 | AE3: =AG3 -> 2026 | AG3: =IF(MONTH(AE5)<=3,TEXT(AE5,"yyyy"),IF(MONTH(AE5)>3,TEXT(AE5,"yyyy"))) -> 2026 | AI3: =AK3 -> 2026 | AK3: =IF(MONTH(AI5)<=3,TEXT(AI5,"yyyy"),IF(MONTH(AI5)>3,TEXT(AI5,"yyyy"))) -> 2026 | AM3: =AO3 -> 2026 | AO3: =IF(MONTH(AM5)<=3,TEXT(AM5,"yyyy"),IF(MONTH(AM5)>3,TEXT(AM5,"yyyy"))) -> 2026 | AQ3: =AS3 -> 2026 | AS3: =IF(MONTH(AQ5)<=3,TEXT(AQ5,"yyyy"),IF(MONTH(AQ5)>3,TEXT(AQ5,"yyyy"))) -> 2026 | AU3: =AW3 -> 2026 | AW3: =IF(MONTH(AU5)<=3,TEXT(AU5,"yyyy"),IF(MONTH(AU5)>3,TEXT(AU5,"yyyy"))) -> 2026 | AY3: =BA3 -> 2026 | BA3: =IF(MONTH(AY5)<=3,TEXT(AY5,"yyyy"),IF(MONTH(AY5)>3,TEXT(AY5,"yyyy"))) -> 2026 | BC3: =BE3 -> 2026 | BE3: =IF(MONTH(BC5)<=3,TEXT(BC5,"yyyy"),IF(MONTH(BC5)>3,TEXT(BC5,"yyyy"))) -> 2026 | BG3: =BI3 -> 2026 | BI3: =IF(MONTH(BG5)<=3,TEXT(BG5,"yyyy"),IF(MONTH(BG5)>3,TEXT(BG5,"yyyy"))) -> 2026 | BK3: =BM3 -> 2026 | BM3: =IF(MONTH(BK5)<=3,TEXT(BK5,"yyyy"),IF(MONTH(BK5)>3,TEXT(BK5,"yyyy"))) -> 2026 | BO3: =BQ3 -> 2026 | BQ3: =IF(MONTH(BO5)<=3,TEXT(BO5,"yyyy"),IF(MONTH(BO5)>3,TEXT(BO5,"yyyy"))) -> 2026 | BS3: =BU3 -> 2027 | BU3: =IF(MONTH(BS5)<=3,TEXT(BS5,"yyyy"),IF(MONTH(BS5)>3,TEXT(BS5,"yyyy"))) -> 2027 | BW3: =BY3 -> 2027 | BY3: =IF(MONTH(BW5)<=3,TEXT(BW5,"yyyy"),IF(MONTH(BW5)>3,TEXT(BW5,"yyyy"))) -> 2027 | CA3: =CC3 -> 2027 | CC3: =IF(MONTH(CA5)<=3,TEXT(CA5,"yyyy"),IF(MONTH(CA5)>3,TEXT(CA5,"yyyy"))) -> 2027 | CE3: =CG3 -> 2027 | CG3: =IF(MONTH(CE5)<=3,TEXT(CE5,"yyyy"),IF(MONTH(CE5)>3,TEXT(CE5,"yyyy"))) -> 2027 | CI3: =CK3 -> 2027 | CK3: =IF(MONTH(CI5)<=3,TEXT(CI5,"yyyy"),IF(MONTH(CI5)>3,TEXT(CI5,"yyyy"))) -> 2027 | CM3: =CO3 -> 2027 | CO3: =IF(MONTH(CM5)<=3,TEXT(CM5,"yyyy"),IF(MONTH(CM5)>3,TEXT(CM5,"yyyy"))) -> 2027 | CQ3: =CS3 -> 2027 | CS3: =IF(MONTH(CQ5)<=3,TEXT(CQ5,"yyyy"),IF(MONTH(CQ5)>3,TEXT(CQ5,"yyyy"))) -> 2027 | CU3: =CW3 -> 2027 | CW3: =IF(MONTH(CU5)<=3,TEXT(CU5,"yyyy"),IF(MONTH(CU5)>3,TEXT(CU5,"yyyy"))) -> 2027 | CY3: =DA3 -> 2027 | DA3: =IF(MONTH(CY5)<=3,TEXT(CY5,"yyyy"),IF(MONTH(CY5)>3,TEXT(CY5,"yyyy"))) -> 2027 | DC3: =DE3 -> 2027 | DE3: =IF(MONTH(DC5)<=3,TEXT(DC5,"yyyy"),IF(MONTH(DC5)>3,TEXT(DC5,"yyyy"))) -> 2027 | DG3: =DI3 -> 2027 | DI3: =IF(MONTH(DG5)<=3,TEXT(DG5,"yyyy"),IF(MONTH(DG5)>3,TEXT(DG5,"yyyy"))) -> 2027 | DK3: =DM3 -> 2027 | DM3: =IF(MONTH(DK5)<=3,TEXT(DK5,"yyyy"),IF(MONTH(DK5)>3,TEXT(DK5,"yyyy"))) -> 2027 | DO3: =DQ3 -> 2028 | DQ3: =IF(MONTH(DO5)<=3,TEXT(DO5,"yyyy"),IF(MONTH(DO5)>3,TEXT(DO5,"yyyy"))) -> 2028 | DS3: =DU3 -> 2028 | DU3: =IF(MONTH(DS5)<=3,TEXT(DS5,"yyyy"),IF(MONTH(DS5)>3,TEXT(DS5,"yyyy"))) -> 2028 | DW3: =DY3 -> 2028 | DY3: =IF(MONTH(DW5)<=3,TEXT(DW5,"yyyy"),IF(MONTH(DW5)>3,TEXT(DW5,"yyyy"))) -> 2028 | EA3: =EC3 -> 2028 | EC3: =IF(MONTH(EA5)<=3,TEXT(EA5,"yyyy"),IF(MONTH(EA5)>3,TEXT(EA5,"yyyy"))) -> 2028 | EE3: =EG3 -> 2028 | EG3: =IF(MONTH(EE5)<=3,TEXT(EE5,"yyyy"),IF(MONTH(EE5)>3,TEXT(EE5,"yyyy"))) -> 2028 | EI3: =EK3 -> 2028 | EK3: =IF(MONTH(EI5)<=3,TEXT(EI5,"yyyy"),IF(MONTH(EI5)>3,TEXT(EI5,"yyyy"))) -> 2028 | EM3: =EO3 -> 2028 | EO3: =IF(MONTH(EM5)<=3,TEXT(EM5,"yyyy"),IF(MONTH(EM5)>3,TEXT(EM5,"yyyy"))) -> 2028 | EQ3: =ES3 -> 2028 | ES3: =IF(MONTH(EQ5)<=3,TEXT(EQ5,"yyyy"),IF(MONTH(EQ5)>3,TEXT(EQ5,"yyyy"))) -> 2028 | EU3: =EW3 -> 2028 | EW3: =IF(MONTH(EU5)<=3,TEXT(EU5,"yyyy"),IF(MONTH(EU5)>3,TEXT(EU5,"yyyy"))) -> 2028 | EY3: =FA3 -> 2028 | FA3: =IF(MONTH(EY5)<=3,TEXT(EY5,"yyyy"),IF(MONTH(EY5)>3,TEXT(EY5,"yyyy"))) -> 2028 | FC3: =FE3 -> 2028 | FE3: =IF(MONTH(FC5)<=3,TEXT(FC5,"yyyy"),IF(MONTH(FC5)>3,TEXT(FC5,"yyyy"))) -> 2028 | FG3: =FI3 -> 2028 | FI3: =IF(MONTH(FG5)<=3,TEXT(FG5,"yyyy"),IF(MONTH(FG5)>3,TEXT(FG5,"yyyy"))) -> 2028 | FK3: =FM3 -> 2029 | FM3: =IF(MONTH(FK5)<=3,TEXT(FK5,"yyyy"),IF(MONTH(FK5)>3,TEXT(FK5,"yyyy"))) -> 2029 | FO3: =FQ3 -> 2029 | FQ3: =IF(MONTH(FO5)<=3,TEXT(FO5,"yyyy"),IF(MONTH(FO5)>3,TEXT(FO5,"yyyy"))) -> 2029 | FS3: =FU3 -> 2029 | FU3: =IF(MONTH(FS5)<=3,TEXT(FS5,"yyyy"),IF(MONTH(FS5)>3,TEXT(FS5,"yyyy"))) -> 2029 | FW3: =FY3 -> 2029 | FY3: =IF(MONTH(FW5)<=3,TEXT(FW5,"yyyy"),IF(MONTH(FW5)>3,TEXT(FW5,"yyyy"))) -> 2029 | GA3: =GC3 -> 2029 | GC3: =IF(MONTH(GA5)<=3,TEXT(GA5,"yyyy"),IF(MONTH(GA5)>3,TEXT(GA5,"yyyy"))) -> 2029 | GE3: =GG3 -> 2029 | GG3: =IF(MONTH(GE5)<=3,TEXT(GE5,"yyyy"),IF(MONTH(GE5)>3,TEXT(GE5,"yyyy"))) -> 2029 | GI3: =GK3 -> 2029 | GK3: =IF(MONTH(GI5)<=3,TEXT(GI5,"yyyy"),IF(MONTH(GI5)>3,TEXT(GI5,"yyyy"))) -> 2029 | GM3: =GO3 -> 2029 | GO3: =IF(MONTH(GM5)<=3,TEXT(GM5,"yyyy"),IF(MONTH(GM5)>3,TEXT(GM5,"yyyy"))) -> 2029 | GQ3: =GS3 -> 2029 | GS3: =IF(MONTH(GQ5)<=3,TEXT(GQ5,"yyyy"),IF(MONTH(GQ5)>3,TEXT(GQ5,"yyyy"))) -> 2029 | GU3: =GW3 -> 2029 | GW3: =IF(MONTH(GU5)<=3,TEXT(GU5,"yyyy"),IF(MONTH(GU5)>3,TEXT(GU5,"yyyy"))) -> 2029 | GY3: =HA3 -> 2029 | HA3: =IF(MONTH(GY5)<=3,TEXT(GY5,"yyyy"),IF(MONTH(GY5)>3,TEXT(GY5,"yyyy"))) -> 2029 | HC3: =HE3 -> 2029 | HE3: =IF(MONTH(HC5)<=3,TEXT(HC5,"yyyy"),IF(MONTH(HC5)>3,TEXT(HC5,"yyyy"))) -> 2029 | HG3: =HI3 -> 2030 | HI3: =IF(MONTH(HG5)<=3,TEXT(HG5,"yyyy"),IF(MONTH(HG5)>3,TEXT(HG5,"yyyy"))) -> 2030 | HK3: =HM3 -> 2030 | HM3: =IF(MONTH(HK5)<=3,TEXT(HK5,"yyyy"),IF(MONTH(HK5)>3,TEXT(HK5,"yyyy"))) -> 2030 | HO3: =HQ3 -> 2030 | HQ3: =IF(MONTH(HO5)<=3,TEXT(HO5,"yyyy"),IF(MONTH(HO5)>3,TEXT(HO5,"yyyy"))) -> 2030 | HS3: =HU3 -> 2030 | HU3: =IF(MONTH(HS5)<=3,TEXT(HS5,"yyyy"),IF(MONTH(HS5)>3,TEXT(HS5,"yyyy"))) -> 2030 | HW3: =HY3 -> 2030 | HY3: =IF(MONTH(HW5)<=3,TEXT(HW5,"yyyy"),IF(MONTH(HW5)>3,TEXT(HW5,"yyyy"))) -> 2030 | IA3: =IC3 -> 2030 | IC3: =IF(MONTH(IA5)<=3,TEXT(IA5,"yyyy"),IF(MONTH(IA5)>3,TEXT(IA5,"yyyy"))) -> 2030 | IE3: =IG3 -> 2030 | IG3: =IF(MONTH(IE5)<=3,TEXT(IE5,"yyyy"),IF(MONTH(IE5)>3,TEXT(IE5,"yyyy"))) -> 2030 | II3: =IK3 -> 2030 | IK3: =IF(MONTH(II5)<=3,TEXT(II5,"yyyy"),IF(MONTH(II5)>3,TEXT(II5,"yyyy"))) -> 2030 | IM3: =IO3 -> 2030 | IO3: =IF(MONTH(IM5)<=3,TEXT(IM5,"yyyy"),IF(MONTH(IM5)>3,TEXT(IM5,"yyyy"))) -> 2030 | IQ3: =IS3 -> 2030 | IS3: =IF(MONTH(IQ5)<=3,TEXT(IQ5,"yyyy"),IF(MONTH(IQ5)>3,TEXT(IQ5,"yyyy"))) -> 2030 | IU3: =IW3 -> 2030 | IW3: =IF(MONTH(IU5)<=3,TEXT(IU5,"yyyy"),IF(MONTH(IU5)>3,TEXT(IU5,"yyyy"))) -> 2030 | IY3: =JA3 -> 2030 | JA3: =IF(MONTH(IY5)<=3,TEXT(IY5,"yyyy"),IF(MONTH(IY5)>3,TEXT(IY5,"yyyy"))) -> 2030 | JC3: =JE3 -> 2031 | JE3: =IF(MONTH(JC5)<=3,TEXT(JC5,"yyyy"),IF(MONTH(JC5)>3,TEXT(JC5,"yyyy"))) -> 2031 | JG3: =JI3 -> 2031 | JI3: =IF(MONTH(JG5)<=3,TEXT(JG5,"yyyy"),IF(MONTH(JG5)>3,TEXT(JG5,"yyyy"))) -> 2031 | JK3: =JM3 -> 2031 | JM3: =IF(MONTH(JK5)<=3,TEXT(JK5,"yyyy"),IF(MONTH(JK5)>3,TEXT(JK5,"yyyy"))) -> 2031 | JO3: =JQ3 -> 2031 | JQ3: =IF(MONTH(JO5)<=3,TEXT(JO5,"yyyy"),IF(MONTH(JO5)>3,TEXT(JO5,"yyyy"))) -> 2031 | JS3: =JU3 -> 2031 | JU3: =IF(MONTH(JS5)<=3,TEXT(JS5,"yyyy"),IF(MONTH(JS5)>3,TEXT(JS5,"yyyy"))) -> 2031 | JW3: =JY3 -> 2031 | JY3: =IF(MONTH(JW5)<=3,TEXT(JW5,"yyyy"),IF(MONTH(JW5)>3,TEXT(JW5,"yyyy"))) -> 2031 | KA3: =KC3 -> 2031 | KC3: =IF(MONTH(KA5)<=3,TEXT(KA5,"yyyy"),IF(MONTH(KA5)>3,TEXT(KA5,"yyyy"))) -> 2031 | KE3: =KG3 -> 2031 | KG3: =IF(MONTH(KE5)<=3,TEXT(KE5,"yyyy"),IF(MONTH(KE5)>3,TEXT(KE5,"yyyy"))) -> 2031
C4: Particulars | H4: Month - | I4: 1 | L4: Month - | M4: =I4+1 -> 2 | P4: Month - | Q4: =M4+1 -> 3 | T4: Month - | U4: =Q4+1 -> 4 | X4: Month - | Y4: =U4+1 -> 5 | AB4: Month - | AC4: =Y4+1 -> 6 | AF4: Month - | AG4: =AC4+1 -> 7 | AJ4: Month - | AK4: =AG4+1 -> 8 | AN4: Month - | AO4: =AK4+1 -> 9 | AR4: Month - | AS4: =AO4+1 -> 10 | AV4: Month - | AW4: =AS4+1 -> 11 | AZ4: Month - | BA4: =AW4+1 -> 12 | BD4: Month - | BE4: =BA4+1 -> 13 | BH4: Month - | BI4: =BE4+1 -> 14 | BL4: Month - | BM4: =BI4+1 -> 15 | BP4: Month - | BQ4: =BM4+1 -> 16 | BT4: Month - | BU4: =BQ4+1 -> 17 | BX4: Month - | BY4: =BU4+1 -> 18 | CB4: Month - | CC4: =BY4+1 -> 19 | CF4: Month - | CG4: =CC4+1 -> 20 | CJ4: Month - | CK4: =CG4+1 -> 21 | CN4: Month - | CO4: =CK4+1 -> 22 | CR4: Month - | CS4: =CO4+1 -> 23 | CV4: Month - | CW4: =CS4+1 -> 24 | CZ4: Month - | DA4: =CW4+1 -> 25 | DD4: Month - | DE4: =DA4+1 -> 26 | DH4: Month - | DI4: =DE4+1 -> 27 | DL4: Month - | DM4: =DI4+1 -> 28 | DP4: Month - | DQ4: =DM4+1 -> 29 | DT4: Month - | DU4: =DQ4+1 -> 30 | DX4: Month - | DY4: =DU4+1 -> 31 | EB4: Month - | EC4: =DY4+1 -> 32 | EF4: Month - | EG4: =EC4+1 -> 33 | EJ4: Month - | EK4: =EG4+1 -> 34 | EN4: Month - | EO4: =EK4+1 -> 35 | ER4: Month - | ES4: =EO4+1 -> 36 | EV4: Month - | EW4: =ES4+1 -> 37 | EZ4: Month - | FA4: =EW4+1 -> 38 | FD4: Month - | FE4: =FA4+1 -> 39 | FH4: Month - | FI4: =FE4+1 -> 40 | FL4: Month - | FM4: =FI4+1 -> 41 | FP4: Month - | FQ4: =FM4+1 -> 42 | FT4: Month - | FU4: =FQ4+1 -> 43 | FX4: Month - | FY4: =FU4+1 -> 44 | GB4: Month - | GC4: =FY4+1 -> 45 | GF4: Month - | GG4: =GC4+1 -> 46 | GJ4: Month - | GK4: =GG4+1 -> 47 | GN4: Month - | GO4: =GK4+1 -> 48 | GR4: Month - | GS4: =GO4+1 -> 49 | GV4: Month - | GW4: =GS4+1 -> 50 | GZ4: Month - | HA4: =GW4+1 -> 51 | HD4: Month - | HE4: =HA4+1 -> 52 | HH4: Month - | HI4: =HE4+1 -> 53 | HL4: Month - | HM4: =HI4+1 -> 54 | HP4: Month - | HQ4: =HM4+1 -> 55 | HT4: Month - | HU4: =HQ4+1 -> 56 | HX4: Month - | HY4: =HU4+1 -> 57 | IB4: Month - | IC4: =HY4+1 -> 58 | IF4: Month - | IG4: =IC4+1 -> 59 | IJ4: Month - | IK4: =IG4+1 -> 60 | IN4: Month - | IO4: =IK4+1 -> 61 | IR4: Month - | IS4: =IO4+1 -> 62 | IV4: Month - | IW4: =IS4+1 -> 63 | IZ4: Month - | JA4: =IW4+1 -> 64 | JD4: Month - | JE4: =JA4+1 -> 65 | JH4: Month - | JI4: =JE4+1 -> 66 | JL4: Month - | JM4: =JI4+1 -> 67 | JP4: Month - | JQ4: =JM4+1 -> 68 | JT4: Month - | JU4: =JQ4+1 -> 69 | JX4: Month - | JY4: =JU4+1 -> 70 | KB4: Month - | KC4: =JY4+1 -> 71 | KF4: Month - | KG4: =KC4+1 -> 72 | KI4: Year 1 | KM4: Year 2 | KQ4: Year 3 | KU4: Year 4 | KY4: Year 5 | LC4: Year 6
G5: =EOMONTH('2. Basics'!$D$16,1) -> 45930 | K5: =EOMONTH($G$5,1) -> 45961 | O5: =EOMONTH($G$5,2) -> 45991 | S5: =EOMONTH($G$5,3) -> 46022 | W5: =EOMONTH($G$5,4) -> 46053 | AA5: =EOMONTH($G$5,5) -> 46081 | AE5: =EOMONTH($G$5,6) -> 46112 | AI5: =EOMONTH($G$5,7) -> 46142 | AM5: =EOMONTH($G$5,8) -> 46173 | AQ5: =EOMONTH($G$5,9) -> 46203 | AU5: =EOMONTH($G$5,10) -> 46234 | AY5: =EOMONTH($G$5,11) -> 46265 | BC5: =EOMONTH($G$5,12) -> 46295 | BG5: =EOMONTH($G$5,13) -> 46326 | BK5: =EOMONTH($G$5,14) -> 46356 | BO5: =EOMONTH($G$5,15) -> 46387 | BS5: =EOMONTH($G$5,16) -> 46418 | BW5: =EOMONTH($G$5,17) -> 46446 | CA5: =EOMONTH($G$5,18) -> 46477 | CE5: =EOMONTH($G$5,19) -> 46507 | CI5: =EOMONTH($G$5,20) -> 46538 | CM5: =EOMONTH($G$5,21) -> 46568 | CQ5: =EOMONTH($G$5,22) -> 46599 | CU5: =EOMONTH($G$5,23) -> 46630 | CY5: =EOMONTH($G$5,24) -> 46660 | DC5: =EOMONTH($G$5,25) -> 46691 | DG5: =EOMONTH($G$5,26) -> 46721 | DK5: =EOMONTH($G$5,27) -> 46752 | DO5: =EOMONTH($G$5,28) -> 46783 | DS5: =EOMONTH($G$5,29) -> 46812 | DW5: =EOMONTH($G$5,30) -> 46843 | EA5: =EOMONTH($G$5,31) -> 46873 | EE5: =EOMONTH($G$5,32) -> 46904 | EI5: =EOMONTH($G$5,33) -> 46934 | EM5: =EOMONTH($G$5,34) -> 46965 | EQ5: =EOMONTH($G$5,35) -> 46996 | EU5: =EOMONTH($G$5,36) -> 47026 | EY5: =EOMONTH($G$5,37) -> 47057 | FC5: =EOMONTH($G$5,38) -> 47087 | FG5: =EOMONTH($G$5,39) -> 47118 | FK5: =EOMONTH($G$5,40) -> 47149 | FO5: =EOMONTH($G$5,41) -> 47177 | FS5: =EOMONTH($G$5,42) -> 47208 | FW5: =EOMONTH($G$5,43) -> 47238 | GA5: =EOMONTH($G$5,44) -> 47269 | GE5: =EOMONTH($G$5,45) -> 47299 | GI5: =EOMONTH($G$5,46) -> 47330 | GM5: =EOMONTH($G$5,47) -> 47361 | GQ5: =EOMONTH($G$5,48) -> 47391 | GU5: =EOMONTH($G$5,49) -> 47422 | GY5: =EOMONTH($G$5,50) -> 47452 | HC5: =EOMONTH($G$5,51) -> 47483 | HG5: =EOMONTH($G$5,52) -> 47514 | HK5: =EOMONTH($G$5,53) -> 47542 | HO5: =EOMONTH($G$5,54) -> 47573 | HS5: =EOMONTH($G$5,55) -> 47603 | HW5: =EOMONTH($G$5,56) -> 47634 | IA5: =EOMONTH($G$5,57) -> 47664 | IE5: =EOMONTH($G$5,58) -> 47695 | II5: =EOMONTH($G$5,59) -> 47726 | IM5: =EOMONTH($G$5,60) -> 47756 | IQ5: =EOMONTH($G$5,61) -> 47787 | IU5: =EOMONTH($G$5,62) -> 47817 | IY5: =EOMONTH($G$5,63) -> 47848 | JC5: =EOMONTH($G$5,64) -> 47879 | JG5: =EOMONTH($G$5,65) -> 47907 | JK5: =EOMONTH($G$5,66) -> 47938 | JO5: =EOMONTH($G$5,67) -> 47968 | JS5: =EOMONTH($G$5,68) -> 47999 | JW5: =EOMONTH($G$5,69) -> 48029 | KA5: =EOMONTH($G$5,70) -> 48060 | KE5: =EOMONTH($G$5,71) -> 48091 | KI5: 2025 | KM5: 2026 | KQ5: 2027 | KU5: 2028 | KY5: 2029 | LC5: 2030
C6: PHASE - I REVENUES | G6: Qty | H6: Per Unit Cost | I6: Total Revenue | K6: Qty | L6: Per Unit Cost | M6: Total Revenue | O6: Qty | P6: Per Unit Cost | Q6: Total Revenue | S6: Qty | T6: Per Unit Cost | U6: Total Revenue | W6: Qty | X6: Per Unit Cost | Y6: Total Revenue | AA6: Qty | AB6: Per Unit Cost | AC6: Total Revenue | AE6: Qty | AF6: Per Unit Cost | AG6: Total Revenue | AI6: Qty | AJ6: Per Unit Cost | AK6: Total Revenue | AM6: Qty | AN6: Per Unit Cost | AO6: Total Revenue | AQ6: Qty | AR6: Per Unit Cost | AS6: Total Revenue | AU6: Qty | AV6: Per Unit Cost | AW6: Total Revenue | AY6: Qty | AZ6: Per Unit Cost | BA6: Total Revenue | BC6: Qty | BD6: Per Unit Cost | BE6: Total Revenue | BG6: Qty | BH6: Per Unit Cost | BI6: Total Revenue | BK6: Qty | BL6: Per Unit Cost | BM6: Total Revenue | BO6: Qty | BP6: Per Unit Cost | BQ6: Total Revenue | BS6: Qty | BT6: Per Unit Cost | BU6: Total Revenue | BW6: Qty | BX6: Per Unit Cost | BY6: Total Revenue | CA6: Qty | CB6: Per Unit Cost | CC6: Total Revenue | CE6: Qty | CF6: Per Unit Cost | CG6: Total Revenue | CI6: Qty | CJ6: Per Unit Cost | CK6: Total Revenue | CM6: Qty | CN6: Per Unit Cost | CO6: Total Revenue | CQ6: Qty | CR6: Per Unit Cost | CS6: Total Revenue | CU6: Qty | CV6: Per Unit Cost | CW6: Total Revenue | CY6: Qty | CZ6: Per Unit Cost | DA6: Total Revenue | DC6: Qty | DD6: Per Unit Cost | DE6: Total Revenue | DG6: Qty | DH6: Per Unit Cost | DI6: Total Revenue | DK6: Qty | DL6: Per Unit Cost | DM6: Total Revenue | DO6: Qty | DP6: Per Unit Cost | DQ6: Total Revenue | DS6: Qty | DT6: Per Unit Cost | DU6: Total Revenue | DW6: Qty | DX6: Per Unit Cost | DY6: Total Revenue | EA6: Qty | EB6: Per Unit Cost | EC6: Total Revenue | EE6: Qty | EF6: Per Unit Cost | EG6: Total Revenue | EI6: Qty | EJ6: Per Unit Cost | EK6: Total Revenue | EM6: Qty | EN6: Per Unit Cost | EO6: Total Revenue | EQ6: Qty | ER6: Per Unit Cost | ES6: Total Revenue | EU6: Qty | EV6: Per Unit Cost | EW6: Total Revenue | EY6: Qty | EZ6: Per Unit Cost | FA6: Total Revenue | FC6: Qty | FD6: Per Unit Cost | FE6: Total Revenue | FG6: Qty | FH6: Per Unit Cost | FI6: Total Revenue | FK6: Qty | FL6: Per Unit Cost | FM6: Total Revenue | FO6: Qty | FP6: Per Unit Cost | FQ6: Total Revenue | FS6: Qty | FT6: Per Unit Cost | FU6: Total Revenue | FW6: Qty | FX6: Per Unit Cost | FY6: Total Revenue | GA6: Qty | GB6: Per Unit Cost | GC6: Total Revenue | GE6: Qty | GF6: Per Unit Cost | GG6: Total Revenue | GI6: Qty | GJ6: Per Unit Cost | GK6: Total Revenue | GM6: Qty | GN6: Per Unit Cost | GO6: Total Revenue | GQ6: Qty | GR6: Per Unit Cost | GS6: Total Revenue | GU6: Qty | GV6: Per Unit Cost | GW6: Total Revenue | GY6: Qty | GZ6: Per Unit Cost | HA6: Total Revenue | HC6: Qty | HD6: Per Unit Cost | HE6: Total Revenue | HG6: Qty | HH6: Per Unit Cost | HI6: Total Revenue | HK6: Qty | HL6: Per Unit Cost | HM6: Total Revenue | HO6: Qty | HP6: Per Unit Cost | HQ6: Total Revenue | HS6: Qty | HT6: Per Unit Cost | HU6: Total Revenue | HW6: Qty | HX6: Per Unit Cost | HY6: Total Revenue | IA6: Qty | IB6: Per Unit Cost | IC6: Total Revenue | IE6: Qty | IF6: Per Unit Cost | IG6: Total Revenue | II6: Qty | IJ6: Per Unit Cost | IK6: Total Revenue | IM6: Qty | IN6: Per Unit Cost | IO6: Total Revenue | IQ6: Qty | IR6: Per Unit Cost | IS6: Total Revenue | IU6: Qty | IV6: Per Unit Cost | IW6: Total Revenue | IY6: Qty | IZ6: Per Unit Cost | JA6: Total Revenue | JC6: Qty | JD6: Per Unit Cost | JE6: Total Revenue | JG6: Qty | JH6: Per Unit Cost | JI6: Total Revenue | JK6: Qty | JL6: Per Unit Cost | JM6: Total Revenue | JO6: Qty | JP6: Per Unit Cost | JQ6: Total Revenue | JS6: Qty | JT6: Per Unit Cost | JU6: Total Revenue | JW6: Qty | JX6: Per Unit Cost | JY6: Total Revenue | KA6: Qty | KB6: Per Unit Cost | KC6: Total Revenue | KE6: Qty | KF6: Per Unit Cost | KG6: Total Revenue | KI6: Qty | KJ6: Cost Per Month | KK6: Total Revenue | KM6: Qty | KN6: Cost Per Month | KO6: Total Revenue | KQ6: Qty | KR6: Cost Per Month | KS6: Total Revenue | KU6: Qty | KV6: Cost Per Month | KW6: Total Revenue | KY6: Qty | KZ6: Cost Per Month | LA6: Total Revenue | LC6: Qty | LD6: Cost Per Month | LE6: Total Revenue
C8: Services | D8: Sub Services | E8: Product | K8: 1 | L8: 1 | O8: =K8 -> 1 | P8: 1 | S8: =O8 -> 1 | T8: 1 | W8: =S8 -> 1 | X8: 1 | AA8: =W8 -> 1 | AB8: 1 | AE8: =AA8 -> 1 | AF8: 1 | AI8: =AE8+'A.I Revenue Streams - P1'!L10 -> 1.25 | AJ8: 1 | AM8: =IF(AM3=AI3,1,0) -> 1 | AN8: 1 | AQ8: =AM8 -> 1 | AR8: 1 | AU8: 1 | AV8: 1 | AY8: =AU8 -> 1 | AZ8: 1 | BC8: 1 | BD8: 1 | BG8: 1 | BH8: 1 | BK8: 1 | BL8: 1 | BO8: =BK8 -> 1 | BP8: 1 | BS8: =BO8 -> 1 | BT8: 1 | BW8: =BS8 -> 1 | BX8: 1 | CA8: =BW8 -> 1 | CB8: 1 | CE8: ='A.I Revenue Streams - P1'!N10+100% -> 1.2 | CF8: 1 | CI8: 1 | CJ8: 1 | CM8: 1 | CN8: 1 | CQ8: 1 | CR8: 1 | CU8: =CQ8 -> 1 | CV8: 1 | CY8: =CU8 -> 1 | CZ8: 1 | DC8: 1 | DD8: 1 | DG8: =DC8 -> 1 | DH8: 1 | DK8: =DG8 -> 1 | DL8: 1 | DO8: =DK8 -> 1 | DP8: 1 | DS8: =DO8 -> 1 | DT8: 1 | DW8: =DS8 -> 1 | DX8: 1 | EA8: ='A.I Revenue Streams - P1'!P10+100% -> 1.1 | EB8: 1 | EE8: 1 | EF8: 1 | EI8: 1 | EJ8: 1 | EM8: 1 | EN8: 1 | EQ8: =EM8 -> 1 | ER8: 1 | EU8: =EQ8 -> 1 | EV8: 1 | EY8: 1 | EZ8: 1 | FC8: =EY8 -> 1 | FD8: 1 | FG8: =FC8 -> 1 | FH8: 1 | FK8: =FG8 -> 1 | FL8: 1 | FO8: =FK8 -> 1 | FP8: 1 | FS8: =FO8 -> 1 | FT8: 1 | FW8: ='A.I Revenue Streams - P1'!R10+100% -> 1.1 | FX8: 1 | GA8: 1 | GB8: 1 | GE8: 1 | GF8: 1 | GI8: 1 | GJ8: 1 | GM8: =GI8 -> 1 | GN8: 1 | GQ8: 1 | GR8: 1 | GU8: 1 | GV8: 1 | GY8: =GU8 -> 1 | GZ8: 1 | HC8: =GY8 -> 1 | HD8: 1 | HG8: =HC8 -> 1 | HH8: 1 | HK8: =HG8 -> 1 | HL8: 1 | HO8: =HK8 -> 1 | HP8: 1 | HS8: ='A.I Revenue Streams - P1'!T10+100% -> 1.15 | HT8: 1 | HW8: 1 | HX8: 1 | IA8: 1 | IB8: 1 | IE8: 1 | IF8: 1 | II8: =IE8 -> 1 | IJ8: 1 | IM8: =II8 -> 1 | IN8: 1 | IQ8: =IM8 -> 1 | IR8: 1 | IU8: =IQ8 -> 1 | IV8: 1 | IY8: =IU8 -> 1 | IZ8: 1 | JC8: =IY8 -> 1 | JD8: 1 | JG8: =JC8 -> 1 | JH8: 1 | JK8: =JG8 -> 1 | JL8: 1 | JO8: ='A.I Revenue Streams - P1'!V10+100% -> 1.01 | JP8: ='A.I Revenue Streams - P1'!W10+100% -> 1 | JS8: =JP8 -> 1 | JT8: 1 | JW8: =JS8 -> 1 | JX8: 1 | KA8: =JW8 -> 1 | KB8: 1 | KE8: =KA8 -> 1 | KF8: 1 | KI8: ='A.I Revenue Streams - P2'!DI10+100% -> 1 | KJ8: 1 | KM8: ='A.I Revenue Streams - P2'!DM10+100% -> 1 | KN8: 1 | KQ8: ='A.I Revenue Streams - P2'!DQ10+100% -> 1 | KR8: 1 | KU8: ='A.I Revenue Streams - P2'!DU10+100% -> 1 | KV8: 1 | KY8: ='A.I Revenue Streams - P2'!DY10+100% -> 1 | KZ8: 1 | LC8: ='A.I Revenue Streams - P2'!EC10+100% -> 1 | LD8: 1
B9: 1 | C9: ='A.I Revenue Streams - P1'!D9 -> Clinical Revenue | D9: ='A.I Revenue Streams - P1'!E9 -> Dental
B10: 1a | E10: ='A.I Revenue Streams - P1'!F10 -> Root Canal | H10: ='A.I Revenue Streams - P1'!J10 -> Q | I10: =G10*H10 -> #VALUE! | K10: ='A.I Revenue Streams - P1'!H10*K$2*L$2 -> 3.6 | L10: =H10*$L$8 -> #VALUE! | M10: =K10*L10 -> #VALUE! | O10: =K10*O$8*O$2/K$2*P$2 -> 3.843 | P10: =L10*P$8 -> #VALUE! | Q10: =O10*P10 -> #VALUE! | S10: =O10*S$8*S$2/O$2*T$2 -> 5.8926 | T10: =P10*T$8 -> #VALUE! | U10: =S10*T10 -> #VALUE! | W10: =S10*W$8*W$2/S$2*X$2 -> 8.4706125 | X10: =T10*X$8 -> #VALUE! | Y10: =W10*X10 -> #VALUE! | AA10: =W10*AA$8*AA$2/W$2*AB$2 -> 15.585927 | AB10: =X10*AB$8 -> #VALUE! | AC10: =AA10*AB10 -> #VALUE! | AE10: =AA10*AE$8*AE$2/AA$2*AF$2 -> 22.40477 | AF10: =AB10*AF$8 -> #VALUE! | AG10: =AE10*AF10 -> #VALUE! | AI10: =AE10*AI$8*AI$2/AE$2*AJ$2 -> 32.206857 | AJ10: =AF10*AJ$8 -> #VALUE! | AK10: =AI10*AJ10 -> #VALUE! | AM10: =AI10*AM$8*AM$2/AI$2*AN$2 -> 37.037886 | AN10: =AJ10*AN$8 -> #VALUE! | AO10: =AM10*AN10 -> #VALUE! | AQ10: =AM10*AQ$8*AQ$2/AM$2*AR$2 -> 42.593568 | AR10: =AN10*AR$8 -> #VALUE! | AS10: =AQ10*AR10 -> #VALUE! | AU10: =AQ10*AU$8*AU$2/AQ$2*AV$2 -> 48.982604 | AV10: =AR10*AV$8 -> #VALUE! | AW10: =AU10*AV10 -> #VALUE! | AY10: =AU10*AY$8*AY$2/AU$2*AZ$2 -> 56.329994 | AZ10: =AV10*AZ$8 -> #VALUE! | BA10: =AY10*AZ10 -> #VALUE! | BC10: =AY10*BC$8*BC$2/AY$2*BD$2 -> 64.779493 | BD10: =AZ10*BD$8 -> #VALUE! | BE10: =BC10*BD10 -> #VALUE! | BG10: =BC10*BG$8*BG$2/BC$2*BH$2 -> 74.496417 | BH10: =BD10*BH$8 -> #VALUE! | BI10: =BG10*BH10 -> #VALUE! | BK10: =BG10*BK$8*BK$2/BG$2*BL$2 -> 85.67088 | BL10: =BH10*BL$8 -> #VALUE! | BM10: =BK10*BL10 -> #VALUE! | BO10: =BK10*BO$8*BO$2/BK$2*BP$2 -> 98.521512 | BP10: =BL10*BP$8 -> #VALUE! | BQ10: =BO10*BP10 -> #VALUE! | BS10: =BO10*BS$8*BS$2/BO$2*BT$2 -> 113.29974 | BT10: =BP10*BT$8 -> #VALUE! | BU10: =BS10*BT10 -> #VALUE! | BW10: =BS10*BW$8*BW$2/BS$2*BX$2 -> 130.2947 | BX10: =BT10*BX$8 -> #VALUE! | BY10: =BW10*BX10 -> #VALUE! | CA10: =BW10*CA$8*CA$2/BW$2*CB$2 -> 149.8389 | CB10: =BX10*CB$8 -> #VALUE! | CC10: =CA10*CB10 -> #VALUE! | CE10: =CA10*CE$8*CE$2/CA$2*CF$2 -> 206.77769 | CF10: =CB10*CF$8 -> #VALUE! | CG10: =CE10*CF10 -> #VALUE! | CI10: =CE10*CI$8*CI$2/CE$2*CJ$2 -> 237.79434 | CJ10: =CF10*CJ$8 -> #VALUE! | CK10: =CI10*CJ10 -> #VALUE! | CM10: =CI10*CM$8*CM$2/CI$2*CN$2 -> 273.46349 | CN10: =CJ10*CN$8 -> #VALUE! | CO10: =CM10*CN10 -> #VALUE! | CQ10: =CM10*CQ$8*CQ$2/CM$2*CR$2 -> 314.48302 | CR10: =CN10*CR$8 -> #VALUE! | CS10: =CQ10*CR10 -> #VALUE! | CU10: =CQ10*CU$8*CU$2/CQ$2*CV$2 -> 361.65547 | CV10: =CR10*CV$8 -> #VALUE! | CW10: =CU10*CV10 -> #VALUE! | CY10: =CU10*CY$8*CY$2/CU$2*CZ$2 -> 415.90379 | CZ10: =CV10*CZ$8 -> #VALUE! | DA10: =CY10*CZ10 -> #VALUE! | DC10: =CY10*DC$8*DC$2/CY$2*DD$2 -> 478.28936 | DD10: =CZ10*DD$8 -> #VALUE! | DE10: =DC10*DD10 -> #VALUE! | DG10: =DC10*DG$8*DG$2/DC$2*DH$2 -> 550.03276 | DH10: =DD10*DH$8 -> #VALUE! | DI10: =DG10*DH10 -> #VALUE! | DK10: =DG10*DK$8*DK$2/DG$2*DL$2 -> 632.53767 | DL10: =DH10*DL$8 -> #VALUE! | DM10: =DK10*DL10 -> #VALUE! | DO10: =DK10*DO$8*DO$2/DK$2*DP$2 -> 727.41833 | DP10: =DL10*DP$8 -> #VALUE! | DQ10: =DO10*DP10 -> #VALUE! | DS10: =DO10*DS$8*DS$2/DO$2*DT$2 -> 836.53107 | DT10: =DP10*DT$8 -> #VALUE! | DU10: =DS10*DT10 -> #VALUE! | DW10: =DS10*DW$8*DW$2/DS$2*DX$2 -> 962.01074 | DX10: =DT10*DX$8 -> #VALUE! | DY10: =DW10*DX10 -> #VALUE! | EA10: =DW10*EA$8*EA$2/DW$2*EB$2 -> 1216.9436 | EB10: =DX10*EB$8 -> #VALUE! | EC10: =EA10*EB10 -> #VALUE! | EE10: =EA10*EE$8*EE$2/EA$2*EF$2 -> 1399.4851 | EF10: =EB10*EF$8 -> #VALUE! | EG10: =EE10*EF10 -> #VALUE! | EI10: =EE10*EI$8*EI$2/EE$2*EJ$2 -> 1609.4079 | EJ10: =EF10*EJ$8 -> #VALUE! | EK10: =EI10*EJ10 -> #VALUE! | EM10: =EI10*EM$8*EM$2/EI$2*EN$2 -> 1850.8191 | EN10: =EJ10*EN$8 -> #VALUE! | EO10: =EM10*EN10 -> #VALUE! | EQ10: =EM10*EQ$8*EQ$2/EM$2*ER$2 -> 2128.4419 | ER10: =EN10*ER$8 -> #VALUE! | ES10: =EQ10*ER10 -> #VALUE! | EU10: =EQ10*EU$8*EU$2/EQ$2*EV$2 -> 2447.7082 | EV10: =ER10*EV$8 -> #VALUE! | EW10: =EU10*EV10 -> #VALUE! | EY10: =EU10*EY$8*EY$2/EU$2*EZ$2 -> 2814.8645 | EZ10: =EV10*EZ$8 -> #VALUE! | FA10: =EY10*EZ10 -> #VALUE! | FC10: =EY10*FC$8*FC$2/EY$2*FD$2 -> 3237.0941 | FD10: =EZ10*FD$8 -> #VALUE! | FE10: =FC10*FD10 -> #VALUE! | FG10: =FC10*FG$8*FG$2/FC$2*FH$2 -> 3722.6582 | FH10: =FD10*FH$8 -> #VALUE! | FI10: =FG10*FH10 -> #VALUE! | FK10: =FG10*FK$8*FK$2/FG$2*FL$2 -> 4281.057 | FL10: =FH10*FL$8 -> #VALUE! | FM10: =FK10*FL10 -> #VALUE! | FO10: =FK10*FO$8*FO$2/FK$2*FP$2 -> 4923.2155 | FP10: =FL10*FP$8 -> #VALUE! | FQ10: =FO10*FP10 -> #VALUE! | FS10: =FO10*FS$8*FS$2/FO$2*FT$2 -> 5661.6978 | FT10: =FP10*FT$8 -> #VALUE! | FU10: =FS10*FT10 -> #VALUE! | FW10: =FS10*FW$8*FW$2/FS$2*FX$2 -> 7162.0478 | FX10: =FT10*FX$8 -> #VALUE! | FY10: =FW10*FX10 -> #VALUE! | GA10: =FW10*GA$8*GA$2/FW$2*GB$2 -> 8236.3549 | GB10: =FX10*GB$8 -> #VALUE! | GC10: =GA10*GB10 -> #VALUE! | GE10: =GA10*GE$8*GE$2/GA$2*GF$2 -> 9471.8082 | GF10: =GB10*GF$8 -> #VALUE! | GG10: =GE10*GF10 -> #VALUE! | GI10: =GE10*GI$8*GI$2/GE$2*GJ$2 -> 10892.579 | GJ10: =GF10*GJ$8 -> #VALUE! | GK10: =GI10*GJ10 -> #VALUE! | GM10: =GI10*GM$8*GM$2/GI$2*GN$2 -> 12526.466 | GN10: =GJ10*GN$8 -> #VALUE! | GO10: =GM10*GN10 -> #VALUE! | GQ10: =GM10*GQ$8*GQ$2/GM$2*GR$2 -> 14405.436 | GR10: =GN10*GR$8 -> #VALUE! | GS10: =GQ10*GR10 -> #VALUE! | GU10: =GQ10*GU$8*GU$2/GQ$2*GV$2 -> 16566.252 | GV10: =GR10*GV$8 -> #VALUE! | GW10: =GU10*GV10 -> #VALUE! | GY10: =GU10*GY$8*GY$2/GU$2*GZ$2 -> 19051.189 | GZ10: =GV10*GZ$8 -> #VALUE! | HA10: =GY10*GZ10 -> #VALUE! | HC10: =GY10*HC$8*HC$2/GY$2*HD$2 -> 21908.868 | HD10: =GZ10*HD$8 -> #VALUE! | HE10: =HC10*HD10 -> #VALUE! | HG10: =HC10*HG$8*HG$2/HC$2*HH$2 -> 25195.198 | HH10: =HD10*HH$8 -> #VALUE! | HI10: =HG10*HH10 -> #VALUE! | HK10: =HG10*HK$8*HK$2/HG$2*HL$2 -> 28974.478 | HL10: =HH10*HL$8 -> #VALUE! | HM10: =HK10*HL10 -> #VALUE! | HO10: =HK10*HO$8*HO$2/HK$2*HP$2 -> 33320.649 | HP10: =HL10*HP$8 -> #VALUE! | HQ10: =HO10*HP10 -> #VALUE! | HS10: =HO10*HS$8*HS$2/HO$2*HT$2 -> 44066.559 | HT10: =HP10*HT$8 -> #VALUE! | HU10: =HS10*HT10 -> #VALUE! | HW10: =HS10*HW$8*HW$2/HS$2*HX$2 -> 50676.543 | HX10: =HT10*HX$8 -> #VALUE! | HY10: =HW10*HX10 -> #VALUE! | IA10: =HW10*IA$8*IA$2/HW$2*IB$2 -> 58278.024 | IB10: =HX10*IB$8 -> #VALUE! | IC10: =IA10*IB10 -> #VALUE! | IE10: =IA10*IE$8*IE$2/IA$2*IF$2 -> 67019.728 | IF10: =IB10*IF$8 -> #VALUE! | IG10: =IE10*IF10 -> #VALUE! | II10: =IE10*II$8*II$2/IE$2*IJ$2 -> 77072.687 | IJ10: =IF10*IJ$8 -> #VALUE! | IK10: =II10*IJ10 -> #VALUE! | IM10: =II10*IM$8*IM$2/II$2*IN$2 -> 88633.59 | IN10: =IJ10*IN$8 -> #VALUE! | IO10: =IM10*IN10 -> #VALUE! | IQ10: =IM10*IQ$8*IQ$2/IM$2*IR$2 -> 101928.63 | IR10: =IN10*IR$8 -> #VALUE! | IS10: =IQ10*IR10 -> #VALUE! | IU10: =IQ10*IU$8*IU$2/IQ$2*IV$2 -> 117217.92 | IV10: =IR10*IV$8 -> #VALUE! | IW10: =IU10*IV10 -> #VALUE! | IY10: =IU10*IY$8*IY$2/IU$2*IZ$2 -> 134800.61 | IZ10: =IV10*IZ$8 -> #VALUE! | JA10: =IY10*IZ10 -> #VALUE! | JC10: =IY10*JC$8*JC$2/IY$2*JD$2 -> 155020.7 | JD10: =IZ10*JD$8 -> #VALUE! | JE10: =JC10*JD10 -> #VALUE! | JG10: =JC10*JG$8*JG$2/JC$2*JH$2 -> 178273.81 | JH10: =JD10*JH$8 -> #VALUE! | JI10: =JG10*JH10 -> #VALUE! | JK10: =JG10*JK$8*JK$2/JG$2*JL$2 -> 205014.88 | JL10: =JH10*JL$8 -> #VALUE! | JM10: =JK10*JL10 -> #VALUE! | JO10: =JK10*JO$8*JO$2/JK$2*JP$2 -> 238124.78 | JP10: =JL10*JP$8 -> #VALUE! | JQ10: =JO10*JP10 -> #VALUE! | JS10: =JO10*JS$8*JS$2/JO$2*JT$2 -> 273843.5 | JT10: =JP10*JT$8 -> #VALUE! | JU10: =JS10*JT10 -> #VALUE! | JW10: =JS10*JW$8*JW$2/JS$2*JX$2 -> 314920.02 | JX10: =JT10*JX$8 -> #VALUE! | JY10: =JW10*JX10 -> #VALUE! | KA10: =JW10*KA$8*KA$2/JW$2*KB$2 -> 362158.03 | KB10: =JX10*KB$8 -> #VALUE! | KC10: =KA10*KB10 -> #VALUE! | KE10: =KA10*KE$8*KE$2/KA$2*KF$2 -> 416481.73 | KF10: =KB10*KF$8 -> #VALUE! | KG10: =KE10*KF10 -> #VALUE! | KI10: =SUMIFS($G10:$KG10,$G$3:$KG$3,KI$5,$G$6:$KG$6,KI$6) -> 13.3356 | KJ10: =KK10/KI10 -> #VALUE! | KK10: =SUMIFS($G10:$KG10,$G$3:$KG$3,KI$5,$G$6:$KG$6,KK$6) -> #VALUE! | KM10: =SUMIFS($G10:$KG10,$G$3:$KG$3,KM$5,$G$6:$KG$6,KM$6) -> 587.08052 | KN10: =KO10/KM10 -> #VALUE! | KO10: =SUMIFS($G10:$KG10,$G$3:$KG$3,KM$5,$G$6:$KG$6,KO$6) -> #VALUE! | KQ10: =SUMIFS($G10:$KG10,$G$3:$KG$3,KQ$5,$G$6:$KG$6,KQ$6) -> 3864.3709 | KR10: =KS10/KQ10 -> #VALUE! | KS10: =SUMIFS($G10:$KG10,$G$3:$KG$3,KQ$5,$G$6:$KG$6,KS$6) -> #VALUE! | KU10: =SUMIFS($G10:$KG10,$G$3:$KG$3,KU$5,$G$6:$KG$6,KU$6) -> 22953.383 | KV10: =KW10/KU10 -> #VALUE! | KW10: =SUMIFS($G10:$KG10,$G$3:$KG$3,KU$5,$G$6:$KG$6,KW$6) -> #VALUE! | KY10: =SUMIFS($G10:$KG10,$G$3:$KG$3,KY$5,$G$6:$KG$6,KY$6) -> 135086.97 | KZ10: =LA10/KY10 -> #VALUE! | LA10: =SUMIFS($G10:$KG10,$G$3:$KG$3,KY$5,$G$6:$KG$6,LA$6) -> #VALUE! | LC10: =SUMIFS($G10:$KG10,$G$3:$KG$3,LC$5,$G$6:$KG$6,LC$6) -> 827184.62 | LD10: =LE10/LC10 -> #VALUE! | LE10: =SUMIFS($G10:$KG10,$G$3:$KG$3,LC$5,$G$6:$KG$6,LE$6) -> #VALUE!
B11: 1b | E11: ='A.I Revenue Streams - P1'!F11 -> Teeth Extraction | H11: ='A.I Revenue Streams - P1'!J11 -> 1500 | I11: =G11*H11 -> 0 | K11: ='A.I Revenue Streams - P1'!H11*K$2*L$2 -> 3.6 | L11: =H11*$L$8 -> 1500 | M11: =K11*L11 -> 5400 | O11: =K11*O$8*O$2/K$2*P$2 -> 3.843 | P11: =L11*P$8 -> 1500 | Q11: =O11*P11 -> 5764.5 | S11: =O11*S$8*S$2/O$2*T$2 -> 5.8926 | T11: =P11*T$8 -> 1500 | U11: =S11*T11 -> 8838.9 | W11: =S11*W$8*W$2/S$2*X$2 -> 8.4706125 | X11: =T11*X$8 -> 1500 | Y11: =W11*X11 -> 12705.919 | AA11: =W11*AA$8*AA$2/W$2*AB$2 -> 15.585927 | AB11: =X11*AB$8 -> 1500 | AC11: =AA11*AB11 -> 23378.89 | AE11: =AA11*AE$8*AE$2/AA$2*AF$2 -> 22.40477 | AF11: =AB11*AF$8 -> 1500 | AG11: =AE11*AF11 -> 33607.155 | AI11: =AE11*AI$8*AI$2/AE$2*AJ$2 -> 32.206857 | AJ11: =AF11*AJ$8 -> 1500 | AK11: =AI11*AJ11 -> 48310.285 | AM11: =AI11*AM$8*AM$2/AI$2*AN$2 -> 37.037886 | AN11: =AJ11*AN$8 -> 1500 | AO11: =AM11*AN11 -> 55556.828 | AQ11: =AM11*AQ$8*AQ$2/AM$2*AR$2 -> 42.593568 | AR11: =AN11*AR$8 -> 1500 | AS11: =AQ11*AR11 -> 63890.353 | AU11: =AQ11*AU$8*AU$2/AQ$2*AV$2 -> 48.982604 | AV11: =AR11*AV$8 -> 1500 | AW11: =AU11*AV11 -> 73473.905 | AY11: =AU11*AY$8*AY$2/AU$2*AZ$2 -> 56.329994 | AZ11: =AV11*AZ$8 -> 1500 | BA11: =AY11*AZ11 -> 84494.991 | BC11: =AY11*BC$8*BC$2/AY$2*BD$2 -> 64.779493 | BD11: =AZ11*BD$8 -> 1500 | BE11: =BC11*BD11 -> 97169.24 | BG11: =BC11*BG$8*BG$2/BC$2*BH$2 -> 74.496417 | BH11: =BD11*BH$8 -> 1500 | BI11: =BG11*BH11 -> 111744.63 | BK11: =BG11*BK$8*BK$2/BG$2*BL$2 -> 85.67088 | BL11: =BH11*BL$8 -> 1500 | BM11: =BK11*BL11 -> 128506.32 | BO11: =BK11*BO$8*BO$2/BK$2*BP$2 -> 98.521512 | BP11: =BL11*BP$8 -> 1500 | BQ11: =BO11*BP11 -> 147782.27 | BS11: =BO11*BS$8*BS$2/BO$2*BT$2 -> 113.29974 | BT11: =BP11*BT$8 -> 1500 | BU11: =BS11*BT11 -> 169949.61 | BW11: =BS11*BW$8*BW$2/BS$2*BX$2 -> 130.2947 | BX11: =BT11*BX$8 -> 1500 | BY11: =BW11*BX11 -> 195442.05 | CA11: =BW11*CA$8*CA$2/BW$2*CB$2 -> 149.8389 | CB11: =BX11*CB$8 -> 1500 | CC11: =CA11*CB11 -> 224758.36 | CE11: =CA11*CE$8*CE$2/CA$2*CF$2 -> 206.77769 | CF11: =CB11*CF$8 -> 1500 | CG11: =CE11*CF11 -> 310166.53 | CI11: =CE11*CI$8*CI$2/CE$2*CJ$2 -> 237.79434 | CJ11: =CF11*CJ$8 -> 1500 | CK11: =CI11*CJ11 -> 356691.51 | CM11: =CI11*CM$8*CM$2/CI$2*CN$2 -> 273.46349 | CN11: =CJ11*CN$8 -> 1500 | CO11: =CM11*CN11 -> 410195.24 | CQ11: =CM11*CQ$8*CQ$2/CM$2*CR$2 -> 314.48302 | CR11: =CN11*CR$8 -> 1500 | CS11: =CQ11*CR11 -> 471724.52 | CU11: =CQ11*CU$8*CU$2/CQ$2*CV$2 -> 361.65547 | CV11: =CR11*CV$8 -> 1500 | CW11: =CU11*CV11 -> 542483.2 | CY11: =CU11*CY$8*CY$2/CU$2*CZ$2 -> 415.90379 | CZ11: =CV11*CZ$8 -> 1500 | DA11: =CY11*CZ11 -> 623855.68 | DC11: =CY11*DC$8*DC$2/CY$2*DD$2 -> 478.28936 | DD11: =CZ11*DD$8 -> 1500 | DE11: =DC11*DD11 -> 717434.04 | DG11: =DC11*DG$8*DG$2/DC$2*DH$2 -> 550.03276 | DH11: =DD11*DH$8 -> 1500 | DI11: =DG11*DH11 -> 825049.14 | DK11: =DG11*DK$8*DK$2/DG$2*DL$2 -> 632.53767 | DL11: =DH11*DL$8 -> 1500 | DM11: =DK11*DL11 -> 948806.51 | DO11: =DK11*DO$8*DO$2/DK$2*DP$2 -> 727.41833 | DP11: =DL11*DP$8 -> 1500 | DQ11: =DO11*DP11 -> 1091127.5 | DS11: =DO11*DS$8*DS$2/DO$2*DT$2 -> 836.53107 | DT11: =DP11*DT$8 -> 1500 | DU11: =DS11*DT11 -> 1254796.6 | DW11: =DS11*DW$8*DW$2/DS$2*DX$2 -> 962.01074 | DX11: =DT11*DX$8 -> 1500 | DY11: =DW11*DX11 -> 1443016.1 | EA11: =DW11*EA$8*EA$2/DW$2*EB$2 -> 1216.9436 | EB11: =DX11*EB$8 -> 1500 | EC11: =EA11*EB11 -> 1825415.4 | EE11: =EA11*EE$8*EE$2/EA$2*EF$2 -> 1399.4851 | EF11: =EB11*EF$8 -> 1500 | EG11: =EE11*EF11 -> 2099227.7 | EI11: =EE11*EI$8*EI$2/EE$2*EJ$2 -> 1609.4079 | EJ11: =EF11*EJ$8 -> 1500 | EK11: =EI11*EJ11 -> 2414111.8 | EM11: =EI11*EM$8*EM$2/EI$2*EN$2 -> 1850.8191 | EN11: =EJ11*EN$8 -> 1500 | EO11: =EM11*EN11 -> 2776228.6 | EQ11: =EM11*EQ$8*EQ$2/EM$2*ER$2 -> 2128.4419 | ER11: =EN11*ER$8 -> 1500 | ES11: =EQ11*ER11 -> 3192662.9 | EU11: =EQ11*EU$8*EU$2/EQ$2*EV$2 -> 2447.7082 | EV11: =ER11*EV$8 -> 1500 | EW11: =EU11*EV11 -> 3671562.3 | EY11: =EU11*EY$8*EY$2/EU$2*EZ$2 -> 2814.8645 | EZ11: =EV11*EZ$8 -> 1500 | FA11: =EY11*EZ11 -> 4222296.7 | FC11: =EY11*FC$8*FC$2/EY$2*FD$2 -> 3237.0941 | FD11: =EZ11*FD$8 -> 1500 | FE11: =FC11*FD11 -> 4855641.2 | FG11: =FC11*FG$8*FG$2/FC$2*FH$2 -> 3722.6582 | FH11: =FD11*FH$8 -> 1500 | FI11: =FG11*FH11 -> 5583987.4 | FK11: =FG11*FK$8*FK$2/FG$2*FL$2 -> 4281.057 | FL11: =FH11*FL$8 -> 1500 | FM11: =FK11*FL11 -> 6421585.5 | FO11: =FK11*FO$8*FO$2/FK$2*FP$2 -> 4923.2155 | FP11: =FL11*FP$8 -> 1500 | FQ11: =FO11*FP11 -> 7384823.3 | FS11: =FO11*FS$8*FS$2/FO$2*FT$2 -> 5661.6978 | FT11: =FP11*FT$8 -> 1500 | FU11: =FS11*FT11 -> 8492546.8 | FW11: =FS11*FW$8*FW$2/FS$2*FX$2 -> 7162.0478 | FX11: =FT11*FX$8 -> 1500 | FY11: =FW11*FX11 -> 10743072 | GA11: =FW11*GA$8*GA$2/FW$2*GB$2 -> 8236.3549 | GB11: =FX11*GB$8 -> 1500 | GC11: =GA11*GB11 -> 12354532 | GE11: =GA11*GE$8*GE$2/GA$2*GF$2 -> 9471.8082 | GF11: =GB11*GF$8 -> 1500 | GG11: =GE11*GF11 -> 14207712 | GI11: =GE11*GI$8*GI$2/GE$2*GJ$2 -> 10892.579 | GJ11: =GF11*GJ$8 -> 1500 | GK11: =GI11*GJ11 -> 16338869 | GM11: =GI11*GM$8*GM$2/GI$2*GN$2 -> 12526.466 | GN11: =GJ11*GN$8 -> 1500 | GO11: =GM11*GN11 -> 18789699 | GQ11: =GM11*GQ$8*GQ$2/GM$2*GR$2 -> 14405.436 | GR11: =GN11*GR$8 -> 1500 | GS11: =GQ11*GR11 -> 21608154 | GU11: =GQ11*GU$8*GU$2/GQ$2*GV$2 -> 16566.252 | GV11: =GR11*GV$8 -> 1500 | GW11: =GU11*GV11 -> 24849378 | GY11: =GU11*GY$8*GY$2/GU$2*GZ$2 -> 19051.189 | GZ11: =GV11*GZ$8 -> 1500 | HA11: =GY11*GZ11 -> 28576784 | HC11: =GY11*HC$8*HC$2/GY$2*HD$2 -> 21908.868 | HD11: =GZ11*HD$8 -> 1500 | HE11: =HC11*HD11 -> 32863302 | HG11: =HC11*HG$8*HG$2/HC$2*HH$2 -> 25195.198 | HH11: =HD11*HH$8 -> 1500 | HI11: =HG11*HH11 -> 37792797 | HK11: =HG11*HK$8*HK$2/HG$2*HL$2 -> 28974.478 | HL11: =HH11*HL$8 -> 1500 | HM11: =HK11*HL11 -> 43461717 | HO11: =HK11*HO$8*HO$2/HK$2*HP$2 -> 33320.649 | HP11: =HL11*HP$8 -> 1500 | HQ11: =HO11*HP11 -> 49980974 | HS11: =HO11*HS$8*HS$2/HO$2*HT$2 -> 44066.559 | HT11: =HP11*HT$8 -> 1500 | HU11: =HS11*HT11 -> 66099838 | HW11: =HS11*HW$8*HW$2/HS$2*HX$2 -> 50676.543 | HX11: =HT11*HX$8 -> 1500 | HY11: =HW11*HX11 -> 76014814 | IA11: =HW11*IA$8*IA$2/HW$2*IB$2 -> 58278.024 | IB11: =HX11*IB$8 -> 1500 | IC11: =IA11*IB11 -> 87417036 | IE11: =IA11*IE$8*IE$2/IA$2*IF$2 -> 67019.728 | IF11: =IB11*IF$8 -> 1500 | IG11: =IE11*IF11 -> 1.0052959e+08 | II11: =IE11*II$8*II$2/IE$2*IJ$2 -> 77072.687 | IJ11: =IF11*IJ$8 -> 1500 | IK11: =II11*IJ11 -> 1.1560903e+08 | IM11: =II11*IM$8*IM$2/II$2*IN$2 -> 88633.59 | IN11: =IJ11*IN$8 -> 1500 | IO11: =IM11*IN11 -> 1.3295038e+08 | IQ11: =IM11*IQ$8*IQ$2/IM$2*IR$2 -> 101928.63 | IR11: =IN11*IR$8 -> 1500 | IS11: =IQ11*IR11 -> 1.5289294e+08 | IU11: =IQ11*IU$8*IU$2/IQ$2*IV$2 -> 117217.92 | IV11: =IR11*IV$8 -> 1500 | IW11: =IU11*IV11 -> 1.7582688e+08 | IY11: =IU11*IY$8*IY$2/IU$2*IZ$2 -> 134800.61 | IZ11: =IV11*IZ$8 -> 1500 | JA11: =IY11*IZ11 -> 2.0220092e+08 | JC11: =IY11*JC$8*JC$2/IY$2*JD$2 -> 155020.7 | JD11: =IZ11*JD$8 -> 1500 | JE11: =JC11*JD11 -> 2.3253105e+08 | JG11: =JC11*JG$8*JG$2/JC$2*JH$2 -> 178273.81 | JH11: =JD11*JH$8 -> 1500 | JI11: =JG11*JH11 -> 2.6741071e+08 | JK11: =JG11*JK$8*JK$2/JG$2*JL$2 -> 205014.88 | JL11: =JH11*JL$8 -> 1500 | JM11: =JK11*JL11 -> 3.0752232e+08 | JO11: =JK11*JO$8*JO$2/JK$2*JP$2 -> 238124.78 | JP11: =JL11*JP$8 -> 1500 | JQ11: =JO11*JP11 -> 3.5718717e+08 | JS11: =JO11*JS$8*JS$2/JO$2*JT$2 -> 273843.5 | JT11: =JP11*JT$8 -> 1500 | JU11: =JS11*JT11 -> 4.1076525e+08 | JW11: =JS11*JW$8*JW$2/JS$2*JX$2 -> 314920.02 | JX11: =JT11*JX$8 -> 1500 | JY11: =JW11*JX11 -> 4.7238004e+08 | KA11: =JW11*KA$8*KA$2/JW$2*KB$2 -> 362158.03 | KB11: =JX11*KB$8 -> 1500 | KC11: =KA11*KB11 -> 5.4323704e+08 | KE11: =KA11*KE$8*KE$2/KA$2*KF$2 -> 416481.73 | KF11: =KB11*KF$8 -> 1500 | KG11: =KE11*KF11 -> 6.247226e+08 | KI11: =SUMIFS($G11:$KG11,$G$3:$KG$3,KI$5,$G$6:$KG$6,KI$6) -> 13.3356 | KJ11: =KK11/KI11 -> 1500 | KK11: =SUMIFS($G11:$KG11,$G$3:$KG$3,KI$5,$G$6:$KG$6,KK$6) -> 20003.4 | KM11: =SUMIFS($G11:$KG11,$G$3:$KG$3,KM$5,$G$6:$KG$6,KM$6) -> 587.08052 | KN11: =KO11/KM11 -> 1500 | KO11: =SUMIFS($G11:$KG11,$G$3:$KG$3,KM$5,$G$6:$KG$6,KO$6) -> 880620.78 | KQ11: =SUMIFS($G11:$KG11,$G$3:$KG$3,KQ$5,$G$6:$KG$6,KQ$6) -> 3864.3709 | KR11: =KS11/KQ11 -> 1500 | KS11: =SUMIFS($G11:$KG11,$G$3:$KG$3,KQ$5,$G$6:$KG$6,KS$6) -> 5796556.4 | KU11: =SUMIFS($G11:$KG11,$G$3:$KG$3,KU$5,$G$6:$KG$6,KU$6) -> 22953.383 | KV11: =KW11/KU11 -> 1500 | KW11: =SUMIFS($G11:$KG11,$G$3:$KG$3,KU$5,$G$6:$KG$6,KW$6) -> 34430074 | KY11: =SUMIFS($G11:$KG11,$G$3:$KG$3,KY$5,$G$6:$KG$6,KY$6) -> 135086.97 | KZ11: =LA11/KY11 -> 1500 | LA11: =SUMIFS($G11:$KG11,$G$3:$KG$3,KY$5,$G$6:$KG$6,LA$6) -> 2.0263046e+08 | LC11: =SUMIFS($G11:$KG11,$G$3:$KG$3,LC$5,$G$6:$KG$6,LC$6) -> 827184.62 | LD11: =LE11/LC11 -> 1500 | LE11: =SUMIFS($G11:$KG11,$G$3:$KG$3,LC$5,$G$6:$KG$6,LE$6) -> 1.2407769e+09
B12: 1c | E12: ='A.I Revenue Streams - P1'!F12 -> Wisdom tooth Removal | H12: ='A.I Revenue Streams - P1'!J12 -> 5500 | I12: =G12*H12 -> 0 | K12: ='A.I Revenue Streams - P1'!H12*K$2*L$2 -> 1.8 | L12: =H12*$L$8 -> 5500 | M12: =K12*L12 -> 9900 | O12: =K12*O$8*O$2/K$2*P$2 -> 1.9215 | P12: =L12*P$8 -> 5500 | Q12: =O12*P12 -> 10568.25 | S12: =O12*S$8*S$2/O$2*T$2 -> 2.9463 | T12: =P12*T$8 -> 5500 | U12: =S12*T12 -> 16204.65 | W12: =S12*W$8*W$2/S$2*X$2 -> 4.2353062 | X12: =T12*X$8 -> 5500 | Y12: =W12*X12 -> 23294.184 | AA12: =W12*AA$8*AA$2/W$2*AB$2 -> 7.7929635 | AB12: =X12*AB$8 -> 5500 | AC12: =AA12*AB12 -> 42861.299 | AE12: =AA12*AE$8*AE$2/AA$2*AF$2 -> 11.202385 | AF12: =AB12*AF$8 -> 5500 | AG12: =AE12*AF12 -> 61613.118 | AI12: =AE12*AI$8*AI$2/AE$2*AJ$2 -> 16.103428 | AJ12: =AF12*AJ$8 -> 5500 | AK12: =AI12*AJ12 -> 88568.857 | AM12: =AI12*AM$8*AM$2/AI$2*AN$2 -> 18.518943 | AN12: =AJ12*AN$8 -> 5500 | AO12: =AM12*AN12 -> 101854.19 | AQ12: =AM12*AQ$8*AQ$2/AM$2*AR$2 -> 21.296784 | AR12: =AN12*AR$8 -> 5500 | AS12: =AQ12*AR12 -> 117132.31 | AU12: =AQ12*AU$8*AU$2/AQ$2*AV$2 -> 24.491302 | AV12: =AR12*AV$8 -> 5500 | AW12: =AU12*AV12 -> 134702.16 | AY12: =AU12*AY$8*AY$2/AU$2*AZ$2 -> 28.164997 | AZ12: =AV12*AZ$8 -> 5500 | BA12: =AY12*AZ12 -> 154907.48 | BC12: =AY12*BC$8*BC$2/AY$2*BD$2 -> 32.389747 | BD12: =AZ12*BD$8 -> 5500 | BE12: =BC12*BD12 -> 178143.61 | BG12: =BC12*BG$8*BG$2/BC$2*BH$2 -> 37.248209 | BH12: =BD12*BH$8 -> 5500 | BI12: =BG12*BH12 -> 204865.15 | BK12: =BG12*BK$8*BK$2/BG$2*BL$2 -> 42.83544 | BL12: =BH12*BL$8 -> 5500 | BM12: =BK12*BL12 -> 235594.92 | BO12: =BK12*BO$8*BO$2/BK$2*BP$2 -> 49.260756 | BP12: =BL12*BP$8 -> 5500 | BQ12: =BO12*BP12 -> 270934.16 | BS12: =BO12*BS$8*BS$2/BO$2*BT$2 -> 56.649869 | BT12: =BP12*BT$8 -> 5500 | BU12: =BS12*BT12 -> 311574.28 | BW12: =BS12*BW$8*BW$2/BS$2*BX$2 -> 65.14735 | BX12: =BT12*BX$8 -> 5500 | BY12: =BW12*BX12 -> 358310.42 | CA12: =BW12*CA$8*CA$2/BW$2*CB$2 -> 74.919452 | CB12: =BX12*CB$8 -> 5500 | CC12: =CA12*CB12 -> 412056.99 | CE12: =CA12*CE$8*CE$2/CA$2*CF$2 -> 103.38884 | CF12: =CB12*CF$8 -> 5500 | CG12: =CE12*CF12 -> 568638.64 | CI12: =CE12*CI$8*CI$2/CE$2*CJ$2 -> 118.89717 | CJ12: =CF12*CJ$8 -> 5500 | CK12: =CI12*CJ12 -> 653934.44 | CM12: =CI12*CM$8*CM$2/CI$2*CN$2 -> 136.73175 | CN12: =CJ12*CN$8 -> 5500 | CO12: =CM12*CN12 -> 752024.6 | CQ12: =CM12*CQ$8*CQ$2/CM$2*CR$2 -> 157.24151 | CR12: =CN12*CR$8 -> 5500 | CS12: =CQ12*CR12 -> 864828.29 | CU12: =CQ12*CU$8*CU$2/CQ$2*CV$2 -> 180.82773 | CV12: =CR12*CV$8 -> 5500 | CW12: =CU12*CV12 -> 994552.54 | CY12: =CU12*CY$8*CY$2/CU$2*CZ$2 -> 207.95189 | CZ12: =CV12*CZ$8 -> 5500 | DA12: =CY12*CZ12 -> 1143735.4 | DC12: =CY12*DC$8*DC$2/CY$2*DD$2 -> 239.14468 | DD12: =CZ12*DD$8 -> 5500 | DE12: =DC12*DD12 -> 1315295.7 | DG12: =DC12*DG$8*DG$2/DC$2*DH$2 -> 275.01638 | DH12: =DD12*DH$8 -> 5500 | DI12: =DG12*DH12 -> 1512590.1 | DK12: =DG12*DK$8*DK$2/DG$2*DL$2 -> 316.26884 | DL12: =DH12*DL$8 -> 5500 | DM12: =DK12*DL12 -> 1739478.6 | DO12: =DK12*DO$8*DO$2/DK$2*DP$2 -> 363.70916 | DP12: =DL12*DP$8 -> 5500 | DQ12: =DO12*DP12 -> 2000400.4 | DS12: =DO12*DS$8*DS$2/DO$2*DT$2 -> 418.26554 | DT12: =DP12*DT$8 -> 5500 | DU12: =DS12*DT12 -> 2300460.5 | DW12: =DS12*DW$8*DW$2/DS$2*DX$2 -> 481.00537 | DX12: =DT12*DX$8 -> 5500 | DY12: =DW12*DX12 -> 2645529.5 | EA12: =DW12*EA$8*EA$2/DW$2*EB$2 -> 608.47179 | EB12: =DX12*EB$8 -> 5500 | EC12: =EA12*EB12 -> 3346594.8 | EE12: =EA12*EE$8*EE$2/EA$2*EF$2 -> 699.74256 | EF12: =EB12*EF$8 -> 5500 | EG12: =EE12*EF12 -> 3848584.1 | EI12: =EE12*EI$8*EI$2/EE$2*EJ$2 -> 804.70394 | EJ12: =EF12*EJ$8 -> 5500 | EK12: =EI12*EJ12 -> 4425871.7 | EM12: =EI12*EM$8*EM$2/EI$2*EN$2 -> 925.40953 | EN12: =EJ12*EN$8 -> 5500 | EO12: =EM12*EN12 -> 5089752.4 | EQ12: =EM12*EQ$8*EQ$2/EM$2*ER$2 -> 1064.221 | ER12: =EN12*ER$8 -> 5500 | ES12: =EQ12*ER12 -> 5853215.3 | EU12: =EQ12*EU$8*EU$2/EQ$2*EV$2 -> 1223.8541 | EV12: =ER12*EV$8 -> 5500 | EW12: =EU12*EV12 -> 6731197.6 | EY12: =EU12*EY$8*EY$2/EU$2*EZ$2 -> 1407.4322 | EZ12: =EV12*EZ$8 -> 5500 | FA12: =EY12*EZ12 -> 7740877.2 | FC12: =EY12*FC$8*FC$2/EY$2*FD$2 -> 1618.5471 | FD12: =EZ12*FD$8 -> 5500 | FE12: =FC12*FD12 -> 8902008.8 | FG12: =FC12*FG$8*FG$2/FC$2*FH$2 -> 1861.3291 | FH12: =FD12*FH$8 -> 5500 | FI12: =FG12*FH12 -> 10237310 | FK12: =FG12*FK$8*FK$2/FG$2*FL$2 -> 2140.5285 | FL12: =FH12*FL$8 -> 5500 | FM12: =FK12*FL12 -> 11772907 | FO12: =FK12*FO$8*FO$2/FK$2*FP$2 -> 2461.6078 | FP12: =FL12*FP$8 -> 5500 | FQ12: =FO12*FP12 -> 13538843 | FS12: =FO12*FS$8*FS$2/FO$2*FT$2 -> 2830.8489 | FT12: =FP12*FT$8 -> 5500 | FU12: =FS12*FT12 -> 15569669 | FW12: =FS12*FW$8*FW$2/FS$2*FX$2 -> 3581.0239 | FX12: =FT12*FX$8 -> 5500 | FY12: =FW12*FX12 -> 19695631 | GA12: =FW12*GA$8*GA$2/FW$2*GB$2 -> 4118.1775 | GB12: =FX12*GB$8 -> 5500 | GC12: =GA12*GB12 -> 22649976 | GE12: =GA12*GE$8*GE$2/GA$2*GF$2 -> 4735.9041 | GF12: =GB12*GF$8 -> 5500 | GG12: =GE12*GF12 -> 26047472 | GI12: =GE12*GI$8*GI$2/GE$2*GJ$2 -> 5446.2897 | GJ12: =GF12*GJ$8 -> 5500 | GK12: =GI12*GJ12 -> 29954593 | GM12: =GI12*GM$8*GM$2/GI$2*GN$2 -> 6263.2332 | GN12: =GJ12*GN$8 -> 5500 | GO12: =GM12*GN12 -> 34447782 | GQ12: =GM12*GQ$8*GQ$2/GM$2*GR$2 -> 7202.7181 | GR12: =GN12*GR$8 -> 5500 | GS12: =GQ12*GR12 -> 39614950 | GU12: =GQ12*GU$8*GU$2/GQ$2*GV$2 -> 8283.1259 | GV12: =GR12*GV$8 -> 5500 | GW12: =GU12*GV12 -> 45557192 | GY12: =GU12*GY$8*GY$2/GU$2*GZ$2 -> 9525.5947 | GZ12: =GV12*GZ$8 -> 5500 | HA12: =GY12*GZ12 -> 52390771 | HC12: =GY12*HC$8*HC$2/GY$2*HD$2 -> 10954.434 | HD12: =GZ12*HD$8 -> 5500 | HE12: =HC12*HD12 -> 60249387 | HG12: =HC12*HG$8*HG$2/HC$2*HH$2 -> 12597.599 | HH12: =HD12*HH$8 -> 5500 | HI12: =HG12*HH12 -> 69286795 | HK12: =HG12*HK$8*HK$2/HG$2*HL$2 -> 14487.239 | HL12: =HH12*HL$8 -> 5500 | HM12: =HK12*HL12 -> 79679814 | HO12: =HK12*HO$8*HO$2/HK$2*HP$2 -> 16660.325 | HP12: =HL12*HP$8 -> 5500 | HQ12: =HO12*HP12 -> 91631786 | HS12: =HO12*HS$8*HS$2/HO$2*HT$2 -> 22033.279 | HT12: =HP12*HT$8 -> 5500 | HU12: =HS12*HT12 -> 1.2118304e+08 | HW12: =HS12*HW$8*HW$2/HS$2*HX$2 -> 25338.271 | HX12: =HT12*HX$8 -> 5500 | HY12: =HW12*HX12 -> 1.3936049e+08 | IA12: =HW12*IA$8*IA$2/HW$2*IB$2 -> 29139.012 | IB12: =HX12*IB$8 -> 5500 | IC12: =IA12*IB12 -> 1.6026457e+08 | IE12: =IA12*IE$8*IE$2/IA$2*IF$2 -> 33509.864 | IF12: =IB12*IF$8 -> 5500 | IG12: =IE12*IF12 -> 1.8430425e+08 | II12: =IE12*II$8*II$2/IE$2*IJ$2 -> 38536.343 | IJ12: =IF12*IJ$8 -> 5500 | IK12: =II12*IJ12 -> 2.1194989e+08 | IM12: =II12*IM$8*IM$2/II$2*IN$2 -> 44316.795 | IN12: =IJ12*IN$8 -> 5500 | IO12: =IM12*IN12 -> 2.4374237e+08 | IQ12: =IM12*IQ$8*IQ$2/IM$2*IR$2 -> 50964.314 | IR12: =IN12*IR$8 -> 5500 | IS12: =IQ12*IR12 -> 2.8030373e+08 | IU12: =IQ12*IU$8*IU$2/IQ$2*IV$2 -> 58608.961 | IV12: =IR12*IV$8 -> 5500 | IW12: =IU12*IV12 -> 3.2234929e+08 | IY12: =IU12*IY$8*IY$2/IU$2*IZ$2 -> 67400.306 | IZ12: =IV12*IZ$8 -> 5500 | JA12: =IY12*IZ12 -> 3.7070168e+08 | JC12: =IY12*JC$8*JC$2/IY$2*JD$2 -> 77510.351 | JD12: =IZ12*JD$8 -> 5500 | JE12: =JC12*JD12 -> 4.2630693e+08 | JG12: =JC12*JG$8*JG$2/JC$2*JH$2 -> 89136.904 | JH12: =JD12*JH$8 -> 5500 | JI12: =JG12*JH12 -> 4.9025297e+08 | JK12: =JG12*JK$8*JK$2/JG$2*JL$2 -> 102507.44 | JL12: =JH12*JL$8 -> 5500 | JM12: =JK12*JL12 -> 5.6379092e+08 | JO12: =JK12*JO$8*JO$2/JK$2*JP$2 -> 119062.39 | JP12: =JL12*JP$8 -> 5500 | JQ12: =JO12*JP12 -> 6.5484315e+08 | JS12: =JO12*JS$8*JS$2/JO$2*JT$2 -> 136921.75 | JT12: =JP12*JT$8 -> 5500 | JU12: =JS12*JT12 -> 7.5306962e+08 | JW12: =JS12*JW$8*JW$2/JS$2*JX$2 -> 157460.01 | JX12: =JT12*JX$8 -> 5500 | JY12: =JW12*JX12 -> 8.6603007e+08 | KA12: =JW12*KA$8*KA$2/JW$2*KB$2 -> 181079.01 | KB12: =JX12*KB$8 -> 5500 | KC12: =KA12*KB12 -> 9.9593458e+08 | KE12: =KA12*KE$8*KE$2/KA$2*KF$2 -> 208240.87 | KF12: =KB12*KF$8 -> 5500 | KG12: =KE12*KF12 -> 1.1453248e+09 | KI12: =SUMIFS($G12:$KG12,$G$3:$KG$3,KI$5,$G$6:$KG$6,KI$6) -> 6.6678 | KJ12: =KK12/KI12 -> 5500 | KK12: =SUMIFS($G12:$KG12,$G$3:$KG$3,KI$5,$G$6:$KG$6,KK$6) -> 36672.9 | KM12: =SUMIFS($G12:$KG12,$G$3:$KG$3,KM$5,$G$6:$KG$6,KM$6) -> 293.54026 | KN12: =KO12/KM12 -> 5500 | KO12: =SUMIFS($G12:$KG12,$G$3:$KG$3,KM$5,$G$6:$KG$6,KO$6) -> 1614471.4 | KQ12: =SUMIFS($G12:$KG12,$G$3:$KG$3,KQ$5,$G$6:$KG$6,KQ$6) -> 1932.1855 | KR12: =KS12/KQ12 -> 5500 | KS12: =SUMIFS($G12:$KG12,$G$3:$KG$3,KQ$5,$G$6:$KG$6,KS$6) -> 10627020 | KU12: =SUMIFS($G12:$KG12,$G$3:$KG$3,KU$5,$G$6:$KG$6,KU$6) -> 11476.691 | KV12: =KW12/KU12 -> 5500 | KW12: =SUMIFS($G12:$KG12,$G$3:$KG$3,KU$5,$G$6:$KG$6,KW$6) -> 63121803 | KY12: =SUMIFS($G12:$KG12,$G$3:$KG$3,KY$5,$G$6:$KG$6,KY$6) -> 67543.486 | KZ12: =LA12/KY12 -> 5500 | LA12: =SUMIFS($G12:$KG12,$G$3:$KG$3,KY$5,$G$6:$KG$6,LA$6) -> 3.7148917e+08 | LC12: =SUMIFS($G12:$KG12,$G$3:$KG$3,LC$5,$G$6:$KG$6,LC$6) -> 413592.31 | LD12: =LE12/LC12 -> 5500 | LE12: =SUMIFS($G12:$KG12,$G$3:$KG$3,LC$5,$G$6:$KG$6,LE$6) -> 2.2747577e+09
B13: 1d | E13: ='A.I Revenue Streams - P1'!F13 -> Implant | H13: ='A.I Revenue Streams - P1'!J13 -> 22000 | I13: =G13*H13 -> 0 | K13: ='A.I Revenue Streams - P1'!H13*K$2*L$2 -> 0.9 | L13: =H13*$L$8 -> 22000 | M13: =K13*L13 -> 19800 | O13: =K13*O$8*O$2/K$2*P$2 -> 0.96075 | P13: =L13*P$8 -> 22000 | Q13: =O13*P13 -> 21136.5 | S13: =O13*S$8*S$2/O$2*T$2 -> 1.47315 | T13: =P13*T$8 -> 22000 | U13: =S13*T13 -> 32409.3 | W13: =S13*W$8*W$2/S$2*X$2 -> 2.1176531 | X13: =T13*X$8 -> 22000 | Y13: =W13*X13 -> 46588.369 | AA13: =W13*AA$8*AA$2/W$2*AB$2 -> 3.8964817 | AB13: =X13*AB$8 -> 22000 | AC13: =AA13*AB13 -> 85722.598 | AE13: =AA13*AE$8*AE$2/AA$2*AF$2 -> 5.6011925 | AF13: =AB13*AF$8 -> 22000 | AG13: =AE13*AF13 -> 123226.24 | AI13: =AE13*AI$8*AI$2/AE$2*AJ$2 -> 8.0517142 | AJ13: =AF13*AJ$8 -> 22000 | AK13: =AI13*AJ13 -> 177137.71 | AM13: =AI13*AM$8*AM$2/AI$2*AN$2 -> 9.2594714 | AN13: =AJ13*AN$8 -> 22000 | AO13: =AM13*AN13 -> 203708.37 | AQ13: =AM13*AQ$8*AQ$2/AM$2*AR$2 -> 10.648392 | AR13: =AN13*AR$8 -> 22000 | AS13: =AQ13*AR13 -> 234264.63 | AU13: =AQ13*AU$8*AU$2/AQ$2*AV$2 -> 12.245651 | AV13: =AR13*AV$8 -> 22000 | AW13: =AU13*AV13 -> 269404.32 | AY13: =AU13*AY$8*AY$2/AU$2*AZ$2 -> 14.082499 | AZ13: =AV13*AZ$8 -> 22000 | BA13: =AY13*AZ13 -> 309814.97 | BC13: =AY13*BC$8*BC$2/AY$2*BD$2 -> 16.194873 | BD13: =AZ13*BD$8 -> 22000 | BE13: =BC13*BD13 -> 356287.21 | BG13: =BC13*BG$8*BG$2/BC$2*BH$2 -> 18.624104 | BH13: =BD13*BH$8 -> 22000 | BI13: =BG13*BH13 -> 409730.29 | BK13: =BG13*BK$8*BK$2/BG$2*BL$2 -> 21.41772 | BL13: =BH13*BL$8 -> 22000 | BM13: =BK13*BL13 -> 471189.84 | BO13: =BK13*BO$8*BO$2/BK$2*BP$2 -> 24.630378 | BP13: =BL13*BP$8 -> 22000 | BQ13: =BO13*BP13 -> 541868.31 | BS13: =BO13*BS$8*BS$2/BO$2*BT$2 -> 28.324935 | BT13: =BP13*BT$8 -> 22000 | BU13: =BS13*BT13 -> 623148.56 | BW13: =BS13*BW$8*BW$2/BS$2*BX$2 -> 32.573675 | BX13: =BT13*BX$8 -> 22000 | BY13: =BW13*BX13 -> 716620.85 | CA13: =BW13*CA$8*CA$2/BW$2*CB$2 -> 37.459726 | CB13: =BX13*CB$8 -> 22000 | CC13: =CA13*CB13 -> 824113.97 | CE13: =CA13*CE$8*CE$2/CA$2*CF$2 -> 51.694422 | CF13: =CB13*CF$8 -> 22000 | CG13: =CE13*CF13 -> 1137277.3 | CI13: =CE13*CI$8*CI$2/CE$2*CJ$2 -> 59.448585 | CJ13: =CF13*CJ$8 -> 22000 | CK13: =CI13*CJ13 -> 1307868.9 | CM13: =CI13*CM$8*CM$2/CI$2*CN$2 -> 68.365873 | CN13: =CJ13*CN$8 -> 22000 | CO13: =CM13*CN13 -> 1504049.2 | CQ13: =CM13*CQ$8*CQ$2/CM$2*CR$2 -> 78.620754 | CR13: =CN13*CR$8 -> 22000 | CS13: =CQ13*CR13 -> 1729656.6 | CU13: =CQ13*CU$8*CU$2/CQ$2*CV$2 -> 90.413867 | CV13: =CR13*CV$8 -> 22000 | CW13: =CU13*CV13 -> 1989105.1 | CY13: =CU13*CY$8*CY$2/CU$2*CZ$2 -> 103.97595 | CZ13: =CV13*CZ$8 -> 22000 | DA13: =CY13*CZ13 -> 2287470.8 | DC13: =CY13*DC$8*DC$2/CY$2*DD$2 -> 119.57234 | DD13: =CZ13*DD$8 -> 22000 | DE13: =DC13*DD13 -> 2630591.5 | DG13: =DC13*DG$8*DG$2/DC$2*DH$2 -> 137.50819 | DH13: =DD13*DH$8 -> 22000 | DI13: =DG13*DH13 -> 3025180.2 | DK13: =DG13*DK$8*DK$2/DG$2*DL$2 -> 158.13442 | DL13: =DH13*DL$8 -> 22000 | DM13: =DK13*DL13 -> 3478957.2 | DO13: =DK13*DO$8*DO$2/DK$2*DP$2 -> 181.85458 | DP13: =DL13*DP$8 -> 22000 | DQ13: =DO13*DP13 -> 4000800.8 | DS13: =DO13*DS$8*DS$2/DO$2*DT$2 -> 209.13277 | DT13: =DP13*DT$8 -> 22000 | DU13: =DS13*DT13 -> 4600920.9 | DW13: =DS13*DW$8*DW$2/DS$2*DX$2 -> 240.50268 | DX13: =DT13*DX$8 -> 22000 | DY13: =DW13*DX13 -> 5291059 | EA13: =DW13*EA$8*EA$2/DW$2*EB$2 -> 304.2359 | EB13: =DX13*EB$8 -> 22000 | EC13: =EA13*EB13 -> 6693189.7 | EE13: =EA13*EE$8*EE$2/EA$2*EF$2 -> 349.87128 | EF13: =EB13*EF$8 -> 22000 | EG13: =EE13*EF13 -> 7697168.1 | EI13: =EE13*EI$8*EI$2/EE$2*EJ$2 -> 402.35197 | EJ13: =EF13*EJ$8 -> 22000 | EK13: =EI13*EJ13 -> 8851743.4 | EM13: =EI13*EM$8*EM$2/EI$2*EN$2 -> 462.70477 | EN13: =EJ13*EN$8 -> 22000 | EO13: =EM13*EN13 -> 10179505 | EQ13: =EM13*EQ$8*EQ$2/EM$2*ER$2 -> 532.11048 | ER13: =EN13*ER$8 -> 22000 | ES13: =EQ13*ER13 -> 11706431 | EU13: =EQ13*EU$8*EU$2/EQ$2*EV$2 -> 611.92705 | EV13: =ER13*EV$8 -> 22000 | EW13: =EU13*EV13 -> 13462395 | EY13: =EU13*EY$8*EY$2/EU$2*EZ$2 -> 703.71611 | EZ13: =EV13*EZ$8 -> 22000 | FA13: =EY13*EZ13 -> 15481754 | FC13: =EY13*FC$8*FC$2/EY$2*FD$2 -> 809.27353 | FD13: =EZ13*FD$8 -> 22000 | FE13: =FC13*FD13 -> 17804018 | FG13: =FC13*FG$8*FG$2/FC$2*FH$2 -> 930.66456 | FH13: =FD13*FH$8 -> 22000 | FI13: =FG13*FH13 -> 20474620 | FK13: =FG13*FK$8*FK$2/FG$2*FL$2 -> 1070.2642 | FL13: =FH13*FL$8 -> 22000 | FM13: =FK13*FL13 -> 23545813 | FO13: =FK13*FO$8*FO$2/FK$2*FP$2 -> 1230.8039 | FP13: =FL13*FP$8 -> 22000 | FQ13: =FO13*FP13 -> 27077685 | FS13: =FO13*FS$8*FS$2/FO$2*FT$2 -> 1415.4245 | FT13: =FP13*FT$8 -> 22000 | FU13: =FS13*FT13 -> 31139338 | FW13: =FS13*FW$8*FW$2/FS$2*FX$2 -> 1790.5119 | FX13: =FT13*FX$8 -> 22000 | FY13: =FW13*FX13 -> 39391263 | GA13: =FW13*GA$8*GA$2/FW$2*GB$2 -> 2059.0887 | GB13: =FX13*GB$8 -> 22000 | GC13: =GA13*GB13 -> 45299952 | GE13: =GA13*GE$8*GE$2/GA$2*GF$2 -> 2367.952 | GF13: =GB13*GF$8 -> 22000 | GG13: =GE13*GF13 -> 52094945 | GI13: =GE13*GI$8*GI$2/GE$2*GJ$2 -> 2723.1449 | GJ13: =GF13*GJ$8 -> 22000 | GK13: =GI13*GJ13 -> 59909187 | GM13: =GI13*GM$8*GM$2/GI$2*GN$2 -> 3131.6166 | GN13: =GJ13*GN$8 -> 22000 | GO13: =GM13*GN13 -> 68895565 | GQ13: =GM13*GQ$8*GQ$2/GM$2*GR$2 -> 3601.3591 | GR13: =GN13*GR$8 -> 22000 | GS13: =GQ13*GR13 -> 79229899 | GU13: =GQ13*GU$8*GU$2/GQ$2*GV$2 -> 4141.5629 | GV13: =GR13*GV$8 -> 22000 | GW13: =GU13*GV13 -> 91114384 | GY13: =GU13*GY$8*GY$2/GU$2*GZ$2 -> 4762.7974 | GZ13: =GV13*GZ$8 -> 22000 | HA13: =GY13*GZ13 -> 1.0478154e+08 | HC13: =GY13*HC$8*HC$2/GY$2*HD$2 -> 5477.217 | HD13: =GZ13*HD$8 -> 22000 | HE13: =HC13*HD13 -> 1.2049877e+08 | HG13: =HC13*HG$8*HG$2/HC$2*HH$2 -> 6298.7995 | HH13: =HD13*HH$8 -> 22000 | HI13: =HG13*HH13 -> 1.3857359e+08 | HK13: =HG13*HK$8*HK$2/HG$2*HL$2 -> 7243.6194 | HL13: =HH13*HL$8 -> 22000 | HM13: =HK13*HL13 -> 1.5935963e+08 | HO13: =HK13*HO$8*HO$2/HK$2*HP$2 -> 8330.1624 | HP13: =HL13*HP$8 -> 22000 | HQ13: =HO13*HP13 -> 1.8326357e+08 | HS13: =HO13*HS$8*HS$2/HO$2*HT$2 -> 11016.64 | HT13: =HP13*HT$8 -> 22000 | HU13: =HS13*HT13 -> 2.4236607e+08 | HW13: =HS13*HW$8*HW$2/HS$2*HX$2 -> 12669.136 | HX13: =HT13*HX$8 -> 22000 | HY13: =HW13*HX13 -> 2.7872098e+08 | IA13: =HW13*IA$8*IA$2/HW$2*IB$2 -> 14569.506 | IB13: =HX13*IB$8 -> 22000 | IC13: =IA13*IB13 -> 3.2052913e+08 | IE13: =IA13*IE$8*IE$2/IA$2*IF$2 -> 16754.932 | IF13: =IB13*IF$8 -> 22000 | IG13: =IE13*IF13 -> 3.686085e+08 | II13: =IE13*II$8*II$2/IE$2*IJ$2 -> 19268.172 | IJ13: =IF13*IJ$8 -> 22000 | IK13: =II13*IJ13 -> 4.2389978e+08 | IM13: =II13*IM$8*IM$2/II$2*IN$2 -> 22158.397 | IN13: =IJ13*IN$8 -> 22000 | IO13: =IM13*IN13 -> 4.8748474e+08 | IQ13: =IM13*IQ$8*IQ$2/IM$2*IR$2 -> 25482.157 | IR13: =IN13*IR$8 -> 22000 | IS13: =IQ13*IR13 -> 5.6060746e+08 | IU13: =IQ13*IU$8*IU$2/IQ$2*IV$2 -> 29304.481 | IV13: =IR13*IV$8 -> 22000 | IW13: =IU13*IV13 -> 6.4469857e+08 | IY13: =IU13*IY$8*IY$2/IU$2*IZ$2 -> 33700.153 | IZ13: =IV13*IZ$8 -> 22000 | JA13: =IY13*IZ13 -> 7.4140336e+08 | JC13: =IY13*JC$8*JC$2/IY$2*JD$2 -> 38755.176 | JD13: =IZ13*JD$8 -> 22000 | JE13: =JC13*JD13 -> 8.5261387e+08 | JG13: =JC13*JG$8*JG$2/JC$2*JH$2 -> 44568.452 | JH13: =JD13*JH$8 -> 22000 | JI13: =JG13*JH13 -> 9.8050595e+08 | JK13: =JG13*JK$8*JK$2/JG$2*JL$2 -> 51253.72 | JL13: =JH13*JL$8 -> 22000 | JM13: =JK13*JL13 -> 1.1275818e+09 | JO13: =JK13*JO$8*JO$2/JK$2*JP$2 -> 59531.196 | JP13: =JL13*JP$8 -> 22000 | JQ13: =JO13*JP13 -> 1.3096863e+09 | JS13: =JO13*JS$8*JS$2/JO$2*JT$2 -> 68460.875 | JT13: =JP13*JT$8 -> 22000 | JU13: =JS13*JT13 -> 1.5061392e+09 | JW13: =JS13*JW$8*JW$2/JS$2*JX$2 -> 78730.006 | JX13: =JT13*JX$8 -> 22000 | JY13: =JW13*JX13 -> 1.7320601e+09 | KA13: =JW13*KA$8*KA$2/JW$2*KB$2 -> 90539.507 | KB13: =JX13*KB$8 -> 22000 | KC13: =KA13*KB13 -> 1.9918692e+09 | KE13: =KA13*KE$8*KE$2/KA$2*KF$2 -> 104120.43 | KF13: =KB13*KF$8 -> 22000 | KG13: =KE13*KF13 -> 2.2906495e+09 | KI13: =SUMIFS($G13:$KG13,$G$3:$KG$3,KI$5,$G$6:$KG$6,KI$6) -> 3.3339 | KJ13: =KK13/KI13 -> 22000 | KK13: =SUMIFS($G13:$KG13,$G$3:$KG$3,KI$5,$G$6:$KG$6,KK$6) -> 73345.8 | KM13: =SUMIFS($G13:$KG13,$G$3:$KG$3,KM$5,$G$6:$KG$6,KM$6) -> 146.77013 | KN13: =KO13/KM13 -> 22000 | KO13: =SUMIFS($G13:$KG13,$G$3:$KG$3,KM$5,$G$6:$KG$6,KO$6) -> 3228942.9 | KQ13: =SUMIFS($G13:$KG13,$G$3:$KG$3,KQ$5,$G$6:$KG$6,KQ$6) -> 966.09273 | KR13: =KS13/KQ13 -> 22000 | KS13: =SUMIFS($G13:$KG13,$G$3:$KG$3,KQ$5,$G$6:$KG$6,KS$6) -> 21254040 | KU13: =SUMIFS($G13:$KG13,$G$3:$KG$3,KU$5,$G$6:$KG$6,KU$6) -> 5738.3457 | KV13: =KW13/KU13 -> 22000 | KW13: =SUMIFS($G13:$KG13,$G$3:$KG$3,KU$5,$G$6:$KG$6,KW$6) -> 1.2624361e+08 | KY13: =SUMIFS($G13:$KG13,$G$3:$KG$3,KY$5,$G$6:$KG$6,KY$6) -> 33771.743 | KZ13: =LA13/KY13 -> 22000 | LA13: =SUMIFS($G13:$KG13,$G$3:$KG$3,KY$5,$G$6:$KG$6,LA$6) -> 7.4297835e+08 | LC13: =SUMIFS($G13:$KG13,$G$3:$KG$3,LC$5,$G$6:$KG$6,LC$6) -> 206796.15 | LD13: =LE13/LC13 -> 22000 | LE13: =SUMIFS($G13:$KG13,$G$3:$KG$3,LC$5,$G$6:$KG$6,LE$6) -> 4.5495154e+09
E14: ='A.I Revenue Streams - P1'!F14 -> X Ray | H14: ='A.I Revenue Streams - P1'!J14 -> 300 | I14: =G14*H14 -> 0 | K14: ='A.I Revenue Streams - P1'!H14*K$2*L$2 -> 135 | L14: =H14*$L$8 -> 300 | M14: =K14*L14 -> 40500 | O14: =K14*O$8*O$2/K$2*P$2 -> 144.1125 | P14: =L14*P$8 -> 300 | Q14: =O14*P14 -> 43233.75 | S14: =O14*S$8*S$2/O$2*T$2 -> 220.9725 | T14: =P14*T$8 -> 300 | U14: =S14*T14 -> 66291.75 | W14: =S14*W$8*W$2/S$2*X$2 -> 317.64797 | X14: =T14*X$8 -> 300 | Y14: =W14*X14 -> 95294.391 | AA14: =W14*AA$8*AA$2/W$2*AB$2 -> 584.47226 | AB14: =X14*AB$8 -> 300 | AC14: =AA14*AB14 -> 175341.68 | AE14: =AA14*AE$8*AE$2/AA$2*AF$2 -> 840.17888 | AF14: =AB14*AF$8 -> 300 | AG14: =AE14*AF14 -> 252053.66 | AI14: =AE14*AI$8*AI$2/AE$2*AJ$2 -> 1207.7571 | AJ14: =AF14*AJ$8 -> 300 | AK14: =AI14*AJ14 -> 362327.14 | AM14: =AI14*AM$8*AM$2/AI$2*AN$2 -> 1388.9207 | AN14: =AJ14*AN$8 -> 300 | AO14: =AM14*AN14 -> 416676.21 | AQ14: =AM14*AQ$8*AQ$2/AM$2*AR$2 -> 1597.2588 | AR14: =AN14*AR$8 -> 300 | AS14: =AQ14*AR14 -> 479177.64 | AU14: =AQ14*AU$8*AU$2/AQ$2*AV$2 -> 1836.8476 | AV14: =AR14*AV$8 -> 300 | AW14: =AU14*AV14 -> 551054.29 | AY14: =AU14*AY$8*AY$2/AU$2*AZ$2 -> 2112.3748 | AZ14: =AV14*AZ$8 -> 300 | BA14: =AY14*AZ14 -> 633712.43 | BC14: =AY14*BC$8*BC$2/AY$2*BD$2 -> 2429.231 | BD14: =AZ14*BD$8 -> 300 | BE14: =BC14*BD14 -> 728769.3 | BG14: =BC14*BG$8*BG$2/BC$2*BH$2 -> 2793.6156 | BH14: =BD14*BH$8 -> 300 | BI14: =BG14*BH14 -> 838084.69 | BK14: =BG14*BK$8*BK$2/BG$2*BL$2 -> 3212.658 | BL14: =BH14*BL$8 -> 300 | BM14: =BK14*BL14 -> 963797.4 | BO14: =BK14*BO$8*BO$2/BK$2*BP$2 -> 3694.5567 | BP14: =BL14*BP$8 -> 300 | BQ14: =BO14*BP14 -> 1108367 | BS14: =BO14*BS$8*BS$2/BO$2*BT$2 -> 4248.7402 | BT14: =BP14*BT$8 -> 300 | BU14: =BS14*BT14 -> 1274622.1 | BW14: =BS14*BW$8*BW$2/BS$2*BX$2 -> 4886.0512 | BX14: =BT14*BX$8 -> 300 | BY14: =BW14*BX14 -> 1465815.4 | CA14: =BW14*CA$8*CA$2/BW$2*CB$2 -> 5618.9589 | CB14: =BX14*CB$8 -> 300 | CC14: =CA14*CB14 -> 1685687.7 | CE14: =CA14*CE$8*CE$2/CA$2*CF$2 -> 7754.1633 | CF14: =CB14*CF$8 -> 300 | CG14: =CE14*CF14 -> 2326249 | CI14: =CE14*CI$8*CI$2/CE$2*CJ$2 -> 8917.2878 | CJ14: =CF14*CJ$8 -> 300 | CK14: =CI14*CJ14 -> 2675186.3 | CM14: =CI14*CM$8*CM$2/CI$2*CN$2 -> 10254.881 | CN14: =CJ14*CN$8 -> 300 | CO14: =CM14*CN14 -> 3076464.3 | CQ14: =CM14*CQ$8*CQ$2/CM$2*CR$2 -> 11793.113 | CR14: =CN14*CR$8 -> 300 | CS14: =CQ14*CR14 -> 3537933.9 | CU14: =CQ14*CU$8*CU$2/CQ$2*CV$2 -> 13562.08 | CV14: =CR14*CV$8 -> 300 | CW14: =CU14*CV14 -> 4068624 | CY14: =CU14*CY$8*CY$2/CU$2*CZ$2 -> 15596.392 | CZ14: =CV14*CZ$8 -> 300 | DA14: =CY14*CZ14 -> 4678917.6 | DC14: =CY14*DC$8*DC$2/CY$2*DD$2 -> 17935.851 | DD14: =CZ14*DD$8 -> 300 | DE14: =DC14*DD14 -> 5380755.3 | DG14: =DC14*DG$8*DG$2/DC$2*DH$2 -> 20626.229 | DH14: =DD14*DH$8 -> 300 | DI14: =DG14*DH14 -> 6187868.6 | DK14: =DG14*DK$8*DK$2/DG$2*DL$2 -> 23720.163 | DL14: =DH14*DL$8 -> 300 | DM14: =DK14*DL14 -> 7116048.8 | DO14: =DK14*DO$8*DO$2/DK$2*DP$2 -> 27278.187 | DP14: =DL14*DP$8 -> 300 | DQ14: =DO14*DP14 -> 8183456.2 | DS14: =DO14*DS$8*DS$2/DO$2*DT$2 -> 31369.915 | DT14: =DP14*DT$8 -> 300 | DU14: =DS14*DT14 -> 9410974.6 | DW14: =DS14*DW$8*DW$2/DS$2*DX$2 -> 36075.403 | DX14: =DT14*DX$8 -> 300 | DY14: =DW14*DX14 -> 10822621 | EA14: =DW14*EA$8*EA$2/DW$2*EB$2 -> 45635.384 | EB14: =DX14*EB$8 -> 300 | EC14: =EA14*EB14 -> 13690615 | EE14: =EA14*EE$8*EE$2/EA$2*EF$2 -> 52480.692 | EF14: =EB14*EF$8 -> 300 | EG14: =EE14*EF14 -> 15744208 | EI14: =EE14*EI$8*EI$2/EE$2*EJ$2 -> 60352.796 | EJ14: =EF14*EJ$8 -> 300 | EK14: =EI14*EJ14 -> 18105839 | EM14: =EI14*EM$8*EM$2/EI$2*EN$2 -> 69405.715 | EN14: =EJ14*EN$8 -> 300 | EO14: =EM14*EN14 -> 20821715 | EQ14: =EM14*EQ$8*EQ$2/EM$2*ER$2 -> 79816.572 | ER14: =EN14*ER$8 -> 300 | ES14: =EQ14*ER14 -> 23944972 | EU14: =EQ14*EU$8*EU$2/EQ$2*EV$2 -> 91789.058 | EV14: =ER14*EV$8 -> 300 | EW14: =EU14*EV14 -> 27536717 | EY14: =EU14*EY$8*EY$2/EU$2*EZ$2 -> 105557.42 | EZ14: =EV14*EZ$8 -> 300 | FA14: =EY14*EZ14 -> 31667225 | FC14: =EY14*FC$8*FC$2/EY$2*FD$2 -> 121391.03 | FD14: =EZ14*FD$8 -> 300 | FE14: =FC14*FD14 -> 36417309 | FG14: =FC14*FG$8*FG$2/FC$2*FH$2 -> 139599.68 | FH14: =FD14*FH$8 -> 300 | FI14: =FG14*FH14 -> 41879905 | FK14: =FG14*FK$8*FK$2/FG$2*FL$2 -> 160539.64 | FL14: =FH14*FL$8 -> 300 | FM14: =FK14*FL14 -> 48161891 | FO14: =FK14*FO$8*FO$2/FK$2*FP$2 -> 184620.58 | FP14: =FL14*FP$8 -> 300 | FQ14: =FO14*FP14 -> 55386175 | FS14: =FO14*FS$8*FS$2/FO$2*FT$2 -> 212313.67 | FT14: =FP14*FT$8 -> 300 | FU14: =FS14*FT14 -> 63694101 | FW14: =FS14*FW$8*FW$2/FS$2*FX$2 -> 268576.79 | FX14: =FT14*FX$8 -> 300 | FY14: =FW14*FX14 -> 80573037 | GA14: =FW14*GA$8*GA$2/FW$2*GB$2 -> 308863.31 | GB14: =FX14*GB$8 -> 300 | GC14: =GA14*GB14 -> 92658993 | GE14: =GA14*GE$8*GE$2/GA$2*GF$2 -> 355192.81 | GF14: =GB14*GF$8 -> 300 | GG14: =GE14*GF14 -> 1.0655784e+08 | GI14: =GE14*GI$8*GI$2/GE$2*GJ$2 -> 408471.73 | GJ14: =GF14*GJ$8 -> 300 | GK14: =GI14*GJ14 -> 1.2254152e+08 | GM14: =GI14*GM$8*GM$2/GI$2*GN$2 -> 469742.49 | GN14: =GJ14*GN$8 -> 300 | GO14: =GM14*GN14 -> 1.4092275e+08 | GQ14: =GM14*GQ$8*GQ$2/GM$2*GR$2 -> 540203.86 | GR14: =GN14*GR$8 -> 300 | GS14: =GQ14*GR14 -> 1.6206116e+08 | GU14: =GQ14*GU$8*GU$2/GQ$2*GV$2 -> 621234.44 | GV14: =GR14*GV$8 -> 300 | GW14: =GU14*GV14 -> 1.8637033e+08 | GY14: =GU14*GY$8*GY$2/GU$2*GZ$2 -> 714419.6 | GZ14: =GV14*GZ$8 -> 300 | HA14: =GY14*GZ14 -> 2.1432588e+08 | HC14: =GY14*HC$8*HC$2/GY$2*HD$2 -> 821582.55 | HD14: =GZ14*HD$8 -> 300 | HE14: =HC14*HD14 -> 2.4647476e+08 | HG14: =HC14*HG$8*HG$2/HC$2*HH$2 -> 944819.93 | HH14: =HD14*HH$8 -> 300 | HI14: =HG14*HH14 -> 2.8344598e+08 | HK14: =HG14*HK$8*HK$2/HG$2*HL$2 -> 1086542.9 | HL14: =HH14*HL$8 -> 300 | HM14: =HK14*HL14 -> 3.2596287e+08 | HO14: =HK14*HO$8*HO$2/HK$2*HP$2 -> 1249524.4 | HP14: =HL14*HP$8 -> 300 | HQ14: =HO14*HP14 -> 3.7485731e+08 | HS14: =HO14*HS$8*HS$2/HO$2*HT$2 -> 1652496 | HT14: =HP14*HT$8 -> 300 | HU14: =HS14*HT14 -> 4.9574879e+08 | HW14: =HS14*HW$8*HW$2/HS$2*HX$2 -> 1900370.4 | HX14: =HT14*HX$8 -> 300 | HY14: =HW14*HX14 -> 5.7011111e+08 | IA14: =HW14*IA$8*IA$2/HW$2*IB$2 -> 2185425.9 | IB14: =HX14*IB$8 -> 300 | IC14: =IA14*IB14 -> 6.5562777e+08 | IE14: =IA14*IE$8*IE$2/IA$2*IF$2 -> 2513239.8 | IF14: =IB14*IF$8 -> 300 | IG14: =IE14*IF14 -> 7.5397194e+08 | II14: =IE14*II$8*II$2/IE$2*IJ$2 -> 2890225.8 | IJ14: =IF14*IJ$8 -> 300 | IK14: =II14*IJ14 -> 8.6706773e+08 | IM14: =II14*IM$8*IM$2/II$2*IN$2 -> 3323759.6 | IN14: =IJ14*IN$8 -> 300 | IO14: =IM14*IN14 -> 9.9712789e+08 | IQ14: =IM14*IQ$8*IQ$2/IM$2*IR$2 -> 3822323.6 | IR14: =IN14*IR$8 -> 300 | IS14: =IQ14*IR14 -> 1.1466971e+09 | IU14: =IQ14*IU$8*IU$2/IQ$2*IV$2 -> 4395672.1 | IV14: =IR14*IV$8 -> 300 | IW14: =IU14*IV14 -> 1.3187016e+09 | IY14: =IU14*IY$8*IY$2/IU$2*IZ$2 -> 5055022.9 | IZ14: =IV14*IZ$8 -> 300 | JA14: =IY14*IZ14 -> 1.5165069e+09 | JC14: =IY14*JC$8*JC$2/IY$2*JD$2 -> 5813276.4 | JD14: =IZ14*JD$8 -> 300 | JE14: =JC14*JD14 -> 1.7439829e+09 | JG14: =JC14*JG$8*JG$2/JC$2*JH$2 -> 6685267.8 | JH14: =JD14*JH$8 -> 300 | JI14: =JG14*JH14 -> 2.0055803e+09 | JK14: =JG14*JK$8*JK$2/JG$2*JL$2 -> 7688058 | JL14: =JH14*JL$8 -> 300 | JM14: =JK14*JL14 -> 2.3064174e+09 | JO14: =JK14*JO$8*JO$2/JK$2*JP$2 -> 8929679.3 | JP14: =JL14*JP$8 -> 300 | JQ14: =JO14*JP14 -> 2.6789038e+09 | JS14: =JO14*JS$8*JS$2/JO$2*JT$2 -> 10269131 | JT14: =JP14*JT$8 -> 300 | JU14: =JS14*JT14 -> 3.0807394e+09 | JW14: =JS14*JW$8*JW$2/JS$2*JX$2 -> 11809501 | JX14: =JT14*JX$8 -> 300 | JY14: =JW14*JX14 -> 3.5428503e+09 | KA14: =JW14*KA$8*KA$2/JW$2*KB$2 -> 13580926 | KB14: =JX14*KB$8 -> 300 | KC14: =KA14*KB14 -> 4.0742778e+09 | KE14: =KA14*KE$8*KE$2/KA$2*KF$2 -> 15618065 | KF14: =KB14*KF$8 -> 300 | KG14: =KE14*KF14 -> 4.6854195e+09 | KI14: =SUMIFS($G14:$KG14,$G$3:$KG$3,KI$5,$G$6:$KG$6,KI$6) -> 500.085 | KJ14: =KK14/KI14 -> 300 | KK14: =SUMIFS($G14:$KG14,$G$3:$KG$3,KI$5,$G$6:$KG$6,KK$6) -> 150025.5 | KM14: =SUMIFS($G14:$KG14,$G$3:$KG$3,KM$5,$G$6:$KG$6,KM$6) -> 22015.52 | KN14: =KO14/KM14 -> 300 | KO14: =SUMIFS($G14:$KG14,$G$3:$KG$3,KM$5,$G$6:$KG$6,KO$6) -> 6604655.9 | KQ14: =SUMIFS($G14:$KG14,$G$3:$KG$3,KQ$5,$G$6:$KG$6,KQ$6) -> 144913.91 | KR14: =KS14/KQ14 -> 300 | KS14: =SUMIFS($G14:$KG14,$G$3:$KG$3,KQ$5,$G$6:$KG$6,KS$6) -> 43474173 | KU14: =SUMIFS($G14:$KG14,$G$3:$KG$3,KU$5,$G$6:$KG$6,KU$6) -> 860751.85 | KV14: =KW14/KU14 -> 300 | KW14: =SUMIFS($G14:$KG14,$G$3:$KG$3,KU$5,$G$6:$KG$6,KW$6) -> 2.5822556e+08 | KY14: =SUMIFS($G14:$KG14,$G$3:$KG$3,KY$5,$G$6:$KG$6,KY$6) -> 5065761.5 | KZ14: =LA14/KY14 -> 300 | LA14: =SUMIFS($G14:$KG14,$G$3:$KG$3,KY$5,$G$6:$KG$6,LA$6) -> 1.5197284e+09 | LC14: =SUMIFS($G14:$KG14,$G$3:$KG$3,LC$5,$G$6:$KG$6,LC$6) -> 31019423 | LD14: =LE14/LC14 -> 300 | LE14: =SUMIFS($G14:$KG14,$G$3:$KG$3,LC$5,$G$6:$KG$6,LE$6) -> 9.305827e+09
E15: ='A.I Revenue Streams - P1'!F15 -> Scaling | H15: ='A.I Revenue Streams - P1'!J15 -> 1800 | I15: =G15*H15 -> 0 | K15: ='A.I Revenue Streams - P1'!H15*K$2*L$2 -> 3.6 | L15: =H15*$L$8 -> 1800 | M15: =K15*L15 -> 6480 | O15: =K15*O$8*O$2/K$2*P$2 -> 3.843 | P15: =L15*P$8 -> 1800 | Q15: =O15*P15 -> 6917.4 | S15: =O15*S$8*S$2/O$2*T$2 -> 5.8926 | T15: =P15*T$8 -> 1800 | U15: =S15*T15 -> 10606.68 | W15: =S15*W$8*W$2/S$2*X$2 -> 8.4706125 | X15: =T15*X$8 -> 1800 | Y15: =W15*X15 -> 15247.102 | AA15: =W15*AA$8*AA$2/W$2*AB$2 -> 15.585927 | AB15: =X15*AB$8 -> 1800 | AC15: =AA15*AB15 -> 28054.669 | AE15: =AA15*AE$8*AE$2/AA$2*AF$2 -> 22.40477 | AF15: =AB15*AF$8 -> 1800 | AG15: =AE15*AF15 -> 40328.586 | AI15: =AE15*AI$8*AI$2/AE$2*AJ$2 -> 32.206857 | AJ15: =AF15*AJ$8 -> 1800 | AK15: =AI15*AJ15 -> 57972.343 | AM15: =AI15*AM$8*AM$2/AI$2*AN$2 -> 37.037886 | AN15: =AJ15*AN$8 -> 1800 | AO15: =AM15*AN15 -> 66668.194 | AQ15: =AM15*AQ$8*AQ$2/AM$2*AR$2 -> 42.593568 | AR15: =AN15*AR$8 -> 1800 | AS15: =AQ15*AR15 -> 76668.423 | AU15: =AQ15*AU$8*AU$2/AQ$2*AV$2 -> 48.982604 | AV15: =AR15*AV$8 -> 1800 | AW15: =AU15*AV15 -> 88168.686 | AY15: =AU15*AY$8*AY$2/AU$2*AZ$2 -> 56.329994 | AZ15: =AV15*AZ$8 -> 1800 | BA15: =AY15*AZ15 -> 101393.99 | BC15: =AY15*BC$8*BC$2/AY$2*BD$2 -> 64.779493 | BD15: =AZ15*BD$8 -> 1800 | BE15: =BC15*BD15 -> 116603.09 | BG15: =BC15*BG$8*BG$2/BC$2*BH$2 -> 74.496417 | BH15: =BD15*BH$8 -> 1800 | BI15: =BG15*BH15 -> 134093.55 | BK15: =BG15*BK$8*BK$2/BG$2*BL$2 -> 85.67088 | BL15: =BH15*BL$8 -> 1800 | BM15: =BK15*BL15 -> 154207.58 | BO15: =BK15*BO$8*BO$2/BK$2*BP$2 -> 98.521512 | BP15: =BL15*BP$8 -> 1800 | BQ15: =BO15*BP15 -> 177338.72 | BS15: =BO15*BS$8*BS$2/BO$2*BT$2 -> 113.29974 | BT15: =BP15*BT$8 -> 1800 | BU15: =BS15*BT15 -> 203939.53 | BW15: =BS15*BW$8*BW$2/BS$2*BX$2 -> 130.2947 | BX15: =BT15*BX$8 -> 1800 | BY15: =BW15*BX15 -> 234530.46 | CA15: =BW15*CA$8*CA$2/BW$2*CB$2 -> 149.8389 | CB15: =BX15*CB$8 -> 1800 | CC15: =CA15*CB15 -> 269710.03 | CE15: =CA15*CE$8*CE$2/CA$2*CF$2 -> 206.77769 | CF15: =CB15*CF$8 -> 1800 | CG15: =CE15*CF15 -> 372199.84 | CI15: =CE15*CI$8*CI$2/CE$2*CJ$2 -> 237.79434 | CJ15: =CF15*CJ$8 -> 1800 | CK15: =CI15*CJ15 -> 428029.81 | CM15: =CI15*CM$8*CM$2/CI$2*CN$2 -> 273.46349 | CN15: =CJ15*CN$8 -> 1800 | CO15: =CM15*CN15 -> 492234.29 | CQ15: =CM15*CQ$8*CQ$2/CM$2*CR$2 -> 314.48302 | CR15: =CN15*CR$8 -> 1800 | CS15: =CQ15*CR15 -> 566069.43 | CU15: =CQ15*CU$8*CU$2/CQ$2*CV$2 -> 361.65547 | CV15: =CR15*CV$8 -> 1800 | CW15: =CU15*CV15 -> 650979.84 | CY15: =CU15*CY$8*CY$2/CU$2*CZ$2 -> 415.90379 | CZ15: =CV15*CZ$8 -> 1800 | DA15: =CY15*CZ15 -> 748626.82 | DC15: =CY15*DC$8*DC$2/CY$2*DD$2 -> 478.28936 | DD15: =CZ15*DD$8 -> 1800 | DE15: =DC15*DD15 -> 860920.84 | DG15: =DC15*DG$8*DG$2/DC$2*DH$2 -> 550.03276 | DH15: =DD15*DH$8 -> 1800 | DI15: =DG15*DH15 -> 990058.97 | DK15: =DG15*DK$8*DK$2/DG$2*DL$2 -> 632.53767 | DL15: =DH15*DL$8 -> 1800 | DM15: =DK15*DL15 -> 1138567.8 | DO15: =DK15*DO$8*DO$2/DK$2*DP$2 -> 727.41833 | DP15: =DL15*DP$8 -> 1800 | DQ15: =DO15*DP15 -> 1309353 | DS15: =DO15*DS$8*DS$2/DO$2*DT$2 -> 836.53107 | DT15: =DP15*DT$8 -> 1800 | DU15: =DS15*DT15 -> 1505755.9 | DW15: =DS15*DW$8*DW$2/DS$2*DX$2 -> 962.01074 | DX15: =DT15*DX$8 -> 1800 | DY15: =DW15*DX15 -> 1731619.3 | EA15: =DW15*EA$8*EA$2/DW$2*EB$2 -> 1216.9436 | EB15: =DX15*EB$8 -> 1800 | EC15: =EA15*EB15 -> 2190498.4 | EE15: =EA15*EE$8*EE$2/EA$2*EF$2 -> 1399.4851 | EF15: =EB15*EF$8 -> 1800 | EG15: =EE15*EF15 -> 2519073.2 | EI15: =EE15*EI$8*EI$2/EE$2*EJ$2 -> 1609.4079 | EJ15: =EF15*EJ$8 -> 1800 | EK15: =EI15*EJ15 -> 2896934.2 | EM15: =EI15*EM$8*EM$2/EI$2*EN$2 -> 1850.8191 | EN15: =EJ15*EN$8 -> 1800 | EO15: =EM15*EN15 -> 3331474.3 | EQ15: =EM15*EQ$8*EQ$2/EM$2*ER$2 -> 2128.4419 | ER15: =EN15*ER$8 -> 1800 | ES15: =EQ15*ER15 -> 3831195.5 | EU15: =EQ15*EU$8*EU$2/EQ$2*EV$2 -> 2447.7082 | EV15: =ER15*EV$8 -> 1800 | EW15: =EU15*EV15 -> 4405874.8 | EY15: =EU15*EY$8*EY$2/EU$2*EZ$2 -> 2814.8645 | EZ15: =EV15*EZ$8 -> 1800 | FA15: =EY15*EZ15 -> 5066756 | FC15: =EY15*FC$8*FC$2/EY$2*FD$2 -> 3237.0941 | FD15: =EZ15*FD$8 -> 1800 | FE15: =FC15*FD15 -> 5826769.4 | FG15: =FC15*FG$8*FG$2/FC$2*FH$2 -> 3722.6582 | FH15: =FD15*FH$8 -> 1800 | FI15: =FG15*FH15 -> 6700784.8 | FK15: =FG15*FK$8*FK$2/FG$2*FL$2 -> 4281.057 | FL15: =FH15*FL$8 -> 1800 | FM15: =FK15*FL15 -> 7705902.5 | FO15: =FK15*FO$8*FO$2/FK$2*FP$2 -> 4923.2155 | FP15: =FL15*FP$8 -> 1800 | FQ15: =FO15*FP15 -> 8861787.9 | FS15: =FO15*FS$8*FS$2/FO$2*FT$2 -> 5661.6978 | FT15: =FP15*FT$8 -> 1800 | FU15: =FS15*FT15 -> 10191056 | FW15: =FS15*FW$8*FW$2/FS$2*FX$2 -> 7162.0478 | FX15: =FT15*FX$8 -> 1800 | FY15: =FW15*FX15 -> 12891686 | GA15: =FW15*GA$8*GA$2/FW$2*GB$2 -> 8236.3549 | GB15: =FX15*GB$8 -> 1800 | GC15: =GA15*GB15 -> 14825439 | GE15: =GA15*GE$8*GE$2/GA$2*GF$2 -> 9471.8082 | GF15: =GB15*GF$8 -> 1800 | GG15: =GE15*GF15 -> 17049255 | GI15: =GE15*GI$8*GI$2/GE$2*GJ$2 -> 10892.579 | GJ15: =GF15*GJ$8 -> 1800 | GK15: =GI15*GJ15 -> 19606643 | GM15: =GI15*GM$8*GM$2/GI$2*GN$2 -> 12526.466 | GN15: =GJ15*GN$8 -> 1800 | GO15: =GM15*GN15 -> 22547639 | GQ15: =GM15*GQ$8*GQ$2/GM$2*GR$2 -> 14405.436 | GR15: =GN15*GR$8 -> 1800 | GS15: =GQ15*GR15 -> 25929785 | GU15: =GQ15*GU$8*GU$2/GQ$2*GV$2 -> 16566.252 | GV15: =GR15*GV$8 -> 1800 | GW15: =GU15*GV15 -> 29819253 | GY15: =GU15*GY$8*GY$2/GU$2*GZ$2 -> 19051.189 | GZ15: =GV15*GZ$8 -> 1800 | HA15: =GY15*GZ15 -> 34292141 | HC15: =GY15*HC$8*HC$2/GY$2*HD$2 -> 21908.868 | HD15: =GZ15*HD$8 -> 1800 | HE15: =HC15*HD15 -> 39435962 | HG15: =HC15*HG$8*HG$2/HC$2*HH$2 -> 25195.198 | HH15: =HD15*HH$8 -> 1800 | HI15: =HG15*HH15 -> 45351357 | HK15: =HG15*HK$8*HK$2/HG$2*HL$2 -> 28974.478 | HL15: =HH15*HL$8 -> 1800 | HM15: =HK15*HL15 -> 52154060 | HO15: =HK15*HO$8*HO$2/HK$2*HP$2 -> 33320.649 | HP15: =HL15*HP$8 -> 1800 | HQ15: =HO15*HP15 -> 59977169 | HS15: =HO15*HS$8*HS$2/HO$2*HT$2 -> 44066.559 | HT15: =HP15*HT$8 -> 1800 | HU15: =HS15*HT15 -> 79319806 | HW15: =HS15*HW$8*HW$2/HS$2*HX$2 -> 50676.543 | HX15: =HT15*HX$8 -> 1800 | HY15: =HW15*HX15 -> 91217777 | IA15: =HW15*IA$8*IA$2/HW$2*IB$2 -> 58278.024 | IB15: =HX15*IB$8 -> 1800 | IC15: =IA15*IB15 -> 1.0490044e+08 | IE15: =IA15*IE$8*IE$2/IA$2*IF$2 -> 67019.728 | IF15: =IB15*IF$8 -> 1800 | IG15: =IE15*IF15 -> 1.2063551e+08 | II15: =IE15*II$8*II$2/IE$2*IJ$2 -> 77072.687 | IJ15: =IF15*IJ$8 -> 1800 | IK15: =II15*IJ15 -> 1.3873084e+08 | IM15: =II15*IM$8*IM$2/II$2*IN$2 -> 88633.59 | IN15: =IJ15*IN$8 -> 1800 | IO15: =IM15*IN15 -> 1.5954046e+08 | IQ15: =IM15*IQ$8*IQ$2/IM$2*IR$2 -> 101928.63 | IR15: =IN15*IR$8 -> 1800 | IS15: =IQ15*IR15 -> 1.8347153e+08 | IU15: =IQ15*IU$8*IU$2/IQ$2*IV$2 -> 117217.92 | IV15: =IR15*IV$8 -> 1800 | IW15: =IU15*IV15 -> 2.1099226e+08 | IY15: =IU15*IY$8*IY$2/IU$2*IZ$2 -> 134800.61 | IZ15: =IV15*IZ$8 -> 1800 | JA15: =IY15*IZ15 -> 2.426411e+08 | JC15: =IY15*JC$8*JC$2/IY$2*JD$2 -> 155020.7 | JD15: =IZ15*JD$8 -> 1800 | JE15: =JC15*JD15 -> 2.7903726e+08 | JG15: =JC15*JG$8*JG$2/JC$2*JH$2 -> 178273.81 | JH15: =JD15*JH$8 -> 1800 | JI15: =JG15*JH15 -> 3.2089285e+08 | JK15: =JG15*JK$8*JK$2/JG$2*JL$2 -> 205014.88 | JL15: =JH15*JL$8 -> 1800 | JM15: =JK15*JL15 -> 3.6902678e+08 | JO15: =JK15*JO$8*JO$2/JK$2*JP$2 -> 238124.78 | JP15: =JL15*JP$8 -> 1800 | JQ15: =JO15*JP15 -> 4.2862461e+08 | JS15: =JO15*JS$8*JS$2/JO$2*JT$2 -> 273843.5 | JT15: =JP15*JT$8 -> 1800 | JU15: =JS15*JT15 -> 4.929183e+08 | JW15: =JS15*JW$8*JW$2/JS$2*JX$2 -> 314920.02 | JX15: =JT15*JX$8 -> 1800 | JY15: =JW15*JX15 -> 5.6685604e+08 | KA15: =JW15*KA$8*KA$2/JW$2*KB$2 -> 362158.03 | KB15: =JX15*KB$8 -> 1800 | KC15: =KA15*KB15 -> 6.5188445e+08 | KE15: =KA15*KE$8*KE$2/KA$2*KF$2 -> 416481.73 | KF15: =KB15*KF$8 -> 1800 | KG15: =KE15*KF15 -> 7.4966712e+08 | KI15: =SUMIFS($G15:$KG15,$G$3:$KG$3,KI$5,$G$6:$KG$6,KI$6) -> 13.3356 | KJ15: =KK15/KI15 -> 1800 | KK15: =SUMIFS($G15:$KG15,$G$3:$KG$3,KI$5,$G$6:$KG$6,KK$6) -> 24004.08 | KM15: =SUMIFS($G15:$KG15,$G$3:$KG$3,KM$5,$G$6:$KG$6,KM$6) -> 587.08052 | KN15: =KO15/KM15 -> 1800 | KO15: =SUMIFS($G15:$KG15,$G$3:$KG$3,KM$5,$G$6:$KG$6,KO$6) -> 1056744.9 | KQ15: =SUMIFS($G15:$KG15,$G$3:$KG$3,KQ$5,$G$6:$KG$6,KQ$6) -> 3864.3709 | KR15: =KS15/KQ15 -> 1800 | KS15: =SUMIFS($G15:$KG15,$G$3:$KG$3,KQ$5,$G$6:$KG$6,KS$6) -> 6955867.7 | KU15: =SUMIFS($G15:$KG15,$G$3:$KG$3,KU$5,$G$6:$KG$6,KU$6) -> 22953.383 | KV15: =KW15/KU15 -> 1800 | KW15: =SUMIFS($G15:$KG15,$G$3:$KG$3,KU$5,$G$6:$KG$6,KW$6) -> 41316089 | KY15: =SUMIFS($G15:$KG15,$G$3:$KG$3,KY$5,$G$6:$KG$6,KY$6) -> 135086.97 | KZ15: =LA15/KY15 -> 1800 | LA15: =SUMIFS($G15:$KG15,$G$3:$KG$3,KY$5,$G$6:$KG$6,LA$6) -> 2.4315655e+08 | LC15: =SUMIFS($G15:$KG15,$G$3:$KG$3,LC$5,$G$6:$KG$6,LC$6) -> 827184.62 | LD15: =LE15/LC15 -> 1800 | LE15: =SUMIFS($G15:$KG15,$G$3:$KG$3,LC$5,$G$6:$KG$6,LE$6) -> 1.4889323e+09
E16: ='A.I Revenue Streams - P1'!F16 -> Flap Surgery | H16: ='A.I Revenue Streams - P1'!J16 -> 33000 | I16: =G16*H16 -> 0 | K16: ='A.I Revenue Streams - P1'!H16*K$2*L$2 -> 0.45 | L16: =H16*$L$8 -> 33000 | M16: =K16*L16 -> 14850 | O16: =K16*O$8*O$2/K$2*P$2 -> 0.480375 | P16: =L16*P$8 -> 33000 | Q16: =O16*P16 -> 15852.375 | S16: =O16*S$8*S$2/O$2*T$2 -> 0.736575 | T16: =P16*T$8 -> 33000 | U16: =S16*T16 -> 24306.975 | W16: =S16*W$8*W$2/S$2*X$2 -> 1.0588266 | X16: =T16*X$8 -> 33000 | Y16: =W16*X16 -> 34941.277 | AA16: =W16*AA$8*AA$2/W$2*AB$2 -> 1.9482409 | AB16: =X16*AB$8 -> 33000 | AC16: =AA16*AB16 -> 64291.949 | AE16: =AA16*AE$8*AE$2/AA$2*AF$2 -> 2.8005963 | AF16: =AB16*AF$8 -> 33000 | AG16: =AE16*AF16 -> 92419.677 | AI16: =AE16*AI$8*AI$2/AE$2*AJ$2 -> 4.0258571 | AJ16: =AF16*AJ$8 -> 33000 | AK16: =AI16*AJ16 -> 132853.28 | AM16: =AI16*AM$8*AM$2/AI$2*AN$2 -> 4.6297357 | AN16: =AJ16*AN$8 -> 33000 | AO16: =AM16*AN16 -> 152781.28 | AQ16: =AM16*AQ$8*AQ$2/AM$2*AR$2 -> 5.324196 | AR16: =AN16*AR$8 -> 33000 | AS16: =AQ16*AR16 -> 175698.47 | AU16: =AQ16*AU$8*AU$2/AQ$2*AV$2 -> 6.1228254 | AV16: =AR16*AV$8 -> 33000 | AW16: =AU16*AV16 -> 202053.24 | AY16: =AU16*AY$8*AY$2/AU$2*AZ$2 -> 7.0412493 | AZ16: =AV16*AZ$8 -> 33000 | BA16: =AY16*AZ16 -> 232361.23 | BC16: =AY16*BC$8*BC$2/AY$2*BD$2 -> 8.0974367 | BD16: =AZ16*BD$8 -> 33000 | BE16: =BC16*BD16 -> 267215.41 | BG16: =BC16*BG$8*BG$2/BC$2*BH$2 -> 9.3120522 | BH16: =BD16*BH$8 -> 33000 | BI16: =BG16*BH16 -> 307297.72 | BK16: =BG16*BK$8*BK$2/BG$2*BL$2 -> 10.70886 | BL16: =BH16*BL$8 -> 33000 | BM16: =BK16*BL16 -> 353392.38 | BO16: =BK16*BO$8*BO$2/BK$2*BP$2 -> 12.315189 | BP16: =BL16*BP$8 -> 33000 | BQ16: =BO16*BP16 -> 406401.24 | BS16: =BO16*BS$8*BS$2/BO$2*BT$2 -> 14.162467 | BT16: =BP16*BT$8 -> 33000 | BU16: =BS16*BT16 -> 467361.42 | BW16: =BS16*BW$8*BW$2/BS$2*BX$2 -> 16.286837 | BX16: =BT16*BX$8 -> 33000 | BY16: =BW16*BX16 -> 537465.63 | CA16: =BW16*CA$8*CA$2/BW$2*CB$2 -> 18.729863 | CB16: =BX16*CB$8 -> 33000 | CC16: =CA16*CB16 -> 618085.48 | CE16: =CA16*CE$8*CE$2/CA$2*CF$2 -> 25.847211 | CF16: =CB16*CF$8 -> 33000 | CG16: =CE16*CF16 -> 852957.96 | CI16: =CE16*CI$8*CI$2/CE$2*CJ$2 -> 29.724293 | CJ16: =CF16*CJ$8 -> 33000 | CK16: =CI16*CJ16 -> 980901.66 | CM16: =CI16*CM$8*CM$2/CI$2*CN$2 -> 34.182937 | CN16: =CJ16*CN$8 -> 33000 | CO16: =CM16*CN16 -> 1128036.9 | CQ16: =CM16*CQ$8*CQ$2/CM$2*CR$2 -> 39.310377 | CR16: =CN16*CR$8 -> 33000 | CS16: =CQ16*CR16 -> 1297242.4 | CU16: =CQ16*CU$8*CU$2/CQ$2*CV$2 -> 45.206934 | CV16: =CR16*CV$8 -> 33000 | CW16: =CU16*CV16 -> 1491828.8 | CY16: =CU16*CY$8*CY$2/CU$2*CZ$2 -> 51.987974 | CZ16: =CV16*CZ$8 -> 33000 | DA16: =CY16*CZ16 -> 1715603.1 | DC16: =CY16*DC$8*DC$2/CY$2*DD$2 -> 59.78617 | DD16: =CZ16*DD$8 -> 33000 | DE16: =DC16*DD16 -> 1972943.6 | DG16: =DC16*DG$8*DG$2/DC$2*DH$2 -> 68.754095 | DH16: =DD16*DH$8 -> 33000 | DI16: =DG16*DH16 -> 2268885.1 | DK16: =DG16*DK$8*DK$2/DG$2*DL$2 -> 79.067209 | DL16: =DH16*DL$8 -> 33000 | DM16: =DK16*DL16 -> 2609217.9 | DO16: =DK16*DO$8*DO$2/DK$2*DP$2 -> 90.927291 | DP16: =DL16*DP$8 -> 33000 | DQ16: =DO16*DP16 -> 3000600.6 | DS16: =DO16*DS$8*DS$2/DO$2*DT$2 -> 104.56638 | DT16: =DP16*DT$8 -> 33000 | DU16: =DS16*DT16 -> 3450690.7 | DW16: =DS16*DW$8*DW$2/DS$2*DX$2 -> 120.25134 | DX16: =DT16*DX$8 -> 33000 | DY16: =DW16*DX16 -> 3968294.3 | EA16: =DW16*EA$8*EA$2/DW$2*EB$2 -> 152.11795 | EB16: =DX16*EB$8 -> 33000 | EC16: =EA16*EB16 -> 5019892.3 | EE16: =EA16*EE$8*EE$2/EA$2*EF$2 -> 174.93564 | EF16: =EB16*EF$8 -> 33000 | EG16: =EE16*EF16 -> 5772876.1 | EI16: =EE16*EI$8*EI$2/EE$2*EJ$2 -> 201.17599 | EJ16: =EF16*EJ$8 -> 33000 | EK16: =EI16*EJ16 -> 6638807.5 | EM16: =EI16*EM$8*EM$2/EI$2*EN$2 -> 231.35238 | EN16: =EJ16*EN$8 -> 33000 | EO16: =EM16*EN16 -> 7634628.7 | EQ16: =EM16*EQ$8*EQ$2/EM$2*ER$2 -> 266.05524 | ER16: =EN16*ER$8 -> 33000 | ES16: =EQ16*ER16 -> 8779823 | EU16: =EQ16*EU$8*EU$2/EQ$2*EV$2 -> 305.96353 | EV16: =ER16*EV$8 -> 33000 | EW16: =EU16*EV16 -> 10096796 | EY16: =EU16*EY$8*EY$2/EU$2*EZ$2 -> 351.85806 | EZ16: =EV16*EZ$8 -> 33000 | FA16: =EY16*EZ16 -> 11611316 | FC16: =EY16*FC$8*FC$2/EY$2*FD$2 -> 404.63676 | FD16: =EZ16*FD$8 -> 33000 | FE16: =FC16*FD16 -> 13353013 | FG16: =FC16*FG$8*FG$2/FC$2*FH$2 -> 465.33228 | FH16: =FD16*FH$8 -> 33000 | FI16: =FG16*FH16 -> 15355965 | FK16: =FG16*FK$8*FK$2/FG$2*FL$2 -> 535.13212 | FL16: =FH16*FL$8 -> 33000 | FM16: =FK16*FL16 -> 17659360 | FO16: =FK16*FO$8*FO$2/FK$2*FP$2 -> 615.40194 | FP16: =FL16*FP$8 -> 33000 | FQ16: =FO16*FP16 -> 20308264 | FS16: =FO16*FS$8*FS$2/FO$2*FT$2 -> 707.71223 | FT16: =FP16*FT$8 -> 33000 | FU16: =FS16*FT16 -> 23354504 | FW16: =FS16*FW$8*FW$2/FS$2*FX$2 -> 895.25597 | FX16: =FT16*FX$8 -> 33000 | FY16: =FW16*FX16 -> 29543447 | GA16: =FW16*GA$8*GA$2/FW$2*GB$2 -> 1029.5444 | GB16: =FX16*GB$8 -> 33000 | GC16: =GA16*GB16 -> 33974964 | GE16: =GA16*GE$8*GE$2/GA$2*GF$2 -> 1183.976 | GF16: =GB16*GF$8 -> 33000 | GG16: =GE16*GF16 -> 39071209 | GI16: =GE16*GI$8*GI$2/GE$2*GJ$2 -> 1361.5724 | GJ16: =GF16*GJ$8 -> 33000 | GK16: =GI16*GJ16 -> 44931890 | GM16: =GI16*GM$8*GM$2/GI$2*GN$2 -> 1565.8083 | GN16: =GJ16*GN$8 -> 33000 | GO16: =GM16*GN16 -> 51671674 | GQ16: =GM16*GQ$8*GQ$2/GM$2*GR$2 -> 1800.6795 | GR16: =GN16*GR$8 -> 33000 | GS16: =GQ16*GR16 -> 59422425 | GU16: =GQ16*GU$8*GU$2/GQ$2*GV$2 -> 2070.7815 | GV16: =GR16*GV$8 -> 33000 | GW16: =GU16*GV16 -> 68335788 | GY16: =GU16*GY$8*GY$2/GU$2*GZ$2 -> 2381.3987 | GZ16: =GV16*GZ$8 -> 33000 | HA16: =GY16*GZ16 -> 78586157 | HC16: =GY16*HC$8*HC$2/GY$2*HD$2 -> 2738.6085 | HD16: =GZ16*HD$8 -> 33000 | HE16: =HC16*HD16 -> 90374080 | HG16: =HC16*HG$8*HG$2/HC$2*HH$2 -> 3149.3998 | HH16: =HD16*HH$8 -> 33000 | HI16: =HG16*HH16 -> 1.0393019e+08 | HK16: =HG16*HK$8*HK$2/HG$2*HL$2 -> 3621.8097 | HL16: =HH16*HL$8 -> 33000 | HM16: =HK16*HL16 -> 1.1951972e+08 | HO16: =HK16*HO$8*HO$2/HK$2*HP$2 -> 4165.0812 | HP16: =HL16*HP$8 -> 33000 | HQ16: =HO16*HP16 -> 1.3744768e+08 | HS16: =HO16*HS$8*HS$2/HO$2*HT$2 -> 5508.3199 | HT16: =HP16*HT$8 -> 33000 | HU16: =HS16*HT16 -> 1.8177456e+08 | HW16: =HS16*HW$8*HW$2/HS$2*HX$2 -> 6334.5678 | HX16: =HT16*HX$8 -> 33000 | HY16: =HW16*HX16 -> 2.0904074e+08 | IA16: =HW16*IA$8*IA$2/HW$2*IB$2 -> 7284.753 | IB16: =HX16*IB$8 -> 33000 | IC16: =IA16*IB16 -> 2.4039685e+08 | IE16: =IA16*IE$8*IE$2/IA$2*IF$2 -> 8377.466 | IF16: =IB16*IF$8 -> 33000 | IG16: =IE16*IF16 -> 2.7645638e+08 | II16: =IE16*II$8*II$2/IE$2*IJ$2 -> 9634.0859 | IJ16: =IF16*IJ$8 -> 33000 | IK16: =II16*IJ16 -> 3.1792483e+08 | IM16: =II16*IM$8*IM$2/II$2*IN$2 -> 11079.199 | IN16: =IJ16*IN$8 -> 33000 | IO16: =IM16*IN16 -> 3.6561356e+08 | IQ16: =IM16*IQ$8*IQ$2/IM$2*IR$2 -> 12741.079 | IR16: =IN16*IR$8 -> 33000 | IS16: =IQ16*IR16 -> 4.2045559e+08 | IU16: =IQ16*IU$8*IU$2/IQ$2*IV$2 -> 14652.24 | IV16: =IR16*IV$8 -> 33000 | IW16: =IU16*IV16 -> 4.8352393e+08 | IY16: =IU16*IY$8*IY$2/IU$2*IZ$2 -> 16850.076 | IZ16: =IV16*IZ$8 -> 33000 | JA16: =IY16*IZ16 -> 5.5605252e+08 | JC16: =IY16*JC$8*JC$2/IY$2*JD$2 -> 19377.588 | JD16: =IZ16*JD$8 -> 33000 | JE16: =JC16*JD16 -> 6.394604e+08 | JG16: =JC16*JG$8*JG$2/JC$2*JH$2 -> 22284.226 | JH16: =JD16*JH$8 -> 33000 | JI16: =JG16*JH16 -> 7.3537946e+08 | JK16: =JG16*JK$8*JK$2/JG$2*JL$2 -> 25626.86 | JL16: =JH16*JL$8 -> 33000 | JM16: =JK16*JL16 -> 8.4568638e+08 | JO16: =JK16*JO$8*JO$2/JK$2*JP$2 -> 29765.598 | JP16: =JL16*JP$8 -> 33000 | JQ16: =JO16*JP16 -> 9.8226473e+08 | JS16: =JO16*JS$8*JS$2/JO$2*JT$2 -> 34230.437 | JT16: =JP16*JT$8 -> 33000 | JU16: =JS16*JT16 -> 1.1296044e+09 | JW16: =JS16*JW$8*JW$2/JS$2*JX$2 -> 39365.003 | JX16: =JT16*JX$8 -> 33000 | JY16: =JW16*JX16 -> 1.2990451e+09 | KA16: =JW16*KA$8*KA$2/JW$2*KB$2 -> 45269.754 | KB16: =JX16*KB$8 -> 33000 | KC16: =KA16*KB16 -> 1.4939019e+09 | KE16: =KA16*KE$8*KE$2/KA$2*KF$2 -> 52060.217 | KF16: =KB16*KF$8 -> 33000 | KG16: =KE16*KF16 -> 1.7179871e+09 | KI16: =SUMIFS($G16:$KG16,$G$3:$KG$3,KI$5,$G$6:$KG$6,KI$6) -> 1.66695 | KJ16: =KK16/KI16 -> 33000 | KK16: =SUMIFS($G16:$KG16,$G$3:$KG$3,KI$5,$G$6:$KG$6,KK$6) -> 55009.35 | KM16: =SUMIFS($G16:$KG16,$G$3:$KG$3,KM$5,$G$6:$KG$6,KM$6) -> 73.385065 | KN16: =KO16/KM16 -> 33000 | KO16: =SUMIFS($G16:$KG16,$G$3:$KG$3,KM$5,$G$6:$KG$6,KO$6) -> 2421707.1 | KQ16: =SUMIFS($G16:$KG16,$G$3:$KG$3,KQ$5,$G$6:$KG$6,KQ$6) -> 483.04637 | KR16: =KS16/KQ16 -> 33000 | KS16: =SUMIFS($G16:$KG16,$G$3:$KG$3,KQ$5,$G$6:$KG$6,KS$6) -> 15940530 | KU16: =SUMIFS($G16:$KG16,$G$3:$KG$3,KU$5,$G$6:$KG$6,KU$6) -> 2869.1728 | KV16: =KW16/KU16 -> 33000 | KW16: =SUMIFS($G16:$KG16,$G$3:$KG$3,KU$5,$G$6:$KG$6,KW$6) -> 94682704 | KY16: =SUMIFS($G16:$KG16,$G$3:$KG$3,KY$5,$G$6:$KG$6,KY$6) -> 16885.872 | KZ16: =LA16/KY16 -> 33000 | LA16: =SUMIFS($G16:$KG16,$G$3:$KG$3,KY$5,$G$6:$KG$6,LA$6) -> 5.5723376e+08 | LC16: =SUMIFS($G16:$KG16,$G$3:$KG$3,LC$5,$G$6:$KG$6,LC$6) -> 103398.08 | LD16: =LE16/LC16 -> 33000 | LE16: =SUMIFS($G16:$KG16,$G$3:$KG$3,LC$5,$G$6:$KG$6,LE$6) -> 3.4121365e+09
E17: ='A.I Revenue Streams - P1'!F17 -> Curetta (2-3 teeth) | H17: ='A.I Revenue Streams - P1'!J17 -> 3700 | I17: =G17*H17 -> 0 | K17: ='A.I Revenue Streams - P1'!H17*K$2*L$2 -> 1.8 | L17: =H17*$L$8 -> 3700 | M17: =K17*L17 -> 6660 | O17: =K17*O$8*O$2/K$2*P$2 -> 1.9215 | P17: =L17*P$8 -> 3700 | Q17: =O17*P17 -> 7109.55 | S17: =O17*S$8*S$2/O$2*T$2 -> 2.9463 | T17: =P17*T$8 -> 3700 | U17: =S17*T17 -> 10901.31 | W17: =S17*W$8*W$2/S$2*X$2 -> 4.2353062 | X17: =T17*X$8 -> 3700 | Y17: =W17*X17 -> 15670.633 | AA17: =W17*AA$8*AA$2/W$2*AB$2 -> 7.7929635 | AB17: =X17*AB$8 -> 3700 | AC17: =AA17*AB17 -> 28833.965 | AE17: =AA17*AE$8*AE$2/AA$2*AF$2 -> 11.202385 | AF17: =AB17*AF$8 -> 3700 | AG17: =AE17*AF17 -> 41448.825 | AI17: =AE17*AI$8*AI$2/AE$2*AJ$2 -> 16.103428 | AJ17: =AF17*AJ$8 -> 3700 | AK17: =AI17*AJ17 -> 59582.685 | AM17: =AI17*AM$8*AM$2/AI$2*AN$2 -> 18.518943 | AN17: =AJ17*AN$8 -> 3700 | AO17: =AM17*AN17 -> 68520.088 | AQ17: =AM17*AQ$8*AQ$2/AM$2*AR$2 -> 21.296784 | AR17: =AN17*AR$8 -> 3700 | AS17: =AQ17*AR17 -> 78798.101 | AU17: =AQ17*AU$8*AU$2/AQ$2*AV$2 -> 24.491302 | AV17: =AR17*AV$8 -> 3700 | AW17: =AU17*AV17 -> 90617.817 | AY17: =AU17*AY$8*AY$2/AU$2*AZ$2 -> 28.164997 | AZ17: =AV17*AZ$8 -> 3700 | BA17: =AY17*AZ17 -> 104210.49 | BC17: =AY17*BC$8*BC$2/AY$2*BD$2 -> 32.389747 | BD17: =AZ17*BD$8 -> 3700 | BE17: =BC17*BD17 -> 119842.06 | BG17: =BC17*BG$8*BG$2/BC$2*BH$2 -> 37.248209 | BH17: =BD17*BH$8 -> 3700 | BI17: =BG17*BH17 -> 137818.37 | BK17: =BG17*BK$8*BK$2/BG$2*BL$2 -> 42.83544 | BL17: =BH17*BL$8 -> 3700 | BM17: =BK17*BL17 -> 158491.13 | BO17: =BK17*BO$8*BO$2/BK$2*BP$2 -> 49.260756 | BP17: =BL17*BP$8 -> 3700 | BQ17: =BO17*BP17 -> 182264.8 | BS17: =BO17*BS$8*BS$2/BO$2*BT$2 -> 56.649869 | BT17: =BP17*BT$8 -> 3700 | BU17: =BS17*BT17 -> 209604.52 | BW17: =BS17*BW$8*BW$2/BS$2*BX$2 -> 65.14735 | BX17: =BT17*BX$8 -> 3700 | BY17: =BW17*BX17 -> 241045.19 | CA17: =BW17*CA$8*CA$2/BW$2*CB$2 -> 74.919452 | CB17: =BX17*CB$8 -> 3700 | CC17: =CA17*CB17 -> 277201.97 | CE17: =CA17*CE$8*CE$2/CA$2*CF$2 -> 103.38884 | CF17: =CB17*CF$8 -> 3700 | CG17: =CE17*CF17 -> 382538.72 | CI17: =CE17*CI$8*CI$2/CE$2*CJ$2 -> 118.89717 | CJ17: =CF17*CJ$8 -> 3700 | CK17: =CI17*CJ17 -> 439919.53 | CM17: =CI17*CM$8*CM$2/CI$2*CN$2 -> 136.73175 | CN17: =CJ17*CN$8 -> 3700 | CO17: =CM17*CN17 -> 505907.46 | CQ17: =CM17*CQ$8*CQ$2/CM$2*CR$2 -> 157.24151 | CR17: =CN17*CR$8 -> 3700 | CS17: =CQ17*CR17 -> 581793.58 | CU17: =CQ17*CU$8*CU$2/CQ$2*CV$2 -> 180.82773 | CV17: =CR17*CV$8 -> 3700 | CW17: =CU17*CV17 -> 669062.62 | CY17: =CU17*CY$8*CY$2/CU$2*CZ$2 -> 207.95189 | CZ17: =CV17*CZ$8 -> 3700 | DA17: =CY17*CZ17 -> 769422.01 | DC17: =CY17*DC$8*DC$2/CY$2*DD$2 -> 239.14468 | DD17: =CZ17*DD$8 -> 3700 | DE17: =DC17*DD17 -> 884835.31 | DG17: =DC17*DG$8*DG$2/DC$2*DH$2 -> 275.01638 | DH17: =DD17*DH$8 -> 3700 | DI17: =DG17*DH17 -> 1017560.6 | DK17: =DG17*DK$8*DK$2/DG$2*DL$2 -> 316.26884 | DL17: =DH17*DL$8 -> 3700 | DM17: =DK17*DL17 -> 1170194.7 | DO17: =DK17*DO$8*DO$2/DK$2*DP$2 -> 363.70916 | DP17: =DL17*DP$8 -> 3700 | DQ17: =DO17*DP17 -> 1345723.9 | DS17: =DO17*DS$8*DS$2/DO$2*DT$2 -> 418.26554 | DT17: =DP17*DT$8 -> 3700 | DU17: =DS17*DT17 -> 1547582.5 | DW17: =DS17*DW$8*DW$2/DS$2*DX$2 -> 481.00537 | DX17: =DT17*DX$8 -> 3700 | DY17: =DW17*DX17 -> 1779719.9 | EA17: =DW17*EA$8*EA$2/DW$2*EB$2 -> 608.47179 | EB17: =DX17*EB$8 -> 3700 | EC17: =EA17*EB17 -> 2251345.6 | EE17: =EA17*EE$8*EE$2/EA$2*EF$2 -> 699.74256 | EF17: =EB17*EF$8 -> 3700 | EG17: =EE17*EF17 -> 2589047.5 | EI17: =EE17*EI$8*EI$2/EE$2*EJ$2 -> 804.70394 | EJ17: =EF17*EJ$8 -> 3700 | EK17: =EI17*EJ17 -> 2977404.6 | EM17: =EI17*EM$8*EM$2/EI$2*EN$2 -> 925.40953 | EN17: =EJ17*EN$8 -> 3700 | EO17: =EM17*EN17 -> 3424015.3 | EQ17: =EM17*EQ$8*EQ$2/EM$2*ER$2 -> 1064.221 | ER17: =EN17*ER$8 -> 3700 | ES17: =EQ17*ER17 -> 3937617.6 | EU17: =EQ17*EU$8*EU$2/EQ$2*EV$2 -> 1223.8541 | EV17: =ER17*EV$8 -> 3700 | EW17: =EU17*EV17 -> 4528260.2 | EY17: =EU17*EY$8*EY$2/EU$2*EZ$2 -> 1407.4322 | EZ17: =EV17*EZ$8 -> 3700 | FA17: =EY17*EZ17 -> 5207499.2 | FC17: =EY17*FC$8*FC$2/EY$2*FD$2 -> 1618.5471 | FD17: =EZ17*FD$8 -> 3700 | FE17: =FC17*FD17 -> 5988624.1 | FG17: =FC17*FG$8*FG$2/FC$2*FH$2 -> 1861.3291 | FH17: =FD17*FH$8 -> 3700 | FI17: =FG17*FH17 -> 6886917.7 | FK17: =FG17*FK$8*FK$2/FG$2*FL$2 -> 2140.5285 | FL17: =FH17*FL$8 -> 3700 | FM17: =FK17*FL17 -> 7919955.4 | FO17: =FK17*FO$8*FO$2/FK$2*FP$2 -> 2461.6078 | FP17: =FL17*FP$8 -> 3700 | FQ17: =FO17*FP17 -> 9107948.7 | FS17: =FO17*FS$8*FS$2/FO$2*FT$2 -> 2830.8489 | FT17: =FP17*FT$8 -> 3700 | FU17: =FS17*FT17 -> 10474141 | FW17: =FS17*FW$8*FW$2/FS$2*FX$2 -> 3581.0239 | FX17: =FT17*FX$8 -> 3700 | FY17: =FW17*FX17 -> 13249788 | GA17: =FW17*GA$8*GA$2/FW$2*GB$2 -> 4118.1775 | GB17: =FX17*GB$8 -> 3700 | GC17: =GA17*GB17 -> 15237257 | GE17: =GA17*GE$8*GE$2/GA$2*GF$2 -> 4735.9041 | GF17: =GB17*GF$8 -> 3700 | GG17: =GE17*GF17 -> 17522845 | GI17: =GE17*GI$8*GI$2/GE$2*GJ$2 -> 5446.2897 | GJ17: =GF17*GJ$8 -> 3700 | GK17: =GI17*GJ17 -> 20151272 | GM17: =GI17*GM$8*GM$2/GI$2*GN$2 -> 6263.2332 | GN17: =GJ17*GN$8 -> 3700 | GO17: =GM17*GN17 -> 23173963 | GQ17: =GM17*GQ$8*GQ$2/GM$2*GR$2 -> 7202.7181 | GR17: =GN17*GR$8 -> 3700 | GS17: =GQ17*GR17 -> 26650057 | GU17: =GQ17*GU$8*GU$2/GQ$2*GV$2 -> 8283.1259 | GV17: =GR17*GV$8 -> 3700 | GW17: =GU17*GV17 -> 30647566 | GY17: =GU17*GY$8*GY$2/GU$2*GZ$2 -> 9525.5947 | GZ17: =GV17*GZ$8 -> 3700 | HA17: =GY17*GZ17 -> 35244701 | HC17: =GY17*HC$8*HC$2/GY$2*HD$2 -> 10954.434 | HD17: =GZ17*HD$8 -> 3700 | HE17: =HC17*HD17 -> 40531406 | HG17: =HC17*HG$8*HG$2/HC$2*HH$2 -> 12597.599 | HH17: =HD17*HH$8 -> 3700 | HI17: =HG17*HH17 -> 46611116 | HK17: =HG17*HK$8*HK$2/HG$2*HL$2 -> 14487.239 | HL17: =HH17*HL$8 -> 3700 | HM17: =HK17*HL17 -> 53602784 | HO17: =HK17*HO$8*HO$2/HK$2*HP$2 -> 16660.325 | HP17: =HL17*HP$8 -> 3700 | HQ17: =HO17*HP17 -> 61643201 | HS17: =HO17*HS$8*HS$2/HO$2*HT$2 -> 22033.279 | HT17: =HP17*HT$8 -> 3700 | HU17: =HS17*HT17 -> 81523134 | HW17: =HS17*HW$8*HW$2/HS$2*HX$2 -> 25338.271 | HX17: =HT17*HX$8 -> 3700 | HY17: =HW17*HX17 -> 93751604 | IA17: =HW17*IA$8*IA$2/HW$2*IB$2 -> 29139.012 | IB17: =HX17*IB$8 -> 3700 | IC17: =IA17*IB17 -> 1.0781434e+08 | IE17: =IA17*IE$8*IE$2/IA$2*IF$2 -> 33509.864 | IF17: =IB17*IF$8 -> 3700 | IG17: =IE17*IF17 -> 1.239865e+08 | II17: =IE17*II$8*II$2/IE$2*IJ$2 -> 38536.343 | IJ17: =IF17*IJ$8 -> 3700 | IK17: =II17*IJ17 -> 1.4258447e+08 | IM17: =II17*IM$8*IM$2/II$2*IN$2 -> 44316.795 | IN17: =IJ17*IN$8 -> 3700 | IO17: =IM17*IN17 -> 1.6397214e+08 | IQ17: =IM17*IQ$8*IQ$2/IM$2*IR$2 -> 50964.314 | IR17: =IN17*IR$8 -> 3700 | IS17: =IQ17*IR17 -> 1.8856796e+08 | IU17: =IQ17*IU$8*IU$2/IQ$2*IV$2 -> 58608.961 | IV17: =IR17*IV$8 -> 3700 | IW17: =IU17*IV17 -> 2.1685316e+08 | IY17: =IU17*IY$8*IY$2/IU$2*IZ$2 -> 67400.306 | IZ17: =IV17*IZ$8 -> 3700 | JA17: =IY17*IZ17 -> 2.4938113e+08 | JC17: =IY17*JC$8*JC$2/IY$2*JD$2 -> 77510.351 | JD17: =IZ17*JD$8 -> 3700 | JE17: =JC17*JD17 -> 2.867883e+08 | JG17: =JC17*JG$8*JG$2/JC$2*JH$2 -> 89136.904 | JH17: =JD17*JH$8 -> 3700 | JI17: =JG17*JH17 -> 3.2980655e+08 | JK17: =JG17*JK$8*JK$2/JG$2*JL$2 -> 102507.44 | JL17: =JH17*JL$8 -> 3700 | JM17: =JK17*JL17 -> 3.7927753e+08 | JO17: =JK17*JO$8*JO$2/JK$2*JP$2 -> 119062.39 | JP17: =JL17*JP$8 -> 3700 | JQ17: =JO17*JP17 -> 4.4053085e+08 | JS17: =JO17*JS$8*JS$2/JO$2*JT$2 -> 136921.75 | JT17: =JP17*JT$8 -> 3700 | JU17: =JS17*JT17 -> 5.0661047e+08 | JW17: =JS17*JW$8*JW$2/JS$2*JX$2 -> 157460.01 | JX17: =JT17*JX$8 -> 3700 | JY17: =JW17*JX17 -> 5.8260205e+08 | KA17: =JW17*KA$8*KA$2/JW$2*KB$2 -> 181079.01 | KB17: =JX17*KB$8 -> 3700 | KC17: =KA17*KB17 -> 6.6999235e+08 | KE17: =KA17*KE$8*KE$2/KA$2*KF$2 -> 208240.87 | KF17: =KB17*KF$8 -> 3700 | KG17: =KE17*KF17 -> 7.7049121e+08 | KI17: =SUMIFS($G17:$KG17,$G$3:$KG$3,KI$5,$G$6:$KG$6,KI$6) -> 6.6678 | KJ17: =KK17/KI17 -> 3700 | KK17: =SUMIFS($G17:$KG17,$G$3:$KG$3,KI$5,$G$6:$KG$6,KK$6) -> 24670.86 | KM17: =SUMIFS($G17:$KG17,$G$3:$KG$3,KM$5,$G$6:$KG$6,KM$6) -> 293.54026 | KN17: =KO17/KM17 -> 3700 | KO17: =SUMIFS($G17:$KG17,$G$3:$KG$3,KM$5,$G$6:$KG$6,KO$6) -> 1086099 | KQ17: =SUMIFS($G17:$KG17,$G$3:$KG$3,KQ$5,$G$6:$KG$6,KQ$6) -> 1932.1855 | KR17: =KS17/KQ17 -> 3700 | KS17: =SUMIFS($G17:$KG17,$G$3:$KG$3,KQ$5,$G$6:$KG$6,KS$6) -> 7149086.2 | KU17: =SUMIFS($G17:$KG17,$G$3:$KG$3,KU$5,$G$6:$KG$6,KU$6) -> 11476.691 | KV17: =KW17/KU17 -> 3700 | KW17: =SUMIFS($G17:$KG17,$G$3:$KG$3,KU$5,$G$6:$KG$6,KW$6) -> 42463758 | KY17: =SUMIFS($G17:$KG17,$G$3:$KG$3,KY$5,$G$6:$KG$6,KY$6) -> 67543.486 | KZ17: =LA17/KY17 -> 3700 | LA17: =SUMIFS($G17:$KG17,$G$3:$KG$3,KY$5,$G$6:$KG$6,LA$6) -> 2.499109e+08 | LC17: =SUMIFS($G17:$KG17,$G$3:$KG$3,LC$5,$G$6:$KG$6,LC$6) -> 413592.31 | LD17: =LE17/LC17 -> 3700 | LE17: =SUMIFS($G17:$KG17,$G$3:$KG$3,LC$5,$G$6:$KG$6,LE$6) -> 1.5302915e+09
E18: ='A.I Revenue Streams - P1'!F18 -> Complete Denture | H18: ='A.I Revenue Streams - P1'!J18 -> 30000 | I18: =G18*H18 -> 0 | K18: ='A.I Revenue Streams - P1'!H18*K$2*L$2 -> 0.225 | L18: =H18*$L$8 -> 30000 | M18: =K18*L18 -> 6750 | O18: =K18*O$8*O$2/K$2*P$2 -> 0.2401875 | P18: =L18*P$8 -> 30000 | Q18: =O18*P18 -> 7205.625 | S18: =O18*S$8*S$2/O$2*T$2 -> 0.3682875 | T18: =P18*T$8 -> 30000 | U18: =S18*T18 -> 11048.625 | W18: =S18*W$8*W$2/S$2*X$2 -> 0.52941328 | X18: =T18*X$8 -> 30000 | Y18: =W18*X18 -> 15882.398 | AA18: =W18*AA$8*AA$2/W$2*AB$2 -> 0.97412044 | AB18: =X18*AB$8 -> 30000 | AC18: =AA18*AB18 -> 29223.613 | AE18: =AA18*AE$8*AE$2/AA$2*AF$2 -> 1.4002981 | AF18: =AB18*AF$8 -> 30000 | AG18: =AE18*AF18 -> 42008.944 | AI18: =AE18*AI$8*AI$2/AE$2*AJ$2 -> 2.0129286 | AJ18: =AF18*AJ$8 -> 30000 | AK18: =AI18*AJ18 -> 60387.857 | AM18: =AI18*AM$8*AM$2/AI$2*AN$2 -> 2.3148678 | AN18: =AJ18*AN$8 -> 30000 | AO18: =AM18*AN18 -> 69446.035 | AQ18: =AM18*AQ$8*AQ$2/AM$2*AR$2 -> 2.662098 | AR18: =AN18*AR$8 -> 30000 | AS18: =AQ18*AR18 -> 79862.941 | AU18: =AQ18*AU$8*AU$2/AQ$2*AV$2 -> 3.0614127 | AV18: =AR18*AV$8 -> 30000 | AW18: =AU18*AV18 -> 91842.382 | AY18: =AU18*AY$8*AY$2/AU$2*AZ$2 -> 3.5206246 | AZ18: =AV18*AZ$8 -> 30000 | BA18: =AY18*AZ18 -> 105618.74 | BC18: =AY18*BC$8*BC$2/AY$2*BD$2 -> 4.0487183 | BD18: =AZ18*BD$8 -> 30000 | BE18: =BC18*BD18 -> 121461.55 | BG18: =BC18*BG$8*BG$2/BC$2*BH$2 -> 4.6560261 | BH18: =BD18*BH$8 -> 30000 | BI18: =BG18*BH18 -> 139680.78 | BK18: =BG18*BK$8*BK$2/BG$2*BL$2 -> 5.35443 | BL18: =BH18*BL$8 -> 30000 | BM18: =BK18*BL18 -> 160632.9 | BO18: =BK18*BO$8*BO$2/BK$2*BP$2 -> 6.1575945 | BP18: =BL18*BP$8 -> 30000 | BQ18: =BO18*BP18 -> 184727.83 | BS18: =BO18*BS$8*BS$2/BO$2*BT$2 -> 7.0812337 | BT18: =BP18*BT$8 -> 30000 | BU18: =BS18*BT18 -> 212437.01 | BW18: =BS18*BW$8*BW$2/BS$2*BX$2 -> 8.1434187 | BX18: =BT18*BX$8 -> 30000 | BY18: =BW18*BX18 -> 244302.56 | CA18: =BW18*CA$8*CA$2/BW$2*CB$2 -> 9.3649315 | CB18: =BX18*CB$8 -> 30000 | CC18: =CA18*CB18 -> 280947.95 | CE18: =CA18*CE$8*CE$2/CA$2*CF$2 -> 12.923605 | CF18: =CB18*CF$8 -> 30000 | CG18: =CE18*CF18 -> 387708.16 | CI18: =CE18*CI$8*CI$2/CE$2*CJ$2 -> 14.862146 | CJ18: =CF18*CJ$8 -> 30000 | CK18: =CI18*CJ18 -> 445864.39 | CM18: =CI18*CM$8*CM$2/CI$2*CN$2 -> 17.091468 | CN18: =CJ18*CN$8 -> 30000 | CO18: =CM18*CN18 -> 512744.05 | CQ18: =CM18*CQ$8*CQ$2/CM$2*CR$2 -> 19.655189 | CR18: =CN18*CR$8 -> 30000 | CS18: =CQ18*CR18 -> 589655.66 | CU18: =CQ18*CU$8*CU$2/CQ$2*CV$2 -> 22.603467 | CV18: =CR18*CV$8 -> 30000 | CW18: =CU18*CV18 -> 678104 | CY18: =CU18*CY$8*CY$2/CU$2*CZ$2 -> 25.993987 | CZ18: =CV18*CZ$8 -> 30000 | DA18: =CY18*CZ18 -> 779819.6 | DC18: =CY18*DC$8*DC$2/CY$2*DD$2 -> 29.893085 | DD18: =CZ18*DD$8 -> 30000 | DE18: =DC18*DD18 -> 896792.54 | DG18: =DC18*DG$8*DG$2/DC$2*DH$2 -> 34.377048 | DH18: =DD18*DH$8 -> 30000 | DI18: =DG18*DH18 -> 1031311.4 | DK18: =DG18*DK$8*DK$2/DG$2*DL$2 -> 39.533605 | DL18: =DH18*DL$8 -> 30000 | DM18: =DK18*DL18 -> 1186008.1 | DO18: =DK18*DO$8*DO$2/DK$2*DP$2 -> 45.463645 | DP18: =DL18*DP$8 -> 30000 | DQ18: =DO18*DP18 -> 1363909.4 | DS18: =DO18*DS$8*DS$2/DO$2*DT$2 -> 52.283192 | DT18: =DP18*DT$8 -> 30000 | DU18: =DS18*DT18 -> 1568495.8 | DW18: =DS18*DW$8*DW$2/DS$2*DX$2 -> 60.125671 | DX18: =DT18*DX$8 -> 30000 | DY18: =DW18*DX18 -> 1803770.1 | EA18: =DW18*EA$8*EA$2/DW$2*EB$2 -> 76.058974 | EB18: =DX18*EB$8 -> 30000 | EC18: =EA18*EB18 -> 2281769.2 | EE18: =EA18*EE$8*EE$2/EA$2*EF$2 -> 87.46782 | EF18: =EB18*EF$8 -> 30000 | EG18: =EE18*EF18 -> 2624034.6 | EI18: =EE18*EI$8*EI$2/EE$2*EJ$2 -> 100.58799 | EJ18: =EF18*EJ$8 -> 30000 | EK18: =EI18*EJ18 -> 3017639.8 | EM18: =EI18*EM$8*EM$2/EI$2*EN$2 -> 115.67619 | EN18: =EJ18*EN$8 -> 30000 | EO18: =EM18*EN18 -> 3470285.8 | EQ18: =EM18*EQ$8*EQ$2/EM$2*ER$2 -> 133.02762 | ER18: =EN18*ER$8 -> 30000 | ES18: =EQ18*ER18 -> 3990828.6 | EU18: =EQ18*EU$8*EU$2/EQ$2*EV$2 -> 152.98176 | EV18: =ER18*EV$8 -> 30000 | EW18: =EU18*EV18 -> 4589452.9 | EY18: =EU18*EY$8*EY$2/EU$2*EZ$2 -> 175.92903 | EZ18: =EV18*EZ$8 -> 30000 | FA18: =EY18*EZ18 -> 5277870.8 | FC18: =EY18*FC$8*FC$2/EY$2*FD$2 -> 202.31838 | FD18: =EZ18*FD$8 -> 30000 | FE18: =FC18*FD18 -> 6069551.5 | FG18: =FC18*FG$8*FG$2/FC$2*FH$2 -> 232.66614 | FH18: =FD18*FH$8 -> 30000 | FI18: =FG18*FH18 -> 6979984.2 | FK18: =FG18*FK$8*FK$2/FG$2*FL$2 -> 267.56606 | FL18: =FH18*FL$8 -> 30000 | FM18: =FK18*FL18 -> 8026981.8 | FO18: =FK18*FO$8*FO$2/FK$2*FP$2 -> 307.70097 | FP18: =FL18*FP$8 -> 30000 | FQ18: =FO18*FP18 -> 9231029.1 | FS18: =FO18*FS$8*FS$2/FO$2*FT$2 -> 353.85612 | FT18: =FP18*FT$8 -> 30000 | FU18: =FS18*FT18 -> 10615683 | FW18: =FS18*FW$8*FW$2/FS$2*FX$2 -> 447.62799 | FX18: =FT18*FX$8 -> 30000 | FY18: =FW18*FX18 -> 13428840 | GA18: =FW18*GA$8*GA$2/FW$2*GB$2 -> 514.77218 | GB18: =FX18*GB$8 -> 30000 | GC18: =GA18*GB18 -> 15443166 | GE18: =GA18*GE$8*GE$2/GA$2*GF$2 -> 591.98801 | GF18: =GB18*GF$8 -> 30000 | GG18: =GE18*GF18 -> 17759640 | GI18: =GE18*GI$8*GI$2/GE$2*GJ$2 -> 680.78621 | GJ18: =GF18*GJ$8 -> 30000 | GK18: =GI18*GJ18 -> 20423586 | GM18: =GI18*GM$8*GM$2/GI$2*GN$2 -> 782.90414 | GN18: =GJ18*GN$8 -> 30000 | GO18: =GM18*GN18 -> 23487124 | GQ18: =GM18*GQ$8*GQ$2/GM$2*GR$2 -> 900.33977 | GR18: =GN18*GR$8 -> 30000 | GS18: =GQ18*GR18 -> 27010193 | GU18: =GQ18*GU$8*GU$2/GQ$2*GV$2 -> 1035.3907 | GV18: =GR18*GV$8 -> 30000 | GW18: =GU18*GV18 -> 31061722 | GY18: =GU18*GY$8*GY$2/GU$2*GZ$2 -> 1190.6993 | GZ18: =GV18*GZ$8 -> 30000 | HA18: =GY18*GZ18 -> 35720980 | HC18: =GY18*HC$8*HC$2/GY$2*HD$2 -> 1369.3042 | HD18: =GZ18*HD$8 -> 30000 | HE18: =HC18*HD18 -> 41079127 | HG18: =HC18*HG$8*HG$2/HC$2*HH$2 -> 1574.6999 | HH18: =HD18*HH$8 -> 30000 | HI18: =HG18*HH18 -> 47240996 | HK18: =HG18*HK$8*HK$2/HG$2*HL$2 -> 1810.9049 | HL18: =HH18*HL$8 -> 30000 | HM18: =HK18*HL18 -> 54327146 | HO18: =HK18*HO$8*HO$2/HK$2*HP$2 -> 2082.5406 | HP18: =HL18*HP$8 -> 30000 | HQ18: =HO18*HP18 -> 62476218 | HS18: =HO18*HS$8*HS$2/HO$2*HT$2 -> 2754.1599 | HT18: =HP18*HT$8 -> 30000 | HU18: =HS18*HT18 -> 82624798 | HW18: =HS18*HW$8*HW$2/HS$2*HX$2 -> 3167.2839 | HX18: =HT18*HX$8 -> 30000 | HY18: =HW18*HX18 -> 95018518 | IA18: =HW18*IA$8*IA$2/HW$2*IB$2 -> 3642.3765 | IB18: =HX18*IB$8 -> 30000 | IC18: =IA18*IB18 -> 1.092713e+08 | IE18: =IA18*IE$8*IE$2/IA$2*IF$2 -> 4188.733 | IF18: =IB18*IF$8 -> 30000 | IG18: =IE18*IF18 -> 1.2566199e+08 | II18: =IE18*II$8*II$2/IE$2*IJ$2 -> 4817.0429 | IJ18: =IF18*IJ$8 -> 30000 | IK18: =II18*IJ18 -> 1.4451129e+08 | IM18: =II18*IM$8*IM$2/II$2*IN$2 -> 5539.5994 | IN18: =IJ18*IN$8 -> 30000 | IO18: =IM18*IN18 -> 1.6618798e+08 | IQ18: =IM18*IQ$8*IQ$2/IM$2*IR$2 -> 6370.5393 | IR18: =IN18*IR$8 -> 30000 | IS18: =IQ18*IR18 -> 1.9111618e+08 | IU18: =IQ18*IU$8*IU$2/IQ$2*IV$2 -> 7326.1202 | IV18: =IR18*IV$8 -> 30000 | IW18: =IU18*IV18 -> 2.1978361e+08 | IY18: =IU18*IY$8*IY$2/IU$2*IZ$2 -> 8425.0382 | IZ18: =IV18*IZ$8 -> 30000 | JA18: =IY18*IZ18 -> 2.5275115e+08 | JC18: =IY18*JC$8*JC$2/IY$2*JD$2 -> 9688.7939 | JD18: =IZ18*JD$8 -> 30000 | JE18: =JC18*JD18 -> 2.9066382e+08 | JG18: =JC18*JG$8*JG$2/JC$2*JH$2 -> 11142.113 | JH18: =JD18*JH$8 -> 30000 | JI18: =JG18*JH18 -> 3.3426339e+08 | JK18: =JG18*JK$8*JK$2/JG$2*JL$2 -> 12813.43 | JL18: =JH18*JL$8 -> 30000 | JM18: =JK18*JL18 -> 3.844029e+08 | JO18: =JK18*JO$8*JO$2/JK$2*JP$2 -> 14882.799 | JP18: =JL18*JP$8 -> 30000 | JQ18: =JO18*JP18 -> 4.4648397e+08 | JS18: =JO18*JS$8*JS$2/JO$2*JT$2 -> 17115.219 | JT18: =JP18*JT$8 -> 30000 | JU18: =JS18*JT18 -> 5.1345656e+08 | JW18: =JS18*JW$8*JW$2/JS$2*JX$2 -> 19682.502 | JX18: =JT18*JX$8 -> 30000 | JY18: =JW18*JX18 -> 5.9047505e+08 | KA18: =JW18*KA$8*KA$2/JW$2*KB$2 -> 22634.877 | KB18: =JX18*KB$8 -> 30000 | KC18: =KA18*KB18 -> 6.790463e+08 | KE18: =KA18*KE$8*KE$2/KA$2*KF$2 -> 26030.108 | KF18: =KB18*KF$8 -> 30000 | KG18: =KE18*KF18 -> 7.8090325e+08 | KI18: =SUMIFS($G18:$KG18,$G$3:$KG$3,KI$5,$G$6:$KG$6,KI$6) -> 0.833475 | KJ18: =KK18/KI18 -> 30000 | KK18: =SUMIFS($G18:$KG18,$G$3:$KG$3,KI$5,$G$6:$KG$6,KK$6) -> 25004.25 | KM18: =SUMIFS($G18:$KG18,$G$3:$KG$3,KM$5,$G$6:$KG$6,KM$6) -> 36.692533 | KN18: =KO18/KM18 -> 30000 | KO18: =SUMIFS($G18:$KG18,$G$3:$KG$3,KM$5,$G$6:$KG$6,KO$6) -> 1100776 | KQ18: =SUMIFS($G18:$KG18,$G$3:$KG$3,KQ$5,$G$6:$KG$6,KQ$6) -> 241.52318 | KR18: =KS18/KQ18 -> 30000 | KS18: =SUMIFS($G18:$KG18,$G$3:$KG$3,KQ$5,$G$6:$KG$6,KS$6) -> 7245695.5 | KU18: =SUMIFS($G18:$KG18,$G$3:$KG$3,KU$5,$G$6:$KG$6,KU$6) -> 1434.5864 | KV18: =KW18/KU18 -> 30000 | KW18: =SUMIFS($G18:$KG18,$G$3:$KG$3,KU$5,$G$6:$KG$6,KW$6) -> 43037593 | KY18: =SUMIFS($G18:$KG18,$G$3:$KG$3,KY$5,$G$6:$KG$6,KY$6) -> 8442.9358 | KZ18: =LA18/KY18 -> 30000 | LA18: =SUMIFS($G18:$KG18,$G$3:$KG$3,KY$5,$G$6:$KG$6,LA$6) -> 2.5328807e+08 | LC18: =SUMIFS($G18:$KG18,$G$3:$KG$3,LC$5,$G$6:$KG$6,LC$6) -> 51699.039 | LD18: =LE18/LC18 -> 30000 | LE18: =SUMIFS($G18:$KG18,$G$3:$KG$3,LC$5,$G$6:$KG$6,LE$6) -> 1.5509712e+09
E19: ='A.I Revenue Streams - P1'!F19 -> Comple Denture (BPS Denture) | H19: ='A.I Revenue Streams - P1'!J19 -> 47000 | I19: =G19*H19 -> 0 | K19: ='A.I Revenue Streams - P1'!H19*K$2*L$2 -> 0.225 | L19: =H19*$L$8 -> 47000 | M19: =K19*L19 -> 10575 | O19: =K19*O$8*O$2/K$2*P$2 -> 0.2401875 | P19: =L19*P$8 -> 47000 | Q19: =O19*P19 -> 11288.812 | S19: =O19*S$8*S$2/O$2*T$2 -> 0.3682875 | T19: =P19*T$8 -> 47000 | U19: =S19*T19 -> 17309.512 | W19: =S19*W$8*W$2/S$2*X$2 -> 0.52941328 | X19: =T19*X$8 -> 47000 | Y19: =W19*X19 -> 24882.424 | AA19: =W19*AA$8*AA$2/W$2*AB$2 -> 0.97412044 | AB19: =X19*AB$8 -> 47000 | AC19: =AA19*AB19 -> 45783.661 | AE19: =AA19*AE$8*AE$2/AA$2*AF$2 -> 1.4002981 | AF19: =AB19*AF$8 -> 47000 | AG19: =AE19*AF19 -> 65814.012 | AI19: =AE19*AI$8*AI$2/AE$2*AJ$2 -> 2.0129286 | AJ19: =AF19*AJ$8 -> 47000 | AK19: =AI19*AJ19 -> 94607.642 | AM19: =AI19*AM$8*AM$2/AI$2*AN$2 -> 2.3148678 | AN19: =AJ19*AN$8 -> 47000 | AO19: =AM19*AN19 -> 108798.79 | AQ19: =AM19*AQ$8*AQ$2/AM$2*AR$2 -> 2.662098 | AR19: =AN19*AR$8 -> 47000 | AS19: =AQ19*AR19 -> 125118.61 | AU19: =AQ19*AU$8*AU$2/AQ$2*AV$2 -> 3.0614127 | AV19: =AR19*AV$8 -> 47000 | AW19: =AU19*AV19 -> 143886.4 | AY19: =AU19*AY$8*AY$2/AU$2*AZ$2 -> 3.5206246 | AZ19: =AV19*AZ$8 -> 47000 | BA19: =AY19*AZ19 -> 165469.36 | BC19: =AY19*BC$8*BC$2/AY$2*BD$2 -> 4.0487183 | BD19: =AZ19*BD$8 -> 47000 | BE19: =BC19*BD19 -> 190289.76 | BG19: =BC19*BG$8*BG$2/BC$2*BH$2 -> 4.6560261 | BH19: =BD19*BH$8 -> 47000 | BI19: =BG19*BH19 -> 218833.23 | BK19: =BG19*BK$8*BK$2/BG$2*BL$2 -> 5.35443 | BL19: =BH19*BL$8 -> 47000 | BM19: =BK19*BL19 -> 251658.21 | BO19: =BK19*BO$8*BO$2/BK$2*BP$2 -> 6.1575945 | BP19: =BL19*BP$8 -> 47000 | BQ19: =BO19*BP19 -> 289406.94 | BS19: =BO19*BS$8*BS$2/BO$2*BT$2 -> 7.0812337 | BT19: =BP19*BT$8 -> 47000 | BU19: =BS19*BT19 -> 332817.98 | BW19: =BS19*BW$8*BW$2/BS$2*BX$2 -> 8.1434187 | BX19: =BT19*BX$8 -> 47000 | BY19: =BW19*BX19 -> 382740.68 | CA19: =BW19*CA$8*CA$2/BW$2*CB$2 -> 9.3649315 | CB19: =BX19*CB$8 -> 47000 | CC19: =CA19*CB19 -> 440151.78 | CE19: =CA19*CE$8*CE$2/CA$2*CF$2 -> 12.923605 | CF19: =CB19*CF$8 -> 47000 | CG19: =CE19*CF19 -> 607409.46 | CI19: =CE19*CI$8*CI$2/CE$2*CJ$2 -> 14.862146 | CJ19: =CF19*CJ$8 -> 47000 | CK19: =CI19*CJ19 -> 698520.88 | CM19: =CI19*CM$8*CM$2/CI$2*CN$2 -> 17.091468 | CN19: =CJ19*CN$8 -> 47000 | CO19: =CM19*CN19 -> 803299.01 | CQ19: =CM19*CQ$8*CQ$2/CM$2*CR$2 -> 19.655189 | CR19: =CN19*CR$8 -> 47000 | CS19: =CQ19*CR19 -> 923793.86 | CU19: =CQ19*CU$8*CU$2/CQ$2*CV$2 -> 22.603467 | CV19: =CR19*CV$8 -> 47000 | CW19: =CU19*CV19 -> 1062362.9 | CY19: =CU19*CY$8*CY$2/CU$2*CZ$2 -> 25.993987 | CZ19: =CV19*CZ$8 -> 47000 | DA19: =CY19*CZ19 -> 1221717.4 | DC19: =CY19*DC$8*DC$2/CY$2*DD$2 -> 29.893085 | DD19: =CZ19*DD$8 -> 47000 | DE19: =DC19*DD19 -> 1404975 | DG19: =DC19*DG$8*DG$2/DC$2*DH$2 -> 34.377048 | DH19: =DD19*DH$8 -> 47000 | DI19: =DG19*DH19 -> 1615721.2 | DK19: =DG19*DK$8*DK$2/DG$2*DL$2 -> 39.533605 | DL19: =DH19*DL$8 -> 47000 | DM19: =DK19*DL19 -> 1858079.4 | DO19: =DK19*DO$8*DO$2/DK$2*DP$2 -> 45.463645 | DP19: =DL19*DP$8 -> 47000 | DQ19: =DO19*DP19 -> 2136791.3 | DS19: =DO19*DS$8*DS$2/DO$2*DT$2 -> 52.283192 | DT19: =DP19*DT$8 -> 47000 | DU19: =DS19*DT19 -> 2457310 | DW19: =DS19*DW$8*DW$2/DS$2*DX$2 -> 60.125671 | DX19: =DT19*DX$8 -> 47000 | DY19: =DW19*DX19 -> 2825906.5 | EA19: =DW19*EA$8*EA$2/DW$2*EB$2 -> 76.058974 | EB19: =DX19*EB$8 -> 47000 | EC19: =EA19*EB19 -> 3574771.8 | EE19: =EA19*EE$8*EE$2/EA$2*EF$2 -> 87.46782 | EF19: =EB19*EF$8 -> 47000 | EG19: =EE19*EF19 -> 4110987.5 | EI19: =EE19*EI$8*EI$2/EE$2*EJ$2 -> 100.58799 | EJ19: =EF19*EJ$8 -> 47000 | EK19: =EI19*EJ19 -> 4727635.7 | EM19: =EI19*EM$8*EM$2/EI$2*EN$2 -> 115.67619 | EN19: =EJ19*EN$8 -> 47000 | EO19: =EM19*EN19 -> 5436781 | EQ19: =EM19*EQ$8*EQ$2/EM$2*ER$2 -> 133.02762 | ER19: =EN19*ER$8 -> 47000 | ES19: =EQ19*ER19 -> 6252298.2 | EU19: =EQ19*EU$8*EU$2/EQ$2*EV$2 -> 152.98176 | EV19: =ER19*EV$8 -> 47000 | EW19: =EU19*EV19 -> 7190142.9 | EY19: =EU19*EY$8*EY$2/EU$2*EZ$2 -> 175.92903 | EZ19: =EV19*EZ$8 -> 47000 | FA19: =EY19*EZ19 -> 8268664.3 | FC19: =EY19*FC$8*FC$2/EY$2*FD$2 -> 202.31838 | FD19: =EZ19*FD$8 -> 47000 | FE19: =FC19*FD19 -> 9508964 | FG19: =FC19*FG$8*FG$2/FC$2*FH$2 -> 232.66614 | FH19: =FD19*FH$8 -> 47000 | FI19: =FG19*FH19 -> 10935309 | FK19: =FG19*FK$8*FK$2/FG$2*FL$2 -> 267.56606 | FL19: =FH19*FL$8 -> 47000 | FM19: =FK19*FL19 -> 12575605 | FO19: =FK19*FO$8*FO$2/FK$2*FP$2 -> 307.70097 | FP19: =FL19*FP$8 -> 47000 | FQ19: =FO19*FP19 -> 14461946 | FS19: =FO19*FS$8*FS$2/FO$2*FT$2 -> 353.85612 | FT19: =FP19*FT$8 -> 47000 | FU19: =FS19*FT19 -> 16631237 | FW19: =FS19*FW$8*FW$2/FS$2*FX$2 -> 447.62799 | FX19: =FT19*FX$8 -> 47000 | FY19: =FW19*FX19 -> 21038515 | GA19: =FW19*GA$8*GA$2/FW$2*GB$2 -> 514.77218 | GB19: =FX19*GB$8 -> 47000 | GC19: =GA19*GB19 -> 24194293 | GE19: =GA19*GE$8*GE$2/GA$2*GF$2 -> 591.98801 | GF19: =GB19*GF$8 -> 47000 | GG19: =GE19*GF19 -> 27823437 | GI19: =GE19*GI$8*GI$2/GE$2*GJ$2 -> 680.78621 | GJ19: =GF19*GJ$8 -> 47000 | GK19: =GI19*GJ19 -> 31996952 | GM19: =GI19*GM$8*GM$2/GI$2*GN$2 -> 782.90414 | GN19: =GJ19*GN$8 -> 47000 | GO19: =GM19*GN19 -> 36796495 | GQ19: =GM19*GQ$8*GQ$2/GM$2*GR$2 -> 900.33977 | GR19: =GN19*GR$8 -> 47000 | GS19: =GQ19*GR19 -> 42315969 | GU19: =GQ19*GU$8*GU$2/GQ$2*GV$2 -> 1035.3907 | GV19: =GR19*GV$8 -> 47000 | GW19: =GU19*GV19 -> 48663364 | GY19: =GU19*GY$8*GY$2/GU$2*GZ$2 -> 1190.6993 | GZ19: =GV19*GZ$8 -> 47000 | HA19: =GY19*GZ19 -> 55962869 | HC19: =GY19*HC$8*HC$2/GY$2*HD$2 -> 1369.3042 | HD19: =GZ19*HD$8 -> 47000 | HE19: =HC19*HD19 -> 64357299 | HG19: =HC19*HG$8*HG$2/HC$2*HH$2 -> 1574.6999 | HH19: =HD19*HH$8 -> 47000 | HI19: =HG19*HH19 -> 74010894 | HK19: =HG19*HK$8*HK$2/HG$2*HL$2 -> 1810.9049 | HL19: =HH19*HL$8 -> 47000 | HM19: =HK19*HL19 -> 85112528 | HO19: =HK19*HO$8*HO$2/HK$2*HP$2 -> 2082.5406 | HP19: =HL19*HP$8 -> 47000 | HQ19: =HO19*HP19 -> 97879408 | HS19: =HO19*HS$8*HS$2/HO$2*HT$2 -> 2754.1599 | HT19: =HP19*HT$8 -> 47000 | HU19: =HS19*HT19 -> 1.2944552e+08 | HW19: =HS19*HW$8*HW$2/HS$2*HX$2 -> 3167.2839 | HX19: =HT19*HX$8 -> 47000 | HY19: =HW19*HX19 -> 1.4886234e+08 | IA19: =HW19*IA$8*IA$2/HW$2*IB$2 -> 3642.3765 | IB19: =HX19*IB$8 -> 47000 | IC19: =IA19*IB19 -> 1.711917e+08 | IE19: =IA19*IE$8*IE$2/IA$2*IF$2 -> 4188.733 | IF19: =IB19*IF$8 -> 47000 | IG19: =IE19*IF19 -> 1.9687045e+08 | II19: =IE19*II$8*II$2/IE$2*IJ$2 -> 4817.0429 | IJ19: =IF19*IJ$8 -> 47000 | IK19: =II19*IJ19 -> 2.2640102e+08 | IM19: =II19*IM$8*IM$2/II$2*IN$2 -> 5539.5994 | IN19: =IJ19*IN$8 -> 47000 | IO19: =IM19*IN19 -> 2.6036117e+08 | IQ19: =IM19*IQ$8*IQ$2/IM$2*IR$2 -> 6370.5393 | IR19: =IN19*IR$8 -> 47000 | IS19: =IQ19*IR19 -> 2.9941535e+08 | IU19: =IQ19*IU$8*IU$2/IQ$2*IV$2 -> 7326.1202 | IV19: =IR19*IV$8 -> 47000 | IW19: =IU19*IV19 -> 3.4432765e+08 | IY19: =IU19*IY$8*IY$2/IU$2*IZ$2 -> 8425.0382 | IZ19: =IV19*IZ$8 -> 47000 | JA19: =IY19*IZ19 -> 3.959768e+08 | JC19: =IY19*JC$8*JC$2/IY$2*JD$2 -> 9688.7939 | JD19: =IZ19*JD$8 -> 47000 | JE19: =JC19*JD19 -> 4.5537331e+08 | JG19: =JC19*JG$8*JG$2/JC$2*JH$2 -> 11142.113 | JH19: =JD19*JH$8 -> 47000 | JI19: =JG19*JH19 -> 5.2367931e+08 | JK19: =JG19*JK$8*JK$2/JG$2*JL$2 -> 12813.43 | JL19: =JH19*JL$8 -> 47000 | JM19: =JK19*JL19 -> 6.0223121e+08 | JO19: =JK19*JO$8*JO$2/JK$2*JP$2 -> 14882.799 | JP19: =JL19*JP$8 -> 47000 | JQ19: =JO19*JP19 -> 6.9949155e+08 | JS19: =JO19*JS$8*JS$2/JO$2*JT$2 -> 17115.219 | JT19: =JP19*JT$8 -> 47000 | JU19: =JS19*JT19 -> 8.0441528e+08 | JW19: =JS19*JW$8*JW$2/JS$2*JX$2 -> 19682.502 | JX19: =JT19*JX$8 -> 47000 | JY19: =JW19*JX19 -> 9.2507757e+08 | KA19: =JW19*KA$8*KA$2/JW$2*KB$2 -> 22634.877 | KB19: =JX19*KB$8 -> 47000 | KC19: =KA19*KB19 -> 1.0638392e+09 | KE19: =KA19*KE$8*KE$2/KA$2*KF$2 -> 26030.108 | KF19: =KB19*KF$8 -> 47000 | KG19: =KE19*KF19 -> 1.2234151e+09 | KI19: =SUMIFS($G19:$KG19,$G$3:$KG$3,KI$5,$G$6:$KG$6,KI$6) -> 0.833475 | KJ19: =KK19/KI19 -> 47000 | KK19: =SUMIFS($G19:$KG19,$G$3:$KG$3,KI$5,$G$6:$KG$6,KK$6) -> 39173.325 | KM19: =SUMIFS($G19:$KG19,$G$3:$KG$3,KM$5,$G$6:$KG$6,KM$6) -> 36.692533 | KN19: =KO19/KM19 -> 47000 | KO19: =SUMIFS($G19:$KG19,$G$3:$KG$3,KM$5,$G$6:$KG$6,KO$6) -> 1724549 | KQ19: =SUMIFS($G19:$KG19,$G$3:$KG$3,KQ$5,$G$6:$KG$6,KQ$6) -> 241.52318 | KR19: =KS19/KQ19 -> 47000 | KS19: =SUMIFS($G19:$KG19,$G$3:$KG$3,KQ$5,$G$6:$KG$6,KS$6) -> 11351590 | KU19: =SUMIFS($G19:$KG19,$G$3:$KG$3,KU$5,$G$6:$KG$6,KU$6) -> 1434.5864 | KV19: =KW19/KU19 -> 47000 | KW19: =SUMIFS($G19:$KG19,$G$3:$KG$3,KU$5,$G$6:$KG$6,KW$6) -> 67425562 | KY19: =SUMIFS($G19:$KG19,$G$3:$KG$3,KY$5,$G$6:$KG$6,KY$6) -> 8442.9358 | KZ19: =LA19/KY19 -> 47000 | LA19: =SUMIFS($G19:$KG19,$G$3:$KG$3,KY$5,$G$6:$KG$6,LA$6) -> 3.9681798e+08 | LC19: =SUMIFS($G19:$KG19,$G$3:$KG$3,LC$5,$G$6:$KG$6,LC$6) -> 51699.039 | LD19: =LE19/LC19 -> 47000 | LE19: =SUMIFS($G19:$KG19,$G$3:$KG$3,LC$5,$G$6:$KG$6,LE$6) -> 2.4298548e+09
E20: ='A.I Revenue Streams - P1'!F20 -> Removable Partial Denture | H20: ='A.I Revenue Streams - P1'!J20 -> 1500 | I20: =G20*H20 -> 0 | K20: ='A.I Revenue Streams - P1'!H20*K$2*L$2 -> 0.9 | L20: =H20*$L$8 -> 1500 | M20: =K20*L20 -> 1350 | O20: =K20*O$8*O$2/K$2*P$2 -> 0.96075 | P20: =L20*P$8 -> 1500 | Q20: =O20*P20 -> 1441.125 | S20: =O20*S$8*S$2/O$2*T$2 -> 1.47315 | T20: =P20*T$8 -> 1500 | U20: =S20*T20 -> 2209.725 | W20: =S20*W$8*W$2/S$2*X$2 -> 2.1176531 | X20: =T20*X$8 -> 1500 | Y20: =W20*X20 -> 3176.4797 | AA20: =W20*AA$8*AA$2/W$2*AB$2 -> 3.8964817 | AB20: =X20*AB$8 -> 1500 | AC20: =AA20*AB20 -> 5844.7226 | AE20: =AA20*AE$8*AE$2/AA$2*AF$2 -> 5.6011925 | AF20: =AB20*AF$8 -> 1500 | AG20: =AE20*AF20 -> 8401.7888 | AI20: =AE20*AI$8*AI$2/AE$2*AJ$2 -> 8.0517142 | AJ20: =AF20*AJ$8 -> 1500 | AK20: =AI20*AJ20 -> 12077.571 | AM20: =AI20*AM$8*AM$2/AI$2*AN$2 -> 9.2594714 | AN20: =AJ20*AN$8 -> 1500 | AO20: =AM20*AN20 -> 13889.207 | AQ20: =AM20*AQ$8*AQ$2/AM$2*AR$2 -> 10.648392 | AR20: =AN20*AR$8 -> 1500 | AS20: =AQ20*AR20 -> 15972.588 | AU20: =AQ20*AU$8*AU$2/AQ$2*AV$2 -> 12.245651 | AV20: =AR20*AV$8 -> 1500 | AW20: =AU20*AV20 -> 18368.476 | AY20: =AU20*AY$8*AY$2/AU$2*AZ$2 -> 14.082499 | AZ20: =AV20*AZ$8 -> 1500 | BA20: =AY20*AZ20 -> 21123.748 | BC20: =AY20*BC$8*BC$2/AY$2*BD$2 -> 16.194873 | BD20: =AZ20*BD$8 -> 1500 | BE20: =BC20*BD20 -> 24292.31 | BG20: =BC20*BG$8*BG$2/BC$2*BH$2 -> 18.624104 | BH20: =BD20*BH$8 -> 1500 | BI20: =BG20*BH20 -> 27936.156 | BK20: =BG20*BK$8*BK$2/BG$2*BL$2 -> 21.41772 | BL20: =BH20*BL$8 -> 1500 | BM20: =BK20*BL20 -> 32126.58 | BO20: =BK20*BO$8*BO$2/BK$2*BP$2 -> 24.630378 | BP20: =BL20*BP$8 -> 1500 | BQ20: =BO20*BP20 -> 36945.567 | BS20: =BO20*BS$8*BS$2/BO$2*BT$2 -> 28.324935 | BT20: =BP20*BT$8 -> 1500 | BU20: =BS20*BT20 -> 42487.402 | BW20: =BS20*BW$8*BW$2/BS$2*BX$2 -> 32.573675 | BX20: =BT20*BX$8 -> 1500 | BY20: =BW20*BX20 -> 48860.512 | CA20: =BW20*CA$8*CA$2/BW$2*CB$2 -> 37.459726 | CB20: =BX20*CB$8 -> 1500 | CC20: =CA20*CB20 -> 56189.589 | CE20: =CA20*CE$8*CE$2/CA$2*CF$2 -> 51.694422 | CF20: =CB20*CF$8 -> 1500 | CG20: =CE20*CF20 -> 77541.633 | CI20: =CE20*CI$8*CI$2/CE$2*CJ$2 -> 59.448585 | CJ20: =CF20*CJ$8 -> 1500 | CK20: =CI20*CJ20 -> 89172.878 | CM20: =CI20*CM$8*CM$2/CI$2*CN$2 -> 68.365873 | CN20: =CJ20*CN$8 -> 1500 | CO20: =CM20*CN20 -> 102548.81 | CQ20: =CM20*CQ$8*CQ$2/CM$2*CR$2 -> 78.620754 | CR20: =CN20*CR$8 -> 1500 | CS20: =CQ20*CR20 -> 117931.13 | CU20: =CQ20*CU$8*CU$2/CQ$2*CV$2 -> 90.413867 | CV20: =CR20*CV$8 -> 1500 | CW20: =CU20*CV20 -> 135620.8 | CY20: =CU20*CY$8*CY$2/CU$2*CZ$2 -> 103.97595 | CZ20: =CV20*CZ$8 -> 1500 | DA20: =CY20*CZ20 -> 155963.92 | DC20: =CY20*DC$8*DC$2/CY$2*DD$2 -> 119.57234 | DD20: =CZ20*DD$8 -> 1500 | DE20: =DC20*DD20 -> 179358.51 | DG20: =DC20*DG$8*DG$2/DC$2*DH$2 -> 137.50819 | DH20: =DD20*DH$8 -> 1500 | DI20: =DG20*DH20 -> 206262.29 | DK20: =DG20*DK$8*DK$2/DG$2*DL$2 -> 158.13442 | DL20: =DH20*DL$8 -> 1500 | DM20: =DK20*DL20 -> 237201.63 | DO20: =DK20*DO$8*DO$2/DK$2*DP$2 -> 181.85458 | DP20: =DL20*DP$8 -> 1500 | DQ20: =DO20*DP20 -> 272781.87 | DS20: =DO20*DS$8*DS$2/DO$2*DT$2 -> 209.13277 | DT20: =DP20*DT$8 -> 1500 | DU20: =DS20*DT20 -> 313699.15 | DW20: =DS20*DW$8*DW$2/DS$2*DX$2 -> 240.50268 | DX20: =DT20*DX$8 -> 1500 | DY20: =DW20*DX20 -> 360754.03 | EA20: =DW20*EA$8*EA$2/DW$2*EB$2 -> 304.2359 | EB20: =DX20*EB$8 -> 1500 | EC20: =EA20*EB20 -> 456353.84 | EE20: =EA20*EE$8*EE$2/EA$2*EF$2 -> 349.87128 | EF20: =EB20*EF$8 -> 1500 | EG20: =EE20*EF20 -> 524806.92 | EI20: =EE20*EI$8*EI$2/EE$2*EJ$2 -> 402.35197 | EJ20: =EF20*EJ$8 -> 1500 | EK20: =EI20*EJ20 -> 603527.96 | EM20: =EI20*EM$8*EM$2/EI$2*EN$2 -> 462.70477 | EN20: =EJ20*EN$8 -> 1500 | EO20: =EM20*EN20 -> 694057.15 | EQ20: =EM20*EQ$8*EQ$2/EM$2*ER$2 -> 532.11048 | ER20: =EN20*ER$8 -> 1500 | ES20: =EQ20*ER20 -> 798165.72 | EU20: =EQ20*EU$8*EU$2/EQ$2*EV$2 -> 611.92705 | EV20: =ER20*EV$8 -> 1500 | EW20: =EU20*EV20 -> 917890.58 | EY20: =EU20*EY$8*EY$2/EU$2*EZ$2 -> 703.71611 | EZ20: =EV20*EZ$8 -> 1500 | FA20: =EY20*EZ20 -> 1055574.2 | FC20: =EY20*FC$8*FC$2/EY$2*FD$2 -> 809.27353 | FD20: =EZ20*FD$8 -> 1500 | FE20: =FC20*FD20 -> 1213910.3 | FG20: =FC20*FG$8*FG$2/FC$2*FH$2 -> 930.66456 | FH20: =FD20*FH$8 -> 1500 | FI20: =FG20*FH20 -> 1395996.8 | FK20: =FG20*FK$8*FK$2/FG$2*FL$2 -> 1070.2642 | FL20: =FH20*FL$8 -> 1500 | FM20: =FK20*FL20 -> 1605396.4 | FO20: =FK20*FO$8*FO$2/FK$2*FP$2 -> 1230.8039 | FP20: =FL20*FP$8 -> 1500 | FQ20: =FO20*FP20 -> 1846205.8 | FS20: =FO20*FS$8*FS$2/FO$2*FT$2 -> 1415.4245 | FT20: =FP20*FT$8 -> 1500 | FU20: =FS20*FT20 -> 2123136.7 | FW20: =FS20*FW$8*FW$2/FS$2*FX$2 -> 1790.5119 | FX20: =FT20*FX$8 -> 1500 | FY20: =FW20*FX20 -> 2685767.9 | GA20: =FW20*GA$8*GA$2/FW$2*GB$2 -> 2059.0887 | GB20: =FX20*GB$8 -> 1500 | GC20: =GA20*GB20 -> 3088633.1 | GE20: =GA20*GE$8*GE$2/GA$2*GF$2 -> 2367.952 | GF20: =GB20*GF$8 -> 1500 | GG20: =GE20*GF20 -> 3551928.1 | GI20: =GE20*GI$8*GI$2/GE$2*GJ$2 -> 2723.1449 | GJ20: =GF20*GJ$8 -> 1500 | GK20: =GI20*GJ20 -> 4084717.3 | GM20: =GI20*GM$8*GM$2/GI$2*GN$2 -> 3131.6166 | GN20: =GJ20*GN$8 -> 1500 | GO20: =GM20*GN20 -> 4697424.9 | GQ20: =GM20*GQ$8*GQ$2/GM$2*GR$2 -> 3601.3591 | GR20: =GN20*GR$8 -> 1500 | GS20: =GQ20*GR20 -> 5402038.6 | GU20: =GQ20*GU$8*GU$2/GQ$2*GV$2 -> 4141.5629 | GV20: =GR20*GV$8 -> 1500 | GW20: =GU20*GV20 -> 6212344.4 | GY20: =GU20*GY$8*GY$2/GU$2*GZ$2 -> 4762.7974 | GZ20: =GV20*GZ$8 -> 1500 | HA20: =GY20*GZ20 -> 7144196 | HC20: =GY20*HC$8*HC$2/GY$2*HD$2 -> 5477.217 | HD20: =GZ20*HD$8 -> 1500 | HE20: =HC20*HD20 -> 8215825.5 | HG20: =HC20*HG$8*HG$2/HC$2*HH$2 -> 6298.7995 | HH20: =HD20*HH$8 -> 1500 | HI20: =HG20*HH20 -> 9448199.3 | HK20: =HG20*HK$8*HK$2/HG$2*HL$2 -> 7243.6194 | HL20: =HH20*HL$8 -> 1500 | HM20: =HK20*HL20 -> 10865429 | HO20: =HK20*HO$8*HO$2/HK$2*HP$2 -> 8330.1624 | HP20: =HL20*HP$8 -> 1500 | HQ20: =HO20*HP20 -> 12495244 | HS20: =HO20*HS$8*HS$2/HO$2*HT$2 -> 11016.64 | HT20: =HP20*HT$8 -> 1500 | HU20: =HS20*HT20 -> 16524960 | HW20: =HS20*HW$8*HW$2/HS$2*HX$2 -> 12669.136 | HX20: =HT20*HX$8 -> 1500 | HY20: =HW20*HX20 -> 19003704 | IA20: =HW20*IA$8*IA$2/HW$2*IB$2 -> 14569.506 | IB20: =HX20*IB$8 -> 1500 | IC20: =IA20*IB20 -> 21854259 | IE20: =IA20*IE$8*IE$2/IA$2*IF$2 -> 16754.932 | IF20: =IB20*IF$8 -> 1500 | IG20: =IE20*IF20 -> 25132398 | II20: =IE20*II$8*II$2/IE$2*IJ$2 -> 19268.172 | IJ20: =IF20*IJ$8 -> 1500 | IK20: =II20*IJ20 -> 28902258 | IM20: =II20*IM$8*IM$2/II$2*IN$2 -> 22158.397 | IN20: =IJ20*IN$8 -> 1500 | IO20: =IM20*IN20 -> 33237596 | IQ20: =IM20*IQ$8*IQ$2/IM$2*IR$2 -> 25482.157 | IR20: =IN20*IR$8 -> 1500 | IS20: =IQ20*IR20 -> 38223236 | IU20: =IQ20*IU$8*IU$2/IQ$2*IV$2 -> 29304.481 | IV20: =IR20*IV$8 -> 1500 | IW20: =IU20*IV20 -> 43956721 | IY20: =IU20*IY$8*IY$2/IU$2*IZ$2 -> 33700.153 | IZ20: =IV20*IZ$8 -> 1500 | JA20: =IY20*IZ20 -> 50550229 | JC20: =IY20*JC$8*JC$2/IY$2*JD$2 -> 38755.176 | JD20: =IZ20*JD$8 -> 1500 | JE20: =JC20*JD20 -> 58132764 | JG20: =JC20*JG$8*JG$2/JC$2*JH$2 -> 44568.452 | JH20: =JD20*JH$8 -> 1500 | JI20: =JG20*JH20 -> 66852678 | JK20: =JG20*JK$8*JK$2/JG$2*JL$2 -> 51253.72 | JL20: =JH20*JL$8 -> 1500 | JM20: =JK20*JL20 -> 76880580 | JO20: =JK20*JO$8*JO$2/JK$2*JP$2 -> 59531.196 | JP20: =JL20*JP$8 -> 1500 | JQ20: =JO20*JP20 -> 89296793 | JS20: =JO20*JS$8*JS$2/JO$2*JT$2 -> 68460.875 | JT20: =JP20*JT$8 -> 1500 | JU20: =JS20*JT20 -> 1.0269131e+08 | JW20: =JS20*JW$8*JW$2/JS$2*JX$2 -> 78730.006 | JX20: =JT20*JX$8 -> 1500 | JY20: =JW20*JX20 -> 1.1809501e+08 | KA20: =JW20*KA$8*KA$2/JW$2*KB$2 -> 90539.507 | KB20: =JX20*KB$8 -> 1500 | KC20: =KA20*KB20 -> 1.3580926e+08 | KE20: =KA20*KE$8*KE$2/KA$2*KF$2 -> 104120.43 | KF20: =KB20*KF$8 -> 1500 | KG20: =KE20*KF20 -> 1.5618065e+08 | KI20: =SUMIFS($G20:$KG20,$G$3:$KG$3,KI$5,$G$6:$KG$6,KI$6) -> 3.3339 | KJ20: =KK20/KI20 -> 1500 | KK20: =SUMIFS($G20:$KG20,$G$3:$KG$3,KI$5,$G$6:$KG$6,KK$6) -> 5000.85 | KM20: =SUMIFS($G20:$KG20,$G$3:$KG$3,KM$5,$G$6:$KG$6,KM$6) -> 146.77013 | KN20: =KO20/KM20 -> 1500 | KO20: =SUMIFS($G20:$KG20,$G$3:$KG$3,KM$5,$G$6:$KG$6,KO$6) -> 220155.2 | KQ20: =SUMIFS($G20:$KG20,$G$3:$KG$3,KQ$5,$G$6:$KG$6,KQ$6) -> 966.09273 | KR20: =KS20/KQ20 -> 1500 | KS20: =SUMIFS($G20:$KG20,$G$3:$KG$3,KQ$5,$G$6:$KG$6,KS$6) -> 1449139.1 | KU20: =SUMIFS($G20:$KG20,$G$3:$KG$3,KU$5,$G$6:$KG$6,KU$6) -> 5738.3457 | KV20: =KW20/KU20 -> 1500 | KW20: =SUMIFS($G20:$KG20,$G$3:$KG$3,KU$5,$G$6:$KG$6,KW$6) -> 8607518.5 | KY20: =SUMIFS($G20:$KG20,$G$3:$KG$3,KY$5,$G$6:$KG$6,KY$6) -> 33771.743 | KZ20: =LA20/KY20 -> 1500 | LA20: =SUMIFS($G20:$KG20,$G$3:$KG$3,KY$5,$G$6:$KG$6,LA$6) -> 50657615 | LC20: =SUMIFS($G20:$KG20,$G$3:$KG$3,LC$5,$G$6:$KG$6,LC$6) -> 206796.15 | LD20: =LE20/LC20 -> 1500 | LE20: =SUMIFS($G20:$KG20,$G$3:$KG$3,LC$5,$G$6:$KG$6,LE$6) -> 3.1019423e+08
