Workbook

Sheet 1. Basics
B2: 1 | C2: Legal Name of the Business | D2: CYNCURA PRIVATE LIMITED
B4: 2 | C4: Trade Name of the Business | D4: CYNCURA PRIVATE LIMITED
B6: 3 | C6: Registered Office Address | D6: 6-1-19 and 6-1-19/A, old no 108/3, Flat no 206, Musheerabad (Delivery), Hyderabad, Hyderabad- 500020, Telangana
B8: 4 | C8: Official Email Id | D8: Karimsavenue@gmail.com
B10: 5 | C10: Official Contact Number
B12: 6 | C12: Details of the Promoter
B14: 6.a | C14: Total number of Promoters | D14: 4
B16: 7 | C16: Tentative Start Date of the project Phase 1 | D16: 46112 | E16: DD/MM/YYYY
B18: 8 | C18: Company Description
B20: 9 | C20: Link to Company Pitch Deck
B22: 10 | C22: Burning Desire of the company
B24: 11 | C24: Tentative Start Date of the project Phase 2

Sheet A. Data Needed
C2: Major heads of the data needed for the business plan
D3: Hyperlink to open
B4: I | C4: We need to clearly define the Revenue Streams | D4: Nature of services. click here for the link to enter the revenue streams
B7: II | C7: Sales price per revenue streams | D7: Click
B9: III | C9: Costing headers | D9: =A.IIOPEX!C2 -> Opex, Click on the link to refer to OPEX
B11: IIV | C11: Capex Information | D11: Capex Click on the link to refer to Capex
B13: V | C13: Other Information

Sheet A.I Revenue Streams - P1
C2: Revenue Streams
C3: This Sheet assists us in getting the data related to Sales
C5: PHASE - 1 | E5: ='1. Basics'!D16 -> 46112
K6: 2026-27 | M6: 2027-28 | O6: 2028-29 | Q6: 2029-30 | S6: 2030-31 | U6: 2031-32
D8: Major Header | E8: Minor Header | G8: Number of Products sold per month | I8: Sale Price of each product | K8: Monthly Growth Rate in Y2 | M8: Yearly Growth Rate from Y2 to Y3 | O8: Yearly Growth Rate from Y3 to Y4 | Q8: Yearly Growth Rate from Y4 to Y5 | S8: Yearly Growth Rate from Y5 to Y6 | U8: Yearly Growth Rate from Y6 to Y7
C9: 1 | D9: Doctor Consultations
C10: 1a | E10: Platform Access Fees | G10: =2000*50%*28 -> 28000 | I10: 30 | K10: 0.01 | M10: 0.82 | O10: 0.7 | Q10: 0.55 | S10: 0.45 | U10: 0.4
C11: 1b | K11: =$K$10 -> 0.01 | M11: =$M$10 -> 0.82 | O11: =$O$10 -> 0.7 | Q11: =$Q$10 -> 0.55 | S11: =$S$10 -> 0.45 | U11: =$U$10 -> 0.4
C12: 1c | K12: =$K$10 -> 0.01 | M12: =$M$10 -> 0.82 | O12: =$O$10 -> 0.7 | Q12: =$Q$10 -> 0.55 | S12: =$S$10 -> 0.45 | U12: =$U$10 -> 0.4
C13: 1d | K13: =$K$10 -> 0.01 | M13: =$M$10 -> 0.82 | O13: =$O$10 -> 0.7 | Q13: =$Q$10 -> 0.55 | S13: =$S$10 -> 0.45 | U13: =$U$10 -> 0.4
C14: 1e | K14: =$K$10 -> 0.01 | M14: =$M$10 -> 0.82 | O14: =$O$10 -> 0.7 | Q14: =$Q$10 -> 0.55 | S14: =$S$10 -> 0.45 | U14: =$U$10 -> 0.4
C15: Grand Total
C18: 2 | D18: Advertisement
C19: 2a | E19: Advertisement | K19: 0 | M19: 0 | O19: 0 | Q19: 0 | S19: 0 | U19: 0
C20: 2b | K20: =$K$19 -> 0 | M20: =$M$19 -> 0 | O20: =$O$19 -> 0 | Q20: =$Q$19 -> 0 | S20: =$S$19 -> 0 | U20: =$U$19 -> 0
C21: 2c | K21: =$K$19 -> 0 | M21: =$M$19 -> 0 | O21: =$O$19 -> 0 | Q21: =$Q$19 -> 0 | S21: =$S$19 -> 0 | U21: =$U$19 -> 0
C22: 2d | K22: =$K$19 -> 0 | M22: =$M$19 -> 0 | O22: =$O$19 -> 0 | Q22: =$Q$19 -> 0 | S22: =$S$19 -> 0 | U22: =$U$19 -> 0
C23: 2e | K23: =$K$19 -> 0 | M23: =$M$19 -> 0 | O23: =$O$19 -> 0 | Q23: =$Q$19 -> 0 | S23: =$S$19 -> 0 | U23: =$U$19 -> 0
C24: Grand Total
C27: 3
C28: 3a | K28: 0 | M28: 0 | O28: 1.23 | Q28: 1.23 | S28: 0 | U28: 0
C29: 3b | K29: =$K$28 -> 0 | M29: =$M$28 -> 0 | O29: =$O$28 -> 1.23 | Q29: =$Q$28 -> 1.23 | S29: =$S$28 -> 0 | U29: =$U$28 -> 0
C30: 3c | K30: =$K$28 -> 0 | M30: =$M$28 -> 0 | O30: =$O$28 -> 1.23 | Q30: =$Q$28 -> 1.23 | S30: =$S$28 -> 0 | U30: =$U$28 -> 0
C31: 3d | K31: =$K$28 -> 0 | M31: =$M$28 -> 0 | O31: =$O$28 -> 1.23 | Q31: =$Q$28 -> 1.23 | S31: =$S$28 -> 0 | U31: =$U$28 -> 0
C32: 3e | K32: =$K$28 -> 0 | M32: =$M$28 -> 0 | O32: =$O$28 -> 1.23 | Q32: =$Q$28 -> 1.23 | S32: =$S$28 -> 0 | U32: =$U$28 -> 0
C33: Grand Total
C36: 4
C37: 4a | K37: 0 | M37: 0 | O37: 1.23 | Q37: 1.23 | S37: 0 | U37: 0
C38: 4b | K38: =$K$37 -> 0 | M38: =$M$37 -> 0 | O38: =$O$37 -> 1.23 | Q38: =$Q$37 -> 1.23 | S38: =$S$37 -> 0 | U38: =$U$37 -> 0
C39: 4c | K39: =$K$37 -> 0 | M39: =$M$37 -> 0 | O39: =$O$37 -> 1.23 | Q39: =$Q$37 -> 1.23 | S39: =$S$37 -> 0 | U39: =$U$37 -> 0
C40: 4d | K40: =$K$37 -> 0 | M40: =$M$37 -> 0 | O40: =$O$37 -> 1.23 | Q40: =$Q$37 -> 1.23 | S40: =$S$37 -> 0 | U40: =$U$37 -> 0
C41: 4e | K41: =$K$37 -> 0 | M41: =$M$37 -> 0 | O41: =$O$37 -> 1.23 | Q41: =$Q$37 -> 1.23 | S41: =$S$37 -> 0 | U41: =$U$37 -> 0
C42: Grand Total
C45: 5
C46: 5a | K46: 0 | M46: 0 | O46: 1.23 | Q46: 1.23 | S46: 0 | U46: 0
C47: 5b | K47: =$K$46 -> 0 | M47: =$M$46 -> 0 | O47: =$O$46 -> 1.23 | Q47: =$Q$46 -> 1.23 | S47: =$S$46 -> 0 | U47: =$U$46 -> 0
C48: 5c | K48: =$K$46 -> 0 | M48: =$M$46 -> 0 | O48: =$O$46 -> 1.23 | Q48: =$Q$46 -> 1.23 | S48: =$S$46 -> 0 | U48: =$U$46 -> 0
C49: 5d | K49: =$K$46 -> 0 | M49: =$M$46 -> 0 | O49: =$O$46 -> 1.23 | Q49: =$Q$46 -> 1.23 | S49: =$S$46 -> 0 | U49: =$U$46 -> 0
C50: 5e | K50: =$K$46 -> 0 | M50: =$M$46 -> 0 | O50: =$O$46 -> 1.23 | Q50: =$Q$46 -> 1.23 | S50: =$S$46 -> 0 | U50: =$U$46 -> 0
C51: Grand Total

Sheet A.I Revenue Streams - P2
C2: Revenue Streams
C3: This Sheet assists us in getting the data related to Sales
C5: PHASE - 2 | E5: ='1. Basics'!D24 -> 0
D8: Major Header | E8: Minor Header | G8: Number of Products sold per Day | I8: Sale Price of each product | K8: Monthly Growth Rate in Y1 | M8: Yearly Growth Rate from Y1 to Y2 | O8: Yearly Growth Rate from Y2 to Y3 | Q8: Yearly Growth Rate from Y3 to Y4 | S8: Yearly Growth Rate from Y4 to Y5 | U8: Yearly Growth Rate from Y5 to Y6
C9: 1 | D9: Cakes
C10: 1a | E10: Cup Cakes | G10: 5 | I10: 20 | K10: 0.1 | M10: 0.1 | O10: 0.1 | Q10: 0.1 | S10: 0.1 | U10: 0.1
C11: 1b | E11: Customised Cakes | G11: 4 | I11: 20 | K11: =$K$10 -> 0.1 | M11: =$M$10 -> 0.1 | O11: =$O$10 -> 0.1 | Q11: =$Q$10 -> 0.1 | S11: =$S$10 -> 0.1 | U11: =$U$10 -> 0.1
C12: 1c | E12: Standard Cake | G12: 3 | I12: 20 | K12: =$K$10 -> 0.1 | M12: =$M$10 -> 0.1 | O12: =$O$10 -> 0.1 | Q12: =$Q$10 -> 0.1 | S12: =$S$10 -> 0.1 | U12: =$U$10 -> 0.1
C13: 1d | E13: Cake Slices | G13: 2 | I13: 20 | K13: =$K$10 -> 0.1 | M13: =$M$10 -> 0.1 | O13: =$O$10 -> 0.1 | Q13: =$Q$10 -> 0.1 | S13: =$S$10 -> 0.1 | U13: =$U$10 -> 0.1
C14: 1e | E14: 0 | G14: 1 | I14: 20 | K14: =$K$10 -> 0.1 | M14: =$M$10 -> 0.1 | O14: =$O$10 -> 0.1 | Q14: =$Q$10 -> 0.1 | S14: =$S$10 -> 0.1 | U14: =$U$10 -> 0.1
C15: Grand Total
C18: 2 | D18: Confectionary
C19: 2a | E19: Burgers | G19: 5 | I19: 20 | K19: 0.1 | M19: 0.1 | O19: 0.1 | Q19: 0.1 | S19: 0.1 | U19: 0.1
C20: 2b | E20: Pizza | G20: 4 | I20: 20 | K20: =$K$19 -> 0.1 | M20: =$M$19 -> 0.1 | O20: =$O$19 -> 0.1 | Q20: =$Q$19 -> 0.1 | S20: =$S$19 -> 0.1 | U20: =$U$19 -> 0.1
C21: 2c | E21: Puffs | G21: 3 | I21: 20 | K21: =$K$19 -> 0.1 | M21: =$M$19 -> 0.1 | O21: =$O$19 -> 0.1 | Q21: =$Q$19 -> 0.1 | S21: =$S$19 -> 0.1 | U21: =$U$19 -> 0.1
C22: 2d | E22: Other 1 | G22: 2 | I22: 20 | K22: =$K$19 -> 0.1 | M22: =$M$19 -> 0.1 | O22: =$O$19 -> 0.1 | Q22: =$Q$19 -> 0.1 | S22: =$S$19 -> 0.1 | U22: =$U$19 -> 0.1
C23: 2e | E23: 0 | G23: 1 | I23: 20 | K23: =$K$19 -> 0.1 | M23: =$M$19 -> 0.1 | O23: =$O$19 -> 0.1 | Q23: =$Q$19 -> 0.1 | S23: =$S$19 -> 0.1 | U23: =$U$19 -> 0.1
C24: Grand Total
C27: 3 | D27: Accessorries
C28: 3a | E28: Poppers | G28: 5 | I28: 20 | K28: 0.1 | M28: 0.1 | O28: 0.1 | Q28: 0.1 | S28: 0.1 | U28: 0.1
C29: 3b | E29: Builders | G29: 4 | I29: 20 | K29: =$K$28 -> 0.1 | M29: =$M$28 -> 0.1 | O29: =$O$28 -> 0.1 | Q29: =$Q$28 -> 0.1 | S29: =$S$28 -> 0.1 | U29: =$U$28 -> 0.1
C30: 3c | E30: Blasters | G30: 3 | I30: 20 | K30: =$K$28 -> 0.1 | M30: =$M$28 -> 0.1 | O30: =$O$28 -> 0.1 | Q30: =$Q$28 -> 0.1 | S30: =$S$28 -> 0.1 | U30: =$U$28 -> 0.1
C31: 3d | E31: Decor | G31: 2 | I31: 20 | K31: =$K$28 -> 0.1 | M31: =$M$28 -> 0.1 | O31: =$O$28 -> 0.1 | Q31: =$Q$28 -> 0.1 | S31: =$S$28 -> 0.1 | U31: =$U$28 -> 0.1
C32: 3e | E32: Others | G32: 1 | I32: 20 | K32: =$K$28 -> 0.1 | M32: =$M$28 -> 0.1 | O32: =$O$28 -> 0.1 | Q32: =$Q$28 -> 0.1 | S32: =$S$28 -> 0.1 | U32: =$U$28 -> 0.1
C33: Grand Total
C36: 4 | D36: Others
C37: 4a | E37: Others 1 | G37: 5 | I37: 20 | K37: 0.1 | M37: 0.1 | O37: 0.1 | Q37: 0.1 | S37: 0.1 | U37: 0.1
C38: 4b | E38: Others 2 | G38: 4 | I38: 20 | K38: =$K$37 -> 0.1 | M38: =$M$37 -> 0.1 | O38: =$O$37 -> 0.1 | Q38: =$Q$37 -> 0.1 | S38: =$S$37 -> 0.1 | U38: =$U$37 -> 0.1
C39: 4c | E39: Others 3 | G39: 3 | I39: 20 | K39: =$K$37 -> 0.1 | M39: =$M$37 -> 0.1 | O39: =$O$37 -> 0.1 | Q39: =$Q$37 -> 0.1 | S39: =$S$37 -> 0.1 | U39: =$U$37 -> 0.1
C40: 4d | E40: Others 4 | G40: 2 | I40: 20 | K40: =$K$37 -> 0.1 | M40: =$M$37 -> 0.1 | O40: =$O$37 -> 0.1 | Q40: =$Q$37 -> 0.1 | S40: =$S$37 -> 0.1 | U40: =$U$37 -> 0.1
C41: 4e | E41: Others 5 | G41: 1 | I41: 20 | K41: =$K$37 -> 0.1 | M41: =$M$37 -> 0.1 | O41: =$O$37 -> 0.1 | Q41: =$Q$37 -> 0.1 | S41: =$S$37 -> 0.1 | U41: =$U$37 -> 0.1
C42: Grand Total
C45: 5 | D45: Others
C46: 5a | E46: Others 1 | G46: 5 | I46: 20 | K46: 0.1 | M46: 0.1 | O46: 0.1 | Q46: 0.1 | S46: 0.1 | U46: 0.1
C47: 5b | E47: Others 2 | G47: 4 | I47: 20 | K47: =$K$46 -> 0.1 | M47: =$M$46 -> 0.1 | O47: =$O$46 -> 0.1 | Q47: =$Q$46 -> 0.1 | S47: =$S$46 -> 0.1 | U47: =$U$46 -> 0.1
C48: 5c | E48: Others 3 | G48: 3 | I48: 20 | K48: =$K$46 -> 0.1 | M48: =$M$46 -> 0.1 | O48: =$O$46 -> 0.1 | Q48: =$Q$46 -> 0.1 | S48: =$S$46 -> 0.1 | U48: =$U$46 -> 0.1
C49: 5d | E49: Others 4 | G49: 2 | I49: 20 | K49: =$K$46 -> 0.1 | M49: =$M$46 -> 0.1 | O49: =$O$46 -> 0.1 | Q49: =$Q$46 -> 0.1 | S49: =$S$46 -> 0.1 | U49: =$U$46 -> 0.1
C50: 5e | E50: Others 5 | G50: 1 | I50: 20 | K50: =$K$46 -> 0.1 | M50: =$M$46 -> 0.1 | O50: =$O$46 -> 0.1 | Q50: =$Q$46 -> 0.1 | S50: =$S$46 -> 0.1 | U50: =$U$46 -> 0.1

Sheet A.IIOPEX
C2: Opex, Click on the link to refer to OPEX
C4: Write down all the major and nimor headers for the costing and list them here
C5: Beside the header you will be able to write the quantity and the price
K6: 2025-26 | M6: 2026-27 | O6: 2027-28 | Q6: 2028-29 | S6: 2029-30 | U6: 2030-31
D8: Major Header | E8: Sub Services | G8: Monthly | I8: Cost per month | K8: Monthly Growth Rate in Y1 | M8: Yearly Growth Rate from Y1 to Y2 | O8: Yearly Growth Rate from Y2 to Y3 | Q8: Yearly Growth Rate from Y3 to Y4 | S8: Yearly Growth Rate from Y4 to Y5 | U8: Yearly Growth Rate from Y5 to Y6
C9: 1 | D9: Technology & Product Development
C10: 1a | E10: App Development | G10: 2 | I10: =1000000/12 -> 83333.333 | K10: -0.2 | M10: 0.35 | O10: 2.5 | Q10: 3.8 | S10: 0.4 | U10: 0.35
C11: 1b | E11: App maintenance | G11: 3 | K11: =$K$10 -> -0.2 | M11: =$M$10 -> 0.35 | O11: =$O$10 -> 2.5 | Q11: =$Q$10 -> 3.8 | S11: =$S$10 -> 0.4 | U11: =$U$10 -> 0.35
C12: 1c | G12: 2 | K12: =$K$10 -> -0.2 | M12: =$M$10 -> 0.35 | O12: =$O$10 -> 2.5 | Q12: =$Q$10 -> 3.8 | S12: =$S$10 -> 0.4 | U12: =$U$10 -> 0.35
C13: 1d | G13: 1 | K13: =$K$10 -> -0.2 | M13: =$M$10 -> 0.35 | O13: =$O$10 -> 2.5 | Q13: =$Q$10 -> 3.8 | S13: =$S$10 -> 0.4 | U13: =$U$10 -> 0.35
C14: 1e | G14: 2 | K14: =$K$10 -> -0.2 | M14: =$M$10 -> 0.35 | O14: =$O$10 -> 2.5 | Q14: =$Q$10 -> 3.8 | S14: =$S$10 -> 0.4 | U14: =$U$10 -> 0.35
C15: 1f | G15: 5 | K15: =$K$10 -> -0.2 | M15: =$M$10 -> 0.35 | O15: =$O$10 -> 2.5 | Q15: =$Q$10 -> 3.8 | S15: =$S$10 -> 0.4 | U15: =$U$10 -> 0.35
C16: 1g | K16: =$K$10 -> -0.2 | M16: =$M$10 -> 0.35 | O16: =$O$10 -> 2.5 | Q16: =$Q$10 -> 3.8 | S16: =$S$10 -> 0.4 | U16: =$U$10 -> 0.35
C17: Grand Total
C20: 2 | D20: Legal, Compliance & Professional Charges
C21: 2a | E21: Professional Charges | G21: 1 | I21: 50000 | K21: -0.08 | M21: 0.02 | O21: 0.15 | Q21: 0.4 | S21: 0.15 | U21: 0.18
C22: 2b | G22: 2 | K22: =$K$21 -> -0.08 | M22: =$M$21 -> 0.02 | O22: =$O$21 -> 0.15 | Q22: =$Q$21 -> 0.4 | S22: =$S$21 -> 0.15 | U22: =$U$21 -> 0.18
C23: 2c | G23: 2 | K23: =$K$21 -> -0.08 | M23: =$M$21 -> 0.02 | O23: =$O$21 -> 0.15 | Q23: =$Q$21 -> 0.4 | S23: =$S$21 -> 0.15 | U23: =$U$21 -> 0.18
C24: 2d | G24: 1 | K24: =$K$21 -> -0.08 | M24: =$M$21 -> 0.02 | O24: =$O$21 -> 0.15 | Q24: =$Q$21 -> 0.4 | S24: =$S$21 -> 0.15 | U24: =$U$21 -> 0.18
C25: 2e | K25: =$K$21 -> -0.08 | M25: =$M$21 -> 0.02 | O25: =$O$21 -> 0.15 | Q25: =$Q$21 -> 0.4 | S25: =$S$21 -> 0.15 | U25: =$U$21 -> 0.18
C26: 2f | K26: =$K$21 -> -0.08 | M26: =$M$21 -> 0.02 | O26: =$O$21 -> 0.15 | Q26: =$Q$21 -> 0.4 | S26: =$S$21 -> 0.15 | U26: =$U$21 -> 0.18
C27: 2g | K27: =$K$21 -> -0.08 | M27: =$M$21 -> 0.02 | O27: =$O$21 -> 0.15 | Q27: =$Q$21 -> 0.4 | S27: =$S$21 -> 0.15 | U27: =$U$21 -> 0.18
C28: Grand Total
C31: 3 | D31: Utilities
C32: 3a | E32: Office Maintenance | G32: 1
C33: 3b | E33: Rent | G33: 1 | K33: =$K$32 -> -0.08 | M33: =$M$32 -> 0.05 | O33: =$O$32 -> 0.35 | Q33: =$Q$32 -> 0.35 | S33: =$S$32 -> 0.3 | U33: =$U$32 -> 0.3
C34: 3c | E34: Power/ Electricity | K34: =$K$32 -> -0.08 | M34: =$M$32 -> 0.05 | O34: =$O$32 -> 0.35 | Q34: =$Q$32 -> 0.35 | S34: =$S$32 -> 0.3 | U34: =$U$32 -> 0.3
C35: 3d | E35: Miscellaneous | G35: 1 | I35: =1500000/12 -> 125000 | K35: =$K$32 -> -0.08 | M35: =$M$32 -> 0.05 | O35: =$O$32 -> 0.35 | Q35: =$Q$32 -> 0.35 | S35: =$S$32 -> 0.3 | U35: =$U$32 -> 0.3
C36: 3e | K36: =$K$32 -> -0.08 | M36: =$M$32 -> 0.05 | O36: =$O$32 -> 0.35 | Q36: =$Q$32 -> 0.35 | S36: =$S$32 -> 0.3 | U36: =$U$32 -> 0.3
C37: 3f | K37: =$K$32 -> -0.08 | M37: =$M$32 -> 0.05 | O37: =$O$32 -> 0.35 | Q37: =$Q$32 -> 0.35 | S37: =$S$32 -> 0.3 | U37: =$U$32 -> 0.3
C38: 3g | G38: 5 | K38: =$K$32 -> -0.08 | M38: =$M$32 -> 0.05 | O38: =$O$32 -> 0.35 | Q38: =$Q$32 -> 0.35 | S38: =$S$32 -> 0.3 | U38: =$U$32 -> 0.3
C39: 3h | G39: 5 | K39: =$K$32 -> -0.08 | M39: =$M$32 -> 0.05 | O39: =$O$32 -> 0.35 | Q39: =$Q$32 -> 0.35 | S39: =$S$32 -> 0.3 | U39: =$U$32 -> 0.3
C40: 3i | K40: =$K$32 -> -0.08 | M40: =$M$32 -> 0.05 | O40: =$O$32 -> 0.35 | Q40: =$Q$32 -> 0.35 | S40: =$S$32 -> 0.3 | U40: =$U$32 -> 0.3
C41: Grand Total
C44: 4 | D44: Support Team
C45: 4a | E45: Salaries – Tech & Ops | I45: 400000 | K45: -0.5 | M45: 0.15 | O45: 0.1 | Q45: 0.9 | S45: 0.35 | U45: 0.6
C46: 4b | E46: Customer Support Team | I46: 120000 | K46: =$K$45 -> -0.5 | M46: =$M$45 -> 0.15 | O46: =$O$45 -> 0.1 | Q46: =$Q$45 -> 0.9 | S46: =$S$45 -> 0.35 | U46: =$U$45 -> 0.6
C47: 4c | E47: Field Agents | I47: 120000 | K47: =$K$45 -> -0.5 | M47: =$M$45 -> 0.15 | O47: =$O$45 -> 0.1 | Q47: =$Q$45 -> 0.9 | S47: =$S$45 -> 0.35 | U47: =$U$45 -> 0.6
C48: 4d | K48: =$K$45 -> -0.5 | M48: =$M$45 -> 0.15 | O48: =$O$45 -> 0.1 | Q48: =$Q$45 -> 0.9 | S48: =$S$45 -> 0.35 | U48: =$U$45 -> 0.6
C49: 4e | K49: =$K$45 -> -0.5 | M49: =$M$45 -> 0.15 | O49: =$O$45 -> 0.1 | Q49: =$Q$45 -> 0.9 | S49: =$S$45 -> 0.35 | U49: =$U$45 -> 0.6
C50: 4f | K50: =$K$45 -> -0.5 | M50: =$M$45 -> 0.15 | O50: =$O$45 -> 0.1 | Q50: =$Q$45 -> 0.9 | S50: =$S$45 -> 0.35 | U50: =$U$45 -> 0.6
C51: 4g | K51: =$K$45 -> -0.5 | M51: =$M$45 -> 0.15 | O51: =$O$45 -> 0.1 | Q51: =$Q$45 -> 0.9 | S51: =$S$45 -> 0.35 | U51: =$U$45 -> 0.6
C52: 4h | K52: =$K$45 -> -0.5 | M52: =$M$45 -> 0.15 | O52: =$O$45 -> 0.1 | Q52: =$Q$45 -> 0.9 | S52: =$S$45 -> 0.35 | U52: =$U$45 -> 0.6
C53: 4i | K53: =$K$45 -> -0.5 | M53: =$M$45 -> 0.15 | O53: =$O$45 -> 0.1 | Q53: =$Q$45 -> 0.9 | S53: =$S$45 -> 0.35 | U53: =$U$45 -> 0.6
C54: Grand Total
C57: 5 | D57: Digital Marketing & Advertisement
C58: 5a | E58: Initial Launch Event or Campaign | I58: =400000/12 -> 33333.333
C59: 5b | E59: Patient Promotions | K59: =$K$58 -> -0.35 | M59: =$M$58 -> 0.02 | O59: =$O$58 -> 1.25 | Q59: =$Q$58 -> 4.5 | S59: =$S$58 -> 0.7 | U59: =$U$58 -> 0.5
C60: 5c | E60: Doctors’ promotions | K60: =$K$58 -> -0.35 | M60: =$M$58 -> 0.02 | O60: =$O$58 -> 1.25 | Q60: =$Q$58 -> 4.5 | S60: =$S$58 -> 0.7 | U60: =$U$58 -> 0.5
C61: 5d | E61: Digital Marketing | K61: =$K$58 -> -0.35 | M61: =$M$58 -> 0.02 | O61: =$O$58 -> 1.25 | Q61: =$Q$58 -> 4.5 | S61: =$S$58 -> 0.7 | U61: =$U$58 -> 0.5
C62: 5e | E62: Social Media Marketing | K62: =$K$58 -> -0.35 | M62: =$M$58 -> 0.02 | O62: =$O$58 -> 1.25 | Q62: =$Q$58 -> 4.5 | S62: =$S$58 -> 0.7 | U62: =$U$58 -> 0.5
C63: 5f | E63: Brand promotions | K63: =$K$58 -> -0.35 | M63: =$M$58 -> 0.02 | O63: =$O$58 -> 1.25 | Q63: =$Q$58 -> 4.5 | S63: =$S$58 -> 0.7 | U63: =$U$58 -> 0.5
C64: 5g | K64: =$K$58 -> -0.35 | M64: =$M$58 -> 0.02 | O64: =$O$58 -> 1.25 | Q64: =$Q$58 -> 4.5 | S64: =$S$58 -> 0.7 | U64: =$U$58 -> 0.5
C65: Grand Total
C68: 6
C69: 6a
C70: 6b | K70: =$K$69 -> 0 | M70: =$M$69 -> 0 | O70: =$O$69 -> 0 | Q70: =$Q$69 -> 0 | S70: =$S$69 -> 0 | U70: =$U$69 -> 0
C71: 6c | K71: =$K$69 -> 0 | M71: =$M$69 -> 0 | O71: =$O$69 -> 0 | Q71: =$Q$69 -> 0 | S71: =$S$69 -> 0 | U71: =$U$69 -> 0
C72: 6d | K72: =$K$69 -> 0 | M72: =$M$69 -> 0 | O72: =$O$69 -> 0 | Q72: =$Q$69 -> 0 | S72: =$S$69 -> 0 | U72: =$U$69 -> 0
C73: 6e | K73: =$K$69 -> 0 | M73: =$M$69 -> 0 | O73: =$O$69 -> 0 | Q73: =$Q$69 -> 0 | S73: =$S$69 -> 0 | U73: =$U$69 -> 0
C74: 6f | K74: =$K$69 -> 0 | M74: =$M$69 -> 0 | O74: =$O$69 -> 0 | Q74: =$Q$69 -> 0 | S74: =$S$69 -> 0 | U74: =$U$69 -> 0
C75: 6g | K75: =$K$69 -> 0 | M75: =$M$69 -> 0 | O75: =$O$69 -> 0 | Q75: =$Q$69 -> 0 | S75: =$S$69 -> 0 | U75: =$U$69 -> 0
C76: 6h | K76: =$K$69 -> 0 | M76: =$M$69 -> 0 | O76: =$O$69 -> 0 | Q76: =$Q$69 -> 0 | S76: =$S$69 -> 0 | U76: =$U$69 -> 0
C77: 6i | K77: =$K$69 -> 0 | M77: =$M$69 -> 0 | O77: =$O$69 -> 0 | Q77: =$Q$69 -> 0 | S77: =$S$69 -> 0 | U77: =$U$69 -> 0
C78: 6j | K78: =$K$69 -> 0 | M78: =$M$69 -> 0 | O78: =$O$69 -> 0 | Q78: =$Q$69 -> 0 | S78: =$S$69 -> 0 | U78: =$U$69 -> 0
C79: 6k | K79: =$K$69 -> 0 | M79: =$M$69 -> 0 | O79: =$O$69 -> 0 | Q79: =$Q$69 -> 0 | S79: =$S$69 -> 0 | U79: =$U$69 -> 0
C80: 6l | K80: =$K$69 -> 0 | M80: =$M$69 -> 0 | O80: =$O$69 -> 0 | Q80: =$Q$69 -> 0 | S80: =$S$69 -> 0 | U80: =$U$69 -> 0
C81: 6m | K81: =$K$69 -> 0 | M81: =$M$69 -> 0 | O81: =$O$69 -> 0 | Q81: =$Q$69 -> 0 | S81: =$S$69 -> 0 | U81: =$U$69 -> 0
... C86: 6r | K86: =$K$69 -> 0 | M86: =$M$69 -> 0 | O86: =$O$69 -> 0 | Q86: =$Q$69 -> 0 | S86: =$S$69 -> 0 | U86: =$U$69 -> 0
C87: Grand Total
C90: 7
C91: 7a | K91: 0 | M91: 0 | O91: 0 | Q91: 0 | S91: 0 | U91: 0
C92: 7b | K92: =$K$91 -> 0 | M92: =$M$91 -> 0 | O92: =$O$91 -> 0 | Q92: =$Q$91 -> 0 | S92: =$S$91 -> 0 | U92: =$U$91 -> 0
C93: 7c | K93: =$K$91 -> 0 | M93: =$M$91 -> 0 | O93: =$O$91 -> 0 | Q93: =$Q$91 -> 0 | S93: =$S$91 -> 0 | U93: =$U$91 -> 0
C94: 7d | K94: =$K$91 -> 0 | M94: =$M$91 -> 0 | O94: =$O$91 -> 0 | Q94: =$Q$91 -> 0 | S94: =$S$91 -> 0 | U94: =$U$91 -> 0
C95: 7e | K95: =$K$91 -> 0 | M95: =$M$91 -> 0 | O95: =$O$91 -> 0 | Q95: =$Q$91 -> 0 | S95: =$S$91 -> 0 | U95: =$U$91 -> 0
C96: Grand Total
C99: 8
C100: 8a | K100: 0 | M100: 0 | O100: 0 | Q100: 0 | S100: 0 | U100: 0
C101: 8b | K101: =$K$100 -> 0 | M101: =$M$100 -> 0 | O101: =$O$100 -> 0 | Q101: =$Q$100 -> 0 | S101: =$S$100 -> 0 | U101: =$U$100 -> 0
C102: 8c | K102: =$K$100 -> 0 | M102: =$M$100 -> 0 | O102: =$O$100 -> 0 | Q102: =$Q$100 -> 0 | S102: =$S$100 -> 0 | U102: =$U$100 -> 0
C103: 8d | K103: =$K$100 -> 0 | M103: =$M$100 -> 0 | O103: =$O$100 -> 0 | Q103: =$Q$100 -> 0 | S103: =$S$100 -> 0 | U103: =$U$100 -> 0
C104: 8e | K104: =$K$100 -> 0 | M104: =$M$100 -> 0 | O104: =$O$100 -> 0 | Q104: =$Q$100 -> 0 | S104: =$S$100 -> 0 | U104: =$U$100 -> 0
C105: 8f | K105: =$K$100 -> 0 | M105: =$M$100 -> 0 | O105: =$O$100 -> 0 | Q105: =$Q$100 -> 0 | S105: =$S$100 -> 0 | U105: =$U$100 -> 0
C106: 8g | K106: =$K$100 -> 0 | M106: =$M$100 -> 0 | O106: =$O$100 -> 0 | Q106: =$Q$100 -> 0 | S106: =$S$100 -> 0 | U106: =$U$100 -> 0

Sheet A.III CAPEX
B2: S No | C2: Nature of the Expense | D2: Total Amount of the Project | E2: Cost for the Period Ending
E3: Year 1 Ending | G3: Year 2 Ending | H3: Year 3 Ending | I3: Year 4 Ending | J3: Year 5 Ending
E4: 31/03/2025 | F4: Year 1 Total | G4: 31/03/2027 | H4: 31/03/2028 | I4: 31/03/2029 | J4: 31/03/2030
B7: 1 | C7: Office Expenses | D7: =SUM(F7:J7) -> 0 | F7: =SUM(E7:E7) -> 0
C8: Laptop | D8: =SUM(F8:J8) -> 0 | F8: =SUM(E8:E8) -> 0
C9: Mobile | D9: =SUM(F9:J9) -> 0 | F9: =SUM(E9:E9) -> 0
C10: Monitor
C11: Tab
C12: Printer
B14: 2
D15: =SUM(F15:J15) -> 0 | F15: =SUM(E15:E15) -> 0
D16: =SUM(F16:J16) -> 0 | F16: =SUM(E16:E16) -> 0
B18: 3 | D18: 0 | F18: 0
D19: 0
D20: 0
D21: 0
B24: 4
D25: 0 | F25: 0
B27: 5 | D27: 0 | F27: 0
B32: 6 | D32: =SUM(F32:J32) -> 0 | F32: =SUM(E32:E32) -> 0
B35: Total Amount | D35: 510000000 | E35: =SUM(E7:E34) -> 0 | F35: =SUM(F7:F34) -> 0 | G35: =SUM(G7:G34) -> 0 | H35: 430000000 | I35: =SUM(I7:I34) -> 0 | J35: =SUM(J7:J34) -> 0
C41: 40 Cr is Equipment
C42: Civil

Sheet B.I Sales - P1
B2: A | C2: Do not enter any data in this sheet
F3: =H3 -> 2026-27 | H3: =IF(MONTH(F5)<=3,TEXT(F5,"yyyy")-1 & "-" & TEXT(F5,"yy"),IF(MONTH(F5)>3,TEXT(F5,"yyyy") & "-" & TEXT(F5,"yy")+1)) -> 2026-27 | J3: =L3 -> 2026-27 | L3: =IF(MONTH(J5)<=3,TEXT(J5,"yyyy")-1 & "-" & TEXT(J5,"yy"),IF(MONTH(J5)>3,TEXT(J5,"yyyy") & "-" & TEXT(J5,"yy")+1)) -> 2026-27 | N3: =P3 -> 2026-27 | P3: =IF(MONTH(N5)<=3,TEXT(N5,"yyyy")-1 & "-" & TEXT(N5,"yy"),IF(MONTH(N5)>3,TEXT(N5,"yyyy") & "-" & TEXT(N5,"yy")+1)) -> 2026-27 | R3: =T3 -> 2026-27 | T3: =IF(MONTH(R5)<=3,TEXT(R5,"yyyy")-1 & "-" & TEXT(R5,"yy"),IF(MONTH(R5)>3,TEXT(R5,"yyyy") & "-" & TEXT(R5,"yy")+1)) -> 2026-27 | V3: =X3 -> 2026-27 | X3: =IF(MONTH(V5)<=3,TEXT(V5,"yyyy")-1 & "-" & TEXT(V5,"yy"),IF(MONTH(V5)>3,TEXT(V5,"yyyy") & "-" & TEXT(V5,"yy")+1)) -> 2026-27 | Z3: =AB3 -> 2026-27 | AB3: =IF(MONTH(Z5)<=3,TEXT(Z5,"yyyy")-1 & "-" & TEXT(Z5,"yy"),IF(MONTH(Z5)>3,TEXT(Z5,"yyyy") & "-" & TEXT(Z5,"yy")+1)) -> 2026-27 | AD3: =AF3 -> 2026-27 | AF3: =IF(MONTH(AD5)<=3,TEXT(AD5,"yyyy")-1 & "-" & TEXT(AD5,"yy"),IF(MONTH(AD5)>3,TEXT(AD5,"yyyy") & "-" & TEXT(AD5,"yy")+1)) -> 2026-27 | AH3: =AJ3 -> 2026-27 | AJ3: =IF(MONTH(AH5)<=3,TEXT(AH5,"yyyy")-1 & "-" & TEXT(AH5,"yy"),IF(MONTH(AH5)>3,TEXT(AH5,"yyyy") & "-" & TEXT(AH5,"yy")+1)) -> 2026-27 | AL3: =AN3 -> 2026-27 | AN3: =IF(MONTH(AL5)<=3,TEXT(AL5,"yyyy")-1 & "-" & TEXT(AL5,"yy"),IF(MONTH(AL5)>3,TEXT(AL5,"yyyy") & "-" & TEXT(AL5,"yy")+1)) -> 2026-27 | AP3: =AR3 -> 2026-27 | AR3: =IF(MONTH(AP5)<=3,TEXT(AP5,"yyyy")-1 & "-" & TEXT(AP5,"yy"),IF(MONTH(AP5)>3,TEXT(AP5,"yyyy") & "-" & TEXT(AP5,"yy")+1)) -> 2026-27 | AT3: =AV3 -> 2026-27 | AV3: =IF(MONTH(AT5)<=3,TEXT(AT5,"yyyy")-1 & "-" & TEXT(AT5,"yy"),IF(MONTH(AT5)>3,TEXT(AT5,"yyyy") & "-" & TEXT(AT5,"yy")+1)) -> 2026-27 | AX3: =AZ3 -> 2026-27 | AZ3: =IF(MONTH(AX5)<=3,TEXT(AX5,"yyyy")-1 & "-" & TEXT(AX5,"yy"),IF(MONTH(AX5)>3,TEXT(AX5,"yyyy") & "-" & TEXT(AX5,"yy")+1)) -> 2026-27 | BB3: =BD3 -> 2027-28 | BD3: =IF(MONTH(BB5)<=3,TEXT(BB5,"yyyy")-1 & "-" & TEXT(BB5,"yy"),IF(MONTH(BB5)>3,TEXT(BB5,"yyyy") & "-" & TEXT(BB5,"yy")+1)) -> 2027-28 | BF3: =BH3 -> 2027-28 | BH3: =IF(MONTH(BF5)<=3,TEXT(BF5,"yyyy")-1 & "-" & TEXT(BF5,"yy"),IF(MONTH(BF5)>3,TEXT(BF5,"yyyy") & "-" & TEXT(BF5,"yy")+1)) -> 2027-28 | BJ3: =BL3 -> 2027-28 | BL3: =IF(MONTH(BJ5)<=3,TEXT(BJ5,"yyyy")-1 & "-" & TEXT(BJ5,"yy"),IF(MONTH(BJ5)>3,TEXT(BJ5,"yyyy") & "-" & TEXT(BJ5,"yy")+1)) -> 2027-28 | BN3: =BP3 -> 2027-28 | BP3: =IF(MONTH(BN5)<=3,TEXT(BN5,"yyyy")-1 & "-" & TEXT(BN5,"yy"),IF(MONTH(BN5)>3,TEXT(BN5,"yyyy") & "-" & TEXT(BN5,"yy")+1)) -> 2027-28 | BR3: =BT3 -> 2027-28 | BT3: =IF(MONTH(BR5)<=3,TEXT(BR5,"yyyy")-1 & "-" & TEXT(BR5,"yy"),IF(MONTH(BR5)>3,TEXT(BR5,"yyyy") & "-" & TEXT(BR5,"yy")+1)) -> 2027-28 | BV3: =BX3 -> 2027-28 | BX3: =IF(MONTH(BV5)<=3,TEXT(BV5,"yyyy")-1 & "-" & TEXT(BV5,"yy"),IF(MONTH(BV5)>3,TEXT(BV5,"yyyy") & "-" & TEXT(BV5,"yy")+1)) -> 2027-28 | BZ3: =CB3 -> 2027-28 | CB3: =IF(MONTH(BZ5)<=3,TEXT(BZ5,"yyyy")-1 & "-" & TEXT(BZ5,"yy"),IF(MONTH(BZ5)>3,TEXT(BZ5,"yyyy") & "-" & TEXT(BZ5,"yy")+1)) -> 2027-28 | CD3: =CF3 -> 2027-28 | CF3: =IF(MONTH(CD5)<=3,TEXT(CD5,"yyyy")-1 & "-" & TEXT(CD5,"yy"),IF(MONTH(CD5)>3,TEXT(CD5,"yyyy") & "-" & TEXT(CD5,"yy")+1)) -> 2027-28 | CH3: =CJ3 -> 2027-28 | CJ3: =IF(MONTH(CH5)<=3,TEXT(CH5,"yyyy")-1 & "-" & TEXT(CH5,"yy"),IF(MONTH(CH5)>3,TEXT(CH5,"yyyy") & "-" & TEXT(CH5,"yy")+1)) -> 2027-28 | CL3: =CN3 -> 2027-28 | CN3: =IF(MONTH(CL5)<=3,TEXT(CL5,"yyyy")-1 & "-" & TEXT(CL5,"yy"),IF(MONTH(CL5)>3,TEXT(CL5,"yyyy") & "-" & TEXT(CL5,"yy")+1)) -> 2027-28 | CP3: =CR3 -> 2027-28 | CR3: =IF(MONTH(CP5)<=3,TEXT(CP5,"yyyy")-1 & "-" & TEXT(CP5,"yy"),IF(MONTH(CP5)>3,TEXT(CP5,"yyyy") & "-" & TEXT(CP5,"yy")+1)) -> 2027-28 | CT3: =CV3 -> 2027-28 | CV3: =IF(MONTH(CT5)<=3,TEXT(CT5,"yyyy")-1 & "-" & TEXT(CT5,"yy"),IF(MONTH(CT5)>3,TEXT(CT5,"yyyy") & "-" & TEXT(CT5,"yy")+1)) -> 2027-28 | CX3: =CZ3 -> 2028-29 | CZ3: =IF(MONTH(CX5)<=3,TEXT(CX5,"yyyy")-1 & "-" & TEXT(CX5,"yy"),IF(MONTH(CX5)>3,TEXT(CX5,"yyyy") & "-" & TEXT(CX5,"yy")+1)) -> 2028-29 | DB3: =DD3 -> 2028-29 | DD3: =IF(MONTH(DB5)<=3,TEXT(DB5,"yyyy")-1 & "-" & TEXT(DB5,"yy"),IF(MONTH(DB5)>3,TEXT(DB5,"yyyy") & "-" & TEXT(DB5,"yy")+1)) -> 2028-29 | DF3: =DH3 -> 2028-29 | DH3: =IF(MONTH(DF5)<=3,TEXT(DF5,"yyyy")-1 & "-" & TEXT(DF5,"yy"),IF(MONTH(DF5)>3,TEXT(DF5,"yyyy") & "-" & TEXT(DF5,"yy")+1)) -> 2028-29 | DJ3: =DL3 -> 2028-29 | DL3: =IF(MONTH(DJ5)<=3,TEXT(DJ5,"yyyy")-1 & "-" & TEXT(DJ5,"yy"),IF(MONTH(DJ5)>3,TEXT(DJ5,"yyyy") & "-" & TEXT(DJ5,"yy")+1)) -> 2028-29 | DN3: =DP3 -> 2028-29 | DP3: =IF(MONTH(DN5)<=3,TEXT(DN5,"yyyy")-1 & "-" & TEXT(DN5,"yy"),IF(MONTH(DN5)>3,TEXT(DN5,"yyyy") & "-" & TEXT(DN5,"yy")+1)) -> 2028-29 | DR3: =DT3 -> 2028-29 | DT3: =IF(MONTH(DR5)<=3,TEXT(DR5,"yyyy")-1 & "-" & TEXT(DR5,"yy"),IF(MONTH(DR5)>3,TEXT(DR5,"yyyy") & "-" & TEXT(DR5,"yy")+1)) -> 2028-29 | DV3: =DX3 -> 2028-29 | DX3: =IF(MONTH(DV5)<=3,TEXT(DV5,"yyyy")-1 & "-" & TEXT(DV5,"yy"),IF(MONTH(DV5)>3,TEXT(DV5,"yyyy") & "-" & TEXT(DV5,"yy")+1)) -> 2028-29 | DZ3: =EB3 -> 2028-29 | EB3: =IF(MONTH(DZ5)<=3,TEXT(DZ5,"yyyy")-1 & "-" & TEXT(DZ5,"yy"),IF(MONTH(DZ5)>3,TEXT(DZ5,"yyyy") & "-" & TEXT(DZ5,"yy")+1)) -> 2028-29 | ED3: =EF3 -> 2028-29 | EF3: =IF(MONTH(ED5)<=3,TEXT(ED5,"yyyy")-1 & "-" & TEXT(ED5,"yy"),IF(MONTH(ED5)>3,TEXT(ED5,"yyyy") & "-" & TEXT(ED5,"yy")+1)) -> 2028-29 | EH3: =EJ3 -> 2028-29 | EJ3: =IF(MONTH(EH5)<=3,TEXT(EH5,"yyyy")-1 & "-" & TEXT(EH5,"yy"),IF(MONTH(EH5)>3,TEXT(EH5,"yyyy") & "-" & TEXT(EH5,"yy")+1)) -> 2028-29 | EL3: =EN3 -> 2028-29 | EN3: =IF(MONTH(EL5)<=3,TEXT(EL5,"yyyy")-1 & "-" & TEXT(EL5,"yy"),IF(MONTH(EL5)>3,TEXT(EL5,"yyyy") & "-" & TEXT(EL5,"yy")+1)) -> 2028-29 | EP3: =ER3 -> 2028-29 | ER3: =IF(MONTH(EP5)<=3,TEXT(EP5,"yyyy")-1 & "-" & TEXT(EP5,"yy"),IF(MONTH(EP5)>3,TEXT(EP5,"yyyy") & "-" & TEXT(EP5,"yy")+1)) -> 2028-29 | ET3: =EV3 -> 2029-30 | EV3: =IF(MONTH(ET5)<=3,TEXT(ET5,"yyyy")-1 & "-" & TEXT(ET5,"yy"),IF(MONTH(ET5)>3,TEXT(ET5,"yyyy") & "-" & TEXT(ET5,"yy")+1)) -> 2029-30 | EX3: =EZ3 -> 2029-30 | EZ3: =IF(MONTH(EX5)<=3,TEXT(EX5,"yyyy")-1 & "-" & TEXT(EX5,"yy"),IF(MONTH(EX5)>3,TEXT(EX5,"yyyy") & "-" & TEXT(EX5,"yy")+1)) -> 2029-30 | FB3: =FD3 -> 2029-30 | FD3: =IF(MONTH(FB5)<=3,TEXT(FB5,"yyyy")-1 & "-" & TEXT(FB5,"yy"),IF(MONTH(FB5)>3,TEXT(FB5,"yyyy") & "-" & TEXT(FB5,"yy")+1)) -> 2029-30 | FF3: =FH3 -> 2029-30 | FH3: =IF(MONTH(FF5)<=3,TEXT(FF5,"yyyy")-1 & "-" & TEXT(FF5,"yy"),IF(MONTH(FF5)>3,TEXT(FF5,"yyyy") & "-" & TEXT(FF5,"yy")+1)) -> 2029-30 | FJ3: =FL3 -> 2029-30 | FL3: =IF(MONTH(FJ5)<=3,TEXT(FJ5,"yyyy")-1 & "-" & TEXT(FJ5,"yy"),IF(MONTH(FJ5)>3,TEXT(FJ5,"yyyy") & "-" & TEXT(FJ5,"yy")+1)) -> 2029-30 | FN3: =FP3 -> 2029-30 | FP3: =IF(MONTH(FN5)<=3,TEXT(FN5,"yyyy")-1 & "-" & TEXT(FN5,"yy"),IF(MONTH(FN5)>3,TEXT(FN5,"yyyy") & "-" & TEXT(FN5,"yy")+1)) -> 2029-30 | FR3: =FT3 -> 2029-30 | FT3: =IF(MONTH(FR5)<=3,TEXT(FR5,"yyyy")-1 & "-" & TEXT(FR5,"yy"),IF(MONTH(FR5)>3,TEXT(FR5,"yyyy") & "-" & TEXT(FR5,"yy")+1)) -> 2029-30 | FV3: =FX3 -> 2029-30 | FX3: =IF(MONTH(FV5)<=3,TEXT(FV5,"yyyy")-1 & "-" & TEXT(FV5,"yy"),IF(MONTH(FV5)>3,TEXT(FV5,"yyyy") & "-" & TEXT(FV5,"yy")+1)) -> 2029-30 | FZ3: =GB3 -> 2029-30 | GB3: =IF(MONTH(FZ5)<=3,TEXT(FZ5,"yyyy")-1 & "-" & TEXT(FZ5,"yy"),IF(MONTH(FZ5)>3,TEXT(FZ5,"yyyy") & "-" & TEXT(FZ5,"yy")+1)) -> 2029-30 | GD3: =GF3 -> 2029-30 | GF3: =IF(MONTH(GD5)<=3,TEXT(GD5,"yyyy")-1 & "-" & TEXT(GD5,"yy"),IF(MONTH(GD5)>3,TEXT(GD5,"yyyy") & "-" & TEXT(GD5,"yy")+1)) -> 2029-30 | GH3: =GJ3 -> 2029-30 | GJ3: =IF(MONTH(GH5)<=3,TEXT(GH5,"yyyy")-1 & "-" & TEXT(GH5,"yy"),IF(MONTH(GH5)>3,TEXT(GH5,"yyyy") & "-" & TEXT(GH5,"yy")+1)) -> 2029-30 | GL3: =GN3 -> 2029-30 | GN3: =IF(MONTH(GL5)<=3,TEXT(GL5,"yyyy")-1 & "-" & TEXT(GL5,"yy"),IF(MONTH(GL5)>3,TEXT(GL5,"yyyy") & "-" & TEXT(GL5,"yy")+1)) -> 2029-30 | GP3: =GR3 -> 2030-31 | GR3: =IF(MONTH(GP5)<=3,TEXT(GP5,"yyyy")-1 & "-" & TEXT(GP5,"yy"),IF(MONTH(GP5)>3,TEXT(GP5,"yyyy") & "-" & TEXT(GP5,"yy")+1)) -> 2030-31 | GT3: =GV3 -> 2030-31 | GV3: =IF(MONTH(GT5)<=3,TEXT(GT5,"yyyy")-1 & "-" & TEXT(GT5,"yy"),IF(MONTH(GT5)>3,TEXT(GT5,"yyyy") & "-" & TEXT(GT5,"yy")+1)) -> 2030-31 | GX3: =GZ3 -> 2030-31 | GZ3: =IF(MONTH(GX5)<=3,TEXT(GX5,"yyyy")-1 & "-" & TEXT(GX5,"yy"),IF(MONTH(GX5)>3,TEXT(GX5,"yyyy") & "-" & TEXT(GX5,"yy")+1)) -> 2030-31 | HB3: =HD3 -> 2030-31 | HD3: =IF(MONTH(HB5)<=3,TEXT(HB5,"yyyy")-1 & "-" & TEXT(HB5,"yy"),IF(MONTH(HB5)>3,TEXT(HB5,"yyyy") & "-" & TEXT(HB5,"yy")+1)) -> 2030-31 | HF3: =HH3 -> 2030-31 | HH3: =IF(MONTH(HF5)<=3,TEXT(HF5,"yyyy")-1 & "-" & TEXT(HF5,"yy"),IF(MONTH(HF5)>3,TEXT(HF5,"yyyy") & "-" & TEXT(HF5,"yy")+1)) -> 2030-31 | HJ3: =HL3 -> 2030-31 | HL3: =IF(MONTH(HJ5)<=3,TEXT(HJ5,"yyyy")-1 & "-" & TEXT(HJ5,"yy"),IF(MONTH(HJ5)>3,TEXT(HJ5,"yyyy") & "-" & TEXT(HJ5,"yy")+1)) -> 2030-31 | HN3: =HP3 -> 2030-31 | HP3: =IF(MONTH(HN5)<=3,TEXT(HN5,"yyyy")-1 & "-" & TEXT(HN5,"yy"),IF(MONTH(HN5)>3,TEXT(HN5,"yyyy") & "-" & TEXT(HN5,"yy")+1)) -> 2030-31 | HR3: =HT3 -> 2030-31 | HT3: =IF(MONTH(HR5)<=3,TEXT(HR5,"yyyy")-1 & "-" & TEXT(HR5,"yy"),IF(MONTH(HR5)>3,TEXT(HR5,"yyyy") & "-" & TEXT(HR5,"yy")+1)) -> 2030-31 | HV3: =HX3 -> 2030-31 | HX3: =IF(MONTH(HV5)<=3,TEXT(HV5,"yyyy")-1 & "-" & TEXT(HV5,"yy"),IF(MONTH(HV5)>3,TEXT(HV5,"yyyy") & "-" & TEXT(HV5,"yy")+1)) -> 2030-31 | HZ3: =IB3 -> 2030-31 | IB3: =IF(MONTH(HZ5)<=3,TEXT(HZ5,"yyyy")-1 & "-" & TEXT(HZ5,"yy"),IF(MONTH(HZ5)>3,TEXT(HZ5,"yyyy") & "-" & TEXT(HZ5,"yy")+1)) -> 2030-31 | ID3: =IF3 -> 2030-31 | IF3: =IF(MONTH(ID5)<=3,TEXT(ID5,"yyyy")-1 & "-" & TEXT(ID5,"yy"),IF(MONTH(ID5)>3,TEXT(ID5,"yyyy") & "-" & TEXT(ID5,"yy")+1)) -> 2030-31 | IH3: =IJ3 -> 2030-31 | IJ3: =IF(MONTH(IH5)<=3,TEXT(IH5,"yyyy")-1 & "-" & TEXT(IH5,"yy"),IF(MONTH(IH5)>3,TEXT(IH5,"yyyy") & "-" & TEXT(IH5,"yy")+1)) -> 2030-31
C4: Particulars | G4: Month - | H4: 1 | K4: Month - | L4: =H4+1 -> 2 | O4: Month - | P4: =L4+1 -> 3 | S4: Month - | T4: =P4+1 -> 4 | W4: Month - | X4: =T4+1 -> 5 | AA4: Month - | AB4: =X4+1 -> 6 | AE4: Month - | AF4: =AB4+1 -> 7 | AI4: Month - | AJ4: =AF4+1 -> 8 | AM4: Month - | AN4: =AJ4+1 -> 9 | AQ4: Month - | AR4: =AN4+1 -> 10 | AU4: Month - | AV4: =AR4+1 -> 11 | AY4: Month - | AZ4: =AV4+1 -> 12 | BC4: Month - | BD4: =AZ4+1 -> 13 | BG4: Month - | BH4: =BD4+1 -> 14 | BK4: Month - | BL4: =BH4+1 -> 15 | BO4: Month - | BP4: =BL4+1 -> 16 | BS4: Month - | BT4: =BP4+1 -> 17 | BW4: Month - | BX4: =BT4+1 -> 18 | CA4: Month - | CB4: =BX4+1 -> 19 | CE4: Month - | CF4: =CB4+1 -> 20 | CI4: Month - | CJ4: =CF4+1 -> 21 | CM4: Month - | CN4: =CJ4+1 -> 22 | CQ4: Month - | CR4: =CN4+1 -> 23 | CU4: Month - | CV4: =CR4+1 -> 24 | CY4: Month - | CZ4: =CV4+1 -> 25 | DC4: Month - | DD4: =CZ4+1 -> 26 | DG4: Month - | DH4: =DD4+1 -> 27 | DK4: Month - | DL4: =DH4+1 -> 28 | DO4: Month - | DP4: =DL4+1 -> 29 | DS4: Month - | DT4: =DP4+1 -> 30 | DW4: Month - | DX4: =DT4+1 -> 31 | EA4: Month - | EB4: =DX4+1 -> 32 | EE4: Month - | EF4: =EB4+1 -> 33 | EI4: Month - | EJ4: =EF4+1 -> 34 | EM4: Month - | EN4: =EJ4+1 -> 35 | EQ4: Month - | ER4: =EN4+1 -> 36 | EU4: Month - | EV4: =ER4+1 -> 37 | EY4: Month - | EZ4: =EV4+1 -> 38 | FC4: Month - | FD4: =EZ4+1 -> 39 | FG4: Month - | FH4: =FD4+1 -> 40 | FK4: Month - | FL4: =FH4+1 -> 41 | FO4: Month - | FP4: =FL4+1 -> 42 | FS4: Month - | FT4: =FP4+1 -> 43 | FW4: Month - | FX4: =FT4+1 -> 44 | GA4: Month - | GB4: =FX4+1 -> 45 | GE4: Month - | GF4: =GB4+1 -> 46 | GI4: Month - | GJ4: =GF4+1 -> 47 | GM4: Month - | GN4: =GJ4+1 -> 48 | GQ4: Month - | GR4: =GN4+1 -> 49 | GU4: Month - | GV4: =GR4+1 -> 50 | GY4: Month - | GZ4: =GV4+1 -> 51 | HC4: Month - | HD4: =GZ4+1 -> 52 | HG4: Month - | HH4: =HD4+1 -> 53 | HK4: Month - | HL4: =HH4+1 -> 54 | HO4: Month - | HP4: =HL4+1 -> 55 | HS4: Month - | HT4: =HP4+1 -> 56 | HW4: Month - | HX4: =HT4+1 -> 57 | IA4: Month - | IB4: =HX4+1 -> 58 | IE4: Month - | IF4: =IB4+1 -> 59 | II4: Month - | IJ4: =IF4+1 -> 60 | IL4: Year 1 | IP4: Year 2 | IT4: Year 3 | IX4: Year 4 | JB4: Year 5 | JF4: Year 6
F5: =EOMONTH('1. Basics'!$D$16,1) -> 46142 | J5: =EOMONTH($F$5,1) -> 46173 | N5: =EOMONTH($F$5,2) -> 46203 | R5: =EOMONTH($F$5,3) -> 46234 | V5: =EOMONTH($F$5,4) -> 46265 | Z5: =EOMONTH($F$5,5) -> 46295 | AD5: =EOMONTH($F$5,6) -> 46326 | AH5: =EOMONTH($F$5,7) -> 46356 | AL5: =EOMONTH($F$5,8) -> 46387 | AP5: =EOMONTH($F$5,9) -> 46418 | AT5: =EOMONTH($F$5,10) -> 46446 | AX5: =EOMONTH($F$5,11) -> 46477 | BB5: =EOMONTH($F$5,12) -> 46507 | BF5: =EOMONTH($F$5,13) -> 46538 | BJ5: =EOMONTH($F$5,14) -> 46568 | BN5: =EOMONTH($F$5,15) -> 46599 | BR5: =EOMONTH($F$5,16) -> 46630 | BV5: =EOMONTH($F$5,17) -> 46660 | BZ5: =EOMONTH($F$5,18) -> 46691 | CD5: =EOMONTH($F$5,19) -> 46721 | CH5: =EOMONTH($F$5,20) -> 46752 | CL5: =EOMONTH($F$5,21) -> 46783 | CP5: =EOMONTH($F$5,22) -> 46812 | CT5: =EOMONTH($F$5,23) -> 46843 | CX5: =EOMONTH($F$5,24) -> 46873 | DB5: =EOMONTH($F$5,25) -> 46904 | DF5: =EOMONTH($F$5,26) -> 46934 | DJ5: =EOMONTH($F$5,27) -> 46965 | DN5: =EOMONTH($F$5,28) -> 46996 | DR5: =EOMONTH($F$5,29) -> 47026 | DV5: =EOMONTH($F$5,30) -> 47057 | DZ5: =EOMONTH($F$5,31) -> 47087 | ED5: =EOMONTH($F$5,32) -> 47118 | EH5: =EOMONTH($F$5,33) -> 47149 | EL5: =EOMONTH($F$5,34) -> 47177 | EP5: =EOMONTH($F$5,35) -> 47208 | ET5: =EOMONTH($F$5,36) -> 47238 | EX5: =EOMONTH($F$5,37) -> 47269 | FB5: =EOMONTH($F$5,38) -> 47299 | FF5: =EOMONTH($F$5,39) -> 47330 | FJ5: =EOMONTH($F$5,40) -> 47361 | FN5: =EOMONTH($F$5,41) -> 47391 | FR5: =EOMONTH($F$5,42) -> 47422 | FV5: =EOMONTH($F$5,43) -> 47452 | FZ5: =EOMONTH($F$5,44) -> 47483 | GD5: =EOMONTH($F$5,45) -> 47514 | GH5: =EOMONTH($F$5,46) -> 47542 | GL5: =EOMONTH($F$5,47) -> 47573 | GP5: =EOMONTH($F$5,48) -> 47603 | GT5: =EOMONTH($F$5,49) -> 47634 | GX5: =EOMONTH($F$5,50) -> 47664 | HB5: =EOMONTH($F$5,51) -> 47695 | HF5: =EOMONTH($F$5,52) -> 47726 | HJ5: =EOMONTH($F$5,53) -> 47756 | HN5: =EOMONTH($F$5,54) -> 47787 | HR5: =EOMONTH($F$5,55) -> 47817 | HV5: =EOMONTH($F$5,56) -> 47848 | HZ5: =EOMONTH($F$5,57) -> 47879 | ID5: =EOMONTH($F$5,58) -> 47907 | IH5: =EOMONTH($F$5,59) -> 47938 | IL5: 2025-26 | IP5: 2026-27 | IT5: 2027-28 | IX5: 2028-29 | JB5: 2029-30 | JF5: 2030-31
C6: PHASE - I REVENUES | F6: Qty | G6: Per Unit Cost | H6: Total Revenue | J6: Qty | K6: Per Unit Cost | L6: Total Revenue | N6: Qty | O6: Per Unit Cost | P6: Total Revenue | R6: Qty | S6: Per Unit Cost | T6: Total Revenue | V6: Qty | W6: Per Unit Cost | X6: Total Revenue | Z6: Qty | AA6: Per Unit Cost | AB6: Total Revenue | AD6: Qty | AE6: Per Unit Cost | AF6: Total Revenue | AH6: Qty | AI6: Per Unit Cost | AJ6: Total Revenue | AL6: Qty | AM6: Per Unit Cost | AN6: Total Revenue | AP6: Qty | AQ6: Per Unit Cost | AR6: Total Revenue | AT6: Qty | AU6: Per Unit Cost | AV6: Total Revenue | AX6: Qty | AY6: Per Unit Cost | AZ6: Total Revenue | BB6: Qty | BC6: Per Unit Cost | BD6: Total Revenue | BF6: Qty | BG6: Per Unit Cost | BH6: Total Revenue | BJ6: Qty | BK6: Per Unit Cost | BL6: Total Revenue | BN6: Qty | BO6: Per Unit Cost | BP6: Total Revenue | BR6: Qty | BS6: Per Unit Cost | BT6: Total Revenue | BV6: Qty | BW6: Per Unit Cost | BX6: Total Revenue | BZ6: Qty | CA6: Per Unit Cost | CB6: Total Revenue | CD6: Qty | CE6: Per Unit Cost | CF6: Total Revenue | CH6: Qty | CI6: Per Unit Cost | CJ6: Total Revenue | CL6: Qty | CM6: Per Unit Cost | CN6: Total Revenue | CP6: Qty | CQ6: Per Unit Cost | CR6: Total Revenue | CT6: Qty | CU6: Per Unit Cost | CV6: Total Revenue | CX6: Qty | CY6: Per Unit Cost | CZ6: Total Revenue | DB6: Qty | DC6: Per Unit Cost | DD6: Total Revenue | DF6: Qty | DG6: Per Unit Cost | DH6: Total Revenue | DJ6: Qty | DK6: Per Unit Cost | DL6: Total Revenue | DN6: Qty | DO6: Per Unit Cost | DP6: Total Revenue | DR6: Qty | DS6: Per Unit Cost | DT6: Total Revenue | DV6: Qty | DW6: Per Unit Cost | DX6: Total Revenue | DZ6: Qty | EA6: Per Unit Cost | EB6: Total Revenue | ED6: Qty | EE6: Per Unit Cost | EF6: Total Revenue | EH6: Qty | EI6: Per Unit Cost | EJ6: Total Revenue | EL6: Qty | EM6: Per Unit Cost | EN6: Total Revenue | EP6: Qty | EQ6: Per Unit Cost | ER6: Total Revenue | ET6: Qty | EU6: Per Unit Cost | EV6: Total Revenue | EX6: Qty | EY6: Per Unit Cost | EZ6: Total Revenue | FB6: Qty | FC6: Per Unit Cost | FD6: Total Revenue | FF6: Qty | FG6: Per Unit Cost | FH6: Total Revenue | FJ6: Qty | FK6: Per Unit Cost | FL6: Total Revenue | FN6: Qty | FO6: Per Unit Cost | FP6: Total Revenue | FR6: Qty | FS6: Per Unit Cost | FT6: Total Revenue | FV6: Qty | FW6: Per Unit Cost | FX6: Total Revenue | FZ6: Qty | GA6: Per Unit Cost | GB6: Total Revenue | GD6: Qty | GE6: Per Unit Cost | GF6: Total Revenue | GH6: Qty | GI6: Per Unit Cost | GJ6: Total Revenue | GL6: Qty | GM6: Per Unit Cost | GN6: Total Revenue | GP6: Qty | GQ6: Per Unit Cost | GR6: Total Revenue | GT6: Qty | GU6: Per Unit Cost | GV6: Total Revenue | GX6: Qty | GY6: Per Unit Cost | GZ6: Total Revenue | HB6: Qty | HC6: Per Unit Cost | HD6: Total Revenue | HF6: Qty | HG6: Per Unit Cost | HH6: Total Revenue | HJ6: Qty | HK6: Per Unit Cost | HL6: Total Revenue | HN6: Qty | HO6: Per Unit Cost | HP6: Total Revenue | HR6: Qty | HS6: Per Unit Cost | HT6: Total Revenue | HV6: Qty | HW6: Per Unit Cost | HX6: Total Revenue | HZ6: Qty | IA6: Per Unit Cost | IB6: Total Revenue | ID6: Qty | IE6: Per Unit Cost | IF6: Total Revenue | IH6: Qty | II6: Per Unit Cost | IJ6: Total Revenue | IL6: Qty | IM6: Cost Per Month | IN6: Total Revenue | IP6: Qty | IQ6: Cost Per Month | IR6: Total Revenue | IT6: Qty | IU6: Cost Per Month | IV6: Total Revenue | IX6: Qty | IY6: Cost Per Month | IZ6: Total Revenue | JB6: Qty | JC6: Cost Per Month | JD6: Total Revenue | JF6: Qty | JG6: Cost Per Month | JH6: Total Revenue
C8: Services | D8: Sub Services | J8: ='A.I Revenue Streams - P1'!K10+100% -> 1.01 | K8: 1 | N8: =J8 -> 1.01 | O8: 1 | R8: =N8 -> 1.01 | S8: 1 | V8: =R8 -> 1.01 | W8: 1 | Z8: =V8 -> 1.01 | AA8: 1 | AD8: =Z8 -> 1.01 | AE8: 1 | AH8: =AD8 -> 1.01 | AI8: 1 | AL8: =AH8 -> 1.01 | AM8: 1 | AP8: 1.1 | AQ8: 1 | AT8: 1 | AU8: 1 | AX8: =AT8 -> 1 | AY8: 1 | BB8: ='A.I Revenue Streams - P1'!M10+100% -> 1.82 | BC8: 1 | BF8: 1 | BG8: 1 | BJ8: 1 | BK8: 1 | BN8: =BJ8 -> 1 | BO8: 1 | BR8: =BN8 -> 1 | BS8: 1 | BV8: =BR8 -> 1 | BW8: 1 | BZ8: =BV8 -> 1 | CA8: 1 | CD8: =BZ8 -> 1 | CE8: 1 | CH8: =CD8 -> 1 | CI8: 1 | CL8: 1 | CM8: 1 | CP8: 1 | CQ8: 1 | CT8: =CP8 -> 1 | CU8: 1 | CX8: ='A.I Revenue Streams - P1'!O10+100% -> 1.7 | CY8: 1 | DB8: 1 | DC8: 1 | DF8: =DB8 -> 1 | DG8: 1 | DJ8: =DF8 -> 1 | DK8: 1 | DN8: =DJ8 -> 1 | DO8: 1 | DR8: =DN8 -> 1 | DS8: 1 | DV8: =DR8 -> 1 | DW8: 1 | DZ8: =DV8 -> 1 | EA8: 1 | ED8: =DZ8 -> 1 | EE8: 1 | EH8: 1 | EI8: 1 | EL8: 1 | EM8: 1 | EP8: =EL8 -> 1 | EQ8: 1 | ET8: ='A.I Revenue Streams - P1'!Q10+100% -> 1.55 | EU8: 1 | EX8: 1 | EY8: 1 | FB8: =EX8 -> 1 | FC8: 1 | FF8: =FB8 -> 1 | FG8: 1 | FJ8: =FF8 -> 1 | FK8: 1 | FN8: =FJ8 -> 1 | FO8: 1 | FR8: =FN8 -> 1 | FS8: 1 | FV8: =FR8 -> 1 | FW8: 1 | FZ8: =FV8 -> 1 | GA8: 1 | GD8: 1 | GE8: 1 | GH8: 1 | GI8: 1 | GL8: =GH8 -> 1 | GM8: 1 | GP8: ='A.I Revenue Streams - P1'!S10+100% -> 1.45 | GQ8: 1 | GT8: 1 | GU8: 1 | GX8: =GT8 -> 1 | GY8: 1 | HB8: =GX8 -> 1 | HC8: 1 | HF8: =HB8 -> 1 | HG8: 1 | HJ8: =HF8 -> 1 | HK8: 1 | HN8: =HJ8 -> 1 | HO8: 1 | HR8: =HN8 -> 1 | HS8: 1 | HV8: =HR8 -> 1 | HW8: 1 | HZ8: 1 | IA8: 1 | ID8: 1 | IE8: 1 | IH8: =ID8 -> 1 | II8: 1 | IL8: ='A.I Revenue Streams - P2'!DI10+100% -> 1 | IM8: 1 | IP8: ='A.I Revenue Streams - P2'!DM10+100% -> 1 | IQ8: 1 | IT8: ='A.I Revenue Streams - P2'!DQ10+100% -> 1 | IU8: 1 | IX8: ='A.I Revenue Streams - P2'!DU10+100% -> 1 | IY8: 1 | JB8: ='A.I Revenue Streams - P2'!DY10+100% -> 1 | JC8: 1 | JF8: ='A.I Revenue Streams - P2'!EC10+100% -> 1 | JG8: 1
B9: 1 | C9: ='A.I Revenue Streams - P1'!D9 -> Doctor Consultations
B10: 1a | D10: ='A.I Revenue Streams - P1'!E10 -> Platform Access Fees | F10: ='A.I Revenue Streams - P1'!G10 -> 28000 | G10: ='A.I Revenue Streams - P1'!I10 -> 30 | H10: =F10*G10 -> 840000 | J10: =F10*$J$8 -> 28280 | K10: =G10*$K$8 -> 30 | L10: =J10*K10 -> 848400 | N10: =J10*$N$8 -> 28562.8 | O10: =K10*$O$8 -> 30 | P10: =N10*O10 -> 856884 | R10: =N10*$R$8 -> 28848.428 | S10: =O10*$S$8 -> 30 | T10: =R10*S10 -> 865452.84 | V10: =R10*$V$8 -> 29136.912 | W10: =S10*$W$8 -> 30 | X10: =V10*W10 -> 874107.37 | Z10: =V10*$Z$8 -> 29428.281 | AA10: =W10*$AA$8 -> 30 | AB10: =Z10*AA10 -> 882848.44 | AD10: =Z10*$AD$8 -> 29722.564 | AE10: =AA10*$AE$8 -> 30 | AF10: =AD10*AE10 -> 891676.93 | AH10: =AD10*$AH$8 -> 30019.79 | AI10: =AE10*$AI$8 -> 30 | AJ10: =AH10*AI10 -> 900593.7 | AL10: =AH10*$AL$8 -> 30319.988 | AM10: =AI10*$AM$8 -> 30 | AN10: =AL10*AM10 -> 909599.63 | AP10: =AL10*$AP$8 -> 33351.987 | AQ10: =AM10*$AQ$8 -> 30 | AR10: =AP10*AQ10 -> 1000559.6 | AT10: =AP10*$AT$8 -> 33351.987 | AU10: =AQ10*$AU$8 -> 30 | AV10: =AT10*AU10 -> 1000559.6 | AX10: =AT10*$AX$8 -> 33351.987 | AY10: =AU10*$AY$8 -> 30 | AZ10: =AX10*AY10 -> 1000559.6 | BB10: =AX10*$BB$8 -> 60700.615 | BC10: =AY10*$BC$8 -> 30 | BD10: =BB10*BC10 -> 1821018.5 | BF10: =BB10*$BF$8 -> 60700.615 | BG10: =BC10*$BG$8 -> 30 | BH10: =BF10*BG10 -> 1821018.5 | BJ10: =BF10*$BJ$8 -> 60700.615 | BK10: =BG10*$BK$8 -> 30 | BL10: =BJ10*BK10 -> 1821018.5 | BN10: =BJ10*$BN$8 -> 60700.615 | BO10: =BK10*$BO$8 -> 30 | BP10: =BN10*BO10 -> 1821018.5 | BR10: =BN10*$BR$8 -> 60700.615 | BS10: =BO10*$BS$8 -> 30 | BT10: =BR10*BS10 -> 1821018.5 | BV10: =BR10*$BV$8 -> 60700.615 | BW10: =BS10*$BW$8 -> 30 | BX10: =BV10*BW10 -> 1821018.5 | BZ10: =BV10*$BZ$8 -> 60700.615 | CA10: =BW10*$CA$8 -> 30 | CB10: =BZ10*CA10 -> 1821018.5 | CD10: =BZ10*$CD$8 -> 60700.615 | CE10: =CA10*$CE$8 -> 30 | CF10: =CD10*CE10 -> 1821018.5 | CH10: =CD10*$CH$8 -> 60700.615 | CI10: =CE10*$CI$8 -> 30 | CJ10: =CH10*CI10 -> 1821018.5 | CL10: =CH10*$CL$8 -> 60700.615 | CM10: =CI10*$CM$8 -> 30 | CN10: =CL10*CM10 -> 1821018.5 | CP10: =CL10*$CP$8 -> 60700.615 | CQ10: =CM10*$CQ$8 -> 30 | CR10: =CP10*CQ10 -> 1821018.5 | CT10: =CP10*$CT$8 -> 60700.615 | CU10: =CQ10*$CU$8 -> 30 | CV10: =CT10*CU10 -> 1821018.5 | CX10: =CT10*$CX$8 -> 103191.05 | CY10: =CU10*$CY$8 -> 30 | CZ10: =CX10*CY10 -> 3095731.4 | DB10: =CX10*$DB$8 -> 103191.05 | DC10: =CY10*$DC$8 -> 30 | DD10: =DB10*DC10 -> 3095731.4 | DF10: =DB10*$DF$8 -> 103191.05 | DG10: =DC10*$DG$8 -> 30 | DH10: =DF10*DG10 -> 3095731.4 | DJ10: =DF10*$DJ$8 -> 103191.05 | DK10: =DG10*$DK$8 -> 30 | DL10: =DJ10*DK10 -> 3095731.4 | DN10: =DJ10*$DN$8 -> 103191.05 | DO10: =DK10*$DO$8 -> 30 | DP10: =DN10*DO10 -> 3095731.4 | DR10: =DN10*$DR$8 -> 103191.05 | DS10: =DO10*$DS$8 -> 30 | DT10: =DR10*DS10 -> 3095731.4 | DV10: =DR10*$DV$8 -> 103191.05 | DW10: =DS10*$DW$8 -> 30 | DX10: =DV10*DW10 -> 3095731.4 | DZ10: =DV10*$DZ$8 -> 103191.05 | EA10: =DW10*$EA$8 -> 30 | EB10: =DZ10*EA10 -> 3095731.4 | ED10: =DZ10*$ED$8 -> 103191.05 | EE10: =EA10*$EE$8 -> 30 | EF10: =ED10*EE10 -> 3095731.4 | EH10: =ED10*$EH$8 -> 103191.05 | EI10: =EE10*$EI$8 -> 30 | EJ10: =EH10*EI10 -> 3095731.4 | EL10: =EH10*$EL$8 -> 103191.05 | EM10: =EI10*$EM$8 -> 30 | EN10: =EL10*EM10 -> 3095731.4 | EP10: =EL10*$EP$8 -> 103191.05 | EQ10: =EM10*$EQ$8 -> 30 | ER10: =EP10*EQ10 -> 3095731.4 | ET10: =EP10*$ET$8 -> 159946.12 | EU10: =EQ10*$EU$8 -> 30 | EV10: =ET10*EU10 -> 4798383.7 | EX10: =ET10*$EX$8 -> 159946.12 | EY10: =EU10*$EY$8 -> 30 | EZ10: =EX10*EY10 -> 4798383.7 | FB10: =EX10*$FB$8 -> 159946.12 | FC10: =EY10*$FC$8 -> 30 | FD10: =FB10*FC10 -> 4798383.7 | FF10: =FB10*$FF$8 -> 159946.12 | FG10: =FC10*$FG$8 -> 30 | FH10: =FF10*FG10 -> 4798383.7 | FJ10: =FF10*$FJ$8 -> 159946.12 | FK10: =FG10*$FK$8 -> 30 | FL10: =FJ10*FK10 -> 4798383.7 | FN10: =FJ10*$FN$8 -> 159946.12 | FO10: =FK10*$FO$8 -> 30 | FP10: =FN10*FO10 -> 4798383.7 | FR10: =FN10*$FR$8 -> 159946.12 | FS10: =FO10*$FS$8 -> 30 | FT10: =FR10*FS10 -> 4798383.7 | FV10: =FR10*$FV$8 -> 159946.12 | FW10: =FS10*$FW$8 -> 30 | FX10: =FV10*FW10 -> 4798383.7 | FZ10: =FV10*$FZ$8 -> 159946.12 | GA10: =FW10*$GA$8 -> 30 | GB10: =FZ10*GA10 -> 4798383.7 | GD10: =FZ10*$GD$8 -> 159946.12 | GE10: =GA10*$GE$8 -> 30 | GF10: =GD10*GE10 -> 4798383.7 | GH10: =GD10*$GH$8 -> 159946.12 | GI10: =GE10*$GI$8 -> 30 | GJ10: =GH10*GI10 -> 4798383.7 | GL10: =GH10*$GL$8 -> 159946.12 | GM10: =GI10*$GM$8 -> 30 | GN10: =GL10*GM10 -> 4798383.7 | GP10: =GL10*$GP$8 -> 231921.88 | GQ10: =GM10*$GQ$8 -> 30 | GR10: =GP10*GQ10 -> 6957656.3 | GT10: =GP10*$GT$8 -> 231921.88 | GU10: =GQ10*$GU$8 -> 30 | GV10: =GT10*GU10 -> 6957656.3 | GX10: =GT10*$GX$8 -> 231921.88 | GY10: =GU10*$GY$8 -> 30 | GZ10: =GX10*GY10 -> 6957656.3 | HB10: =GX10*$HB$8 -> 231921.88 | HC10: =GY10*$HC$8 -> 30 | HD10: =HB10*HC10 -> 6957656.3 | HF10: =HB10*$HF$8 -> 231921.88 | HG10: =HC10*$HG$8 -> 30 | HH10: =HF10*HG10 -> 6957656.3 | HJ10: =HF10*$HJ$8 -> 231921.88 | HK10: =HG10*$HK$8 -> 30 | HL10: =HJ10*HK10 -> 6957656.3 | HN10: =HJ10*$HN$8 -> 231921.88 | HO10: =HK10*$HO$8 -> 30 | HP10: =HN10*HO10 -> 6957656.3 | HR10: =HN10*$HR$8 -> 231921.88 | HS10: =HO10*$HS$8 -> 30 | HT10: =HR10*HS10 -> 6957656.3 | HV10: =HR10*$HV$8 -> 231921.88 | HW10: =HS10*$HW$8 -> 30 | HX10: =HV10*HW10 -> 6957656.3 | HZ10: =HV10*$HZ$8 -> 231921.88 | IA10: =HW10*$IA$8 -> 30 | IB10: =HZ10*IA10 -> 6957656.3 | ID10: =HZ10*$ID$8 -> 231921.88 | IE10: =IA10*$IE$8 -> 30 | IF10: =ID10*IE10 -> 6957656.3 | IH10: =ID10*$IH$8 -> 231921.88 | II10: =IE10*$II$8 -> 30 | IJ10: =IH10*II10 -> 6957656.3 | IL10: =SUMIFS($F10:$IK10,$F$3:$IK$3,IL$5,$F$6:$IK$6,IL$6) -> 0 | IM10: 0 | IN10: =SUMIFS($F10:$IK10,$F$3:$IK$3,IL$5,$F$6:$IK$6,IN$6) -> 0 | IP10: =SUMIFS($F10:$IK10,$F$3:$IK$3,IP$5,$F$6:$IK$6,IP$6) -> 362374.72 | IQ10: =IR10/IP10 -> 30 | IR10: =SUMIFS($F10:$IK10,$F$3:$IK$3,IP$5,$F$6:$IK$6,IR$6) -> 10871242 | IT10: =SUMIFS($F10:$IK10,$F$3:$IK$3,IT$5,$F$6:$IK$6,IT$6) -> 728407.39 | IU10: =IV10/IT10 -> 30 | IV10: =SUMIFS($F10:$IK10,$F$3:$IK$3,IT$5,$F$6:$IK$6,IV$6) -> 21852222 | IX10: =SUMIFS($F10:$IK10,$F$3:$IK$3,IX$5,$F$6:$IK$6,IX$6) -> 1238292.6 | IY10: =IZ10/IX10 -> 30 | IZ10: =SUMIFS($F10:$IK10,$F$3:$IK$3,IX$5,$F$6:$IK$6,IZ$6) -> 37148777 | JB10: =SUMIFS($F10:$IK10,$F$3:$IK$3,JB$5,$F$6:$IK$6,JB$6) -> 1919353.5 | JC10: =JD10/JB10 -> 30 | JD10: =SUMIFS($F10:$IK10,$F$3:$IK$3,JB$5,$F$6:$IK$6,JD$6) -> 57580604 | JF10: =SUMIFS($F10:$IK10,$F$3:$IK$3,JF$5,$F$6:$IK$6,JF$6) -> 2783062.5 | JG10: =JH10/JF10 -> 30 | JH10: =SUMIFS($F10:$IK10,$F$3:$IK$3,JF$5,$F$6:$IK$6,JH$6) -> 83491876
B11: 1b | D11: ='A.I Revenue Streams - P1'!E11 -> 0 | F11: 0 | G11: ='A.I Revenue Streams - P1'!I11 -> 0 | H11: =F11*G11 -> 0 | J11: =F11*$J$8 -> 0 | K11: =G11*$K$8 -> 0 | L11: =J11*K11 -> 0 | N11: =J11*$N$8 -> 0 | O11: =K11*$O$8 -> 0 | P11: =N11*O11 -> 0 | R11: ='A.I Revenue Streams - P1'!G11 -> 0 | S11: =O11*$S$8 -> 0 | T11: =R11*S11 -> 0 | V11: =R11*$V$8 -> 0 | W11: =S11*$W$8 -> 0 | X11: =V11*W11 -> 0 | Z11: =V11*$Z$8 -> 0 | AA11: =W11*$AA$8 -> 0 | AB11: =Z11*AA11 -> 0 | AD11: =Z11*$AD$8 -> 0 | AE11: =AA11*$AE$8 -> 0 | AF11: =AD11*AE11 -> 0 | AH11: =AD11*$AH$8 -> 0 | AI11: =AE11*$AI$8 -> 0 | AJ11: =AH11*AI11 -> 0 | AL11: =AH11*$AL$8 -> 0 | AM11: =AI11*$AM$8 -> 0 | AN11: =AL11*AM11 -> 0 | AP11: =AL11*$AP$8 -> 0 | AQ11: =AM11*$AQ$8 -> 0 | AR11: =AP11*AQ11 -> 0 | AT11: =AP11*$AT$8 -> 0 | AU11: =AQ11*$AU$8 -> 0 | AV11: =AT11*AU11 -> 0 | AX11: =AT11*$AX$8 -> 0 | AY11: =AU11*$AY$8 -> 0 | AZ11: =AX11*AY11 -> 0 | BB11: =AX11*$BB$8 -> 0 | BC11: =AY11*$BC$8 -> 0 | BD11: =BB11*BC11 -> 0 | BF11: =BB11*$BF$8 -> 0 | BG11: =BC11*$BG$8 -> 0 | BH11: =BF11*BG11 -> 0 | BJ11: =BF11*$BJ$8 -> 0 | BK11: =BG11*$BK$8 -> 0 | BL11: =BJ11*BK11 -> 0 | BN11: =BJ11*$BN$8 -> 0 | BO11: =BK11*$BO$8 -> 0 | BP11: =BN11*BO11 -> 0 | BR11: =BN11*$BR$8 -> 0 | BS11: =BO11*$BS$8 -> 0 | BT11: =BR11*BS11 -> 0 | BV11: =BR11*$BV$8 -> 0 | BW11: =BS11*$BW$8 -> 0 | BX11: =BV11*BW11 -> 0 | BZ11: =BV11*$BZ$8 -> 0 | CA11: =BW11*$CA$8 -> 0 | CB11: =BZ11*CA11 -> 0 | CD11: =BZ11*$CD$8 -> 0 | CE11: =CA11*$CE$8 -> 0 | CF11: =CD11*CE11 -> 0 | CH11: =CD11*$CH$8 -> 0 | CI11: =CE11*$CI$8 -> 0 | CJ11: =CH11*CI11 -> 0 | CL11: =CH11*$CL$8 -> 0 | CM11: =CI11*$CM$8 -> 0 | CN11: =CL11*CM11 -> 0 | CP11: =CL11*$CP$8 -> 0 | CQ11: =CM11*$CQ$8 -> 0 | CR11: =CP11*CQ11 -> 0 | CT11: =CP11*$CT$8 -> 0 | CU11: =CQ11*$CU$8 -> 0 | CV11: =CT11*CU11 -> 0 | CX11: =CT11*$CX$8 -> 0 | CY11: =CU11*$CY$8 -> 0 | CZ11: =CX11*CY11 -> 0 | DB11: =CX11*$DB$8 -> 0 | DC11: =CY11*$DC$8 -> 0 | DD11: =DB11*DC11 -> 0 | DF11: =DB11*$DF$8 -> 0 | DG11: =DC11*$DG$8 -> 0 | DH11: =DF11*DG11 -> 0 | DJ11: =DF11*$DJ$8 -> 0 | DK11: =DG11*$DK$8 -> 0 | DL11: =DJ11*DK11 -> 0 | DN11: =DJ11*$DN$8 -> 0 | DO11: =DK11*$DO$8 -> 0 | DP11: =DN11*DO11 -> 0 | DR11: =DN11*$DR$8 -> 0 | DS11: =DO11*$DS$8 -> 0 | DT11: =DR11*DS11 -> 0 | DV11: =DR11*$DV$8 -> 0 | DW11: =DS11*$DW$8 -> 0 | DX11: =DV11*DW11 -> 0 | DZ11: =DV11*$DZ$8 -> 0 | EA11: =DW11*$EA$8 -> 0 | EB11: =DZ11*EA11 -> 0 | ED11: =DZ11*$ED$8 -> 0 | EE11: =EA11*$EE$8 -> 0 | EF11: =ED11*EE11 -> 0 | EH11: =ED11*$EH$8 -> 0 | EI11: =EE11*$EI$8 -> 0 | EJ11: =EH11*EI11 -> 0 | EL11: =EH11*$EL$8 -> 0 | EM11: =EI11*$EM$8 -> 0 | EN11: =EL11*EM11 -> 0 | EP11: =EL11*$EP$8 -> 0 | EQ11: =EM11*$EQ$8 -> 0 | ER11: =EP11*EQ11 -> 0 | ET11: =EP11*$ET$8 -> 0 | EU11: =EQ11*$EU$8 -> 0 | EV11: =ET11*EU11 -> 0 | EX11: =ET11*$EX$8 -> 0 | EY11: =EU11*$EY$8 -> 0 | EZ11: =EX11*EY11 -> 0 | FB11: =EX11*$FB$8 -> 0 | FC11: =EY11*$FC$8 -> 0 | FD11: =FB11*FC11 -> 0 | FF11: =FB11*$FF$8 -> 0 | FG11: =FC11*$FG$8 -> 0 | FH11: =FF11*FG11 -> 0 | FJ11: =FF11*$FJ$8 -> 0 | FK11: =FG11*$FK$8 -> 0 | FL11: =FJ11*FK11 -> 0 | FN11: =FJ11*$FN$8 -> 0 | FO11: =FK11*$FO$8 -> 0 | FP11: =FN11*FO11 -> 0 | FR11: =FN11*$FR$8 -> 0 | FS11: =FO11*$FS$8 -> 0 | FT11: =FR11*FS11 -> 0 | FV11: =FR11*$FV$8 -> 0 | FW11: =FS11*$FW$8 -> 0 | FX11: =FV11*FW11 -> 0 | FZ11: =FV11*$FZ$8 -> 0 | GA11: =FW11*$GA$8 -> 0 | GB11: =FZ11*GA11 -> 0 | GD11: =FZ11*$GD$8 -> 0 | GE11: =GA11*$GE$8 -> 0 | GF11: =GD11*GE11 -> 0 | GH11: =GD11*$GH$8 -> 0 | GI11: =GE11*$GI$8 -> 0 | GJ11: =GH11*GI11 -> 0 | GL11: =GH11*$GL$8 -> 0 | GM11: =GI11*$GM$8 -> 0 | GN11: =GL11*GM11 -> 0 | GP11: =GL11*$GP$8 -> 0 | GQ11: =GM11*$GQ$8 -> 0 | GR11: =GP11*GQ11 -> 0 | GT11: =GP11*$GT$8 -> 0 | GU11: =GQ11*$GU$8 -> 0 | GV11: =GT11*GU11 -> 0 | GX11: =GT11*$GX$8 -> 0 | GY11: =GU11*$GY$8 -> 0 | GZ11: =GX11*GY11 -> 0 | HB11: =GX11*$HB$8 -> 0 | HC11: =GY11*$HC$8 -> 0 | HD11: =HB11*HC11 -> 0 | HF11: =HB11*$HF$8 -> 0 | HG11: =HC11*$HG$8 -> 0 | HH11: =HF11*HG11 -> 0 | HJ11: =HF11*$HJ$8 -> 0 | HK11: =HG11*$HK$8 -> 0 | HL11: =HJ11*HK11 -> 0 | HN11: =HJ11*$HN$8 -> 0 | HO11: =HK11*$HO$8 -> 0 | HP11: =HN11*HO11 -> 0 | HR11: =HN11*$HR$8 -> 0 | HS11: =HO11*$HS$8 -> 0 | HT11: =HR11*HS11 -> 0 | HV11: =HR11*$HV$8 -> 0 | HW11: =HS11*$HW$8 -> 0 | HX11: =HV11*HW11 -> 0 | HZ11: =HV11*$HZ$8 -> 0 | IA11: =HW11*$IA$8 -> 0 | IB11: =HZ11*IA11 -> 0 | ID11: =HZ11*$ID$8 -> 0 | IE11: =IA11*$IE$8 -> 0 | IF11: =ID11*IE11 -> 0 | IH11: =ID11*$IH$8 -> 0 | II11: =IE11*$II$8 -> 0 | IJ11: =IH11*II11 -> 0 | IL11: =SUMIFS($F11:$IK11,$F$3:$IK$3,IL$5,$F$6:$IK$6,IL$6) -> 0 | IM11: 0 | IN11: =SUMIFS($F11:$IK11,$F$3:$IK$3,IL$5,$F$6:$IK$6,IN$6) -> 0 | IP11: =SUMIFS($F11:$IK11,$F$3:$IK$3,IP$5,$F$6:$IK$6,IP$6) -> 0 | IQ11: =IR11/IP11 -> #DIV/0! | IR11: =SUMIFS($F11:$IK11,$F$3:$IK$3,IP$5,$F$6:$IK$6,IR$6) -> 0 | IT11: =SUMIFS($F11:$IK11,$F$3:$IK$3,IT$5,$F$6:$IK$6,IT$6) -> 0 | IU11: =IV11/IT11 -> #DIV/0! | IV11: =SUMIFS($F11:$IK11,$F$3:$IK$3,IT$5,$F$6:$IK$6,IV$6) -> 0 | IX11: =SUMIFS($F11:$IK11,$F$3:$IK$3,IX$5,$F$6:$IK$6,IX$6) -> 0 | IY11: =IZ11/IX11 -> #DIV/0! | IZ11: =SUMIFS($F11:$IK11,$F$3:$IK$3,IX$5,$F$6:$IK$6,IZ$6) -> 0 | JB11: =SUMIFS($F11:$IK11,$F$3:$IK$3,JB$5,$F$6:$IK$6,JB$6) -> 0 | JC11: =JD11/JB11 -> #DIV/0! | JD11: =SUMIFS($F11:$IK11,$F$3:$IK$3,JB$5,$F$6:$IK$6,JD$6) -> 0 | JF11: =SUMIFS($F11:$IK11,$F$3:$IK$3,JF$5,$F$6:$IK$6,JF$6) -> 0 | JG11: =JH11/JF11 -> #DIV/0! | JH11: =SUMIFS($F11:$IK11,$F$3:$IK$3,JF$5,$F$6:$IK$6,JH$6) -> 0
B12: 1c | D12: ='A.I Revenue Streams - P1'!E12 -> 0 | F12: ='A.I Revenue Streams - P1'!G12 -> 0 | G12: ='A.I Revenue Streams - P1'!I12 -> 0 | H12: =F12*G12 -> 0 | J12: =F12*$J$8 -> 0 | K12: =G12*$K$8 -> 0 | L12: =J12*K12 -> 0 | N12: =J12*$N$8 -> 0 | O12: =K12*$O$8 -> 0 | P12: =N12*O12 -> 0 | R12: =N12*$R$8 -> 0 | S12: =O12*$S$8 -> 0 | T12: =R12*S12 -> 0 | V12: =R12*$V$8 -> 0 | W12: =S12*$W$8 -> 0 | X12: =V12*W12 -> 0 | Z12: =V12*$Z$8 -> 0 | AA12: =W12*$AA$8 -> 0 | AB12: =Z12*AA12 -> 0 | AD12: =Z12*$AD$8 -> 0 | AE12: =AA12*$AE$8 -> 0 | AF12: =AD12*AE12 -> 0 | AH12: =AD12*$AH$8 -> 0 | AI12: =AE12*$AI$8 -> 0 | AJ12: =AH12*AI12 -> 0 | AL12: =AH12*$AL$8 -> 0 | AM12: =AI12*$AM$8 -> 0 | AN12: =AL12*AM12 -> 0 | AP12: =AL12*$AP$8 -> 0 | AQ12: =AM12*$AQ$8 -> 0 | AR12: =AP12*AQ12 -> 0 | AT12: =AP12*$AT$8 -> 0 | AU12: =AQ12*$AU$8 -> 0 | AV12: =AT12*AU12 -> 0 | AX12: =AT12*$AX$8 -> 0 | AY12: =AU12*$AY$8 -> 0 | AZ12: =AX12*AY12 -> 0 | BB12: =AX12*$BB$8 -> 0 | BC12: =AY12*$BC$8 -> 0 | BD12: =BB12*BC12 -> 0 | BF12: =BB12*$BF$8 -> 0 | BG12: =BC12*$BG$8 -> 0 | BH12: =BF12*BG12 -> 0 | BJ12: =BF12*$BJ$8 -> 0 | BK12: =BG12*$BK$8 -> 0 | BL12: =BJ12*BK12 -> 0 | BN12: =BJ12*$BN$8 -> 0 | BO12: =BK12*$BO$8 -> 0 | BP12: =BN12*BO12 -> 0 | BR12: =BN12*$BR$8 -> 0 | BS12: =BO12*$BS$8 -> 0 | BT12: =BR12*BS12 -> 0 | BV12: =BR12*$BV$8 -> 0 | BW12: =BS12*$BW$8 -> 0 | BX12: =BV12*BW12 -> 0 | BZ12: =BV12*$BZ$8 -> 0 | CA12: =BW12*$CA$8 -> 0 | CB12: =BZ12*CA12 -> 0 | CD12: =BZ12*$CD$8 -> 0 | CE12: =CA12*$CE$8 -> 0 | CF12: =CD12*CE12 -> 0 | CH12: =CD12*$CH$8 -> 0 | CI12: =CE12*$CI$8 -> 0 | CJ12: =CH12*CI12 -> 0 | CL12: =CH12*$CL$8 -> 0 | CM12: =CI12*$CM$8 -> 0 | CN12: =CL12*CM12 -> 0 | CP12: =CL12*$CP$8 -> 0 | CQ12: =CM12*$CQ$8 -> 0 | CR12: =CP12*CQ12 -> 0 | CT12: =CP12*$CT$8 -> 0 | CU12: =CQ12*$CU$8 -> 0 | CV12: =CT12*CU12 -> 0 | CX12: =CT12*$CX$8 -> 0 | CY12: =CU12*$CY$8 -> 0 | CZ12: =CX12*CY12 -> 0 | DB12: =CX12*$DB$8 -> 0 | DC12: =CY12*$DC$8 -> 0 | DD12: =DB12*DC12 -> 0 | DF12: =DB12*$DF$8 -> 0 | DG12: =DC12*$DG$8 -> 0 | DH12: =DF12*DG12 -> 0 | DJ12: =DF12*$DJ$8 -> 0 | DK12: =DG12*$DK$8 -> 0 | DL12: =DJ12*DK12 -> 0 | DN12: =DJ12*$DN$8 -> 0 | DO12: =DK12*$DO$8 -> 0 | DP12: =DN12*DO12 -> 0 | DR12: =DN12*$DR$8 -> 0 | DS12: =DO12*$DS$8 -> 0 | DT12: =DR12*DS12 -> 0 | DV12: =DR12*$DV$8 -> 0 | DW12: =DS12*$DW$8 -> 0 | DX12: =DV12*DW12 -> 0 | DZ12: =DV12*$DZ$8 -> 0 | EA12: =DW12*$EA$8 -> 0 | EB12: =DZ12*EA12 -> 0 | ED12: =DZ12*$ED$8 -> 0 | EE12: =EA12*$EE$8 -> 0 | EF12: =ED12*EE12 -> 0 | EH12: =ED12*$EH$8 -> 0 | EI12: =EE12*$EI$8 -> 0 | EJ12: =EH12*EI12 -> 0 | EL12: =EH12*$EL$8 -> 0 | EM12: =EI12*$EM$8 -> 0 | EN12: =EL12*EM12 -> 0 | EP12: =EL12*$EP$8 -> 0 | EQ12: =EM12*$EQ$8 -> 0 | ER12: =EP12*EQ12 -> 0 | ET12: =EP12*$ET$8 -> 0 | EU12: =EQ12*$EU$8 -> 0 | EV12: =ET12*EU12 -> 0 | EX12: =ET12*$EX$8 -> 0 | EY12: =EU12*$EY$8 -> 0 | EZ12: =EX12*EY12 -> 0 | FB12: =EX12*$FB$8 -> 0 | FC12: =EY12*$FC$8 -> 0 | FD12: =FB12*FC12 -> 0 | FF12: =FB12*$FF$8 -> 0 | FG12: =FC12*$FG$8 -> 0 | FH12: =FF12*FG12 -> 0 | FJ12: =FF12*$FJ$8 -> 0 | FK12: =FG12*$FK$8 -> 0 | FL12: =FJ12*FK12 -> 0 | FN12: =FJ12*$FN$8 -> 0 | FO12: =FK12*$FO$8 -> 0 | FP12: =FN12*FO12 -> 0 | FR12: =FN12*$FR$8 -> 0 | FS12: =FO12*$FS$8 -> 0 | FT12: =FR12*FS12 -> 0 | FV12: =FR12*$FV$8 -> 0 | FW12: =FS12*$FW$8 -> 0 | FX12: =FV12*FW12 -> 0 | FZ12: =FV12*$FZ$8 -> 0 | GA12: =FW12*$GA$8 -> 0 | GB12: =FZ12*GA12 -> 0 | GD12: =FZ12*$GD$8 -> 0 | GE12: =GA12*$GE$8 -> 0 | GF12: =GD12*GE12 -> 0 | GH12: =GD12*$GH$8 -> 0 | GI12: =GE12*$GI$8 -> 0 | GJ12: =GH12*GI12 -> 0 | GL12: =GH12*$GL$8 -> 0 | GM12: =GI12*$GM$8 -> 0 | GN12: =GL12*GM12 -> 0 | GP12: =GL12*$GP$8 -> 0 | GQ12: =GM12*$GQ$8 -> 0 | GR12: =GP12*GQ12 -> 0 | GT12: =GP12*$GT$8 -> 0 | GU12: =GQ12*$GU$8 -> 0 | GV12: =GT12*GU12 -> 0 | GX12: =GT12*$GX$8 -> 0 | GY12: =GU12*$GY$8 -> 0 | GZ12: =GX12*GY12 -> 0 | HB12: =GX12*$HB$8 -> 0 | HC12: =GY12*$HC$8 -> 0 | HD12: =HB12*HC12 -> 0 | HF12: =HB12*$HF$8 -> 0 | HG12: =HC12*$HG$8 -> 0 | HH12: =HF12*HG12 -> 0 | HJ12: =HF12*$HJ$8 -> 0 | HK12: =HG12*$HK$8 -> 0 | HL12: =HJ12*HK12 -> 0 | HN12: =HJ12*$HN$8 -> 0 | HO12: =HK12*$HO$8 -> 0 | HP12: =HN12*HO12 -> 0 | HR12: =HN12*$HR$8 -> 0 | HS12: =HO12*$HS$8 -> 0 | HT12: =HR12*HS12 -> 0 | HV12: =HR12*$HV$8 -> 0 | HW12: =HS12*$HW$8 -> 0 | HX12: =HV12*HW12 -> 0 | HZ12: =HV12*$HZ$8 -> 0 | IA12: =HW12*$IA$8 -> 0 | IB12: =HZ12*IA12 -> 0 | ID12: =HZ12*$ID$8 -> 0 | IE12: =IA12*$IE$8 -> 0 | IF12: =ID12*IE12 -> 0 | IH12: =ID12*$IH$8 -> 0 | II12: =IE12*$II$8 -> 0 | IJ12: =IH12*II12 -> 0 | IL12: =SUMIFS($F12:$IK12,$F$3:$IK$3,IL$5,$F$6:$IK$6,IL$6) -> 0 | IM12: 0 | IN12: =SUMIFS($F12:$IK12,$F$3:$IK$3,IL$5,$F$6:$IK$6,IN$6) -> 0 | IP12: =SUMIFS($F12:$IK12,$F$3:$IK$3,IP$5,$F$6:$IK$6,IP$6) -> 0 | IQ12: 0 | IR12: =SUMIFS($F12:$IK12,$F$3:$IK$3,IP$5,$F$6:$IK$6,IR$6) -> 0 | IT12: =SUMIFS($F12:$IK12,$F$3:$IK$3,IT$5,$F$6:$IK$6,IT$6) -> 0 | IU12: 0 | IV12: =SUMIFS($F12:$IK12,$F$3:$IK$3,IT$5,$F$6:$IK$6,IV$6) -> 0 | IX12: =SUMIFS($F12:$IK12,$F$3:$IK$3,IX$5,$F$6:$IK$6,IX$6) -> 0 | IY12: 0 | IZ12: =SUMIFS($F12:$IK12,$F$3:$IK$3,IX$5,$F$6:$IK$6,IZ$6) -> 0 | JB12: =SUMIFS($F12:$IK12,$F$3:$IK$3,JB$5,$F$6:$IK$6,JB$6) -> 0 | JC12: 0 | JD12: =SUMIFS($F12:$IK12,$F$3:$IK$3,JB$5,$F$6:$IK$6,JD$6) -> 0 | JF12: =SUMIFS($F12:$IK12,$F$3:$IK$3,JF$5,$F$6:$IK$6,JF$6) -> 0 | JG12: 0 | JH12: =SUMIFS($F12:$IK12,$F$3:$IK$3,JF$5,$F$6:$IK$6,JH$6) -> 0
B13: 1d | D13: ='A.I Revenue Streams - P1'!E13 -> 0 | F13: ='A.I Revenue Streams - P1'!G13 -> 0 | G13: ='A.I Revenue Streams - P1'!I13 -> 0 | H13: =F13*G13 -> 0 | J13: =F13*$J$8 -> 0 | K13: =G13*$K$8 -> 0 | L13: =J13*K13 -> 0 | N13: =J13*$N$8 -> 0 | O13: =K13*$O$8 -> 0 | P13: =N13*O13 -> 0 | R13: =N13*$R$8 -> 0 | S13: =O13*$S$8 -> 0 | T13: =R13*S13 -> 0 | V13: =R13*$V$8 -> 0 | W13: =S13*$W$8 -> 0 | X13: =V13*W13 -> 0 | Z13: =V13*$Z$8 -> 0 | AA13: =W13*$AA$8 -> 0 | AB13: =Z13*AA13 -> 0 | AD13: =Z13*$AD$8 -> 0 | AE13: =AA13*$AE$8 -> 0 | AF13: =AD13*AE13 -> 0 | AH13: =AD13*$AH$8 -> 0 | AI13: =AE13*$AI$8 -> 0 | AJ13: =AH13*AI13 -> 0 | AL13: =AH13*$AL$8 -> 0 | AM13: =AI13*$AM$8 -> 0 | AN13: =AL13*AM13 -> 0 | AP13: =AL13*$AP$8 -> 0 | AQ13: =AM13*$AQ$8 -> 0 | AR13: =AP13*AQ13 -> 0 | AT13: =AP13*$AT$8 -> 0 | AU13: =AQ13*$AU$8 -> 0 | AV13: =AT13*AU13 -> 0 | AX13: =AT13*$AX$8 -> 0 | AY13: =AU13*$AY$8 -> 0 | AZ13: =AX13*AY13 -> 0 | BB13: =AX13*$BB$8 -> 0 | BC13: =AY13*$BC$8 -> 0 | BD13: =BB13*BC13 -> 0 | BF13: =BB13*$BF$8 -> 0 | BG13: =BC13*$BG$8 -> 0 | BH13: =BF13*BG13 -> 0 | BJ13: =BF13*$BJ$8 -> 0 | BK13: =BG13*$BK$8 -> 0 | BL13: =BJ13*BK13 -> 0 | BN13: =BJ13*$BN$8 -> 0 | BO13: =BK13*$BO$8 -> 0 | BP13: =BN13*BO13 -> 0 | BR13: =BN13*$BR$8 -> 0 | BS13: =BO13*$BS$8 -> 0 | BT13: =BR13*BS13 -> 0 | BV13: =BR13*$BV$8 -> 0 | BW13: =BS13*$BW$8 -> 0 | BX13: =BV13*BW13 -> 0 | BZ13: =BV13*$BZ$8 -> 0 | CA13: =BW13*$CA$8 -> 0 | CB13: =BZ13*CA13 -> 0 | CD13: =BZ13*$CD$8 -> 0 | CE13: =CA13*$CE$8 -> 0 | CF13: =CD13*CE13 -> 0 | CH13: =CD13*$CH$8 -> 0 | CI13: =CE13*$CI$8 -> 0 | CJ13: =CH13*CI13 -> 0 | CL13: =CH13*$CL$8 -> 0 | CM13: =CI13*$CM$8 -> 0 | CN13: =CL13*CM13 -> 0 | CP13: =CL13*$CP$8 -> 0 | CQ13: =CM13*$CQ$8 -> 0 | CR13: =CP13*CQ13 -> 0 | CT13: =CP13*$CT$8 -> 0 | CU13: =CQ13*$CU$8 -> 0 | CV13: =CT13*CU13 -> 0 | CX13: =CT13*$CX$8 -> 0 | CY13: =CU13*$CY$8 -> 0 | CZ13: =CX13*CY13 -> 0 | DB13: =CX13*$DB$8 -> 0 | DC13: =CY13*$DC$8 -> 0 | DD13: =DB13*DC13 -> 0 | DF13: =DB13*$DF$8 -> 0 | DG13: =DC13*$DG$8 -> 0 | DH13: =DF13*DG13 -> 0 | DJ13: =DF13*$DJ$8 -> 0 | DK13: =DG13*$DK$8 -> 0 | DL13: =DJ13*DK13 -> 0 | DN13: =DJ13*$DN$8 -> 0 | DO13: =DK13*$DO$8 -> 0 | DP13: =DN13*DO13 -> 0 | DR13: =DN13*$DR$8 -> 0 | DS13: =DO13*$DS$8 -> 0 | DT13: =DR13*DS13 -> 0 | DV13: =DR13*$DV$8 -> 0 | DW13: =DS13*$DW$8 -> 0 | DX13: =DV13*DW13 -> 0 | DZ13: =DV13*$DZ$8 -> 0 | EA13: =DW13*$EA$8 -> 0 | EB13: =DZ13*EA13 -> 0 | ED13: =DZ13*$ED$8 -> 0 | EE13: =EA13*$EE$8 -> 0 | EF13: =ED13*EE13 -> 0 | EH13: =ED13*$EH$8 -> 0 | EI13: =EE13*$EI$8 -> 0 | EJ13: =EH13*EI13 -> 0 | EL13: =EH13*$EL$8 -> 0 | EM13: =EI13*$EM$8 -> 0 | EN13: =EL13*EM13 -> 0 | EP13: =EL13*$EP$8 -> 0 | EQ13: =EM13*$EQ$8 -> 0 | ER13: =EP13*EQ13 -> 0 | ET13: =EP13*$ET$8 -> 0 | EU13: =EQ13*$EU$8 -> 0 | EV13: =ET13*EU13 -> 0 | EX13: =ET13*$EX$8 -> 0 | EY13: =EU13*$EY$8 -> 0 | EZ13: =EX13*EY13 -> 0 | FB13: =EX13*$FB$8 -> 0 | FC13: =EY13*$FC$8 -> 0 | FD13: =FB13*FC13 -> 0 | FF13: =FB13*$FF$8 -> 0 | FG13: =FC13*$FG$8 -> 0 | FH13: =FF13*FG13 -> 0 | FJ13: =FF13*$FJ$8 -> 0 | FK13: =FG13*$FK$8 -> 0 | FL13: =FJ13*FK13 -> 0 | FN13: =FJ13*$FN$8 -> 0 | FO13: =FK13*$FO$8 -> 0 | FP13: =FN13*FO13 -> 0 | FR13: =FN13*$FR$8 -> 0 | FS13: =FO13*$FS$8 -> 0 | FT13: =FR13*FS13 -> 0 | FV13: =FR13*$FV$8 -> 0 | FW13: =FS13*$FW$8 -> 0 | FX13: =FV13*FW13 -> 0 | FZ13: =FV13*$FZ$8 -> 0 | GA13: =FW13*$GA$8 -> 0 | GB13: =FZ13*GA13 -> 0 | GD13: =FZ13*$GD$8 -> 0 | GE13: =GA13*$GE$8 -> 0 | GF13: =GD13*GE13 -> 0 | GH13: =GD13*$GH$8 -> 0 | GI13: =GE13*$GI$8 -> 0 | GJ13: =GH13*GI13 -> 0 | GL13: =GH13*$GL$8 -> 0 | GM13: =GI13*$GM$8 -> 0 | GN13: =GL13*GM13 -> 0 | GP13: =GL13*$GP$8 -> 0 | GQ13: =GM13*$GQ$8 -> 0 | GR13: =GP13*GQ13 -> 0 | GT13: =GP13*$GT$8 -> 0 | GU13: =GQ13*$GU$8 -> 0 | GV13: =GT13*GU13 -> 0 | GX13: =GT13*$GX$8 -> 0 | GY13: =GU13*$GY$8 -> 0 | GZ13: =GX13*GY13 -> 0 | HB13: =GX13*$HB$8 -> 0 | HC13: =GY13*$HC$8 -> 0 | HD13: =HB13*HC13 -> 0 | HF13: =HB13*$HF$8 -> 0 | HG13: =HC13*$HG$8 -> 0 | HH13: =HF13*HG13 -> 0 | HJ13: =HF13*$HJ$8 -> 0 | HK13: =HG13*$HK$8 -> 0 | HL13: =HJ13*HK13 -> 0 | HN13: =HJ13*$HN$8 -> 0 | HO13: =HK13*$HO$8 -> 0 | HP13: =HN13*HO13 -> 0 | HR13: =HN13*$HR$8 -> 0 | HS13: =HO13*$HS$8 -> 0 | HT13: =HR13*HS13 -> 0 | HV13: =HR13*$HV$8 -> 0 | HW13: =HS13*$HW$8 -> 0 | HX13: =HV13*HW13 -> 0 | HZ13: =HV13*$HZ$8 -> 0 | IA13: =HW13*$IA$8 -> 0 | IB13: =HZ13*IA13 -> 0 | ID13: =HZ13*$ID$8 -> 0 | IE13: =IA13*$IE$8 -> 0 | IF13: =ID13*IE13 -> 0 | IH13: =ID13*$IH$8 -> 0 | II13: =IE13*$II$8 -> 0 | IJ13: =IH13*II13 -> 0 | IL13: =SUMIFS($F13:$IK13,$F$3:$IK$3,IL$5,$F$6:$IK$6,IL$6) -> 0 | IM13: 0 | IN13: =SUMIFS($F13:$IK13,$F$3:$IK$3,IL$5,$F$6:$IK$6,IN$6) -> 0 | IP13: =SUMIFS($F13:$IK13,$F$3:$IK$3,IP$5,$F$6:$IK$6,IP$6) -> 0 | IQ13: 0 | IR13: =SUMIFS($F13:$IK13,$F$3:$IK$3,IP$5,$F$6:$IK$6,IR$6) -> 0 | IT13: =SUMIFS($F13:$IK13,$F$3:$IK$3,IT$5,$F$6:$IK$6,IT$6) -> 0 | IU13: 0 | IV13: =SUMIFS($F13:$IK13,$F$3:$IK$3,IT$5,$F$6:$IK$6,IV$6) -> 0 | IX13: =SUMIFS($F13:$IK13,$F$3:$IK$3,IX$5,$F$6:$IK$6,IX$6) -> 0 | IY13: 0 | IZ13: =SUMIFS($F13:$IK13,$F$3:$IK$3,IX$5,$F$6:$IK$6,IZ$6) -> 0 | JB13: =SUMIFS($F13:$IK13,$F$3:$IK$3,JB$5,$F$6:$IK$6,JB$6) -> 0 | JC13: 0 | JD13: =SUMIFS($F13:$IK13,$F$3:$IK$3,JB$5,$F$6:$IK$6,JD$6) -> 0 | JF13: =SUMIFS($F13:$IK13,$F$3:$IK$3,JF$5,$F$6:$IK$6,JF$6) -> 0 | JG13: 0 | JH13: =SUMIFS($F13:$IK13,$F$3:$IK$3,JF$5,$F$6:$IK$6,JH$6) -> 0
B14: 1e | D14: ='A.I Revenue Streams - P1'!E14 -> 0 | F14: ='A.I Revenue Streams - P1'!G14 -> 0 | G14: ='A.I Revenue Streams - P1'!I14 -> 0 | H14: =F14*G14 -> 0 | J14: =F14*$J$8 -> 0 | K14: =G14*$K$8 -> 0 | L14: =J14*K14 -> 0 | N14: =J14*$N$8 -> 0 | O14: =K14*$O$8 -> 0 | P14: =N14*O14 -> 0 | R14: =N14*$R$8 -> 0 | S14: =O14*$S$8 -> 0 | T14: =R14*S14 -> 0 | V14: =R14*$V$8 -> 0 | W14: =S14*$W$8 -> 0 | X14: =V14*W14 -> 0 | Z14: =V14*$Z$8 -> 0 | AA14: =W14*$AA$8 -> 0 | AB14: =Z14*AA14 -> 0 | AD14: =Z14*$AD$8 -> 0 | AE14: =AA14*$AE$8 -> 0 | AF14: =AD14*AE14 -> 0 | AH14: =AD14*$AH$8 -> 0 | AI14: =AE14*$AI$8 -> 0 | AJ14: =AH14*AI14 -> 0 | AL14: =AH14*$AL$8 -> 0 | AM14: =AI14*$AM$8 -> 0 | AN14: =AL14*AM14 -> 0 | AP14: =AL14*$AP$8 -> 0 | AQ14: =AM14*$AQ$8 -> 0 | AR14: =AP14*AQ14 -> 0 | AT14: =AP14*$AT$8 -> 0 | AU14: =AQ14*$AU$8 -> 0 | AV14: =AT14*AU14 -> 0 | AX14: =AT14*$AX$8 -> 0 | AY14: =AU14*$AY$8 -> 0 | AZ14: =AX14*AY14 -> 0 | BB14: =AX14*$BB$8 -> 0 | BC14: =AY14*$BC$8 -> 0 | BD14: =BB14*BC14 -> 0 | BF14: =BB14*$BF$8 -> 0 | BG14: =BC14*$BG$8 -> 0 | BH14: =BF14*BG14 -> 0 | BJ14: =BF14*$BJ$8 -> 0 | BK14: =BG14*$BK$8 -> 0 | BL14: =BJ14*BK14 -> 0 | BN14: =BJ14*$BN$8 -> 0 | BO14: =BK14*$BO$8 -> 0 | BP14: =BN14*BO14 -> 0 | BR14: =BN14*$BR$8 -> 0 | BS14: =BO14*$BS$8 -> 0 | BT14: =BR14*BS14 -> 0 | BV14: =BR14*$BV$8 -> 0 | BW14: =BS14*$BW$8 -> 0 | BX14: =BV14*BW14 -> 0 | BZ14: =BV14*$BZ$8 -> 0 | CA14: =BW14*$CA$8 -> 0 | CB14: =BZ14*CA14 -> 0 | CD14: =BZ14*$CD$8 -> 0 | CE14: =CA14*$CE$8 -> 0 | CF14: =CD14*CE14 -> 0 | CH14: =CD14*$CH$8 -> 0 | CI14: =CE14*$CI$8 -> 0 | CJ14: =CH14*CI14 -> 0 | CL14: =CH14*$CL$8 -> 0 | CM14: =CI14*$CM$8 -> 0 | CN14: =CL14*CM14 -> 0 | CP14: =CL14*$CP$8 -> 0 | CQ14: =CM14*$CQ$8 -> 0 | CR14: =CP14*CQ14 -> 0 | CT14: =CP14*$CT$8 -> 0 | CU14: =CQ14*$CU$8 -> 0 | CV14: =CT14*CU14 -> 0 | CX14: =CT14*$CX$8 -> 0 | CY14: =CU14*$CY$8 -> 0 | CZ14: =CX14*CY14 -> 0 | DB14: =CX14*$DB$8 -> 0 | DC14: =CY14*$DC$8 -> 0 | DD14: =DB14*DC14 -> 0 | DF14: =DB14*$DF$8 -> 0 | DG14: =DC14*$DG$8 -> 0 | DH14: =DF14*DG14 -> 0 | DJ14: =DF14*$DJ$8 -> 0 | DK14: =DG14*$DK$8 -> 0 | DL14: =DJ14*DK14 -> 0 | DN14: =DJ14*$DN$8 -> 0 | DO14: =DK14*$DO$8 -> 0 | DP14: =DN14*DO14 -> 0 | DR14: =DN14*$DR$8 -> 0 | DS14: =DO14*$DS$8 -> 0 | DT14: =DR14*DS14 -> 0 | DV14: =DR14*$DV$8 -> 0 | DW14: =DS14*$DW$8 -> 0 | DX14: =DV14*DW14 -> 0 | DZ14: =DV14*$DZ$8 -> 0 | EA14: =DW14*$EA$8 -> 0 | EB14: =DZ14*EA14 -> 0 | ED14: =DZ14*$ED$8 -> 0 | EE14: =EA14*$EE$8 -> 0 | EF14: =ED14*EE14 -> 0 | EH14: =ED14*$EH$8 -> 0 | EI14: =EE14*$EI$8 -> 0 | EJ14: =EH14*EI14 -> 0 | EL14: =EH14*$EL$8 -> 0 | EM14: =EI14*$EM$8 -> 0 | EN14: =EL14*EM14 -> 0 | EP14: =EL14*$EP$8 -> 0 | EQ14: =EM14*$EQ$8 -> 0 | ER14: =EP14*EQ14 -> 0 | ET14: =EP14*$ET$8 -> 0 | EU14: =EQ14*$EU$8 -> 0 | EV14: =ET14*EU14 -> 0 | EX14: =ET14*$EX$8 -> 0 | EY14: =EU14*$EY$8 -> 0 | EZ14: =EX14*EY14 -> 0 | FB14: =EX14*$FB$8 -> 0 | FC14: =EY14*$FC$8 -> 0 | FD14: =FB14*FC14 -> 0 | FF14: =FB14*$FF$8 -> 0 | FG14: =FC14*$FG$8 -> 0 | FH14: =FF14*FG14 -> 0 | FJ14: =FF14*$FJ$8 -> 0 | FK14: =FG14*$FK$8 -> 0 | FL14: =FJ14*FK14 -> 0 | FN14: =FJ14*$FN$8 -> 0 | FO14: =FK14*$FO$8 -> 0 | FP14: =FN14*FO14 -> 0 | FR14: =FN14*$FR$8 -> 0 | FS14: =FO14*$FS$8 -> 0 | FT14: =FR14*FS14 -> 0 | FV14: =FR14*$FV$8 -> 0 | FW14: =FS14*$FW$8 -> 0 | FX14: =FV14*FW14 -> 0 | FZ14: =FV14*$FZ$8 -> 0 | GA14: =FW14*$GA$8 -> 0 | GB14: =FZ14*GA14 -> 0 | GD14: =FZ14*$GD$8 -> 0 | GE14: =GA14*$GE$8 -> 0 | GF14: =GD14*GE14 -> 0 | GH14: =GD14*$GH$8 -> 0 | GI14: =GE14*$GI$8 -> 0 | GJ14: =GH14*GI14 -> 0 | GL14: =GH14*$GL$8 -> 0 | GM14: =GI14*$GM$8 -> 0 | GN14: =GL14*GM14 -> 0 | GP14: =GL14*$GP$8 -> 0 | GQ14: =GM14*$GQ$8 -> 0 | GR14: =GP14*GQ14 -> 0 | GT14: =GP14*$GT$8 -> 0 | GU14: =GQ14*$GU$8 -> 0 | GV14: =GT14*GU14 -> 0 | GX14: =GT14*$GX$8 -> 0 | GY14: =GU14*$GY$8 -> 0 | GZ14: =GX14*GY14 -> 0 | HB14: =GX14*$HB$8 -> 0 | HC14: =GY14*$HC$8 -> 0 | HD14: =HB14*HC14 -> 0 | HF14: =HB14*$HF$8 -> 0 | HG14: =HC14*$HG$8 -> 0 | HH14: =HF14*HG14 -> 0 | HJ14: =HF14*$HJ$8 -> 0 | HK14: =HG14*$HK$8 -> 0 | HL14: =HJ14*HK14 -> 0 | HN14: =HJ14*$HN$8 -> 0 | HO14: =HK14*$HO$8 -> 0 | HP14: =HN14*HO14 -> 0 | HR14: =HN14*$HR$8 -> 0 | HS14: =HO14*$HS$8 -> 0 | HT14: =HR14*HS14 -> 0 | HV14: =HR14*$HV$8 -> 0 | HW14: =HS14*$HW$8 -> 0 | HX14: =HV14*HW14 -> 0 | HZ14: =HV14*$HZ$8 -> 0 | IA14: =HW14*$IA$8 -> 0 | IB14: =HZ14*IA14 -> 0 | ID14: =HZ14*$ID$8 -> 0 | IE14: =IA14*$IE$8 -> 0 | IF14: =ID14*IE14 -> 0 | IH14: =ID14*$IH$8 -> 0 | II14: =IE14*$II$8 -> 0 | IJ14: =IH14*II14 -> 0 | IL14: =SUMIFS($F14:$IK14,$F$3:$IK$3,IL$5,$F$6:$IK$6,IL$6) -> 0 | IM14: 0 | IN14: =SUMIFS($F14:$IK14,$F$3:$IK$3,IL$5,$F$6:$IK$6,IN$6) -> 0 | IP14: =SUMIFS($F14:$IK14,$F$3:$IK$3,IP$5,$F$6:$IK$6,IP$6) -> 0 | IQ14: 0 | IR14: =SUMIFS($F14:$IK14,$F$3:$IK$3,IP$5,$F$6:$IK$6,IR$6) -> 0 | IT14: =SUMIFS($F14:$IK14,$F$3:$IK$3,IT$5,$F$6:$IK$6,IT$6) -> 0 | IU14: 0 | IV14: =SUMIFS($F14:$IK14,$F$3:$IK$3,IT$5,$F$6:$IK$6,IV$6) -> 0 | IX14: =SUMIFS($F14:$IK14,$F$3:$IK$3,IX$5,$F$6:$IK$6,IX$6) -> 0 | IY14: 0 | IZ14: =SUMIFS($F14:$IK14,$F$3:$IK$3,IX$5,$F$6:$IK$6,IZ$6) -> 0 | JB14: =SUMIFS($F14:$IK14,$F$3:$IK$3,JB$5,$F$6:$IK$6,JB$6) -> 0 | JC14: 0 | JD14: =SUMIFS($F14:$IK14,$F$3:$IK$3,JB$5,$F$6:$IK$6,JD$6) -> 0 | JF14: =SUMIFS($F14:$IK14,$F$3:$IK$3,JF$5,$F$6:$IK$6,JF$6) -> 0 | JG14: 0 | JH14: =SUMIFS($F14:$IK14,$F$3:$IK$3,JF$5,$F$6:$IK$6,JH$6) -> 0
B15: Grand Total | F15: =SUM(F10:F14) -> 28000 | H15: =SUM(H10:H14) -> 840000 | J15: =SUM(J10:J14) -> 28280 | L15: =SUM(L10:L14) -> 848400 | N15: =SUM(N10:N14) -> 28562.8 | P15: =SUM(P10:P14) -> 856884 | R15: =SUM(R10:R14) -> 28848.428 | T15: =SUM(T10:T14) -> 865452.84 | V15: =SUM(V10:V14) -> 29136.912 | X15: =SUM(X10:X14) -> 874107.37 | Z15: =SUM(Z10:Z14) -> 29428.281 | AB15: =SUM(AB10:AB14) -> 882848.44 | AD15: =SUM(AD10:AD14) -> 29722.564 | AF15: =SUM(AF10:AF14) -> 891676.93 | AH15: =SUM(AH10:AH14) -> 30019.79 | AJ15: =SUM(AJ10:AJ14) -> 900593.7 | AL15: =SUM(AL10:AL14) -> 30319.988 | AN15: =SUM(AN10:AN14) -> 909599.63 | AP15: =SUM(AP10:AP14) -> 33351.987 | AR15: =SUM(AR10:AR14) -> 1000559.6 | AT15: =SUM(AT10:AT14) -> 33351.987 | AV15: =SUM(AV10:AV14) -> 1000559.6 | AX15: =SUM(AX10:AX14) -> 33351.987 | AZ15: =SUM(AZ10:AZ14) -> 1000559.6 | BB15: =SUM(BB10:BB14) -> 60700.615 | BD15: =SUM(BD10:BD14) -> 1821018.5 | BF15: =SUM(BF10:BF14) -> 60700.615 | BH15: =SUM(BH10:BH14) -> 1821018.5 | BJ15: =SUM(BJ10:BJ14) -> 60700.615 | BL15: =SUM(BL10:BL14) -> 1821018.5 | BN15: =SUM(BN10:BN14) -> 60700.615 | BP15: =SUM(BP10:BP14) -> 1821018.5 | BR15: =SUM(BR10:BR14) -> 60700.615 | BT15: =SUM(BT10:BT14) -> 1821018.5 | BV15: =SUM(BV10:BV14) -> 60700.615 | BX15: =SUM(BX10:BX14) -> 1821018.5 | BZ15: =SUM(BZ10:BZ14) -> 60700.615 | CB15: =SUM(CB10:CB14) -> 1821018.5 | CD15: =SUM(CD10:CD14) -> 60700.615 | CF15: =SUM(CF10:CF14) -> 1821018.5 | CH15: =SUM(CH10:CH14) -> 60700.615 | CJ15: =SUM(CJ10:CJ14) -> 1821018.5 | CL15: =SUM(CL10:CL14) -> 60700.615 | CN15: =SUM(CN10:CN14) -> 1821018.5 | CP15: =SUM(CP10:CP14) -> 60700.615 | CR15: =SUM(CR10:CR14) -> 1821018.5 | CT15: =SUM(CT10:CT14) -> 60700.615 | CV15: =SUM(CV10:CV14) -> 1821018.5 | CX15: =SUM(CX10:CX14) -> 103191.05 | CZ15: =SUM(CZ10:CZ14) -> 3095731.4 | DB15: =SUM(DB10:DB14) -> 103191.05 | DD15: =SUM(DD10:DD14) -> 3095731.4 | DF15: =SUM(DF10:DF14) -> 103191.05 | DH15: =SUM(DH10:DH14) -> 3095731.4 | DJ15: =SUM(DJ10:DJ14) -> 103191.05 | DL15: =SUM(DL10:DL14) -> 3095731.4 | DN15: =SUM(DN10:DN14) -> 103191.05 | DP15: =SUM(DP10:DP14) -> 3095731.4 | DR15: =SUM(DR10:DR14) -> 103191.05 | DT15: =SUM(DT10:DT14) -> 3095731.4 | DV15: =SUM(DV10:DV14) -> 103191.05 | DX15: =SUM(DX10:DX14) -> 3095731.4 | DZ15: =SUM(DZ10:DZ14) -> 103191.05 | EB15: =SUM(EB10:EB14) -> 3095731.4 | ED15: =SUM(ED10:ED14) -> 103191.05 | EF15: =SUM(EF10:EF14) -> 3095731.4 | EH15: =SUM(EH10:EH14) -> 103191.05 | EJ15: =SUM(EJ10:EJ14) -> 3095731.4 | EL15: =SUM(EL10:EL14) -> 103191.05 | EN15: =SUM(EN10:EN14) -> 3095731.4 | EP15: =SUM(EP10:EP14) -> 103191.05 | ER15: =SUM(ER10:ER14) -> 3095731.4 | ET15: =SUM(ET10:ET14) -> 159946.12 | EV15: =SUM(EV10:EV14) -> 4798383.7 | EX15: =SUM(EX10:EX14) -> 159946.12 | EZ15: =SUM(EZ10:EZ14) -> 4798383.7 | FB15: =SUM(FB10:FB14) -> 159946.12 | FD15: =SUM(FD10:FD14) -> 4798383.7 | FF15: =SUM(FF10:FF14) -> 159946.12 | FH15: =SUM(FH10:FH14) -> 4798383.7 | FJ15: =SUM(FJ10:FJ14) -> 159946.12 | FL15: =SUM(FL10:FL14) -> 4798383.7 | FN15: =SUM(FN10:FN14) -> 159946.12 | FP15: =SUM(FP10:FP14) -> 4798383.7 | FR15: =SUM(FR10:FR14) -> 159946.12 | FT15: =SUM(FT10:FT14) -> 4798383.7 | FV15: =SUM(FV10:FV14) -> 159946.12 | FX15: =SUM(FX10:FX14) -> 4798383.7 | FZ15: =SUM(FZ10:FZ14) -> 159946.12 | GB15: =SUM(GB10:GB14) -> 4798383.7 | GD15: =SUM(GD10:GD14) -> 159946.12 | GF15: =SUM(GF10:GF14) -> 4798383.7 | GH15: =SUM(GH10:GH14) -> 159946.12 | GJ15: =SUM(GJ10:GJ14) -> 4798383.7 | GL15: =SUM(GL10:GL14) -> 159946.12 | GN15: =SUM(GN10:GN14) -> 4798383.7 | GP15: =SUM(GP10:GP14) -> 231921.88 | GR15: =SUM(GR10:GR14) -> 6957656.3 | GT15: =SUM(GT10:GT14) -> 231921.88 | GV15: =SUM(GV10:GV14) -> 6957656.3 | GX15: =SUM(GX10:GX14) -> 231921.88 | GZ15: =SUM(GZ10:GZ14) -> 6957656.3 | HB15: =SUM(HB10:HB14) -> 231921.88 | HD15: =SUM(HD10:HD14) -> 6957656.3 | HF15: =SUM(HF10:HF14) -> 231921.88 | HH15: =SUM(HH10:HH14) -> 6957656.3 | HJ15: =SUM(HJ10:HJ14) -> 231921.88 | HL15: =SUM(HL10:HL14) -> 6957656.3 | HN15: =SUM(HN10:HN14) -> 231921.88 | HP15: =SUM(HP10:HP14) -> 6957656.3 | HR15: =SUM(HR10:HR14) -> 231921.88 | HT15: =SUM(HT10:HT14) -> 6957656.3 | HV15: =SUM(HV10:HV14) -> 231921.88 | HX15: =SUM(HX10:HX14) -> 6957656.3 | HZ15: =SUM(HZ10:HZ14) -> 231921.88 | IB15: =SUM(IB10:IB14) -> 6957656.3 | ID15: =SUM(ID10:ID14) -> 231921.88 | IF15: =SUM(IF10:IF14) -> 6957656.3 | IH15: =SUM(IH10:IH14) -> 231921.88 | IJ15: =SUM(IJ10:IJ14) -> 6957656.3 | IL15: =SUM(IL10:IL14) -> 0 | IN15: =SUM(IN10:IN14) -> 0 | IP15: =SUM(IP10:IP14) -> 362374.72 | IR15: =SUM(IR10:IR14) -> 10871242 | IT15: =SUM(IT10:IT14) -> 728407.39 | IV15: =SUM(IV10:IV14) -> 21852222 | IX15: =SUM(IX10:IX14) -> 1238292.6 | IZ15: =SUM(IZ10:IZ14) -> 37148777 | JB15: =SUM(JB10:JB14) -> 1919353.5 | JD15: =SUM(JD10:JD14) -> 57580604 | JF15: =SUM(JF10:JF14) -> 2783062.5 | JH15: =SUM(JH10:JH14) -> 83491876
J17: ='A.I Revenue Streams - P1'!K19+100% -> 1 | K17: =$K$8 -> 1 | N17: 1 | O17: 1 | R17: =N17 -> 1 | S17: 1 | V17: =R17 -> 1 | W17: 1 | Z17: =V17 -> 1 | AA17: 1 | AD17: =Z17 -> 1 | AE17: 1 | AH17: =AD17 -> 1 | AI17: 1 | AL17: =AH17 -> 1 | AM17: 1 | AP17: 1 | AQ17: 1 | AT17: =AP17 -> 1 | AU17: 1 | AX17: =AT17 -> 1 | AY17: 1 | BB17: ='A.I Revenue Streams - P1'!M19+100% -> 1 | BC17: 1 | BF17: 1 | BG17: 1 | BJ17: =BF17 -> 1 | BK17: 1 | BN17: =BJ17 -> 1 | BO17: 1 | BR17: =BN17 -> 1 | BS17: 1 | BV17: =BR17 -> 1 | BW17: 1 | BZ17: =BV17 -> 1 | CA17: 1 | CD17: =BZ17 -> 1 | CE17: 1 | CH17: =CD17 -> 1 | CI17: 1 | CL17: 1 | CM17: 1 | CP17: 1 | CQ17: 1 | CT17: =CP17 -> 1 | CU17: 1 | CX17: ='A.I Revenue Streams - P1'!O19+100% -> 1 | CY17: 1 | DB17: 1 | DC17: 1 | DF17: =DB17 -> 1 | DG17: 1 | DJ17: =DF17 -> 1 | DK17: 1 | DN17: =DJ17 -> 1 | DO17: 1 | DR17: =DN17 -> 1 | DS17: 1 | DV17: =DR17 -> 1 | DW17: 1 | DZ17: =DV17 -> 1 | EA17: 1 | ED17: =DZ17 -> 1 | EE17: 1 | EH17: 1 | EI17: 1 | EL17: 1 | EM17: 1 | EP17: =EL17 -> 1 | EQ17: 1 | ET17: ='A.I Revenue Streams - P1'!Q19+100% -> 1 | EU17: 1 | EX17: 1 | EY17: 1 | FB17: =EX17 -> 1 | FC17: 1 | FF17: =FB17 -> 1 | FG17: 1 | FJ17: =FF17 -> 1 | FK17: 1 | FN17: =FJ17 -> 1 | FO17: 1 | FR17: =FN17 -> 1 | FS17: 1 | FV17: =FR17 -> 1 | FW17: 1 | FZ17: =FV17 -> 1 | GA17: 1 | GD17: 1 | GE17: 1 | GH17: 1 | GI17: 1 | GL17: =GH17 -> 1 | GM17: 1 | GP17: ='A.I Revenue Streams - P1'!S19+100% -> 1 | GQ17: 1 | GT17: 1 | GU17: 1 | GX17: =GT17 -> 1 | GY17: 1 | HB17: =GX17 -> 1 | HC17: 1 | HF17: =HB17 -> 1 | HG17: 1 | HJ17: =HF17 -> 1 | HK17: 1 | HN17: =HJ17 -> 1 | HO17: 1 | HR17: =HN17 -> 1 | HS17: 1 | HV17: =HR17 -> 1 | HW17: 1 | HZ17: 1 | IA17: 1 | ID17: 1 | IE17: 1 | IH17: =ID17 -> 1 | II17: 1 | IL17: ='A.I Revenue Streams - P2'!DI19+100% -> 1 | IM17: 1 | IP17: ='A.I Revenue Streams - P2'!DM19+100% -> 1 | IQ17: 1 | IT17: ='A.I Revenue Streams - P2'!DQ19+100% -> 1 | IU17: 1 | IX17: ='A.I Revenue Streams - P2'!DU19+100% -> 1 | IY17: 1 | JB17: ='A.I Revenue Streams - P2'!DY19+100% -> 1 | JC17: 1 | JF17: ='A.I Revenue Streams - P2'!EC19+100% -> 1 | JG17: 1
B18: 2 | C18: ='A.I Revenue Streams - P1'!D18 -> Advertisement
B19: 2a | D19: ='A.I Revenue Streams - P1'!E19 -> Advertisement | F19: 0 | G19: ='A.I Revenue Streams - P1'!I19 -> 0 | H19: =F19*G19 -> 0 | J19: =F19*$J$17 -> 0 | K19: =G19*$K$17 -> 0 | L19: =J19*K19 -> 0 | N19: =J19*$N$17 -> 0 | O19: =K19*$O$17 -> 0 | P19: =N19*O19 -> 0 | R19: ='A.I Revenue Streams - P1'!G19 -> 0 | S19: =O19*$S$17 -> 0 | T19: =R19*S19 -> 0 | V19: =R19*$V$17 -> 0 | W19: =S19*$W$17 -> 0 | X19: =V19*W19 -> 0 | Z19: =V19*$Z$17 -> 0 | AA19: =W19*$AA$17 -> 0 | AB19: =Z19*AA19 -> 0 | AD19: =Z19*$AD$17 -> 0 | AE19: =AA19*$AE$17 -> 0 | AF19: =AD19*AE19 -> 0 | AH19: =AD19*$AH$17 -> 0 | AI19: =AE19*$AI$17 -> 0 | AJ19: =AH19*AI19 -> 0 | AL19: =AH19*$AL$17 -> 0 | AM19: =AI19*$AM$17 -> 0 | AN19: =AL19*AM19 -> 0 | AP19: =AL19*$AP$17 -> 0 | AQ19: =AM19*$AQ$17 -> 0 | AR19: =AP19*AQ19 -> 0 | AT19: =AP19*$AT$17 -> 0 | AU19: =AQ19*$AU$17 -> 0 | AV19: =AT19*AU19 -> 0 | AX19: =AT19*$AX$17 -> 0 | AY19: =AU19*$AY$17 -> 0 | AZ19: =AX19*AY19 -> 0 | BB19: =AX19*$BB$17 -> 0 | BC19: =AY19*$BC$17 -> 0 | BD19: =BB19*BC19 -> 0 | BF19: =BB19*$BF$17 -> 0 | BG19: =BC19*$BG$17 -> 0 | BH19: =BF19*BG19 -> 0 | BJ19: =BF19*$BJ$17 -> 0 | BK19: =BG19*$BK$17 -> 0 | BL19: =BJ19*BK19 -> 0 | BN19: =BJ19*$BN$17 -> 0 | BO19: =BK19*$BO$17 -> 0 | BP19: =BN19*BO19 -> 0 | BR19: =BN19*$BR$17 -> 0 | BS19: =BO19*$BS$17 -> 0 | BT19: =BR19*BS19 -> 0 | BV19: =BR19*$BV$17 -> 0 | BW19: =BS19*$BW$17 -> 0 | BX19: =BV19*BW19 -> 0 | BZ19: =BV19*$BZ$17 -> 0 | CA19: =BW19*$CA$17 -> 0 | CB19: =BZ19*CA19 -> 0 | CD19: =BZ19*$CD$17 -> 0 | CE19: =CA19*$CE$17 -> 0 | CF19: =CD19*CE19 -> 0 | CH19: =CD19*$CH$17 -> 0 | CI19: =CE19*$CI$17 -> 0 | CJ19: =CH19*CI19 -> 0 | CL19: =CL10 -> 60700.615 | CM19: 80 | CN19: =CL19*CM19 -> 4856049.2 | CP19: =CP10 -> 60700.615 | CQ19: =CM19*$CQ$17 -> 80 | CR19: =CP19*CQ19 -> 4856049.2 | CT19: =CT10 -> 60700.615 | CU19: =CQ19*$CU$17 -> 80 | CV19: =CT19*CU19 -> 4856049.2 | CX19: =CX10 -> 103191.05 | CY19: 120 | CZ19: =CX19*CY19 -> 12382926 | DB19: =DB10 -> 103191.05 | DC19: =CY19*$DC$17 -> 120 | DD19: =DB19*DC19 -> 12382926 | DF19: =DF10 -> 103191.05 | DG19: =DC19*$DG$17 -> 120 | DH19: =DF19*DG19 -> 12382926 | DJ19: =DJ10 -> 103191.05 | DK19: =DG19*$DK$17 -> 120 | DL19: =DJ19*DK19 -> 12382926 | DN19: =DN10 -> 103191.05 | DO19: =DK19*$DO$17 -> 120 | DP19: =DN19*DO19 -> 12382926 | DR19: =DR10 -> 103191.05 | DS19: =DO19*$DS$17 -> 120 | DT19: =DR19*DS19 -> 12382926 | DV19: =DV10 -> 103191.05 | DW19: =DS19*$DW$17 -> 120 | DX19: =DV19*DW19 -> 12382926 | DZ19: =DZ10 -> 103191.05 | EA19: =DW19*$EA$17 -> 120 | EB19: =DZ19*EA19 -> 12382926 | ED19: =ED10 -> 103191.05 | EE19: =EA19*$EE$17 -> 120 | EF19: =ED19*EE19 -> 12382926 | EH19: =EH10 -> 103191.05 | EI19: =EE19*$EI$17 -> 120 | EJ19: =EH19*EI19 -> 12382926 | EL19: =EL10 -> 103191.05 | EM19: =EI19*$EM$17 -> 120 | EN19: =EL19*EM19 -> 12382926 | EP19: =EP10 -> 103191.05 | EQ19: =EM19*$EQ$17 -> 120 | ER19: =EP19*EQ19 -> 12382926 | ET19: =ET10 -> 159946.12 | EU19: =EQ19*$EU$17 -> 120 | EV19: =ET19*EU19 -> 19193535 | EX19: =EX10 -> 159946.12 | EY19: =EU19*$EY$17 -> 120 | EZ19: =EX19*EY19 -> 19193535 | FB19: =FB10 -> 159946.12 | FC19: =EY19*$FC$17 -> 120 | FD19: =FB19*FC19 -> 19193535 | FF19: =FF10 -> 159946.12 | FG19: =FC19*$FG$17 -> 120 | FH19: =FF19*FG19 -> 19193535 | FJ19: =FJ10 -> 159946.12 | FK19: =FG19*$FK$17 -> 120 | FL19: =FJ19*FK19 -> 19193535 | FN19: =FN10 -> 159946.12 | FO19: =FK19*$FO$17 -> 120 | FP19: =FN19*FO19 -> 19193535 | FR19: =FR10 -> 159946.12 | FS19: =FO19*$FS$17 -> 120 | FT19: =FR19*FS19 -> 19193535 | FV19: =FV10 -> 159946.12 | FW19: =FS19*$FW$17 -> 120 | FX19: =FV19*FW19 -> 19193535 | FZ19: =FZ10 -> 159946.12 | GA19: =FW19*$GA$17 -> 120 | GB19: =FZ19*GA19 -> 19193535 | GD19: =GD10 -> 159946.12 | GE19: =GA19*$GE$17 -> 120 | GF19: =GD19*GE19 -> 19193535 | GH19: =GH10 -> 159946.12 | GI19: =GE19*$GI$17 -> 120 | GJ19: =GH19*GI19 -> 19193535 | GL19: =GL10 -> 159946.12 | GM19: =GI19*$GM$17 -> 120 | GN19: =GL19*GM19 -> 19193535 | GP19: =GP10 -> 231921.88 | GQ19: =GM19*$GQ$17 -> 120 | GR19: =GP19*GQ19 -> 27830625 | GT19: =GT10 -> 231921.88 | GU19: =GQ19*$GU$17 -> 120 | GV19: =GT19*GU19 -> 27830625 | GX19: =GX10 -> 231921.88 | GY19: =GU19*$GY$17 -> 120 | GZ19: =GX19*GY19 -> 27830625 | HB19: =HB10 -> 231921.88 | HC19: =GY19*$HC$17 -> 120 | HD19: =HB19*HC19 -> 27830625 | HF19: =HF10 -> 231921.88 | HG19: =HC19*$HG$17 -> 120 | HH19: =HF19*HG19 -> 27830625 | HJ19: =HJ10 -> 231921.88 | HK19: =HG19*$HK$17 -> 120 | HL19: =HJ19*HK19 -> 27830625 | HN19: =HN10 -> 231921.88 | HO19: =HK19*$HO$17 -> 120 | HP19: =HN19*HO19 -> 27830625 | HR19: =HR10 -> 231921.88 | HS19: =HO19*$HS$17 -> 120 | HT19: =HR19*HS19 -> 27830625 | HV19: =HV10 -> 231921.88 | HW19: =HS19*$HW$17 -> 120 | HX19: =HV19*HW19 -> 27830625 | HZ19: =HZ10 -> 231921.88 | IA19: =HW19*$IA$17 -> 120 | IB19: =HZ19*IA19 -> 27830625 | ID19: =ID10 -> 231921.88 | IE19: =IA19*$IE$17 -> 120 | IF19: =ID19*IE19 -> 27830625 | IH19: =IH10 -> 231921.88 | II19: =IE19*$II$17 -> 120 | IJ19: =IH19*II19 -> 27830625 | IL19: =SUMIFS($F19:$IK19,$F$3:$IK$3,IL$5,$F$6:$IK$6,IL$6) -> 0 | IM19: 0 | IN19: =SUMIFS($F19:$IK19,$F$3:$IK$3,IL$5,$F$6:$IK$6,IN$6) -> 0 | IP19: =SUMIFS($F19:$IK19,$F$3:$IK$3,IP$5,$F$6:$IK$6,IP$6) -> 0 | IQ19: =IR19/IP19 -> #DIV/0! | IR19: =SUMIFS($F19:$IK19,$F$3:$IK$3,IP$5,$F$6:$IK$6,IR$6) -> 0 | IT19: =SUMIFS($F19:$IK19,$F$3:$IK$3,IT$5,$F$6:$IK$6,IT$6) -> 182101.85 | IU19: =IV19/IT19 -> 80 | IV19: =SUMIFS($F19:$IK19,$F$3:$IK$3,IT$5,$F$6:$IK$6,IV$6) -> 14568148 | IX19: =SUMIFS($F19:$IK19,$F$3:$IK$3,IX$5,$F$6:$IK$6,IX$6) -> 1238292.6 | IY19: =IZ19/IX19 -> 120 | IZ19: =SUMIFS($F19:$IK19,$F$3:$IK$3,IX$5,$F$6:$IK$6,IZ$6) -> 1.4859511e+08 | JB19: =SUMIFS($F19:$IK19,$F$3:$IK$3,JB$5,$F$6:$IK$6,JB$6) -> 1919353.5 | JC19: =JD19/JB19 -> 120 | JD19: =SUMIFS($F19:$IK19,$F$3:$IK$3,JB$5,$F$6:$IK$6,JD$6) -> 2.3032242e+08 | JF19: =SUMIFS($F19:$IK19,$F$3:$IK$3,JF$5,$F$6:$IK$6,JF$6) -> 2783062.5 | JG19: =JH19/JF19 -> 120 | JH19: =SUMIFS($F19:$IK19,$F$3:$IK$3,JF$5,$F$6:$IK$6,JH$6) -> 3.339675e+08
B20: 2b | D20: ='A.I Revenue Streams - P1'!E20 -> 0 | F20: 0 | G20: ='A.I Revenue Streams - P1'!I20 -> 0 | H20: =F20*G20 -> 0 | J20: =F20*$J$17 -> 0 | K20: =G20*$K$17 -> 0 | L20: =J20*K20 -> 0 | N20: =J20*$N$17 -> 0 | O20: =K20*$O$17 -> 0 | P20: =N20*O20 -> 0 | R20: ='A.I Revenue Streams - P1'!G20 -> 0 | S20: =O20*$S$17 -> 0 | T20: =R20*S20 -> 0 | V20: =R20*$V$17 -> 0 | W20: =S20*$W$17 -> 0 | X20: =V20*W20 -> 0 | Z20: =V20*$Z$17 -> 0 | AA20: =W20*$AA$17 -> 0 | AB20: =Z20*AA20 -> 0 | AD20: =Z20*$AD$17 -> 0 | AE20: =AA20*$AE$17 -> 0 | AF20: =AD20*AE20 -> 0 | AH20: =AD20*$AH$17 -> 0 | AI20: =AE20*$AI$17 -> 0 | AJ20: =AH20*AI20 -> 0 | AL20: =AH20*$AL$17 -> 0 | AM20: =AI20*$AM$17 -> 0 | AN20: =AL20*AM20 -> 0 | AP20: =AL20*$AP$17 -> 0 | AQ20: =AM20*$AQ$17 -> 0 | AR20: =AP20*AQ20 -> 0 | AT20: =AP20*$AT$17 -> 0 | AU20: =AQ20*$AU$17 -> 0 | AV20: =AT20*AU20 -> 0 | AX20: =AT20*$AX$17 -> 0 | AY20: =AU20*$AY$17 -> 0 | AZ20: =AX20*AY20 -> 0 | BB20: =AX20*$BB$17 -> 0 | BC20: =AY20*$BC$17 -> 0 | BD20: =BB20*BC20 -> 0 | BF20: =BB20*$BF$17 -> 0 | BG20: =BC20*$BG$17 -> 0 | BH20: =BF20*BG20 -> 0 | BJ20: =BF20*$BJ$17 -> 0 | BK20: =BG20*$BK$17 -> 0 | BL20: =BJ20*BK20 -> 0 | BN20: =BJ20*$BN$17 -> 0 | BO20: =BK20*$BO$17 -> 0 | BP20: =BN20*BO20 -> 0 | BR20: =BN20*$BR$17 -> 0 | BS20: =BO20*$BS$17 -> 0 | BT20: =BR20*BS20 -> 0 | BV20: =BR20*$BV$17 -> 0 | BW20: =BS20*$BW$17 -> 0 | BX20: =BV20*BW20 -> 0 | BZ20: =BV20*$BZ$17 -> 0 | CA20: =BW20*$CA$17 -> 0 | CB20: =BZ20*CA20 -> 0 | CD20: =BZ20*$CD$17 -> 0 | CE20: =CA20*$CE$17 -> 0 | CF20: =CD20*CE20 -> 0 | CH20: =CD20*$CH$17 -> 0 | CI20: =CE20*$CI$17 -> 0 | CJ20: =CH20*CI20 -> 0 | CL20: =CH20*$CL$17 -> 0 | CM20: =CI20*$CM$17 -> 0 | CN20: =CL20*CM20 -> 0 | CP20: =CL20*$CP$17 -> 0 | CQ20: =CM20*$CQ$17 -> 0 | CR20: =CP20*CQ20 -> 0 | CT20: =CP20*$CT$17 -> 0 | CU20: =CQ20*$CU$17 -> 0 | CV20: =CT20*CU20 -> 0 | CX20: =CT20*$CX$17 -> 0 | CY20: =CU20*$CY$17 -> 0 | CZ20: =CX20*CY20 -> 0 | DB20: =CX20*$DB$17 -> 0 | DC20: =CY20*$DC$17 -> 0 | DD20: =DB20*DC20 -> 0 | DF20: =DB20*$DF$17 -> 0 | DG20: =DC20*$DG$17 -> 0 | DH20: =DF20*DG20 -> 0 | DJ20: =DF20*$DJ$17 -> 0 | DK20: =DG20*$DK$17 -> 0 | DL20: =DJ20*DK20 -> 0 | DN20: =DJ20*$DN$17 -> 0 | DO20: =DK20*$DO$17 -> 0 | DP20: =DN20*DO20 -> 0 | DR20: =DN20*$DR$17 -> 0 | DS20: =DO20*$DS$17 -> 0 | DT20: =DR20*DS20 -> 0 | DV20: =DR20*$DV$17 -> 0 | DW20: =DS20*$DW$17 -> 0 | DX20: =DV20*DW20 -> 0 | DZ20: =DV20*$DZ$17 -> 0 | EA20: =DW20*$EA$17 -> 0 | EB20: =DZ20*EA20 -> 0 | ED20: =DZ20*$ED$17 -> 0 | EE20: =EA20*$EE$17 -> 0 | EF20: =ED20*EE20 -> 0 | EH20: =ED20*$EH$17 -> 0 | EI20: =EE20*$EI$17 -> 0 | EJ20: =EH20*EI20 -> 0 | EL20: =EH20*$EL$17 -> 0 | EM20: =EI20*$EM$17 -> 0 | EN20: =EL20*EM20 -> 0 | EP20: =EL20*$EP$17 -> 0 | EQ20: =EM20*$EQ$17 -> 0 | ER20: =EP20*EQ20 -> 0 | ET20: =EP20*$ET$17 -> 0 | EU20: =EQ20*$EU$17 -> 0 | EV20: =ET20*EU20 -> 0 | EX20: =ET20*$EX$17 -> 0 | EY20: =EU20*$EY$17 -> 0 | EZ20: =EX20*EY20 -> 0 | FB20: =EX20*$FB$17 -> 0 | FC20: =EY20*$FC$17 -> 0 | FD20: =FB20*FC20 -> 0 | FF20: =FB20*$FF$17 -> 0 | FG20: =FC20*$FG$17 -> 0 | FH20: =FF20*FG20 -> 0 | FJ20: =FF20*$FJ$17 -> 0 | FK20: =FG20*$FK$17 -> 0 | FL20: =FJ20*FK20 -> 0 | FN20: =FJ20*$FN$17 -> 0 | FO20: =FK20*$FO$17 -> 0 | FP20: =FN20*FO20 -> 0 | FR20: =FN20*$FR$17 -> 0 | FS20: =FO20*$FS$17 -> 0 | FT20: =FR20*FS20 -> 0 | FV20: =FR20*$FV$17 -> 0 | FW20: =FS20*$FW$17 -> 0 | FX20: =FV20*FW20 -> 0 | FZ20: =FV20*$FZ$17 -> 0 | GA20: =FW20*$GA$17 -> 0 | GB20: =FZ20*GA20 -> 0 | GD20: =FZ20*$GD$17 -> 0 | GE20: =GA20*$GE$17 -> 0 | GF20: =GD20*GE20 -> 0 | GH20: =GD20*$GH$17 -> 0 | GI20: =GE20*$GI$17 -> 0 | GJ20: =GH20*GI20 -> 0 | GL20: =GH20*$GL$17 -> 0 | GM20: =GI20*$GM$17 -> 0 | GN20: =GL20*GM20 -> 0 | GP20: =GL20*$GP$17 -> 0 | GQ20: =GM20*$GQ$17 -> 0 | GR20: =GP20*GQ20 -> 0 | GT20: =GP20*$GT$17 -> 0 | GU20: =GQ20*$GU$17 -> 0 | GV20: =GT20*GU20 -> 0 | GX20: =GT20*$GX$17 -> 0 | GY20: =GU20*$GY$17 -> 0 | GZ20: =GX20*GY20 -> 0 | HB20: =GX20*$HB$17 -> 0 | HC20: =GY20*$HC$17 -> 0 | HD20: =HB20*HC20 -> 0 | HF20: =HB20*$HF$17 -> 0 | HG20: =HC20*$HG$17 -> 0 | HH20: =HF20*HG20 -> 0 | HJ20: =HF20*$HJ$17 -> 0 | HK20: =HG20*$HK$17 -> 0 | HL20: =HJ20*HK20 -> 0 | HN20: =HJ20*$HN$17 -> 0 | HO20: =HK20*$HO$17 -> 0 | HP20: =HN20*HO20 -> 0 | HR20: =HN20*$HR$17 -> 0 | HS20: =HO20*$HS$17 -> 0 | HT20: =HR20*HS20 -> 0 | HV20: =HR20*$HV$17 -> 0 | HW20: =HS20*$HW$17 -> 0 | HX20: =HV20*HW20 -> 0 | HZ20: =HV20*$HZ$17 -> 0 | IA20: =HW20*$IA$17 -> 0 | IB20: =HZ20*IA20 -> 0 | ID20: =HZ20*$ID$17 -> 0 | IE20: =IA20*$IE$17 -> 0 | IF20: =ID20*IE20 -> 0 | IH20: =ID20*$IH$17 -> 0 | II20: =IE20*$II$17 -> 0 | IJ20: =IH20*II20 -> 0 | IL20: =SUMIFS($F20:$IK20,$F$3:$IK$3,IL$5,$F$6:$IK$6,IL$6) -> 0 | IM20: 0 | IN20: =SUMIFS($F20:$IK20,$F$3:$IK$3,IL$5,$F$6:$IK$6,IN$6) -> 0 | IP20: =SUMIFS($F20:$IK20,$F$3:$IK$3,IP$5,$F$6:$IK$6,IP$6) -> 0 | IQ20: =IR20/IP20 -> #DIV/0! | IR20: =SUMIFS($F20:$IK20,$F$3:$IK$3,IP$5,$F$6:$IK$6,IR$6) -> 0 | IT20: =SUMIFS($F20:$IK20,$F$3:$IK$3,IT$5,$F$6:$IK$6,IT$6) -> 0 | IU20: =IV20/IT20 -> #DIV/0! | IV20: =SUMIFS($F20:$IK20,$F$3:$IK$3,IT$5,$F$6:$IK$6,IV$6) -> 0 | IX20: =SUMIFS($F20:$IK20,$F$3:$IK$3,IX$5,$F$6:$IK$6,IX$6) -> 0 | IY20: =IZ20/IX20 -> #DIV/0! | IZ20: =SUMIFS($F20:$IK20,$F$3:$IK$3,IX$5,$F$6:$IK$6,IZ$6) -> 0 | JB20: =SUMIFS($F20:$IK20,$F$3:$IK$3,JB$5,$F$6:$IK$6,JB$6) -> 0 | JC20: =JD20/JB20 -> #DIV/0! | JD20: =SUMIFS($F20:$IK20,$F$3:$IK$3,JB$5,$F$6:$IK$6,JD$6) -> 0 | JF20: =SUMIFS($F20:$IK20,$F$3:$IK$3,JF$5,$F$6:$IK$6,JF$6) -> 0 | JG20: =JH20/JF20 -> #DIV/0! | JH20: =SUMIFS($F20:$IK20,$F$3:$IK$3,JF$5,$F$6:$IK$6,JH$6) -> 0
B21: 2c | D21: ='A.I Revenue Streams - P1'!E21 -> 0 | F21: ='A.I Revenue Streams - P1'!G21 -> 0 | G21: ='A.I Revenue Streams - P1'!I21 -> 0 | H21: =F21*G21 -> 0 | J21: =F21*$J$17 -> 0 | K21: =G21*$K$17 -> 0 | L21: =J21*K21 -> 0 | N21: =J21*$N$17 -> 0 | O21: =K21*$O$17 -> 0 | P21: =N21*O21 -> 0 | R21: =N21*$R$17 -> 0 | S21: =O21*$S$17 -> 0 | T21: =R21*S21 -> 0 | V21: =R21*$V$17 -> 0 | W21: =S21*$W$17 -> 0 | X21: =V21*W21 -> 0 | Z21: =V21*$Z$17 -> 0 | AA21: =W21*$AA$17 -> 0 | AB21: =Z21*AA21 -> 0 | AD21: =Z21*$AD$17 -> 0 | AE21: =AA21*$AE$17 -> 0 | AF21: =AD21*AE21 -> 0 | AH21: =AD21*$AH$17 -> 0 | AI21: =AE21*$AI$17 -> 0 | AJ21: =AH21*AI21 -> 0 | AL21: =AH21*$AL$17 -> 0 | AM21: =AI21*$AM$17 -> 0 | AN21: =AL21*AM21 -> 0 | AP21: =AL21*$AP$17 -> 0 | AQ21: =AM21*$AQ$17 -> 0 | AR21: =AP21*AQ21 -> 0 | AT21: =AP21*$AT$17 -> 0 | AU21: =AQ21*$AU$17 -> 0 | AV21: =AT21*AU21 -> 0 | AX21: =AT21*$AX$17 -> 0 | AY21: =AU21*$AY$17 -> 0 | AZ21: =AX21*AY21 -> 0 | BB21: =AX21*$BB$17 -> 0 | BC21: =AY21*$BC$17 -> 0 | BD21: =BB21*BC21 -> 0 | BF21: =BB21*$BF$17 -> 0 | BG21: =BC21*$BG$17 -> 0 | BH21: =BF21*BG21 -> 0 | BJ21: =BF21*$BJ$17 -> 0 | BK21: =BG21*$BK$17 -> 0 | BL21: =BJ21*BK21 -> 0 | BN21: =BJ21*$BN$17 -> 0 | BO21: =BK21*$BO$17 -> 0 | BP21: =BN21*BO21 -> 0 | BR21: =BN21*$BR$17 -> 0 | BS21: =BO21*$BS$17 -> 0 | BT21: =BR21*BS21 -> 0 | BV21: =BR21*$BV$17 -> 0 | BW21: =BS21*$BW$17 -> 0 | BX21: =BV21*BW21 -> 0 | BZ21: =BV21*$BZ$17 -> 0 | CA21: =BW21*$CA$17 -> 0 | CB21: =BZ21*CA21 -> 0 | CD21: =BZ21*$CD$17 -> 0 | CE21: =CA21*$CE$17 -> 0 | CF21: =CD21*CE21 -> 0 | CH21: =CD21*$CH$17 -> 0 | CI21: =CE21*$CI$17 -> 0 | CJ21: =CH21*CI21 -> 0 | CL21: =CH21*$CL$17 -> 0 | CM21: =CI21*$CM$17 -> 0 | CN21: =CL21*CM21 -> 0 | CP21: =CL21*$CP$17 -> 0 | CQ21: =CM21*$CQ$17 -> 0 | CR21: =CP21*CQ21 -> 0 | CT21: =CP21*$CT$17 -> 0 | CU21: =CQ21*$CU$17 -> 0 | CV21: =CT21*CU21 -> 0 | CX21: =CT21*$CX$17 -> 0 | CY21: =CU21*$CY$17 -> 0 | CZ21: =CX21*CY21 -> 0 | DB21: =CX21*$DB$17 -> 0 | DC21: =CY21*$DC$17 -> 0 | DD21: =DB21*DC21 -> 0 | DF21: =DB21*$DF$17 -> 0 | DG21: =DC21*$DG$17 -> 0 | DH21: =DF21*DG21 -> 0 | DJ21: =DF21*$DJ$17 -> 0 | DK21: =DG21*$DK$17 -> 0 | DL21: =DJ21*DK21 -> 0 | DN21: =DJ21*$DN$17 -> 0 | DO21: =DK21*$DO$17 -> 0 | DP21: =DN21*DO21 -> 0 | DR21: =DN21*$DR$17 -> 0 | DS21: =DO21*$DS$17 -> 0 | DT21: =DR21*DS21 -> 0 | DV21: =DR21*$DV$17 -> 0 | DW21: =DS21*$DW$17 -> 0 | DX21: =DV21*DW21 -> 0 | DZ21: =DV21*$DZ$17 -> 0 | EA21: =DW21*$EA$17 -> 0 | EB21: =DZ21*EA21 -> 0 | ED21: =DZ21*$ED$17 -> 0 | EE21: =EA21*$EE$17 -> 0 | EF21: =ED21*EE21 -> 0 | EH21: =ED21*$EH$17 -> 0 | EI21: =EE21*$EI$17 -> 0 | EJ21: =EH21*EI21 -> 0 | EL21: =EH21*$EL$17 -> 0 | EM21: =EI21*$EM$17 -> 0 | EN21: =EL21*EM21 -> 0 | EP21: =EL21*$EP$17 -> 0 | EQ21: =EM21*$EQ$17 -> 0 | ER21: =EP21*EQ21 -> 0 | ET21: =EP21*$ET$17 -> 0 | EU21: =EQ21*$EU$17 -> 0 | EV21: =ET21*EU21 -> 0 | EX21: =ET21*$EX$17 -> 0 | EY21: =EU21*$EY$17 -> 0 | EZ21: =EX21*EY21 -> 0 | FB21: =EX21*$FB$17 -> 0 | FC21: =EY21*$FC$17 -> 0 | FD21: =FB21*FC21 -> 0 | FF21: =FB21*$FF$17 -> 0 | FG21: =FC21*$FG$17 -> 0 | FH21: =FF21*FG21 -> 0 | FJ21: =FF21*$FJ$17 -> 0 | FK21: =FG21*$FK$17 -> 0 | FL21: =FJ21*FK21 -> 0 | FN21: =FJ21*$FN$17 -> 0 | FO21: =FK21*$FO$17 -> 0 | FP21: =FN21*FO21 -> 0 | FR21: =FN21*$FR$17 -> 0 | FS21: =FO21*$FS$17 -> 0 | FT21: =FR21*FS21 -> 0 | FV21: =FR21*$FV$17 -> 0 | FW21: =FS21*$FW$17 -> 0 | FX21: =FV21*FW21 -> 0 | FZ21: =FV21*$FZ$17 -> 0 | GA21: =FW21*$GA$17 -> 0 | GB21: =FZ21*GA21 -> 0 | GD21: =FZ21*$GD$17 -> 0 | GE21: =GA21*$GE$17 -> 0 | GF21: =GD21*GE21 -> 0 | GH21: =GD21*$GH$17 -> 0 | GI21: =GE21*$GI$17 -> 0 | GJ21: =GH21*GI21 -> 0 | GL21: =GH21*$GL$17 -> 0 | GM21: =GI21*$GM$17 -> 0 | GN21: =GL21*GM21 -> 0 | GP21: =GL21*$GP$17 -> 0 | GQ21: =GM21*$GQ$17 -> 0 | GR21: =GP21*GQ21 -> 0 | GT21: =GP21*$GT$17 -> 0 | GU21: =GQ21*$GU$17 -> 0 | GV21: =GT21*GU21 -> 0 | GX21: =GT21*$GX$17 -> 0 | GY21: =GU21*$GY$17 -> 0 | GZ21: =GX21*GY21 -> 0 | HB21: =GX21*$HB$17 -> 0 | HC21: =GY21*$HC$17 -> 0 | HD21: =HB21*HC21 -> 0 | HF21: =HB21*$HF$17 -> 0 | HG21: =HC21*$HG$17 -> 0 | HH21: =HF21*HG21 -> 0 | HJ21: =HF21*$HJ$17 -> 0 | HK21: =HG21*$HK$17 -> 0 | HL21: =HJ21*HK21 -> 0 | HN21: =HJ21*$HN$17 -> 0 | HO21: =HK21*$HO$17 -> 0 | HP21: =HN21*HO21 -> 0 | HR21: =HN21*$HR$17 -> 0 | HS21: =HO21*$HS$17 -> 0 | HT21: =HR21*HS21 -> 0 | HV21: =HR21*$HV$17 -> 0 | HW21: =HS21*$HW$17 -> 0 | HX21: =HV21*HW21 -> 0 | HZ21: =HV21*$HZ$17 -> 0 | IA21: =HW21*$IA$17 -> 0 | IB21: =HZ21*IA21 -> 0 | ID21: =HZ21*$ID$17 -> 0 | IE21: =IA21*$IE$17 -> 0 | IF21: =ID21*IE21 -> 0 | IH21: =ID21*$IH$17 -> 0 | II21: =IE21*$II$17 -> 0 | IJ21: =IH21*II21 -> 0 | IL21: =SUMIFS($F21:$IK21,$F$3:$IK$3,IL$5,$F$6:$IK$6,IL$6) -> 0 | IM21: 0 | IN21: =SUMIFS($F21:$IK21,$F$3:$IK$3,IL$5,$F$6:$IK$6,IN$6) -> 0 | IP21: =SUMIFS($F21:$IK21,$F$3:$IK$3,IP$5,$F$6:$IK$6,IP$6) -> 0 | IQ21: 0 | IR21: =SUMIFS($F21:$IK21,$F$3:$IK$3,IP$5,$F$6:$IK$6,IR$6) -> 0 | IT21: =SUMIFS($F21:$IK21,$F$3:$IK$3,IT$5,$F$6:$IK$6,IT$6) -> 0 | IU21: 0 | IV21: =SUMIFS($F21:$IK21,$F$3:$IK$3,IT$5,$F$6:$IK$6,IV$6) -> 0 | IX21: =SUMIFS($F21:$IK21,$F$3:$IK$3,IX$5,$F$6:$IK$6,IX$6) -> 0 | IY21: 0 | IZ21: =SUMIFS($F21:$IK21,$F$3:$IK$3,IX$5,$F$6:$IK$6,IZ$6) -> 0 | JB21: =SUMIFS($F21:$IK21,$F$3:$IK$3,JB$5,$F$6:$IK$6,JB$6) -> 0 | JC21: 0 | JD21: =SUMIFS($F21:$IK21,$F$3:$IK$3,JB$5,$F$6:$IK$6,JD$6) -> 0 | JF21: =SUMIFS($F21:$IK21,$F$3:$IK$3,JF$5,$F$6:$IK$6,JF$6) -> 0 | JG21: 0 | JH21: =SUMIFS($F21:$IK21,$F$3:$IK$3,JF$5,$F$6:$IK$6,JH$6) -> 0
B22: 2d | D22: ='A.I Revenue Streams - P1'!E22 -> 0 | F22: ='A.I Revenue Streams - P1'!G22 -> 0 | G22: ='A.I Revenue Streams - P1'!I22 -> 0 | H22: =F22*G22 -> 0 | J22: =F22*$J$17 -> 0 | K22: =G22*$K$17 -> 0 | L22: =J22*K22 -> 0 | N22: =J22*$N$17 -> 0 | O22: =K22*$O$17 -> 0 | P22: =N22*O22 -> 0 | R22: =N22*$R$17 -> 0 | S22: =O22*$S$17 -> 0 | T22: =R22*S22 -> 0 | V22: =R22*$V$17 -> 0 | W22: =S22*$W$17 -> 0 | X22: =V22*W22 -> 0 | Z22: =V22*$Z$17 -> 0 | AA22: =W22*$AA$17 -> 0 | AB22: =Z22*AA22 -> 0 | AD22: =Z22*$AD$17 -> 0 | AE22: =AA22*$AE$17 -> 0 | AF22: =AD22*AE22 -> 0 | AH22: =AD22*$AH$17 -> 0 | AI22: =AE22*$AI$17 -> 0 | AJ22: =AH22*AI22 -> 0 | AL22: =AH22*$AL$17 -> 0 | AM22: =AI22*$AM$17 -> 0 | AN22: =AL22*AM22 -> 0 | AP22: =AL22*$AP$17 -> 0 | AQ22: =AM22*$AQ$17 -> 0 | AR22: =AP22*AQ22 -> 0 | AT22: =AP22*$AT$17 -> 0 | AU22: =AQ22*$AU$17 -> 0 | AV22: =AT22*AU22 -> 0 | AX22: =AT22*$AX$17 -> 0 | AY22: =AU22*$AY$17 -> 0 | AZ22: =AX22*AY22 -> 0 | BB22: =AX22*$BB$17 -> 0 | BC22: =AY22*$BC$17 -> 0 | BD22: =BB22*BC22 -> 0 | BF22: =BB22*$BF$17 -> 0 | BG22: =BC22*$BG$17 -> 0 | BH22: =BF22*BG22 -> 0 | BJ22: =BF22*$BJ$17 -> 0 | BK22: =BG22*$BK$17 -> 0 | BL22: =BJ22*BK22 -> 0 | BN22: =BJ22*$BN$17 -> 0 | BO22: =BK22*$BO$17 -> 0 | BP22: =BN22*BO22 -> 0 | BR22: =BN22*$BR$17 -> 0 | BS22: =BO22*$BS$17 -> 0 | BT22: =BR22*BS22 -> 0 | BV22: =BR22*$BV$17 -> 0 | BW22: =BS22*$BW$17 -> 0 | BX22: =BV22*BW22 -> 0 | BZ22: =BV22*$BZ$17 -> 0 | CA22: =BW22*$CA$17 -> 0 | CB22: =BZ22*CA22 -> 0 | CD22: =BZ22*$CD$17 -> 0 | CE22: =CA22*$CE$17 -> 0 | CF22: =CD22*CE22 -> 0 | CH22: =CD22*$CH$17 -> 0 | CI22: =CE22*$CI$17 -> 0 | CJ22: =CH22*CI22 -> 0 | CL22: =CH22*$CL$17 -> 0 | CM22: =CI22*$CM$17 -> 0 | CN22: =CL22*CM22 -> 0 | CP22: =CL22*$CP$17 -> 0 | CQ22: =CM22*$CQ$17 -> 0 | CR22: =CP22*CQ22 -> 0 | CT22: =CP22*$CT$17 -> 0 | CU22: =CQ22*$CU$17 -> 0 | CV22: =CT22*CU22 -> 0 | CX22: =CT22*$CX$17 -> 0 | CY22: =CU22*$CY$17 -> 0 | CZ22: =CX22*CY22 -> 0 | DB22: =CX22*$DB$17 -> 0 | DC22: =CY22*$DC$17 -> 0 | DD22: =DB22*DC22 -> 0 | DF22: =DB22*$DF$17 -> 0 | DG22: =DC22*$DG$17 -> 0 | DH22: =DF22*DG22 -> 0 | DJ22: =DF22*$DJ$17 -> 0 | DK22: =DG22*$DK$17 -> 0 | DL22: =DJ22*DK22 -> 0 | DN22: =DJ22*$DN$17 -> 0 | DO22: =DK22*$DO$17 -> 0 | DP22: =DN22*DO22 -> 0 | DR22: =DN22*$DR$17 -> 0 | DS22: =DO22*$DS$17 -> 0 | DT22: =DR22*DS22 -> 0 | DV22: =DR22*$DV$17 -> 0 | DW22: =DS22*$DW$17 -> 0 | DX22: =DV22*DW22 -> 0 | DZ22: =DV22*$DZ$17 -> 0 | EA22: =DW22*$EA$17 -> 0 | EB22: =DZ22*EA22 -> 0 | ED22: =DZ22*$ED$17 -> 0 | EE22: =EA22*$EE$17 -> 0 | EF22: =ED22*EE22 -> 0 | EH22: =ED22*$EH$17 -> 0 | EI22: =EE22*$EI$17 -> 0 | EJ22: =EH22*EI22 -> 0 | EL22: =EH22*$EL$17 -> 0 | EM22: =EI22*$EM$17 -> 0 | EN22: =EL22*EM22 -> 0 | EP22: =EL22*$EP$17 -> 0 | EQ22: =EM22*$EQ$17 -> 0 | ER22: =EP22*EQ22 -> 0 | ET22: =EP22*$ET$17 -> 0 | EU22: =EQ22*$EU$17 -> 0 | EV22: =ET22*EU22 -> 0 | EX22: =ET22*$EX$17 -> 0 | EY22: =EU22*$EY$17 -> 0 | EZ22: =EX22*EY22 -> 0 | FB22: =EX22*$FB$17 -> 0 | FC22: =EY22*$FC$17 -> 0 | FD22: =FB22*FC22 -> 0 | FF22: =FB22*$FF$17 -> 0 | FG22: =FC22*$FG$17 -> 0 | FH22: =FF22*FG22 -> 0 | FJ22: =FF22*$FJ$17 -> 0 | FK22: =FG22*$FK$17 -> 0 | FL22: =FJ22*FK22 -> 0 | FN22: =FJ22*$FN$17 -> 0 | FO22: =FK22*$FO$17 -> 0 | FP22: =FN22*FO22 -> 0 | FR22: =FN22*$FR$17 -> 0 | FS22: =FO22*$FS$17 -> 0 | FT22: =FR22*FS22 -> 0 | FV22: =FR22*$FV$17 -> 0 | FW22: =FS22*$FW$17 -> 0 | FX22: =FV22*FW22 -> 0 | FZ22: =FV22*$FZ$17 -> 0 | GA22: =FW22*$GA$17 -> 0 | GB22: =FZ22*GA22 -> 0 | GD22: =FZ22*$GD$17 -> 0 | GE22: =GA22*$GE$17 -> 0 | GF22: =GD22*GE22 -> 0 | GH22: =GD22*$GH$17 -> 0 | GI22: =GE22*$GI$17 -> 0 | GJ22: =GH22*GI22 -> 0 | GL22: =GH22*$GL$17 -> 0 | GM22: =GI22*$GM$17 -> 0 | GN22: =GL22*GM22 -> 0 | GP22: =GL22*$GP$17 -> 0 | GQ22: =GM22*$GQ$17 -> 0 | GR22: =GP22*GQ22 -> 0 | GT22: =GP22*$GT$17 -> 0 | GU22: =GQ22*$GU$17 -> 0 | GV22: =GT22*GU22 -> 0 | GX22: =GT22*$GX$17 -> 0 | GY22: =GU22*$GY$17 -> 0 | GZ22: =GX22*GY22 -> 0 | HB22: =GX22*$HB$17 -> 0 | HC22: =GY22*$HC$17 -> 0 | HD22: =HB22*HC22 -> 0 | HF22: =HB22*$HF$17 -> 0 | HG22: =HC22*$HG$17 -> 0 | HH22: =HF22*HG22 -> 0 | HJ22: =HF22*$HJ$17 -> 0 | HK22: =HG22*$HK$17 -> 0 | HL22: =HJ22*HK22 -> 0 | HN22: =HJ22*$HN$17 -> 0 | HO22: =HK22*$HO$17 -> 0 | HP22: =HN22*HO22 -> 0 | HR22: =HN22*$HR$17 -> 0 | HS22: =HO22*$HS$17 -> 0 | HT22: =HR22*HS22 -> 0 | HV22: =HR22*$HV$17 -> 0 | HW22: =HS22*$HW$17 -> 0 | HX22: =HV22*HW22 -> 0 | HZ22: =HV22*$HZ$17 -> 0 | IA22: =HW22*$IA$17 -> 0 | IB22: =HZ22*IA22 -> 0 | ID22: =HZ22*$ID$17 -> 0 | IE22: =IA22*$IE$17 -> 0 | IF22: =ID22*IE22 -> 0 | IH22: =ID22*$IH$17 -> 0 | II22: =IE22*$II$17 -> 0 | IJ22: =IH22*II22 -> 0 | IL22: =SUMIFS($F22:$IK22,$F$3:$IK$3,IL$5,$F$6:$IK$6,IL$6) -> 0 | IM22: 0 | IN22: =SUMIFS($F22:$IK22,$F$3:$IK$3,IL$5,$F$6:$IK$6,IN$6) -> 0 | IP22: =SUMIFS($F22:$IK22,$F$3:$IK$3,IP$5,$F$6:$IK$6,IP$6) -> 0 | IQ22: 0 | IR22: =SUMIFS($F22:$IK22,$F$3:$IK$3,IP$5,$F$6:$IK$6,IR$6) -> 0 | IT22: =SUMIFS($F22:$IK22,$F$3:$IK$3,IT$5,$F$6:$IK$6,IT$6) -> 0 | IU22: 0 | IV22: =SUMIFS($F22:$IK22,$F$3:$IK$3,IT$5,$F$6:$IK$6,IV$6) -> 0 | IX22: =SUMIFS($F22:$IK22,$F$3:$IK$3,IX$5,$F$6:$IK$6,IX$6) -> 0 | IY22: 0 | IZ22: =SUMIFS($F22:$IK22,$F$3:$IK$3,IX$5,$F$6:$IK$6,IZ$6) -> 0 | JB22: =SUMIFS($F22:$IK22,$F$3:$IK$3,JB$5,$F$6:$IK$6,JB$6) -> 0 | JC22: 0 | JD22: =SUMIFS($F22:$IK22,$F$3:$IK$3,JB$5,$F$6:$IK$6,JD$6) -> 0 | JF22: =SUMIFS($F22:$IK22,$F$3:$IK$3,JF$5,$F$6:$IK$6,JF$6) -> 0 | JG22: 0 | JH22: =SUMIFS($F22:$IK22,$F$3:$IK$3,JF$5,$F$6:$IK$6,JH$6) -> 0
B23: 2e | D23: ='A.I Revenue Streams - P1'!E23 -> 0 | F23: ='A.I Revenue Streams - P1'!G23 -> 0 | G23: ='A.I Revenue Streams - P1'!I23 -> 0 | H23: =F23*G23 -> 0 | J23: =F23*$J$17 -> 0 | K23: =G23*$K$17 -> 0 | L23: =J23*K23 -> 0 | N23: =J23*$N$17 -> 0 | O23: =K23*$O$17 -> 0 | P23: =N23*O23 -> 0 | R23: =N23*$R$17 -> 0 | S23: =O23*$S$17 -> 0 | T23: =R23*S23 -> 0 | V23: =R23*$V$17 -> 0 | W23: =S23*$W$17 -> 0 | X23: =V23*W23 -> 0 | Z23: =V23*$Z$17 -> 0 | AA23: =W23*$AA$17 -> 0 | AB23: =Z23*AA23 -> 0 | AD23: =Z23*$AD$17 -> 0 | AE23: =AA23*$AE$17 -> 0 | AF23: =AD23*AE23 -> 0 | AH23: =AD23*$AH$17 -> 0 | AI23: =AE23*$AI$17 -> 0 | AJ23: =AH23*AI23 -> 0 | AL23: =AH23*$AL$17 -> 0 | AM23: =AI23*$AM$17 -> 0 | AN23: =AL23*AM23 -> 0 | AP23: =AL23*$AP$17 -> 0 | AQ23: =AM23*$AQ$17 -> 0 | AR23: =AP23*AQ23 -> 0 | AT23: =AP23*$AT$17 -> 0 | AU23: =AQ23*$AU$17 -> 0 | AV23: =AT23*AU23 -> 0 | AX23: =AT23*$AX$17 -> 0 | AY23: =AU23*$AY$17 -> 0 | AZ23: =AX23*AY23 -> 0 | BB23: =AX23*$BB$17 -> 0 | BC23: =AY23*$BC$17 -> 0 | BD23: =BB23*BC23 -> 0 | BF23: =BB23*$BF$17 -> 0 | BG23: =BC23*$BG$17 -> 0 | BH23: =BF23*BG23 -> 0 | BJ23: =BF23*$BJ$17 -> 0 | BK23: =BG23*$BK$17 -> 0 | BL23: =BJ23*BK23 -> 0 | BN23: =BJ23*$BN$17 -> 0 | BO23: =BK23*$BO$17 -> 0 | BP23: =BN23*BO23 -> 0 | BR23: =BN23*$BR$17 -> 0 | BS23: =BO23*$BS$17 -> 0 | BT23: =BR23*BS23 -> 0 | BV23: =BR23*$BV$17 -> 0 | BW23: =BS23*$BW$17 -> 0 | BX23: =BV23*BW23 -> 0 | BZ23: =BV23*$BZ$17 -> 0 | CA23: =BW23*$CA$17 -> 0 | CB23: =BZ23*CA23 -> 0 | CD23: =BZ23*$CD$17 -> 0 | CE23: =CA23*$CE$17 -> 0 | CF23: =CD23*CE23 -> 0 | CH23: =CD23*$CH$17 -> 0 | CI23: =CE23*$CI$17 -> 0 | CJ23: =CH23*CI23 -> 0 | CL23: =CH23*$CL$17 -> 0 | CM23: =CI23*$CM$17 -> 0 | CN23: =CL23*CM23 -> 0 | CP23: =CL23*$CP$17 -> 0 | CQ23: =CM23*$CQ$17 -> 0 | CR23: =CP23*CQ23 -> 0 | CT23: =CP23*$CT$17 -> 0 | CU23: =CQ23*$CU$17 -> 0 | CV23: =CT23*CU23 -> 0 | CX23: =CT23*$CX$17 -> 0 | CY23: =CU23*$CY$17 -> 0 | CZ23: =CX23*CY23 -> 0 | DB23: =CX23*$DB$17 -> 0 | DC23: =CY23*$DC$17 -> 0 | DD23: =DB23*DC23 -> 0 | DF23: =DB23*$DF$17 -> 0 | DG23: =DC23*$DG$17 -> 0 | DH23: =DF23*DG23 -> 0 | DJ23: =DF23*$DJ$17 -> 0 | DK23: =DG23*$DK$17 -> 0 | DL23: =DJ23*DK23 -> 0 | DN23: =DJ23*$DN$17 -> 0 | DO23: =DK23*$DO$17 -> 0 | DP23: =DN23*DO23 -> 0 | DR23: =DN23*$DR$17 -> 0 | DS23: =DO23*$DS$17 -> 0 | DT23: =DR23*DS23 -> 0 | DV23: =DR23*$DV$17 -> 0 | DW23: =DS23*$DW$17 -> 0 | DX23: =DV23*DW23 -> 0 | DZ23: =DV23*$DZ$17 -> 0 | EA23: =DW23*$EA$17 -> 0 | EB23: =DZ23*EA23 -> 0 | ED23: =DZ23*$ED$17 -> 0 | EE23: =EA23*$EE$17 -> 0 | EF23: =ED23*EE23 -> 0 | EH23: =ED23*$EH$17 -> 0 | EI23: =EE23*$EI$17 -> 0 | EJ23: =EH23*EI23 -> 0 | EL23: =EH23*$EL$17 -> 0 | EM23: =EI23*$EM$17 -> 0 | EN23: =EL23*EM23 -> 0 | EP23: =EL23*$EP$17 -> 0 | EQ23: =EM23*$EQ$17 -> 0 | ER23: =EP23*EQ23 -> 0 | ET23: =EP23*$ET$17 -> 0 | EU23: =EQ23*$EU$17 -> 0 | EV23: =ET23*EU23 -> 0 | EX23: =ET23*$EX$17 -> 0 | EY23: =EU23*$EY$17 -> 0 | EZ23: =EX23*EY23 -> 0 | FB23: =EX23*$FB$17 -> 0 | FC23: =EY23*$FC$17 -> 0 | FD23: =FB23*FC23 -> 0 | FF23: =FB23*$FF$17 -> 0 | FG23: =FC23*$FG$17 -> 0 | FH23: =FF23*FG23 -> 0 | FJ23: =FF23*$FJ$17 -> 0 | FK23: =FG23*$FK$17 -> 0 | FL23: =FJ23*FK23 -> 0 | FN23: =FJ23*$FN$17 -> 0 | FO23: =FK23*$FO$17 -> 0 | FP23: =FN23*FO23 -> 0 | FR23: =FN23*$FR$17 -> 0 | FS23: =FO23*$FS$17 -> 0 | FT23: =FR23*FS23 -> 0 | FV23: =FR23*$FV$17 -> 0 | FW23: =FS23*$FW$17 -> 0 | FX23: =FV23*FW23 -> 0 | FZ23: =FV23*$FZ$17 -> 0 | GA23: =FW23*$GA$17 -> 0 | GB23: =FZ23*GA23 -> 0 | GD23: =FZ23*$GD$17 -> 0 | GE23: =GA23*$GE$17 -> 0 | GF23: =GD23*GE23 -> 0 | GH23: =GD23*$GH$17 -> 0 | GI23: =GE23*$GI$17 -> 0 | GJ23: =GH23*GI23 -> 0 | GL23: =GH23*$GL$17 -> 0 | GM23: =GI23*$GM$17 -> 0 | GN23: =GL23*GM23 -> 0 | GP23: =GL23*$GP$17 -> 0 | GQ23: =GM23*$GQ$17 -> 0 | GR23: =GP23*GQ23 -> 0 | GT23: =GP23*$GT$17 -> 0 | GU23: =GQ23*$GU$17 -> 0 | GV23: =GT23*GU23 -> 0 | GX23: =GT23*$GX$17 -> 0 | GY23: =GU23*$GY$17 -> 0 | GZ23: =GX23*GY23 -> 0 | HB23: =GX23*$HB$17 -> 0 | HC23: =GY23*$HC$17 -> 0 | HD23: =HB23*HC23 -> 0 | HF23: =HB23*$HF$17 -> 0 | HG23: =HC23*$HG$17 -> 0 | HH23: =HF23*HG23 -> 0 | HJ23: =HF23*$HJ$17 -> 0 | HK23: =HG23*$HK$17 -> 0 | HL23: =HJ23*HK23 -> 0 | HN23: =HJ23*$HN$17 -> 0 | HO23: =HK23*$HO$17 -> 0 | HP23: =HN23*HO23 -> 0 | HR23: =HN23*$HR$17 -> 0 | HS23: =HO23*$HS$17 -> 0 | HT23: =HR23*HS23 -> 0 | HV23: =HR23*$HV$17 -> 0 | HW23: =HS23*$HW$17 -> 0 | HX23: =HV23*HW23 -> 0 | HZ23: =HV23*$HZ$17 -> 0 | IA23: =HW23*$IA$17 -> 0 | IB23: =HZ23*IA23 -> 0 | ID23: =HZ23*$ID$17 -> 0 | IE23: =IA23*$IE$17 -> 0 | IF23: =ID23*IE23 -> 0 | IH23: =ID23*$IH$17 -> 0 | II23: =IE23*$II$17 -> 0 | IJ23: =IH23*II23 -> 0 | IL23: =SUMIFS($F23:$IK23,$F$3:$IK$3,IL$5,$F$6:$IK$6,IL$6) -> 0 | IM23: 0 | IN23: =SUMIFS($F23:$IK23,$F$3:$IK$3,IL$5,$F$6:$IK$6,IN$6) -> 0 | IP23: =SUMIFS($F23:$IK23,$F$3:$IK$3,IP$5,$F$6:$IK$6,IP$6) -> 0 | IQ23: 0 | IR23: =SUMIFS($F23:$IK23,$F$3:$IK$3,IP$5,$F$6:$IK$6,IR$6) -> 0 | IT23: =SUMIFS($F23:$IK23,$F$3:$IK$3,IT$5,$F$6:$IK$6,IT$6) -> 0 | IU23: 0 | IV23: =SUMIFS($F23:$IK23,$F$3:$IK$3,IT$5,$F$6:$IK$6,IV$6) -> 0 | IX23: =SUMIFS($F23:$IK23,$F$3:$IK$3,IX$5,$F$6:$IK$6,IX$6) -> 0 | IY23: 0 | IZ23: =SUMIFS($F23:$IK23,$F$3:$IK$3,IX$5,$F$6:$IK$6,IZ$6) -> 0 | JB23: =SUMIFS($F23:$IK23,$F$3:$IK$3,JB$5,$F$6:$IK$6,JB$6) -> 0 | JC23: 0 | JD23: =SUMIFS($F23:$IK23,$F$3:$IK$3,JB$5,$F$6:$IK$6,JD$6) -> 0 | JF23: =SUMIFS($F23:$IK23,$F$3:$IK$3,JF$5,$F$6:$IK$6,JF$6) -> 0 | JG23: 0 | JH23: =SUMIFS($F23:$IK23,$F$3:$IK$3,JF$5,$F$6:$IK$6,JH$6) -> 0
B24: Grand Total | F24: =SUM(F19:F23) -> 0 | H24: =SUM(H19:H23) -> 0 | J24: =SUM(J19:J23) -> 0 | L24: =SUM(L19:L23) -> 0 | N24: =SUM(N19:N23) -> 0 | P24: =SUM(P19:P23) -> 0 | R24: =SUM(R19:R23) -> 0 | T24: =SUM(T19:T23) -> 0 | V24: =SUM(V19:V23) -> 0 | X24: =SUM(X19:X23) -> 0 | Z24: =SUM(Z19:Z23) -> 0 | AB24: =SUM(AB19:AB23) -> 0 | AD24: =SUM(AD19:AD23) -> 0 | AF24: =SUM(AF19:AF23) -> 0 | AH24: =SUM(AH19:AH23) -> 0 | AJ24: =SUM(AJ19:AJ23) -> 0 | AL24: =SUM(AL19:AL23) -> 0 | AN24: =SUM(AN19:AN23) -> 0 | AP24: =SUM(AP19:AP23) -> 0 | AR24: =SUM(AR19:AR23) -> 0 | AT24: =SUM(AT19:AT23) -> 0 | AV24: =SUM(AV19:AV23) -> 0 | AX24: =SUM(AX19:AX23) -> 0 | AZ24: =SUM(AZ19:AZ23) -> 0 | BB24: =SUM(BB19:BB23) -> 0 | BD24: =SUM(BD19:BD23) -> 0 | BF24: =SUM(BF19:BF23) -> 0 | BH24: =SUM(BH19:BH23) -> 0 | BJ24: =SUM(BJ19:BJ23) -> 0 | BL24: =SUM(BL19:BL23) -> 0 | BN24: =SUM(BN19:BN23) -> 0 | BP24: =SUM(BP19:BP23) -> 0 | BR24: =SUM(BR19:BR23) -> 0 | BT24: =SUM(BT19:BT23) -> 0 | BV24: =SUM(BV19:BV23) -> 0 | BX24: =SUM(BX19:BX23) -> 0 | BZ24: =SUM(BZ19:BZ23) -> 0 | CB24: =SUM(CB19:CB23) -> 0 | CD24: =SUM(CD19:CD23) -> 0 | CF24: =SUM(CF19:CF23) -> 0 | CH24: =SUM(CH19:CH23) -> 0 | CJ24: =SUM(CJ19:CJ23) -> 0 | CL24: =SUM(CL19:CL23) -> 60700.615 | CN24: =SUM(CN19:CN23) -> 4856049.2 | CP24: =SUM(CP19:CP23) -> 60700.615 | CR24: =SUM(CR19:CR23) -> 4856049.2 | CT24: =SUM(CT19:CT23) -> 60700.615 | CV24: =SUM(CV19:CV23) -> 4856049.2 | CX24: =SUM(CX19:CX23) -> 103191.05 | CZ24: =SUM(CZ19:CZ23) -> 12382926 | DB24: =SUM(DB19:DB23) -> 103191.05 | DD24: =SUM(DD19:DD23) -> 12382926 | DF24: =SUM(DF19:DF23) -> 103191.05 | DH24: =SUM(DH19:DH23) -> 12382926 | DJ24: =SUM(DJ19:DJ23) -> 103191.05 | DL24: =SUM(DL19:DL23) -> 12382926 | DN24: =SUM(DN19:DN23) -> 103191.05 | DP24: =SUM(DP19:DP23) -> 12382926 | DR24: =SUM(DR19:DR23) -> 103191.05 | DT24: =SUM(DT19:DT23) -> 12382926 | DV24: =SUM(DV19:DV23) -> 103191.05 | DX24: =SUM(DX19:DX23) -> 12382926 | DZ24: =SUM(DZ19:DZ23) -> 103191.05 | EB24: =SUM(EB19:EB23) -> 12382926 | ED24: =SUM(ED19:ED23) -> 103191.05 | EF24: =SUM(EF19:EF23) -> 12382926 | EH24: =SUM(EH19:EH23) -> 103191.05 | EJ24: =SUM(EJ19:EJ23) -> 12382926 | EL24: =SUM(EL19:EL23) -> 103191.05 | EN24: =SUM(EN19:EN23) -> 12382926 | EP24: =SUM(EP19:EP23) -> 103191.05 | ER24: =SUM(ER19:ER23) -> 12382926 | ET24: =SUM(ET19:ET23) -> 159946.12 | EV24: =SUM(EV19:EV23) -> 19193535 | EX24: =SUM(EX19:EX23) -> 159946.12 | EZ24: =SUM(EZ19:EZ23) -> 19193535 | FB24: =SUM(FB19:FB23) -> 159946.12 | FD24: =SUM(FD19:FD23) -> 19193535 | FF24: =SUM(FF19:FF23) -> 159946.12 | FH24: =SUM(FH19:FH23) -> 19193535 | FJ24: =SUM(FJ19:FJ23) -> 159946.12 | FL24: =SUM(FL19:FL23) -> 19193535 | FN24: =SUM(FN19:FN23) -> 159946.12 | FP24: =SUM(FP19:FP23) -> 19193535 | FR24: =SUM(FR19:FR23) -> 159946.12 | FT24: =SUM(FT19:FT23) -> 19193535 | FV24: =SUM(FV19:FV23) -> 159946.12 | FX24: =SUM(FX19:FX23) -> 19193535 | FZ24: =SUM(FZ19:FZ23) -> 159946.12 | GB24: =SUM(GB19:GB23) -> 19193535 | GD24: =SUM(GD19:GD23) -> 159946.12 | GF24: =SUM(GF19:GF23) -> 19193535 | GH24: =SUM(GH19:GH23) -> 159946.12 | GJ24: =SUM(GJ19:GJ23) -> 19193535 | GL24: =SUM(GL19:GL23) -> 159946.12 | GN24: =SUM(GN19:GN23) -> 19193535 | GP24: =SUM(GP19:GP23) -> 231921.88 | GR24: =SUM(GR19:GR23) -> 27830625 | GT24: =SUM(GT19:GT23) -> 231921.88 | GV24: =SUM(GV19:GV23) -> 27830625 | GX24: =SUM(GX19:GX23) -> 231921.88 | GZ24: =SUM(GZ19:GZ23) -> 27830625 | HB24: =SUM(HB19:HB23) -> 231921.88 | HD24: =SUM(HD19:HD23) -> 27830625 | HF24: =SUM(HF19:HF23) -> 231921.88 | HH24: =SUM(HH19:HH23) -> 27830625 | HJ24: =SUM(HJ19:HJ23) -> 231921.88 | HL24: =SUM(HL19:HL23) -> 27830625 | HN24: =SUM(HN19:HN23) -> 231921.88 | HP24: =SUM(HP19:HP23) -> 27830625 | HR24: =SUM(HR19:HR23) -> 231921.88 | HT24: =SUM(HT19:HT23) -> 27830625 | HV24: =SUM(HV19:HV23) -> 231921.88 | HX24: =SUM(HX19:HX23) -> 27830625 | HZ24: =SUM(HZ19:HZ23) -> 231921.88 | IB24: =SUM(IB19:IB23) -> 27830625 | ID24: =SUM(ID19:ID23) -> 231921.88 | IF24: =SUM(IF19:IF23) -> 27830625 | IH24: =SUM(IH19:IH23) -> 231921.88 | IJ24: =SUM(IJ19:IJ23) -> 27830625 | IL24: =SUM(IL19:IL23) -> 0 | IN24: =SUM(IN19:IN23) -> 0 | IP24: =SUM(IP19:IP23) -> 0 | IR24: =SUM(IR19:IR23) -> 0 | IT24: =SUM(IT19:IT23) -> 182101.85 | IV24: =SUM(IV19:IV23) -> 14568148 | IX24: =SUM(IX19:IX23) -> 1238292.6 | IZ24: =SUM(IZ19:IZ23) -> 1.4859511e+08 | JB24: =SUM(JB19:JB23) -> 1919353.5 | JD24: =SUM(JD19:JD23) -> 2.3032242e+08 | JF24: =SUM(JF19:JF23) -> 2783062.5 | JH24: =SUM(JH19:JH23) -> 3.339675e+08
J26: 1 | K26: =$K$8 -> 1 | N26: 1 | O26: 1 | R26: =N26 -> 1 | S26: 1 | V26: =R26 -> 1 | W26: 1 | Z26: =V26 -> 1 | AA26: 1 | AD26: =Z26 -> 1 | AE26: 1 | AH26: =AD26 -> 1 | AI26: 1 | AL26: =AH26 -> 1 | AM26: 1 | AP26: 1 | AQ26: 1 | AT26: =AP26 -> 1 | AU26: 1 | AX26: =AT26 -> 1 | AY26: 1 | BB26: ='A.I Revenue Streams - P1'!M28+100% -> 1 | BC26: 1 | BF26: 1 | BG26: 1 | BJ26: =BF26 -> 1 | BK26: 1 | BN26: =BJ26 -> 1 | BO26: 1 | BR26: =BN26 -> 1 | BS26: 1 | BV26: =BR26 -> 1 | BW26: 1 | BZ26: =BV26 -> 1 | CA26: 1 | CD26: =BZ26 -> 1 | CE26: 1 | CH26: =CD26 -> 1 | CI26: 1 | CL26: 1 | CM26: 1 | CP26: 1 | CQ26: 1 | CT26: =CP26 -> 1 | CU26: 1 | CX26: ='A.I Revenue Streams - P1'!O28+100% -> 2.23 | CY26: 1 | DB26: 1 | DC26: 1 | DF26: =DB26 -> 1 | DG26: 1 | DJ26: =DF26 -> 1 | DK26: 1 | DN26: =DJ26 -> 1 | DO26: 1 | DR26: =DN26 -> 1 | DS26: 1 | DV26: =DR26 -> 1 | DW26: 1 | DZ26: =DV26 -> 1 | EA26: 1 | ED26: =DZ26 -> 1 | EE26: 1 | EH26: 1 | EI26: 1 | EL26: 1 | EM26: 1 | EP26: =EL26 -> 1 | EQ26: 1 | ET26: ='A.I Revenue Streams - P1'!Q28+100% -> 2.23 | EU26: 1 | EX26: 1 | EY26: 1 | FB26: =EX26 -> 1 | FC26: 1 | FF26: =FB26 -> 1 | FG26: 1 | FJ26: =FF26 -> 1 | FK26: 1 | FN26: =FJ26 -> 1 | FO26: 1 | FR26: =FN26 -> 1 | FS26: 1 | FV26: =FR26 -> 1 | FW26: 1 | FZ26: =FV26 -> 1 | GA26: 1 | GD26: 1 | GE26: 1 | GH26: 1 | GI26: 1 | GL26: =GH26 -> 1 | GM26: 1 | GP26: ='A.I Revenue Streams - P1'!S28+100% -> 1 | GQ26: 1 | GT26: 1 | GU26: 1 | GX26: =GT26 -> 1 | GY26: 1 | HB26: =GX26 -> 1 | HC26: 1 | HF26: =HB26 -> 1 | HG26: 1 | HJ26: =HF26 -> 1 | HK26: 1 | HN26: =HJ26 -> 1 | HO26: 1 | HR26: =HN26 -> 1 | HS26: 1 | HV26: =HR26 -> 1 | HW26: 1 | HZ26: 1 | IA26: 1 | ID26: 1 | IE26: 1 | IH26: =ID26 -> 1 | II26: 1 | IL26: ='A.I Revenue Streams - P2'!DI28+100% -> 1 | IM26: 1 | IP26: ='A.I Revenue Streams - P2'!DM28+100% -> 1 | IQ26: 1 | IT26: ='A.I Revenue Streams - P2'!DQ28+100% -> 1 | IU26: 1 | IX26: ='A.I Revenue Streams - P2'!DU28+100% -> 1 | IY26: 1 | JB26: ='A.I Revenue Streams - P2'!DY28+100% -> 1 | JC26: 1 | JF26: ='A.I Revenue Streams - P2'!EC28+100% -> 1 | JG26: 1
B27: 3 | C27: ='A.I Revenue Streams - P1'!D27 -> 0
B28: 3a | D28: ='A.I Revenue Streams - P1'!E28 -> 0 | F28: ='A.I Revenue Streams - P1'!G28 -> 0 | G28: ='A.I Revenue Streams - P1'!I28 -> 0 | H28: =F28*G28 -> 0 | J28: =F28*$J$26 -> 0 | K28: =G28*$K$26 -> 0 | L28: =J28*K28 -> 0 | N28: =J28*$J$26 -> 0 | O28: =K28*$O$26 -> 0 | P28: =N28*O28 -> 0 | R28: =N28*$J$26 -> 0 | S28: =O28*$S$26 -> 0 | T28: =R28*S28 -> 0 | V28: =R28*$J$26 -> 0 | W28: =S28*$W$26 -> 0 | X28: =V28*W28 -> 0 | Z28: =V28*$J$26 -> 0 | AA28: =W28*$AA$26 -> 0 | AB28: =Z28*AA28 -> 0 | AD28: =Z28*$J$26 -> 0 | AE28: =AA28*$AE$26 -> 0 | AF28: =AD28*AE28 -> 0 | AH28: =AD28*$J$26 -> 0 | AI28: =AE28*$AI$26 -> 0 | AJ28: =AH28*AI28 -> 0 | AL28: =AH28*$J$26 -> 0 | AM28: =AI28*$AM$26 -> 0 | AN28: =AL28*AM28 -> 0 | AP28: =AL28*$J$26 -> 0 | AQ28: =AM28*$AQ$26 -> 0 | AR28: =AP28*AQ28 -> 0 | AT28: =AP28*$J$26 -> 0 | AU28: =AQ28*$AU$26 -> 0 | AV28: =AT28*AU28 -> 0 | AX28: =AT28*$J$26 -> 0 | AY28: =AU28*$AY$26 -> 0 | AZ28: =AX28*AY28 -> 0 | BB28: =AX28*$J$26 -> 0 | BC28: =AY28*$BC$26 -> 0 | BD28: =BB28*BC28 -> 0 | BF28: =BB28*$J$26 -> 0 | BG28: =BC28*$BG$26 -> 0 | BH28: =BF28*BG28 -> 0 | BJ28: =BF28*$J$26 -> 0 | BK28: =BG28*$BK$26 -> 0 | BL28: =BJ28*BK28 -> 0 | BN28: =BJ28*$J$26 -> 0 | BO28: =BK28*$BO$26 -> 0 | BP28: =BN28*BO28 -> 0 | BR28: =BN28*$J$26 -> 0 | BS28: =BO28*$BS$26 -> 0 | BT28: =BR28*BS28 -> 0 | BV28: =BR28*$J$26 -> 0 | BW28: =BS28*$BW$26 -> 0 | BX28: =BV28*BW28 -> 0 | BZ28: =BV28*$J$26 -> 0 | CA28: =BW28*$CA$26 -> 0 | CB28: =BZ28*CA28 -> 0 | CD28: =BZ28*$J$26 -> 0 | CE28: =CA28*$CE$26 -> 0 | CF28: =CD28*CE28 -> 0 | CH28: =CD28*$J$26 -> 0 | CI28: =CE28*$CI$26 -> 0 | CJ28: =CH28*CI28 -> 0 | CL28: =CH28*$J$26 -> 0 | CM28: =CI28*$CM$26 -> 0 | CN28: =CL28*CM28 -> 0 | CP28: =CL28*$J$26 -> 0 | CQ28: =CM28*$CQ$26 -> 0 | CR28: =CP28*CQ28 -> 0 | CT28: =CP28*$J$26 -> 0 | CU28: =CQ28*$CU$26 -> 0 | CV28: =CT28*CU28 -> 0 | CX28: =CT28*$J$26 -> 0 | CY28: =CU28*$CY$26 -> 0 | CZ28: =CX28*CY28 -> 0 | DB28: =CX28*$J$26 -> 0 | DC28: =CY28*$DC$26 -> 0 | DD28: =DB28*DC28 -> 0 | DF28: =DB28*$J$26 -> 0 | DG28: =DC28*$DG$26 -> 0 | DH28: =DF28*DG28 -> 0 | DJ28: =DF28*$J$26 -> 0 | DK28: =DG28*$DK$26 -> 0 | DL28: =DJ28*DK28 -> 0 | DN28: =DJ28*$J$26 -> 0 | DO28: =DK28*$DO$26 -> 0 | DP28: =DN28*DO28 -> 0 | DR28: =DN28*$J$26 -> 0 | DS28: =DO28*$DS$26 -> 0 | DT28: =DR28*DS28 -> 0 | DV28: =DR28*$J$26 -> 0 | DW28: =DS28*$DW$26 -> 0 | DX28: =DV28*DW28 -> 0 | DZ28: =DV28*$J$26 -> 0 | EA28: =DW28*$EA$26 -> 0 | EB28: =DZ28*EA28 -> 0 | ED28: =DZ28*$J$26 -> 0 | EE28: =EA28*$EE$26 -> 0 | EF28: =ED28*EE28 -> 0 | EH28: =ED28*$J$26 -> 0 | EI28: =EE28*$EI$26 -> 0 | EJ28: =EH28*EI28 -> 0 | EL28: =EH28*$J$26 -> 0 | EM28: =EI28*$EM$26 -> 0 | EN28: =EL28*EM28 -> 0 | EP28: =EL28*$J$26 -> 0 | EQ28: =EM28*$EQ$26 -> 0 | ER28: =EP28*EQ28 -> 0 | ET28: =EP28*$J$26 -> 0 | EU28: =EQ28*$EU$26 -> 0 | EV28: =ET28*EU28 -> 0 | EX28: =ET28*$J$26 -> 0 | EY28: =EU28*$EY$26 -> 0 | EZ28: =EX28*EY28 -> 0 | FB28: =EX28*$J$26 -> 0 | FC28: =EY28*$FC$26 -> 0 | FD28: =FB28*FC28 -> 0 | FF28: =FB28*$J$26 -> 0 | FG28: =FC28*$FG$26 -> 0 | FH28: =FF28*FG28 -> 0 | FJ28: =FF28*$J$26 -> 0 | FK28: =FG28*$FK$26 -> 0 | FL28: =FJ28*FK28 -> 0 | FN28: =FJ28*$J$26 -> 0 | FO28: =FK28*$FO$26 -> 0 | FP28: =FN28*FO28 -> 0 | FR28: =FN28*$J$26 -> 0 | FS28: =FO28*$FS$26 -> 0 | FT28: =FR28*FS28 -> 0 | FV28: =FR28*$J$26 -> 0 | FW28: =FS28*$FW$26 -> 0 | FX28: =FV28*FW28 -> 0 | FZ28: =FV28*$J$26 -> 0 | GA28: =FW28*$GA$26 -> 0 | GB28: =FZ28*GA28 -> 0 | GD28: =FZ28*$J$26 -> 0 | GE28: =GA28*$GE$26 -> 0 | GF28: =GD28*GE28 -> 0 | GH28: =GD28*$J$26 -> 0 | GI28: =GE28*$GI$26 -> 0 | GJ28: =GH28*GI28 -> 0 | GL28: =GH28*$J$26 -> 0 | GM28: =GI28*$GM$26 -> 0 | GN28: =GL28*GM28 -> 0 | GP28: =GL28*$J$26 -> 0 | GQ28: =GM28*$GQ$26 -> 0 | GR28: =GP28*GQ28 -> 0 | GT28: =GP28*$J$26 -> 0 | GU28: =GQ28*$GU$26 -> 0 | GV28: =GT28*GU28 -> 0 | GX28: =GT28*$J$26 -> 0 | GY28: =GU28*$GY$26 -> 0 | GZ28: =GX28*GY28 -> 0 | HB28: =GX28*$J$26 -> 0 | HC28: =GY28*$HC$26 -> 0 | HD28: =HB28*HC28 -> 0 | HF28: =HB28*$J$26 -> 0 | HG28: =HC28*$HG$26 -> 0 | HH28: =HF28*HG28 -> 0 | HJ28: =HF28*$J$26 -> 0 | HK28: =HG28*$HK$26 -> 0 | HL28: =HJ28*HK28 -> 0 | HN28: =HJ28*$J$26 -> 0 | HO28: =HK28*$HO$26 -> 0 | HP28: =HN28*HO28 -> 0 | HR28: =HN28*$J$26 -> 0 | HS28: =HO28*$HS$26 -> 0 | HT28: =HR28*HS28 -> 0 | HV28: =HR28*$J$26 -> 0 | HW28: =HS28*$HW$26 -> 0 | HX28: =HV28*HW28 -> 0 | HZ28: =HV28*$J$26 -> 0 | IA28: =HW28*$IA$26 -> 0 | IB28: =HZ28*IA28 -> 0 | ID28: =HZ28*$J$26 -> 0 | IE28: =IA28*$IE$26 -> 0 | IF28: =ID28*IE28 -> 0 | IH28: =ID28*$J$26 -> 0 | II28: =IE28*$II$26 -> 0 | IJ28: =IH28*II28 -> 0 | IL28: =SUMIFS($F28:$IK28,$F$3:$IK$3,IL$5,$F$6:$IK$6,IL$6) -> 0 | IM28: 0 | IN28: =SUMIFS($F28:$IK28,$F$3:$IK$3,IL$5,$F$6:$IK$6,IN$6) -> 0 | IP28: =SUMIFS($F28:$IK28,$F$3:$IK$3,IP$5,$F$6:$IK$6,IP$6) -> 0 | IQ28: =IR28/IP28 -> #DIV/0! | IR28: =SUMIFS($F28:$IK28,$F$3:$IK$3,IP$5,$F$6:$IK$6,IR$6) -> 0 | IT28: =SUMIFS($F28:$IK28,$F$3:$IK$3,IT$5,$F$6:$IK$6,IT$6) -> 0 | IU28: =IV28/IT28 -> #DIV/0! | IV28: =SUMIFS($F28:$IK28,$F$3:$IK$3,IT$5,$F$6:$IK$6,IV$6) -> 0 | IX28: =SUMIFS($F28:$IK28,$F$3:$IK$3,IX$5,$F$6:$IK$6,IX$6) -> 0 | IY28: =IZ28/IX28 -> #DIV/0! | IZ28: =SUMIFS($F28:$IK28,$F$3:$IK$3,IX$5,$F$6:$IK$6,IZ$6) -> 0 | JB28: =SUMIFS($F28:$IK28,$F$3:$IK$3,JB$5,$F$6:$IK$6,JB$6) -> 0 | JC28: =JD28/JB28 -> #DIV/0! | JD28: =SUMIFS($F28:$IK28,$F$3:$IK$3,JB$5,$F$6:$IK$6,JD$6) -> 0 | JF28: =SUMIFS($F28:$IK28,$F$3:$IK$3,JF$5,$F$6:$IK$6,JF$6) -> 0 | JG28: =JH28/JF28 -> #DIV/0! | JH28: =SUMIFS($F28:$IK28,$F$3:$IK$3,JF$5,$F$6:$IK$6,JH$6) -> 0
B29: 3b | D29: ='A.I Revenue Streams - P1'!E29 -> 0 | F29: ='A.I Revenue Streams - P1'!G29 -> 0 | G29: ='A.I Revenue Streams - P1'!I29 -> 0 | H29: =F29*G29 -> 0 | J29: =F29*$J$26 -> 0 | K29: =G29*$K$26 -> 0 | L29: =J29*K29 -> 0 | N29: =J29*$N$26 -> 0 | O29: =K29*$O$26 -> 0 | P29: =N29*O29 -> 0 | R29: =N29*$R$26 -> 0 | S29: =O29*$S$26 -> 0 | T29: =R29*S29 -> 0 | V29: =R29*$V$26 -> 0 | W29: =S29*$W$26 -> 0 | X29: =V29*W29 -> 0 | Z29: =V29*$Z$26 -> 0 | AA29: =W29*$AA$26 -> 0 | AB29: =Z29*AA29 -> 0 | AD29: =Z29*$AD$26 -> 0 | AE29: =AA29*$AE$26 -> 0 | AF29: =AD29*AE29 -> 0 | AH29: =AD29*$AH$26 -> 0 | AI29: =AE29*$AI$26 -> 0 | AJ29: =AH29*AI29 -> 0 | AL29: =AH29*$AL$26 -> 0 | AM29: =AI29*$AM$26 -> 0 | AN29: =AL29*AM29 -> 0 | AP29: =AL29*$AP$26 -> 0 | AQ29: =AM29*$AQ$26 -> 0 | AR29: =AP29*AQ29 -> 0 | AT29: =AP29*$AT$26 -> 0 | AU29: =AQ29*$AU$26 -> 0 | AV29: =AT29*AU29 -> 0 | AX29: =AT29*$AX$26 -> 0 | AY29: =AU29*$AY$26 -> 0 | AZ29: =AX29*AY29 -> 0 | BB29: =AX29*$BB$26 -> 0 | BC29: =AY29*$BC$26 -> 0 | BD29: =BB29*BC29 -> 0 | BF29: =BB29*$BF$26 -> 0 | BG29: =BC29*$BG$26 -> 0 | BH29: =BF29*BG29 -> 0 | BJ29: =BF29*$BJ$26 -> 0 | BK29: =BG29*$BK$26 -> 0 | BL29: =BJ29*BK29 -> 0 | BN29: =BJ29*$BN$26 -> 0 | BO29: =BK29*$BO$26 -> 0 | BP29: =BN29*BO29 -> 0 | BR29: =BN29*$BR$26 -> 0 | BS29: =BO29*$BS$26 -> 0 | BT29: =BR29*BS29 -> 0 | BV29: =BR29*$BV$26 -> 0 | BW29: =BS29*$BW$26 -> 0 | BX29: =BV29*BW29 -> 0 | BZ29: =BV29*$BZ$26 -> 0 | CA29: =BW29*$CA$26 -> 0 | CB29: =BZ29*CA29 -> 0 | CD29: =BZ29*$CD$26 -> 0 | CE29: =CA29*$CE$26 -> 0 | CF29: =CD29*CE29 -> 0 | CH29: =CD29*$CH$26 -> 0 | CI29: =CE29*$CI$26 -> 0 | CJ29: =CH29*CI29 -> 0 | CL29: =CH29*$CL$26 -> 0 | CM29: =CI29*$CM$26 -> 0 | CN29: =CL29*CM29 -> 0 | CP29: =CL29*$CP$26 -> 0 | CQ29: =CM29*$CQ$26 -> 0 | CR29: =CP29*CQ29 -> 0 | CT29: =CP29*$CT$26 -> 0 | CU29: =CQ29*$CU$26 -> 0 | CV29: =CT29*CU29 -> 0 | CX29: =CT29*$CX$26 -> 0 | CY29: =CU29*$CY$26 -> 0 | CZ29: =CX29*CY29 -> 0 | DB29: =CX29*$DB$26 -> 0 | DC29: =CY29*$DC$26 -> 0 | DD29: =DB29*DC29 -> 0 | DF29: =DB29*$DF$26 -> 0 | DG29: =DC29*$DG$26 -> 0 | DH29: =DF29*DG29 -> 0 | DJ29: =DF29*$DJ$26 -> 0 | DK29: =DG29*$DK$26 -> 0 | DL29: =DJ29*DK29 -> 0 | DN29: =DJ29*$DN$26 -> 0 | DO29: =DK29*$DO$26 -> 0 | DP29: =DN29*DO29 -> 0 | DR29: =DN29*$DR$26 -> 0 | DS29: =DO29*$DS$26 -> 0 | DT29: =DR29*DS29 -> 0 | DV29: =DR29*$DV$26 -> 0 | DW29: =DS29*$DW$26 -> 0 | DX29: =DV29*DW29 -> 0 | DZ29: =DV29*$DZ$26 -> 0 | EA29: =DW29*$EA$26 -> 0 | EB29: =DZ29*EA29 -> 0 | ED29: =DZ29*$ED$26 -> 0 | EE29: =EA29*$EE$26 -> 0 | EF29: =ED29*EE29 -> 0 | EH29: =ED29*$EH$26 -> 0 | EI29: =EE29*$EI$26 -> 0 | EJ29: =EH29*EI29 -> 0 | EL29: =EH29*$EL$26 -> 0 | EM29: =EI29*$EM$26 -> 0 | EN29: =EL29*EM29 -> 0 | EP29: =EL29*$EP$26 -> 0 | EQ29: =EM29*$EQ$26 -> 0 | ER29: =EP29*EQ29 -> 0 | ET29: =EP29*$ET$26 -> 0 | EU29: =EQ29*$EU$26 -> 0 | EV29: =ET29*EU29 -> 0 | EX29: =ET29*$EX$26 -> 0 | EY29: =EU29*$EY$26 -> 0 | EZ29: =EX29*EY29 -> 0 | FB29: =EX29*$FB$26 -> 0 | FC29: =EY29*$FC$26 -> 0 | FD29: =FB29*FC29 -> 0 | FF29: =FB29*$FF$26 -> 0 | FG29: =FC29*$FG$26 -> 0 | FH29: =FF29*FG29 -> 0 | FJ29: =FF29*$FJ$26 -> 0 | FK29: =FG29*$FK$26 -> 0 | FL29: =FJ29*FK29 -> 0 | FN29: =FJ29*$FN$26 -> 0 | FO29: =FK29*$FO$26 -> 0 | FP29: =FN29*FO29 -> 0 | FR29: =FN29*$FR$26 -> 0 | FS29: =FO29*$FS$26 -> 0 | FT29: =FR29*FS29 -> 0 | FV29: =FR29*$FV$26 -> 0 | FW29: =FS29*$FW$26 -> 0 | FX29: =FV29*FW29 -> 0 | FZ29: =FV29*$FZ$26 -> 0 | GA29: =FW29*$GA$26 -> 0 | GB29: =FZ29*GA29 -> 0 | GD29: =FZ29*$GD$26 -> 0 | GE29: =GA29*$GE$26 -> 0 | GF29: =GD29*GE29 -> 0 | GH29: =GD29*$GH$26 -> 0 | GI29: =GE29*$GI$26 -> 0 | GJ29: =GH29*GI29 -> 0 | GL29: =GH29*$GL$26 -> 0 | GM29: =GI29*$GM$26 -> 0 | GN29: =GL29*GM29 -> 0 | GP29: =GL29*$GP$26 -> 0 | GQ29: =GM29*$GQ$26 -> 0 | GR29: =GP29*GQ29 -> 0 | GT29: =GP29*$GT$26 -> 0 | GU29: =GQ29*$GU$26 -> 0 | GV29: =GT29*GU29 -> 0 | GX29: =GT29*$GX$26 -> 0 | GY29: =GU29*$GY$26 -> 0 | GZ29: =GX29*GY29 -> 0 | HB29: =GX29*$HB$26 -> 0 | HC29: =GY29*$HC$26 -> 0 | HD29: =HB29*HC29 -> 0 | HF29: =HB29*$HF$26 -> 0 | HG29: =HC29*$HG$26 -> 0 | HH29: =HF29*HG29 -> 0 | HJ29: =HF29*$HJ$26 -> 0 | HK29: =HG29*$HK$26 -> 0 | HL29: =HJ29*HK29 -> 0 | HN29: =HJ29*$HN$26 -> 0 | HO29: =HK29*$HO$26 -> 0 | HP29: =HN29*HO29 -> 0 | HR29: =HN29*$HR$26 -> 0 | HS29: =HO29*$HS$26 -> 0 | HT29: =HR29*HS29 -> 0 | HV29: =HR29*$HV$26 -> 0 | HW29: =HS29*$HW$26 -> 0 | HX29: =HV29*HW29 -> 0 | HZ29: =HV29*$HZ$26 -> 0 | IA29: =HW29*$IA$26 -> 0 | IB29: =HZ29*IA29 -> 0 | ID29: =HZ29*$ID$26 -> 0 | IE29: =IA29*$IE$26 -> 0 | IF29: =ID29*IE29 -> 0 | IH29: =ID29*$IH$26 -> 0 | II29: =IE29*$II$26 -> 0 | IJ29: =IH29*II29 -> 0 | IL29: =SUMIFS($F29:$IK29,$F$3:$IK$3,IL$5,$F$6:$IK$6,IL$6) -> 0 | IM29: 0 | IN29: =SUMIFS($F29:$IK29,$F$3:$IK$3,IL$5,$F$6:$IK$6,IN$6) -> 0 | IP29: =SUMIFS($F29:$IK29,$F$3:$IK$3,IP$5,$F$6:$IK$6,IP$6) -> 0 | IQ29: 0 | IR29: =SUMIFS($F29:$IK29,$F$3:$IK$3,IP$5,$F$6:$IK$6,IR$6) -> 0 | IT29: =SUMIFS($F29:$IK29,$F$3:$IK$3,IT$5,$F$6:$IK$6,IT$6) -> 0 | IU29: 0 | IV29: =SUMIFS($F29:$IK29,$F$3:$IK$3,IT$5,$F$6:$IK$6,IV$6) -> 0 | IX29: =SUMIFS($F29:$IK29,$F$3:$IK$3,IX$5,$F$6:$IK$6,IX$6) -> 0 | IY29: 0 | IZ29: =SUMIFS($F29:$IK29,$F$3:$IK$3,IX$5,$F$6:$IK$6,IZ$6) -> 0 | JB29: =SUMIFS($F29:$IK29,$F$3:$IK$3,JB$5,$F$6:$IK$6,JB$6) -> 0 | JC29: 0 | JD29: =SUMIFS($F29:$IK29,$F$3:$IK$3,JB$5,$F$6:$IK$6,JD$6) -> 0 | JF29: =SUMIFS($F29:$IK29,$F$3:$IK$3,JF$5,$F$6:$IK$6,JF$6) -> 0 | JG29: 0 | JH29: =SUMIFS($F29:$IK29,$F$3:$IK$3,JF$5,$F$6:$IK$6,JH$6) -> 0
B30: 3c | D30: ='A.I Revenue Streams - P1'!E30 -> 0 | F30: ='A.I Revenue Streams - P1'!G30 -> 0 | G30: ='A.I Revenue Streams - P1'!I30 -> 0 | H30: =F30*G30 -> 0 | J30: =F30*$J$26 -> 0 | K30: =G30*$K$26 -> 0 | L30: =J30*K30 -> 0 | N30: =J30*$N$26 -> 0 | O30: =K30*$O$26 -> 0 | P30: =N30*O30 -> 0 | R30: =N30*$R$26 -> 0 | S30: =O30*$S$26 -> 0 | T30: =R30*S30 -> 0 | V30: =R30*$V$26 -> 0 | W30: =S30*$W$26 -> 0 | X30: =V30*W30 -> 0 | Z30: =V30*$Z$26 -> 0 | AA30: =W30*$AA$26 -> 0 | AB30: =Z30*AA30 -> 0 | AD30: =Z30*$AD$26 -> 0 | AE30: =AA30*$AE$26 -> 0 | AF30: =AD30*AE30 -> 0 | AH30: =AD30*$AH$26 -> 0 | AI30: =AE30*$AI$26 -> 0 | AJ30: =AH30*AI30 -> 0 | AL30: =AH30*$AL$26 -> 0 | AM30: =AI30*$AM$26 -> 0 | AN30: =AL30*AM30 -> 0 | AP30: =AL30*$AP$26 -> 0 | AQ30: =AM30*$AQ$26 -> 0 | AR30: =AP30*AQ30 -> 0 | AT30: =AP30*$AT$26 -> 0 | AU30: =AQ30*$AU$26 -> 0 | AV30: =AT30*AU30 -> 0 | AX30: =AT30*$AX$26 -> 0 | AY30: =AU30*$AY$26 -> 0 | AZ30: =AX30*AY30 -> 0 | BB30: =AX30*$BB$26 -> 0 | BC30: =AY30*$BC$26 -> 0 | BD30: =BB30*BC30 -> 0 | BF30: =BB30*$BF$26 -> 0 | BG30: =BC30*$BG$26 -> 0 | BH30: =BF30*BG30 -> 0 | BJ30: =BF30*$BJ$26 -> 0 | BK30: =BG30*$BK$26 -> 0 | BL30: =BJ30*BK30 -> 0 | BN30: =BJ30*$BN$26 -> 0 | BO30: =BK30*$BO$26 -> 0 | BP30: =BN30*BO30 -> 0 | BR30: =BN30*$BR$26 -> 0 | BS30: =BO30*$BS$26 -> 0 | BT30: =BR30*BS30 -> 0 | BV30: =BR30*$BV$26 -> 0 | BW30: =BS30*$BW$26 -> 0 | BX30: =BV30*BW30 -> 0 | BZ30: =BV30*$BZ$26 -> 0 | CA30: =BW30*$CA$26 -> 0 | CB30: =BZ30*CA30 -> 0 | CD30: =BZ30*$CD$26 -> 0 | CE30: =CA30*$CE$26 -> 0 | CF30: =CD30*CE30 -> 0 | CH30: =CD30*$CH$26 -> 0 | CI30: =CE30*$CI$26 -> 0 | CJ30: =CH30*CI30 -> 0 | CL30: =CH30*$CL$26 -> 0 | CM30: =CI30*$CM$26 -> 0 | CN30: =CL30*CM30 -> 0 | CP30: =CL30*$CP$26 -> 0 | CQ30: =CM30*$CQ$26 -> 0 | CR30: =CP30*CQ30 -> 0 | CT30: =CP30*$CT$26 -> 0 | CU30: =CQ30*$CU$26 -> 0 | CV30: =CT30*CU30 -> 0 | CX30: =CT30*$CX$26 -> 0 | CY30: =CU30*$CY$26 -> 0 | CZ30: =CX30*CY30 -> 0 | DB30: =CX30*$DB$26 -> 0 | DC30: =CY30*$DC$26 -> 0 | DD30: =DB30*DC30 -> 0 | DF30: =DB30*$DF$26 -> 0 | DG30: =DC30*$DG$26 -> 0 | DH30: =DF30*DG30 -> 0 | DJ30: =DF30*$DJ$26 -> 0 | DK30: =DG30*$DK$26 -> 0 | DL30: =DJ30*DK30 -> 0 | DN30: =DJ30*$DN$26 -> 0 | DO30: =DK30*$DO$26 -> 0 | DP30: =DN30*DO30 -> 0 | DR30: =DN30*$DR$26 -> 0 | DS30: =DO30*$DS$26 -> 0 | DT30: =DR30*DS30 -> 0 | DV30: =DR30*$DV$26 -> 0 | DW30: =DS30*$DW$26 -> 0 | DX30: =DV30*DW30 -> 0 | DZ30: =DV30*$DZ$26 -> 0 | EA30: =DW30*$EA$26 -> 0 | EB30: =DZ30*EA30 -> 0 | ED30: =DZ30*$ED$26 -> 0 | EE30: =EA30*$EE$26 -> 0 | EF30: =ED30*EE30 -> 0 | EH30: =ED30*$EH$26 -> 0 | EI30: =EE30*$EI$26 -> 0 | EJ30: =EH30*EI30 -> 0 | EL30: =EH30*$EL$26 -> 0 | EM30: =EI30*$EM$26 -> 0 | EN30: =EL30*EM30 -> 0 | EP30: =EL30*$EP$26 -> 0 | EQ30: =EM30*$EQ$26 -> 0 | ER30: =EP30*EQ30 -> 0 | ET30: =EP30*$ET$26 -> 0 | EU30: =EQ30*$EU$26 -> 0 | EV30: =ET30*EU30 -> 0 | EX30: =ET30*$EX$26 -> 0 | EY30: =EU30*$EY$26 -> 0 | EZ30: =EX30*EY30 -> 0 | FB30: =EX30*$FB$26 -> 0 | FC30: =EY30*$FC$26 -> 0 | FD30: =FB30*FC30 -> 0 | FF30: =FB30*$FF$26 -> 0 | FG30: =FC30*$FG$26 -> 0 | FH30: =FF30*FG30 -> 0 | FJ30: =FF30*$FJ$26 -> 0 | FK30: =FG30*$FK$26 -> 0 | FL30: =FJ30*FK30 -> 0 | FN30: =FJ30*$FN$26 -> 0 | FO30: =FK30*$FO$26 -> 0 | FP30: =FN30*FO30 -> 0 | FR30: =FN30*$FR$26 -> 0 | FS30: =FO30*$FS$26 -> 0 | FT30: =FR30*FS30 -> 0 | FV30: =FR30*$FV$26 -> 0 | FW30: =FS30*$FW$26 -> 0 | FX30: =FV30*FW30 -> 0 | FZ30: =FV30*$FZ$26 -> 0 | GA30: =FW30*$GA$26 -> 0 | GB30: =FZ30*GA30 -> 0 | GD30: =FZ30*$GD$26 -> 0 | GE30: =GA30*$GE$26 -> 0 | GF30: =GD30*GE30 -> 0 | GH30: =GD30*$GH$26 -> 0 | GI30: =GE30*$GI$26 -> 0 | GJ30: =GH30*GI30 -> 0 | GL30: =GH30*$GL$26 -> 0 | GM30: =GI30*$GM$26 -> 0 | GN30: =GL30*GM30 -> 0 | GP30: =GL30*$GP$26 -> 0 | GQ30: =GM30*$GQ$26 -> 0 | GR30: =GP30*GQ30 -> 0 | GT30: =GP30*$GT$26 -> 0 | GU30: =GQ30*$GU$26 -> 0 | GV30: =GT30*GU30 -> 0 | GX30: =GT30*$GX$26 -> 0 | GY30: =GU30*$GY$26 -> 0 | GZ30: =GX30*GY30 -> 0 | HB30: =GX30*$HB$26 -> 0 | HC30: =GY30*$HC$26 -> 0 | HD30: =HB30*HC30 -> 0 | HF30: =HB30*$HF$26 -> 0 | HG30: =HC30*$HG$26 -> 0 | HH30: =HF30*HG30 -> 0 | HJ30: =HF30*$HJ$26 -> 0 | HK30: =HG30*$HK$26 -> 0 | HL30: =HJ30*HK30 -> 0 | HN30: =HJ30*$HN$26 -> 0 | HO30: =HK30*$HO$26 -> 0 | HP30: =HN30*HO30 -> 0 | HR30: =HN30*$HR$26 -> 0 | HS30: =HO30*$HS$26 -> 0 | HT30: =HR30*HS30 -> 0 | HV30: =HR30*$HV$26 -> 0 | HW30: =HS30*$HW$26 -> 0 | HX30: =HV30*HW30 -> 0 | HZ30: =HV30*$HZ$26 -> 0 | IA30: =HW30*$IA$26 -> 0 | IB30: =HZ30*IA30 -> 0 | ID30: =HZ30*$ID$26 -> 0 | IE30: =IA30*$IE$26 -> 0 | IF30: =ID30*IE30 -> 0 | IH30: =ID30*$IH$26 -> 0 | II30: =IE30*$II$26 -> 0 | IJ30: =IH30*II30 -> 0 | IL30: =SUMIFS($F30:$IK30,$F$3:$IK$3,IL$5,$F$6:$IK$6,IL$6) -> 0 | IM30: 0 | IN30: =SUMIFS($F30:$IK30,$F$3:$IK$3,IL$5,$F$6:$IK$6,IN$6) -> 0 | IP30: =SUMIFS($F30:$IK30,$F$3:$IK$3,IP$5,$F$6:$IK$6,IP$6) -> 0 | IQ30: 0 | IR30: =SUMIFS($F30:$IK30,$F$3:$IK$3,IP$5,$F$6:$IK$6,IR$6) -> 0 | IT30: =SUMIFS($F30:$IK30,$F$3:$IK$3,IT$5,$F$6:$IK$6,IT$6) -> 0 | IU30: 0 | IV30: =SUMIFS($F30:$IK30,$F$3:$IK$3,IT$5,$F$6:$IK$6,IV$6) -> 0 | IX30: =SUMIFS($F30:$IK30,$F$3:$IK$3,IX$5,$F$6:$IK$6,IX$6) -> 0 | IY30: 0 | IZ30: =SUMIFS($F30:$IK30,$F$3:$IK$3,IX$5,$F$6:$IK$6,IZ$6) -> 0 | JB30: =SUMIFS($F30:$IK30,$F$3:$IK$3,JB$5,$F$6:$IK$6,JB$6) -> 0 | JC30: 0 | JD30: =SUMIFS($F30:$IK30,$F$3:$IK$3,JB$5,$F$6:$IK$6,JD$6) -> 0 | JF30: =SUMIFS($F30:$IK30,$F$3:$IK$3,JF$5,$F$6:$IK$6,JF$6) -> 0 | JG30: 0 | JH30: =SUMIFS($F30:$IK30,$F$3:$IK$3,JF$5,$F$6:$IK$6,JH$6) -> 0
B31: 3d | D31: ='A.I Revenue Streams - P1'!E31 -> 0 | F31: ='A.I Revenue Streams - P1'!G31 -> 0 | G31: ='A.I Revenue Streams - P1'!I31 -> 0 | H31: =F31*G31 -> 0 | J31: =F31*$J$26 -> 0 | K31: =G31*$K$26 -> 0 | L31: =J31*K31 -> 0 | N31: =J31*$N$26 -> 0 | O31: =K31*$O$26 -> 0 | P31: =N31*O31 -> 0 | R31: =N31*$R$26 -> 0 | S31: =O31*$S$26 -> 0 | T31: =R31*S31 -> 0 | V31: =R31*$V$26 -> 0 | W31: =S31*$W$26 -> 0 | X31: =V31*W31 -> 0 | Z31: =V31*$Z$26 -> 0 | AA31: =W31*$AA$26 -> 0 | AB31: =Z31*AA31 -> 0 | AD31: =Z31*$AD$26 -> 0 | AE31: =AA31*$AE$26 -> 0 | AF31: =AD31*AE31 -> 0 | AH31: =AD31*$AH$26 -> 0 | AI31: =AE31*$AI$26 -> 0 | AJ31: =AH31*AI31 -> 0 | AL31: =AH31*$AL$26 -> 0 | AM31: =AI31*$AM$26 -> 0 | AN31: =AL31*AM31 -> 0 | AP31: =AL31*$AP$26 -> 0 | AQ31: =AM31*$AQ$26 -> 0 | AR31: =AP31*AQ31 -> 0 | AT31: =AP31*$AT$26 -> 0 | AU31: =AQ31*$AU$26 -> 0 | AV31: =AT31*AU31 -> 0 | AX31: =AT31*$AX$26 -> 0 | AY31: =AU31*$AY$26 -> 0 | AZ31: =AX31*AY31 -> 0 | BB31: =AX31*$BB$26 -> 0 | BC31: =AY31*$BC$26 -> 0 | BD31: =BB31*BC31 -> 0 | BF31: =BB31*$BF$26 -> 0 | BG31: =BC31*$BG$26 -> 0 | BH31: =BF31*BG31 -> 0 | BJ31: =BF31*$BJ$26 -> 0 | BK31: =BG31*$BK$26 -> 0 | BL31: =BJ31*BK31 -> 0 | BN31: =BJ31*$BN$26 -> 0 | BO31: =BK31*$BO$26 -> 0 | BP31: =BN31*BO31 -> 0 | BR31: =BN31*$BR$26 -> 0 | BS31: =BO31*$BS$26 -> 0 | BT31: =BR31*BS31 -> 0 | BV31: =BR31*$BV$26 -> 0 | BW31: =BS31*$BW$26 -> 0 | BX31: =BV31*BW31 -> 0 | BZ31: =BV31*$BZ$26 -> 0 | CA31: =BW31*$CA$26 -> 0 | CB31: =BZ31*CA31 -> 0 | CD31: =BZ31*$CD$26 -> 0 | CE31: =CA31*$CE$26 -> 0 | CF31: =CD31*CE31 -> 0 | CH31: =CD31*$CH$26 -> 0 | CI31: =CE31*$CI$26 -> 0 | CJ31: =CH31*CI31 -> 0 | CL31: =CH31*$CL$26 -> 0 | CM31: =CI31*$CM$26 -> 0 | CN31: =CL31*CM31 -> 0 | CP31: =CL31*$CP$26 -> 0 | CQ31: =CM31*$CQ$26 -> 0 | CR31: =CP31*CQ31 -> 0 | CT31: =CP31*$CT$26 -> 0 | CU31: =CQ31*$CU$26 -> 0 | CV31: =CT31*CU31 -> 0 | CX31: =CT31*$CX$26 -> 0 | CY31: =CU31*$CY$26 -> 0 | CZ31: =CX31*CY31 -> 0 | DB31: =CX31*$DB$26 -> 0 | DC31: =CY31*$DC$26 -> 0 | DD31: =DB31*DC31 -> 0 | DF31: =DB31*$DF$26 -> 0 | DG31: =DC31*$DG$26 -> 0 | DH31: =DF31*DG31 -> 0 | DJ31: =DF31*$DJ$26 -> 0 | DK31: =DG31*$DK$26 -> 0 | DL31: =DJ31*DK31 -> 0 | DN31: =DJ31*$DN$26 -> 0 | DO31: =DK31*$DO$26 -> 0 | DP31: =DN31*DO31 -> 0 | DR31: =DN31*$DR$26 -> 0 | DS31: =DO31*$DS$26 -> 0 | DT31: =DR31*DS31 -> 0 | DV31: =DR31*$DV$26 -> 0 | DW31: =DS31*$DW$26 -> 0 | DX31: =DV31*DW31 -> 0 | DZ31: =DV31*$DZ$26 -> 0 | EA31: =DW31*$EA$26 -> 0 | EB31: =DZ31*EA31 -> 0 | ED31: =DZ31*$ED$26 -> 0 | EE31: =EA31*$EE$26 -> 0 | EF31: =ED31*EE31 -> 0 | EH31: =ED31*$EH$26 -> 0 | EI31: =EE31*$EI$26 -> 0 | EJ31: =EH31*EI31 -> 0 | EL31: =EH31*$EL$26 -> 0 | EM31: =EI31*$EM$26 -> 0 | EN31: =EL31*EM31 -> 0 | EP31: =EL31*$EP$26 -> 0 | EQ31: =EM31*$EQ$26 -> 0 | ER31: =EP31*EQ31 -> 0 | ET31: =EP31*$ET$26 -> 0 | EU31: =EQ31*$EU$26 -> 0 | EV31: =ET31*EU31 -> 0 | EX31: =ET31*$EX$26 -> 0 | EY31: =EU31*$EY$26 -> 0 | EZ31: =EX31*EY31 -> 0 | FB31: =EX31*$FB$26 -> 0 | FC31: =EY31*$FC$26 -> 0 | FD31: =FB31*FC31 -> 0 | FF31: =FB31*$FF$26 -> 0 | FG31: =FC31*$FG$26 -> 0 | FH31: =FF31*FG31 -> 0 | FJ31: =FF31*$FJ$26 -> 0 | FK31: =FG31*$FK$26 -> 0 | FL31: =FJ31*FK31 -> 0 | FN31: =FJ31*$FN$26 -> 0 | FO31: =FK31*$FO$26 -> 0 | FP31: =FN31*FO31 -> 0 | FR31: =FN31*$FR$26 -> 0 | FS31: =FO31*$FS$26 -> 0 | FT31: =FR31*FS31 -> 0 | FV31: =FR31*$FV$26 -> 0 | FW31: =FS31*$FW$26 -> 0 | FX31: =FV31*FW31 -> 0 | FZ31: =FV31*$FZ$26 -> 0 | GA31: =FW31*$GA$26 -> 0 | GB31: =FZ31*GA31 -> 0 | GD31: =FZ31*$GD$26 -> 0 | GE31: =GA31*$GE$26 -> 0 | GF31: =GD31*GE31 -> 0 | GH31: =GD31*$GH$26 -> 0 | GI31: =GE31*$GI$26 -> 0 | GJ31: =GH31*GI31 -> 0 | GL31: =GH31*$GL$26 -> 0 | GM31: =GI31*$GM$26 -> 0 | GN31: =GL31*GM31 -> 0 | GP31: =GL31*$GP$26 -> 0 | GQ31: =GM31*$GQ$26 -> 0 | GR31: =GP31*GQ31 -> 0 | GT31: =GP31*$GT$26 -> 0 | GU31: =GQ31*$GU$26 -> 0 | GV31: =GT31*GU31 -> 0 | GX31: =GT31*$GX$26 -> 0 | GY31: =GU31*$GY$26 -> 0 | GZ31: =GX31*GY31 -> 0 | HB31: =GX31*$HB$26 -> 0 | HC31: =GY31*$HC$26 -> 0 | HD31: =HB31*HC31 -> 0 | HF31: =HB31*$HF$26 -> 0 | HG31: =HC31*$HG$26 -> 0 | HH31: =HF31*HG31 -> 0 | HJ31: =HF31*$HJ$26 -> 0 | HK31: =HG31*$HK$26 -> 0 | HL31: =HJ31*HK31 -> 0 | HN31: =HJ31*$HN$26 -> 0 | HO31: =HK31*$HO$26 -> 0 | HP31: =HN31*HO31 -> 0 | HR31: =HN31*$HR$26 -> 0 | HS31: =HO31*$HS$26 -> 0 | HT31: =HR31*HS31 -> 0 | HV31: =HR31*$HV$26 -> 0 | HW31: =HS31*$HW$26 -> 0 | HX31: =HV31*HW31 -> 0 | HZ31: =HV31*$HZ$26 -> 0 | IA31: =HW31*$IA$26 -> 0 | IB31: =HZ31*IA31 -> 0 | ID31: =HZ31*$ID$26 -> 0 | IE31: =IA31*$IE$26 -> 0 | IF31: =ID31*IE31 -> 0 | IH31: =ID31*$IH$26 -> 0 | II31: =IE31*$II$26 -> 0 | IJ31: =IH31*II31 -> 0 | IL31: =SUMIFS($F31:$IK31,$F$3:$IK$3,IL$5,$F$6:$IK$6,IL$6) -> 0 | IM31: 0 | IN31: =SUMIFS($F31:$IK31,$F$3:$IK$3,IL$5,$F$6:$IK$6,IN$6) -> 0 | IP31: =SUMIFS($F31:$IK31,$F$3:$IK$3,IP$5,$F$6:$IK$6,IP$6) -> 0 | IQ31: 0 | IR31: =SUMIFS($F31:$IK31,$F$3:$IK$3,IP$5,$F$6:$IK$6,IR$6) -> 0 | IT31: =SUMIFS($F31:$IK31,$F$3:$IK$3,IT$5,$F$6:$IK$6,IT$6) -> 0 | IU31: 0 | IV31: =SUMIFS($F31:$IK31,$F$3:$IK$3,IT$5,$F$6:$IK$6,IV$6) -> 0 | IX31: =SUMIFS($F31:$IK31,$F$3:$IK$3,IX$5,$F$6:$IK$6,IX$6) -> 0 | IY31: 0 | IZ31: =SUMIFS($F31:$IK31,$F$3:$IK$3,IX$5,$F$6:$IK$6,IZ$6) -> 0 | JB31: =SUMIFS($F31:$IK31,$F$3:$IK$3,JB$5,$F$6:$IK$6,JB$6) -> 0 | JC31: 0 | JD31: =SUMIFS($F31:$IK31,$F$3:$IK$3,JB$5,$F$6:$IK$6,JD$6) -> 0 | JF31: =SUMIFS($F31:$IK31,$F$3:$IK$3,JF$5,$F$6:$IK$6,JF$6) -> 0 | JG31: 0 | JH31: =SUMIFS($F31:$IK31,$F$3:$IK$3,JF$5,$F$6:$IK$6,JH$6) -> 0
B32: 3e | D32: ='A.I Revenue Streams - P1'!E32 -> 0 | F32: ='A.I Revenue Streams - P1'!G32 -> 0 | G32: ='A.I Revenue Streams - P1'!I32 -> 0 | H32: =F32*G32 -> 0 | J32: =F32*$J$26 -> 0 | K32: =G32*$K$26 -> 0 | L32: =J32*K32 -> 0 | N32: =J32*$N$26 -> 0 | O32: =K32*$O$26 -> 0 | P32: =N32*O32 -> 0 | R32: =N32*$R$26 -> 0 | S32: =O32*$S$26 -> 0 | T32: =R32*S32 -> 0 | V32: =R32*$V$26 -> 0 | W32: =S32*$W$26 -> 0 | X32: =V32*W32 -> 0 | Z32: =V32*$Z$26 -> 0 | AA32: =W32*$AA$26 -> 0 | AB32: =Z32*AA32 -> 0 | AD32: =Z32*$AD$26 -> 0 | AE32: =AA32*$AE$26 -> 0 | AF32: =AD32*AE32 -> 0 | AH32: =AD32*$AH$26 -> 0 | AI32: =AE32*$AI$26 -> 0 | AJ32: =AH32*AI32 -> 0 | AL32: =AH32*$AL$26 -> 0 | AM32: =AI32*$AM$26 -> 0 | AN32: =AL32*AM32 -> 0 | AP32: =AL32*$AP$26 -> 0 | AQ32: =AM32*$AQ$26 -> 0 | AR32: =AP32*AQ32 -> 0 | AT32: =AP32*$AT$26 -> 0 | AU32: =AQ32*$AU$26 -> 0 | AV32: =AT32*AU32 -> 0 | AX32: =AT32*$AX$26 -> 0 | AY32: =AU32*$AY$26 -> 0 | AZ32: =AX32*AY32 -> 0 | BB32: =AX32*$BB$26 -> 0 | BC32: =AY32*$BC$26 -> 0 | BD32: =BB32*BC32 -> 0 | BF32: =BB32*$BF$26 -> 0 | BG32: =BC32*$BG$26 -> 0 | BH32: =BF32*BG32 -> 0 | BJ32: =BF32*$BJ$26 -> 0 | BK32: =BG32*$BK$26 -> 0 | BL32: =BJ32*BK32 -> 0 | BN32: =BJ32*$BN$26 -> 0 | BO32: =BK32*$BO$26 -> 0 | BP32: =BN32*BO32 -> 0 | BR32: =BN32*$BR$26 -> 0 | BS32: =BO32*$BS$26 -> 0 | BT32: =BR32*BS32 -> 0 | BV32: =BR32*$BV$26 -> 0 | BW32: =BS32*$BW$26 -> 0 | BX32: =BV32*BW32 -> 0 | BZ32: =BV32*$BZ$26 -> 0 | CA32: =BW32*$CA$26 -> 0 | CB32: =BZ32*CA32 -> 0 | CD32: =BZ32*$CD$26 -> 0 | CE32: =CA32*$CE$26 -> 0 | CF32: =CD32*CE32 -> 0 | CH32: =CD32*$CH$26 -> 0 | CI32: =CE32*$CI$26 -> 0 | CJ32: =CH32*CI32 -> 0 | CL32: =CH32*$CL$26 -> 0 | CM32: =CI32*$CM$26 -> 0 | CN32: =CL32*CM32 -> 0 | CP32: =CL32*$CP$26 -> 0 | CQ32: =CM32*$CQ$26 -> 0 | CR32: =CP32*CQ32 -> 0 | CT32: =CP32*$CT$26 -> 0 | CU32: =CQ32*$CU$26 -> 0 | CV32: =CT32*CU32 -> 0 | CX32: =CT32*$CX$26 -> 0 | CY32: =CU32*$CY$26 -> 0 | CZ32: =CX32*CY32 -> 0 | DB32: =CX32*$DB$26 -> 0 | DC32: =CY32*$DC$26 -> 0 | DD32: =DB32*DC32 -> 0 | DF32: =DB32*$DF$26 -> 0 | DG32: =DC32*$DG$26 -> 0 | DH32: =DF32*DG32 -> 0 | DJ32: =DF32*$DJ$26 -> 0 | DK32: =DG32*$DK$26 -> 0 | DL32: =DJ32*DK32 -> 0 | DN32: =DJ32*$DN$26 -> 0 | DO32: =DK32*$DO$26 -> 0 | DP32: =DN32*DO32 -> 0 | DR32: =DN32*$DR$26 -> 0 | DS32: =DO32*$DS$26 -> 0 | DT32: =DR32*DS32 -> 0 | DV32: =DR32*$DV$26 -> 0 | DW32: =DS32*$DW$26 -> 0 | DX32: =DV32*DW32 -> 0 | DZ32: =DV32*$DZ$26 -> 0 | EA32: =DW32*$EA$26 -> 0 | EB32: =DZ32*EA32 -> 0 | ED32: =DZ32*$ED$26 -> 0 | EE32: =EA32*$EE$26 -> 0 | EF32: =ED32*EE32 -> 0 | EH32: =ED32*$EH$26 -> 0 | EI32: =EE32*$EI$26 -> 0 | EJ32: =EH32*EI32 -> 0 | EL32: =EH32*$EL$26 -> 0 | EM32: =EI32*$EM$26 -> 0 | EN32: =EL32*EM32 -> 0 | EP32: =EL32*$EP$26 -> 0 | EQ32: =EM32*$EQ$26 -> 0 | ER32: =EP32*EQ32 -> 0 | ET32: =EP32*$ET$26 -> 0 | EU32: =EQ32*$EU$26 -> 0 | EV32: =ET32*EU32 -> 0 | EX32: =ET32*$EX$26 -> 0 | EY32: =EU32*$EY$26 -> 0 | EZ32: =EX32*EY32 -> 0 | FB32: =EX32*$FB$26 -> 0 | FC32: =EY32*$FC$26 -> 0 | FD32: =FB32*FC32 -> 0 | FF32: =FB32*$FF$26 -> 0 | FG32: =FC32*$FG$26 -> 0 | FH32: =FF32*FG32 -> 0 | FJ32: =FF32*$FJ$26 -> 0 | FK32: =FG32*$FK$26 -> 0 | FL32: =FJ32*FK32 -> 0 | FN32: =FJ32*$FN$26 -> 0 | FO32: =FK32*$FO$26 -> 0 | FP32: =FN32*FO32 -> 0 | FR32: =FN32*$FR$26 -> 0 | FS32: =FO32*$FS$26 -> 0 | FT32: =FR32*FS32 -> 0 | FV32: =FR32*$FV$26 -> 0 | FW32: =FS32*$FW$26 -> 0 | FX32: =FV32*FW32 -> 0 | FZ32: =FV32*$FZ$26 -> 0 | GA32: =FW32*$GA$26 -> 0 | GB32: =FZ32*GA32 -> 0 | GD32: =FZ32*$GD$26 -> 0 | GE32: =GA32*$GE$26 -> 0 | GF32: =GD32*GE32 -> 0 | GH32: =GD32*$GH$26 -> 0 | GI32: =GE32*$GI$26 -> 0 | GJ32: =GH32*GI32 -> 0 | GL32: =GH32*$GL$26 -> 0 | GM32: =GI32*$GM$26 -> 0 | GN32: =GL32*GM32 -> 0 | GP32: =GL32*$GP$26 -> 0 | GQ32: =GM32*$GQ$26 -> 0 | GR32: =GP32*GQ32 -> 0 | GT32: =GP32*$GT$26 -> 0 | GU32: =GQ32*$GU$26 -> 0 | GV32: =GT32*GU32 -> 0 | GX32: =GT32*$GX$26 -> 0 | GY32: =GU32*$GY$26 -> 0 | GZ32: =GX32*GY32 -> 0 | HB32: =GX32*$HB$26 -> 0 | HC32: =GY32*$HC$26 -> 0 | HD32: =HB32*HC32 -> 0 | HF32: =HB32*$HF$26 -> 0 | HG32: =HC32*$HG$26 -> 0 | HH32: =HF32*HG32 -> 0 | HJ32: =HF32*$HJ$26 -> 0 | HK32: =HG32*$HK$26 -> 0 | HL32: =HJ32*HK32 -> 0 | HN32: =HJ32*$HN$26 -> 0 | HO32: =HK32*$HO$26 -> 0 | HP32: =HN32*HO32 -> 0 | HR32: =HN32*$HR$26 -> 0 | HS32: =HO32*$HS$26 -> 0 | HT32: =HR32*HS32 -> 0 | HV32: =HR32*$HV$26 -> 0 | HW32: =HS32*$HW$26 -> 0 | HX32: =HV32*HW32 -> 0 | HZ32: =HV32*$HZ$26 -> 0 | IA32: =HW32*$IA$26 -> 0 | IB32: =HZ32*IA32 -> 0 | ID32: =HZ32*$ID$26 -> 0 | IE32: =IA32*$IE$26 -> 0 | IF32: =ID32*IE32 -> 0 | IH32: =ID32*$IH$26 -> 0 | II32: =IE32*$II$26 -> 0 | IJ32: =IH32*II32 -> 0 | IL32: =SUMIFS($F32:$IK32,$F$3:$IK$3,IL$5,$F$6:$IK$6,IL$6) -> 0 | IM32: 0 | IN32: =SUMIFS($F32:$IK32,$F$3:$IK$3,IL$5,$F$6:$IK$6,IN$6) -> 0 | IP32: =SUMIFS($F32:$IK32,$F$3:$IK$3,IP$5,$F$6:$IK$6,IP$6) -> 0 | IQ32: 0 | IR32: =SUMIFS($F32:$IK32,$F$3:$IK$3,IP$5,$F$6:$IK$6,IR$6) -> 0 | IT32: =SUMIFS($F32:$IK32,$F$3:$IK$3,IT$5,$F$6:$IK$6,IT$6) -> 0 | IU32: 0 | IV32: =SUMIFS($F32:$IK32,$F$3:$IK$3,IT$5,$F$6:$IK$6,IV$6) -> 0 | IX32: =SUMIFS($F32:$IK32,$F$3:$IK$3,IX$5,$F$6:$IK$6,IX$6) -> 0 | IY32: 0 | IZ32: =SUMIFS($F32:$IK32,$F$3:$IK$3,IX$5,$F$6:$IK$6,IZ$6) -> 0 | JB32: =SUMIFS($F32:$IK32,$F$3:$IK$3,JB$5,$F$6:$IK$6,JB$6) -> 0 | JC32: 0 | JD32: =SUMIFS($F32:$IK32,$F$3:$IK$3,JB$5,$F$6:$IK$6,JD$6) -> 0 | JF32: =SUMIFS($F32:$IK32,$F$3:$IK$3,JF$5,$F$6:$IK$6,JF$6) -> 0 | JG32: 0 | JH32: =SUMIFS($F32:$IK32,$F$3:$IK$3,JF$5,$F$6:$IK$6,JH$6) -> 0
B33: Grand Total | F33: =SUM(F28:F32) -> 0 | H33: =SUM(H28:H32) -> 0 | J33: =SUM(J28:J32) -> 0 | L33: =SUM(L28:L32) -> 0 | N33: =SUM(N28:N32) -> 0 | P33: =SUM(P28:P32) -> 0 | R33: =SUM(R28:R32) -> 0 | T33: =SUM(T28:T32) -> 0 | V33: =SUM(V28:V32) -> 0 | X33: =SUM(X28:X32) -> 0 | Z33: =SUM(Z28:Z32) -> 0 | AB33: =SUM(AB28:AB32) -> 0 | AD33: =SUM(AD28:AD32) -> 0 | AF33: =SUM(AF28:AF32) -> 0 | AH33: =SUM(AH28:AH32) -> 0 | AJ33: =SUM(AJ28:AJ32) -> 0 | AL33: =SUM(AL28:AL32) -> 0 | AN33: =SUM(AN28:AN32) -> 0 | AP33: =SUM(AP27:AP32) -> 0 | AR33: =SUM(AR27:AR32) -> 0 | AT33: =SUM(AT27:AT32) -> 0 | AV33: =SUM(AV27:AV32) -> 0 | AX33: =SUM(AX27:AX32) -> 0 | AZ33: =SUM(AZ27:AZ32) -> 0 | BB33: =SUM(BB27:BB32) -> 0 | BD33: =SUM(BD27:BD32) -> 0 | BF33: =SUM(BF27:BF32) -> 0 | BH33: =SUM(BH27:BH32) -> 0 | BJ33: =SUM(BJ27:BJ32) -> 0 | BL33: =SUM(BL27:BL32) -> 0 | BN33: =SUM(BN27:BN32) -> 0 | BP33: =SUM(BP27:BP32) -> 0 | BR33: =SUM(BR27:BR32) -> 0 | BT33: =SUM(BT27:BT32) -> 0 | BV33: =SUM(BV27:BV32) -> 0 | BX33: =SUM(BX27:BX32) -> 0 | BZ33: =SUM(BZ27:BZ32) -> 0 | CB33: =SUM(CB27:CB32) -> 0 | CD33: =SUM(CD27:CD32) -> 0 | CF33: =SUM(CF27:CF32) -> 0 | CH33: =SUM(CH27:CH32) -> 0 | CJ33: =SUM(CJ27:CJ32) -> 0 | CL33: =SUM(CL27:CL32) -> 0 | CN33: =SUM(CN27:CN32) -> 0 | CP33: =SUM(CP27:CP32) -> 0 | CR33: =SUM(CR27:CR32) -> 0 | CT33: =SUM(CT27:CT32) -> 0 | CV33: =SUM(CV27:CV32) -> 0 | CX33: =SUM(CX27:CX32) -> 0 | CZ33: =SUM(CZ27:CZ32) -> 0 | DB33: =SUM(DB27:DB32) -> 0 | DD33: =SUM(DD27:DD32) -> 0 | DF33: =SUM(DF27:DF32) -> 0 | DH33: =SUM(DH27:DH32) -> 0 | DJ33: =SUM(DJ27:DJ32) -> 0 | DL33: =SUM(DL27:DL32) -> 0 | DN33: =SUM(DN27:DN32) -> 0 | DP33: =SUM(DP27:DP32) -> 0 | DR33: =SUM(DR27:DR32) -> 0 | DT33: =SUM(DT27:DT32) -> 0 | DV33: =SUM(DV27:DV32) -> 0 | DX33: =SUM(DX27:DX32) -> 0 | DZ33: =SUM(DZ27:DZ32) -> 0 | EB33: =SUM(EB27:EB32) -> 0 | ED33: =SUM(ED27:ED32) -> 0 | EF33: =SUM(EF27:EF32) -> 0 | EH33: =SUM(EH27:EH32) -> 0 | EJ33: =SUM(EJ27:EJ32) -> 0 | EL33: =SUM(EL27:EL32) -> 0 | EN33: =SUM(EN27:EN32) -> 0 | EP33: =SUM(EP27:EP32) -> 0 | ER33: =SUM(ER27:ER32) -> 0 | ET33: =SUM(ET27:ET32) -> 0 | EV33: =SUM(EV27:EV32) -> 0 | EX33: =SUM(EX27:EX32) -> 0 | EZ33: =SUM(EZ27:EZ32) -> 0 | FB33: =SUM(FB27:FB32) -> 0 | FD33: =SUM(FD27:FD32) -> 0 | FF33: =SUM(FF27:FF32) -> 0 | FH33: =SUM(FH27:FH32) -> 0 | FJ33: =SUM(FJ27:FJ32) -> 0 | FL33: =SUM(FL27:FL32) -> 0 | FN33: =SUM(FN27:FN32) -> 0 | FP33: =SUM(FP27:FP32) -> 0 | FR33: =SUM(FR27:FR32) -> 0 | FT33: =SUM(FT27:FT32) -> 0 | FV33: =SUM(FV27:FV32) -> 0 | FX33: =SUM(FX27:FX32) -> 0 | FZ33: =SUM(FZ27:FZ32) -> 0 | GB33: =SUM(GB27:GB32) -> 0 | GD33: =SUM(GD27:GD32) -> 0 | GF33: =SUM(GF27:GF32) -> 0 | GH33: =SUM(GH27:GH32) -> 0 | GJ33: =SUM(GJ27:GJ32) -> 0 | GL33: =SUM(GL27:GL32) -> 0 | GN33: =SUM(GN27:GN32) -> 0 | GP33: =SUM(GP27:GP32) -> 0 | GR33: =SUM(GR27:GR32) -> 0 | GT33: =SUM(GT27:GT32) -> 0 | GV33: =SUM(GV27:GV32) -> 0 | GX33: =SUM(GX27:GX32) -> 0 | GZ33: =SUM(GZ27:GZ32) -> 0 | HB33: =SUM(HB27:HB32) -> 0 | HD33: =SUM(HD27:HD32) -> 0 | HF33: =SUM(HF27:HF32) -> 0 | HH33: =SUM(HH27:HH32) -> 0 | HJ33: =SUM(HJ27:HJ32) -> 0 | HL33: =SUM(HL27:HL32) -> 0 | HN33: =SUM(HN27:HN32) -> 0 | HP33: =SUM(HP27:HP32) -> 0 | HR33: =SUM(HR27:HR32) -> 0 | HT33: =SUM(HT27:HT32) -> 0 | HV33: =SUM(HV27:HV32) -> 0 | HX33: =SUM(HX27:HX32) -> 0 | HZ33: =SUM(HZ27:HZ32) -> 0 | IB33: =SUM(IB27:IB32) -> 0 | ID33: =SUM(ID27:ID32) -> 0 | IF33: =SUM(IF27:IF32) -> 0 | IH33: =SUM(IH27:IH32) -> 0 | IJ33: =SUM(IJ27:IJ32) -> 0 | IL33: =SUM(IL27:IL29) -> 0 | IN33: =SUM(IN28:IN32) -> 0 | IP33: =SUM(IP27:IP29) -> 0 | IR33: =SUM(IR28:IR32) -> 0 | IT33: =SUM(IT27:IT29) -> 0 | IV33: =SUM(IV28:IV32) -> 0 | IX33: =SUM(IX27:IX29) -> 0 | IZ33: =SUM(IZ28:IZ32) -> 0 | JB33: =SUM(JB27:JB29) -> 0 | JD33: =SUM(JD28:JD32) -> 0 | JF33: =SUM(JF27:JF29) -> 0 | JH33: =SUM(JH28:JH32) -> 0
J35: ='A.I Revenue Streams - P1'!K37+100% -> 1 | K35: =$K$8 -> 1 | N35: 1 | O35: 1 | R35: =N35 -> 1 | S35: 1 | V35: =R35 -> 1 | W35: 1 | Z35: =V35 -> 1 | AA35: 1 | AD35: =Z35 -> 1 | AE35: 1 | AH35: =AD35 -> 1 | AI35: 1 | AL35: =AH35 -> 1 | AM35: 1 | AP35: 1 | AQ35: 1 | AT35: =AP35 -> 1 | AU35: 1 | AX35: =AT35 -> 1 | AY35: 1 | BB35: ='A.I Revenue Streams - P1'!M37+100% -> 1 | BC35: 1 | BF35: 1 | BG35: 1 | BJ35: =BF35 -> 1 | BK35: 1 | BN35: =BJ35 -> 1 | BO35: 1 | BR35: =BN35 -> 1 | BS35: 1 | BV35: =BR35 -> 1 | BW35: 1 | BZ35: =BV35 -> 1 | CA35: 1 | CD35: =BZ35 -> 1 | CE35: 1 | CH35: =CD35 -> 1 | CI35: 1 | CL35: 1 | CM35: 1 | CP35: 1 | CQ35: 1 | CT35: =CP35 -> 1 | CU35: 1 | CX35: ='A.I Revenue Streams - P1'!O37+100% -> 2.23 | CY35: 1 | DB35: 1 | DC35: 1 | DF35: =DB35 -> 1 | DG35: 1 | DJ35: =DF35 -> 1 | DK35: 1 | DN35: =DJ35 -> 1 | DO35: 1 | DR35: =DN35 -> 1 | DS35: 1 | DV35: =DR35 -> 1 | DW35: 1 | DZ35: =DV35 -> 1 | EA35: 1 | ED35: =DZ35 -> 1 | EE35: 1 | EH35: 1 | EI35: 1 | EL35: 1 | EM35: 1 | EP35: =EL35 -> 1 | EQ35: 1 | ET35: ='A.I Revenue Streams - P1'!Q37+100% -> 2.23 | EU35: 1 | EX35: 1 | EY35: 1 | FB35: =EX35 -> 1 | FC35: 1 | FF35: =FB35 -> 1 | FG35: 1 | FJ35: =FF35 -> 1 | FK35: 1 | FN35: =FJ35 -> 1 | FO35: 1 | FR35: =FN35 -> 1 | FS35: 1 | FV35: =FR35 -> 1 | FW35: 1 | FZ35: =FV35 -> 1 | GA35: 1 | GD35: 1 | GE35: 1 | GH35: 1 | GI35: 1 | GL35: =GH35 -> 1 | GM35: 1 | GP35: ='A.I Revenue Streams - P1'!S37+100% -> 1 | GQ35: 1 | GT35: 1 | GU35: 1 | GX35: =GT35 -> 1 | GY35: 1 | HB35: =GX35 -> 1 | HC35: 1 | HF35: =HB35 -> 1 | HG35: 1 | HJ35: =HF35 -> 1 | HK35: 1 | HN35: =HJ35 -> 1 | HO35: 1 | HR35: =HN35 -> 1 | HS35: 1 | HV35: =HR35 -> 1 | HW35: 1 | HZ35: 1 | IA35: 1 | ID35: 1 | IE35: 1 | IH35: =ID35 -> 1 | II35: 1 | IL35: ='A.I Revenue Streams - P2'!DI37+100% -> 1 | IM35: 1 | IP35: ='A.I Revenue Streams - P2'!DM37+100% -> 1 | IQ35: 1 | IT35: ='A.I Revenue Streams - P2'!DQ37+100% -> 1 | IU35: 1 | IX35: ='A.I Revenue Streams - P2'!DU37+100% -> 1 | IY35: 1 | JB35: ='A.I Revenue Streams - P2'!DY37+100% -> 1 | JC35: 1 | JF35: ='A.I Revenue Streams - P2'!EC37+100% -> 1 | JG35: 1
B36: 4 | C36: ='A.I Revenue Streams - P1'!D36 -> 0
B37: 4a | D37: ='A.I Revenue Streams - P1'!E37 -> 0 | F37: 0 | G37: ='A.I Revenue Streams - P1'!I37 -> 0 | H37: =F37*G37 -> 0 | J37: =F37*$J$35 -> 0 | K37: =G37*$K$35 -> 0 | L37: =J37*K37 -> 0 | N37: =J37*$N$35 -> 0 | O37: =K37*$O$35 -> 0 | P37: =N37*O37 -> 0 | R37: =N37*$R$35 -> 0 | S37: =O37*$S$35 -> 0 | T37: =R37*S37 -> 0 | V37: ='A.I Revenue Streams - P1'!G37 -> 0 | W37: =S37*$W$35 -> 0 | X37: =V37*W37 -> 0 | Z37: =V37*$Z$35 -> 0 | AA37: =W37*$AA$35 -> 0 | AB37: =Z37*AA37 -> 0 | AD37: =Z37*$AD$35 -> 0 | AE37: =AA37*$AE$35 -> 0 | AF37: =AD37*AE37 -> 0 | AH37: =AD37*$AH$35 -> 0 | AI37: =AE37*$AI$35 -> 0 | AJ37: =AH37*AI37 -> 0 | AL37: =AH37*$AL$35 -> 0 | AM37: =AI37*$AM$35 -> 0 | AN37: =AL37*AM37 -> 0 | AP37: =AL37*$AP$35 -> 0 | AQ37: =AM37*$AQ$35 -> 0 | AR37: =AP37*AQ37 -> 0 | AT37: =AP37*$AT$35 -> 0 | AU37: =AQ37*$AU$35 -> 0 | AV37: =AT37*AU37 -> 0 | AX37: =AT37*$AX$35 -> 0 | AY37: =AU37*$AY$35 -> 0 | AZ37: =AX37*AY37 -> 0 | BB37: =AX37*$BB$35 -> 0 | BC37: =AY37*$BC$35 -> 0 | BD37: =BB37*BC37 -> 0 | BF37: =BB37*$BF$35 -> 0 | BG37: =BC37*$BG$35 -> 0 | BH37: =BF37*BG37 -> 0 | BJ37: =BF37*$BJ$35 -> 0 | BK37: =BG37*$BK$35 -> 0 | BL37: =BJ37*BK37 -> 0 | BN37: =BJ37*$BN$35 -> 0 | BO37: =BK37*$BO$35 -> 0 | BP37: =BN37*BO37 -> 0 | BR37: =BN37*$BR$35 -> 0 | BS37: =BO37*$BS$35 -> 0 | BT37: =BR37*BS37 -> 0 | BV37: =BR37*$BV$35 -> 0 | BW37: =BS37*$BW$35 -> 0 | BX37: =BV37*BW37 -> 0 | BZ37: =BV37*$BZ$35 -> 0 | CA37: =BW37*$CA$35 -> 0 | CB37: =BZ37*CA37 -> 0 | CD37: =BZ37*$CD$35 -> 0 | CE37: =CA37*$CE$35 -> 0 | CF37: =CD37*CE37 -> 0 | CH37: =CD37*$CH$35 -> 0 | CI37: =CE37*$CI$35 -> 0 | CJ37: =CH37*CI37 -> 0 | CL37: =CH37*$CL$35 -> 0 | CM37: =CI37*$CM$35 -> 0 | CN37: =CL37*CM37 -> 0 | CP37: =CL37*$CP$35 -> 0 | CQ37: =CM37*$CQ$35 -> 0 | CR37: =CP37*CQ37 -> 0 | CT37: =CP37*$CT$35 -> 0 | CU37: =CQ37*$CU$35 -> 0 | CV37: =CT37*CU37 -> 0 | CX37: =CT37*$CX$35 -> 0 | CY37: =CU37*$CY$35 -> 0 | CZ37: =CX37*CY37 -> 0 | DB37: =CX37*$DB$35 -> 0 | DC37: =CY37*$DC$35 -> 0 | DD37: =DB37*DC37 -> 0 | DF37: =DB37*$DF$35 -> 0 | DG37: =DC37*$DG$35 -> 0 | DH37: =DF37*DG37 -> 0 | DJ37: =DF37*$DJ$35 -> 0 | DK37: =DG37*$DK$35 -> 0 | DL37: =DJ37*DK37 -> 0 | DN37: =DJ37*$DN$35 -> 0 | DO37: =DK37*$DO$35 -> 0 | DP37: =DN37*DO37 -> 0 | DR37: =DN37*$DR$35 -> 0 | DS37: =DO37*$DS$35 -> 0 | DT37: =DR37*DS37 -> 0 | DV37: =DR37*$DV$35 -> 0 | DW37: =DS37*$DW$35 -> 0 | DX37: =DV37*DW37 -> 0 | DZ37: =DV37*$DZ$35 -> 0 | EA37: =DW37*$EA$35 -> 0 | EB37: =DZ37*EA37 -> 0 | ED37: =DZ37*$ED$35 -> 0 | EE37: =EA37*$EE$35 -> 0 | EF37: =ED37*EE37 -> 0 | EH37: =ED37*$EH$35 -> 0 | EI37: =EE37*$EI$35 -> 0 | EJ37: =EH37*EI37 -> 0 | EL37: =EH37*$EL$35 -> 0 | EM37: =EI37*$EM$35 -> 0 | EN37: =EL37*EM37 -> 0 | EP37: =EL37*$EP$35 -> 0 | EQ37: =EM37*$EQ$35 -> 0 | ER37: =EP37*EQ37 -> 0 | ET37: =EP37*$ET$35 -> 0 | EU37: =EQ37*$EU$35 -> 0 | EV37: =ET37*EU37 -> 0 | EX37: =ET37*$EX$35 -> 0 | EY37: =EU37*$EY$35 -> 0 | EZ37: =EX37*EY37 -> 0 | FB37: =EX37*$FB$35 -> 0 | FC37: =EY37*$FC$35 -> 0 | FD37: =FB37*FC37 -> 0 | FF37: =FB37*$FF$35 -> 0 | FG37: =FC37*$FG$35 -> 0 | FH37: =FF37*FG37 -> 0 | FJ37: =FF37*$FJ$35 -> 0 | FK37: =FG37*$FK$35 -> 0 | FL37: =FJ37*FK37 -> 0 | FN37: =FJ37*$FN$35 -> 0 | FO37: =FK37*$FO$35 -> 0 | FP37: =FN37*FO37 -> 0 | FR37: =FN37*$FR$35 -> 0 | FS37: =FO37*$FS$35 -> 0 | FT37: =FR37*FS37 -> 0 | FV37: =FR37*$FV$35 -> 0 | FW37: =FS37*$FW$35 -> 0 | FX37: =FV37*FW37 -> 0 | FZ37: =FV37*$FZ$35 -> 0 | GA37: =FW37*$GA$35 -> 0 | GB37: =FZ37*GA37 -> 0 | GD37: =FZ37*$GD$35 -> 0 | GE37: =GA37*$GE$35 -> 0 | GF37: =GD37*GE37 -> 0 | GH37: =GD37*$GH$35 -> 0 | GI37: =GE37*$GI$35 -> 0 | GJ37: =GH37*GI37 -> 0 | GL37: =GH37*$GL$35 -> 0 | GM37: =GI37*$GM$35 -> 0 | GN37: =GL37*GM37 -> 0 | GP37: =GL37*$GP$35 -> 0 | GQ37: =GM37*$GQ$35 -> 0 | GR37: =GP37*GQ37 -> 0 | GT37: =GP37*$GT$35 -> 0 | GU37: =GQ37*$GU$35 -> 0 | GV37: =GT37*GU37 -> 0 | GX37: =GT37*$GX$35 -> 0 | GY37: =GU37*$GY$35 -> 0 | GZ37: =GX37*GY37 -> 0 | HB37: =GX37*$HB$35 -> 0 | HC37: =GY37*$HC$35 -> 0 | HD37: =HB37*HC37 -> 0 | HF37: =HB37*$HF$35 -> 0 | HG37: =HC37*$HG$35 -> 0 | HH37: =HF37*HG37 -> 0 | HJ37: =HF37*$HJ$35 -> 0 | HK37: =HG37*$HK$35 -> 0 | HL37: =HJ37*HK37 -> 0 | HN37: =HJ37*$HN$35 -> 0 | HO37: =HK37*$HO$35 -> 0 | HP37: =HN37*HO37 -> 0 | HR37: =HN37*$HR$35 -> 0 | HS37: =HO37*$HS$35 -> 0 | HT37: =HR37*HS37 -> 0 | HV37: =HR37*$HV$35 -> 0 | HW37: =HS37*$HW$35 -> 0 | HX37: =HV37*HW37 -> 0 | HZ37: =HV37*$HZ$35 -> 0 | IA37: =HW37*$IA$35 -> 0 | IB37: =HZ37*IA37 -> 0 | ID37: =HZ37*$ID$35 -> 0 | IE37: =IA37*$IE$35 -> 0 | IF37: =ID37*IE37 -> 0 | IH37: =ID37*$IH$35 -> 0 | II37: =IE37*$II$35 -> 0 | IJ37: =IH37*II37 -> 0 | IL37: =SUMIFS($F37:$IK37,$F$3:$IK$3,IL$5,$F$6:$IK$6,IL$6) -> 0 | IM37: 0 | IN37: =SUMIFS($F37:$IK37,$F$3:$IK$3,IL$5,$F$6:$IK$6,IN$6) -> 0 | IP37: =SUMIFS($F37:$IK37,$F$3:$IK$3,IP$5,$F$6:$IK$6,IP$6) -> 0 | IQ37: =IR37/IP37 -> #DIV/0! | IR37: =SUMIFS($F37:$IK37,$F$3:$IK$3,IP$5,$F$6:$IK$6,IR$6) -> 0 | IT37: =SUMIFS($F37:$IK37,$F$3:$IK$3,IT$5,$F$6:$IK$6,IT$6) -> 0 | IU37: =IV37/IT37 -> #DIV/0! | IV37: =SUMIFS($F37:$IK37,$F$3:$IK$3,IT$5,$F$6:$IK$6,IV$6) -> 0 | IX37: =SUMIFS($F37:$IK37,$F$3:$IK$3,IX$5,$F$6:$IK$6,IX$6) -> 0 | IY37: =IZ37/IX37 -> #DIV/0! | IZ37: =SUMIFS($F37:$IK37,$F$3:$IK$3,IX$5,$F$6:$IK$6,IZ$6) -> 0 | JB37: =SUMIFS($F37:$IK37,$F$3:$IK$3,JB$5,$F$6:$IK$6,JB$6) -> 0 | JC37: =JD37/JB37 -> #DIV/0! | JD37: =SUMIFS($F37:$IK37,$F$3:$IK$3,JB$5,$F$6:$IK$6,JD$6) -> 0 | JF37: =SUMIFS($F37:$IK37,$F$3:$IK$3,JF$5,$F$6:$IK$6,JF$6) -> 0 | JG37: =JH37/JF37 -> #DIV/0! | JH37: =SUMIFS($F37:$IK37,$F$3:$IK$3,JF$5,$F$6:$IK$6,JH$6) -> 0
B38: 4b | D38: ='A.I Revenue Streams - P1'!E38 -> 0 | F38: ='A.I Revenue Streams - P1'!G38 -> 0 | G38: ='A.I Revenue Streams - P1'!I38 -> 0 | H38: =F38*G38 -> 0 | J38: =F38*$J$35 -> 0 | K38: =G38*$K$35 -> 0 | L38: =J38*K38 -> 0 | N38: =J38*$N$35 -> 0 | O38: =K38*$O$35 -> 0 | P38: =N38*O38 -> 0 | R38: =N38*$R$35 -> 0 | S38: =O38*$S$35 -> 0 | T38: =R38*S38 -> 0 | V38: =R38*$V$35 -> 0 | W38: =S38*$W$35 -> 0 | X38: =V38*W38 -> 0 | Z38: =V38*$Z$35 -> 0 | AA38: =W38*$AA$35 -> 0 | AB38: =Z38*AA38 -> 0 | AD38: =Z38*$AD$35 -> 0 | AE38: =AA38*$AE$35 -> 0 | AF38: =AD38*AE38 -> 0 | AH38: =AD38*$AH$35 -> 0 | AI38: =AE38*$AI$35 -> 0 | AJ38: =AH38*AI38 -> 0 | AL38: =AH38*$AL$35 -> 0 | AM38: =AI38*$AM$35 -> 0 | AN38: =AL38*AM38 -> 0 | AP38: =AL38*$AP$35 -> 0 | AQ38: =AM38*$AQ$35 -> 0 | AR38: =AP38*AQ38 -> 0 | AT38: =AP38*$AT$35 -> 0 | AU38: =AQ38*$AU$35 -> 0 | AV38: =AT38*AU38 -> 0 | AX38: =AT38*$AX$35 -> 0 | AY38: =AU38*$AY$35 -> 0 | AZ38: =AX38*AY38 -> 0 | BB38: =AX38*$BB$35 -> 0 | BC38: =AY38*$BC$35 -> 0 | BD38: =BB38*BC38 -> 0 | BF38: =BB38*$BF$35 -> 0 | BG38: =BC38*$BG$35 -> 0 | BH38: =BF38*BG38 -> 0 | BJ38: =BF38*$BJ$35 -> 0 | BK38: =BG38*$BK$35 -> 0 | BL38: =BJ38*BK38 -> 0 | BN38: =BJ38*$BN$35 -> 0 | BO38: =BK38*$BO$35 -> 0 | BP38: =BN38*BO38 -> 0 | BR38: =BN38*$BR$35 -> 0 | BS38: =BO38*$BS$35 -> 0 | BT38: =BR38*BS38 -> 0 | BV38: =BR38*$BV$35 -> 0 | BW38: =BS38*$BW$35 -> 0 | BX38: =BV38*BW38 -> 0 | BZ38: =BV38*$BZ$35 -> 0 | CA38: =BW38*$CA$35 -> 0 | CB38: =BZ38*CA38 -> 0 | CD38: =BZ38*$CD$35 -> 0 | CE38: =CA38*$CE$35 -> 0 | CF38: =CD38*CE38 -> 0 | CH38: =CD38*$CH$35 -> 0 | CI38: =CE38*$CI$35 -> 0 | CJ38: =CH38*CI38 -> 0 | CL38: =CH38*$CL$35 -> 0 | CM38: =CI38*$CM$35 -> 0 | CN38: =CL38*CM38 -> 0 | CP38: =CL38*$CP$35 -> 0 | CQ38: =CM38*$CQ$35 -> 0 | CR38: =CP38*CQ38 -> 0 | CT38: =CP38*$CT$35 -> 0 | CU38: =CQ38*$CU$35 -> 0 | CV38: =CT38*CU38 -> 0 | CX38: =CT38*$CX$35 -> 0 | CY38: =CU38*$CY$35 -> 0 | CZ38: =CX38*CY38 -> 0 | DB38: =CX38*$DB$35 -> 0 | DC38: =CY38*$DC$35 -> 0 | DD38: =DB38*DC38 -> 0 | DF38: =DB38*$DF$35 -> 0 | DG38: =DC38*$DG$35 -> 0 | DH38: =DF38*DG38 -> 0 | DJ38: =DF38*$DJ$35 -> 0 | DK38: =DG38*$DK$35 -> 0 | DL38: =DJ38*DK38 -> 0 | DN38: =DJ38*$DN$35 -> 0 | DO38: =DK38*$DO$35 -> 0 | DP38: =DN38*DO38 -> 0 | DR38: =DN38*$DR$35 -> 0 | DS38: =DO38*$DS$35 -> 0 | DT38: =DR38*DS38 -> 0 | DV38: =DR38*$DV$35 -> 0 | DW38: =DS38*$DW$35 -> 0 | DX38: =DV38*DW38 -> 0 | DZ38: =DV38*$DZ$35 -> 0 | EA38: =DW38*$EA$35 -> 0 | EB38: =DZ38*EA38 -> 0 | ED38: =DZ38*$ED$35 -> 0 | EE38: =EA38*$EE$35 -> 0 | EF38: =ED38*EE38 -> 0 | EH38: =ED38*$EH$35 -> 0 | EI38: =EE38*$EI$35 -> 0 | EJ38: =EH38*EI38 -> 0 | EL38: =EH38*$EL$35 -> 0 | EM38: =EI38*$EM$35 -> 0 | EN38: =EL38*EM38 -> 0 | EP38: =EL38*$EP$35 -> 0 | EQ38: =EM38*$EQ$35 -> 0 | ER38: =EP38*EQ38 -> 0 | ET38: =EP38*$ET$35 -> 0 | EU38: =EQ38*$EU$35 -> 0 | EV38: =ET38*EU38 -> 0 | EX38: =ET38*$EX$35 -> 0 | EY38: =EU38*$EY$35 -> 0 | EZ38: =EX38*EY38 -> 0 | FB38: =EX38*$FB$35 -> 0 | FC38: =EY38*$FC$35 -> 0 | FD38: =FB38*FC38 -> 0 | FF38: =FB38*$FF$35 -> 0 | FG38: =FC38*$FG$35 -> 0 | FH38: =FF38*FG38 -> 0 | FJ38: =FF38*$FJ$35 -> 0 | FK38: =FG38*$FK$35 -> 0 | FL38: =FJ38*FK38 -> 0 | FN38: =FJ38*$FN$35 -> 0 | FO38: =FK38*$FO$35 -> 0 | FP38: =FN38*FO38 -> 0 | FR38: =FN38*$FR$35 -> 0 | FS38: =FO38*$FS$35 -> 0 | FT38: =FR38*FS38 -> 0 | FV38: =FR38*$FV$35 -> 0 | FW38: =FS38*$FW$35 -> 0 | FX38: =FV38*FW38 -> 0 | FZ38: =FV38*$FZ$35 -> 0 | GA38: =FW38*$GA$35 -> 0 | GB38: =FZ38*GA38 -> 0 | GD38: =FZ38*$GD$35 -> 0 | GE38: =GA38*$GE$35 -> 0 | GF38: =GD38*GE38 -> 0 | GH38: =GD38*$GH$35 -> 0 | GI38: =GE38*$GI$35 -> 0 | GJ38: =GH38*GI38 -> 0 | GL38: =GH38*$GL$35 -> 0 | GM38: =GI38*$GM$35 -> 0 | GN38: =GL38*GM38 -> 0 | GP38: =GL38*$GP$35 -> 0 | GQ38: =GM38*$GQ$35 -> 0 | GR38: =GP38*GQ38 -> 0 | GT38: =GP38*$GT$35 -> 0 | GU38: =GQ38*$GU$35 -> 0 | GV38: =GT38*GU38 -> 0 | GX38: =GT38*$GX$35 -> 0 | GY38: =GU38*$GY$35 -> 0 | GZ38: =GX38*GY38 -> 0 | HB38: =GX38*$HB$35 -> 0 | HC38: =GY38*$HC$35 -> 0 | HD38: =HB38*HC38 -> 0 | HF38: =HB38*$HF$35 -> 0 | HG38: =HC38*$HG$35 -> 0 | HH38: =HF38*HG38 -> 0 | HJ38: =HF38*$HJ$35 -> 0 | HK38: =HG38*$HK$35 -> 0 | HL38: =HJ38*HK38 -> 0 | HN38: =HJ38*$HN$35 -> 0 | HO38: =HK38*$HO$35 -> 0 | HP38: =HN38*HO38 -> 0 | HR38: =HN38*$HR$35 -> 0 | HS38: =HO38*$HS$35 -> 0 | HT38: =HR38*HS38 -> 0 | HV38: =HR38*$HV$35 -> 0 | HW38: =HS38*$HW$35 -> 0 | HX38: =HV38*HW38 -> 0 | HZ38: =HV38*$HZ$35 -> 0 | IA38: =HW38*$IA$35 -> 0 | IB38: =HZ38*IA38 -> 0 | ID38: =HZ38*$ID$35 -> 0 | IE38: =IA38*$IE$35 -> 0 | IF38: =ID38*IE38 -> 0 | IH38: =ID38*$IH$35 -> 0 | II38: =IE38*$II$35 -> 0 | IJ38: =IH38*II38 -> 0 | IL38: =SUMIFS($F38:$IK38,$F$3:$IK$3,IL$5,$F$6:$IK$6,IL$6) -> 0 | IM38: 0 | IN38: =SUMIFS($F38:$IK38,$F$3:$IK$3,IL$5,$F$6:$IK$6,IN$6) -> 0 | IP38: =SUMIFS($F38:$IK38,$F$3:$IK$3,IP$5,$F$6:$IK$6,IP$6) -> 0 | IQ38: 0 | IR38: =SUMIFS($F38:$IK38,$F$3:$IK$3,IP$5,$F$6:$IK$6,IR$6) -> 0 | IT38: =SUMIFS($F38:$IK38,$F$3:$IK$3,IT$5,$F$6:$IK$6,IT$6) -> 0 | IU38: 0 | IV38: =SUMIFS($F38:$IK38,$F$3:$IK$3,IT$5,$F$6:$IK$6,IV$6) -> 0 | IX38: =SUMIFS($F38:$IK38,$F$3:$IK$3,IX$5,$F$6:$IK$6,IX$6) -> 0 | IY38: 0 | IZ38: =SUMIFS($F38:$IK38,$F$3:$IK$3,IX$5,$F$6:$IK$6,IZ$6) -> 0 | JB38: =SUMIFS($F38:$IK38,$F$3:$IK$3,JB$5,$F$6:$IK$6,JB$6) -> 0 | JC38: 0 | JD38: =SUMIFS($F38:$IK38,$F$3:$IK$3,JB$5,$F$6:$IK$6,JD$6) -> 0 | JF38: =SUMIFS($F38:$IK38,$F$3:$IK$3,JF$5,$F$6:$IK$6,JF$6) -> 0 | JG38: 0 | JH38: =SUMIFS($F38:$IK38,$F$3:$IK$3,JF$5,$F$6:$IK$6,JH$6) -> 0
B39: 4c | D39: ='A.I Revenue Streams - P1'!E39 -> 0 | F39: ='A.I Revenue Streams - P1'!G39 -> 0 | G39: ='A.I Revenue Streams - P1'!I39 -> 0 | H39: =F39*G39 -> 0 | J39: =F39*$J$35 -> 0 | K39: =G39*$K$35 -> 0 | L39: =J39*K39 -> 0 | N39: =J39*$N$35 -> 0 | O39: =K39*$O$35 -> 0 | P39: =N39*O39 -> 0 | R39: =N39*$R$35 -> 0 | S39: =O39*$S$35 -> 0 | T39: =R39*S39 -> 0 | V39: =R39*$V$35 -> 0 | W39: =S39*$W$35 -> 0 | X39: =V39*W39 -> 0 | Z39: =V39*$Z$35 -> 0 | AA39: =W39*$AA$35 -> 0 | AB39: =Z39*AA39 -> 0 | AD39: =Z39*$AD$35 -> 0 | AE39: =AA39*$AE$35 -> 0 | AF39: =AD39*AE39 -> 0 | AH39: =AD39*$AH$35 -> 0 | AI39: =AE39*$AI$35 -> 0 | AJ39: =AH39*AI39 -> 0 | AL39: =AH39*$AL$35 -> 0 | AM39: =AI39*$AM$35 -> 0 | AN39: =AL39*AM39 -> 0 | AP39: =AL39*$AP$35 -> 0 | AQ39: =AM39*$AQ$35 -> 0 | AR39: =AP39*AQ39 -> 0 | AT39: =AP39*$AT$35 -> 0 | AU39: =AQ39*$AU$35 -> 0 | AV39: =AT39*AU39 -> 0 | AX39: =AT39*$AX$35 -> 0 | AY39: =AU39*$AY$35 -> 0 | AZ39: =AX39*AY39 -> 0 | BB39: =AX39*$BB$35 -> 0 | BC39: =AY39*$BC$35 -> 0 | BD39: =BB39*BC39 -> 0 | BF39: =BB39*$BF$35 -> 0 | BG39: =BC39*$BG$35 -> 0 | BH39: =BF39*BG39 -> 0 | BJ39: =BF39*$BJ$35 -> 0 | BK39: =BG39*$BK$35 -> 0 | BL39: =BJ39*BK39 -> 0 | BN39: =BJ39*$BN$35 -> 0 | BO39: =BK39*$BO$35 -> 0 | BP39: =BN39*BO39 -> 0 | BR39: =BN39*$BR$35 -> 0 | BS39: =BO39*$BS$35 -> 0 | BT39: =BR39*BS39 -> 0 | BV39: =BR39*$BV$35 -> 0 | BW39: =BS39*$BW$35 -> 0 | BX39: =BV39*BW39 -> 0 | BZ39: =BV39*$BZ$35 -> 0 | CA39: =BW39*$CA$35 -> 0 | CB39: =BZ39*CA39 -> 0 | CD39: =BZ39*$CD$35 -> 0 | CE39: =CA39*$CE$35 -> 0 | CF39: =CD39*CE39 -> 0 | CH39: =CD39*$CH$35 -> 0 | CI39: =CE39*$CI$35 -> 0 | CJ39: =CH39*CI39 -> 0 | CL39: =CH39*$CL$35 -> 0 | CM39: =CI39*$CM$35 -> 0 | CN39: =CL39*CM39 -> 0 | CP39: =CL39*$CP$35 -> 0 | CQ39: =CM39*$CQ$35 -> 0 | CR39: =CP39*CQ39 -> 0 | CT39: =CP39*$CT$35 -> 0 | CU39: =CQ39*$CU$35 -> 0 | CV39: =CT39*CU39 -> 0 | CX39: =CT39*$CX$35 -> 0 | CY39: =CU39*$CY$35 -> 0 | CZ39: =CX39*CY39 -> 0 | DB39: =CX39*$DB$35 -> 0 | DC39: =CY39*$DC$35 -> 0 | DD39: =DB39*DC39 -> 0 | DF39: =DB39*$DF$35 -> 0 | DG39: =DC39*$DG$35 -> 0 | DH39: =DF39*DG39 -> 0 | DJ39: =DF39*$DJ$35 -> 0 | DK39: =DG39*$DK$35 -> 0 | DL39: =DJ39*DK39 -> 0 | DN39: =DJ39*$DN$35 -> 0 | DO39: =DK39*$DO$35 -> 0 | DP39: =DN39*DO39 -> 0 | DR39: =DN39*$DR$35 -> 0 | DS39: =DO39*$DS$35 -> 0 | DT39: =DR39*DS39 -> 0 | DV39: =DR39*$DV$35 -> 0 | DW39: =DS39*$DW$35 -> 0 | DX39: =DV39*DW39 -> 0 | DZ39: =DV39*$DZ$35 -> 0 | EA39: =DW39*$EA$35 -> 0 | EB39: =DZ39*EA39 -> 0 | ED39: =DZ39*$ED$35 -> 0 | EE39: =EA39*$EE$35 -> 0 | EF39: =ED39*EE39 -> 0 | EH39: =ED39*$EH$35 -> 0 | EI39: =EE39*$EI$35 -> 0 | EJ39: =EH39*EI39 -> 0 | EL39: =EH39*$EL$35 -> 0 | EM39: =EI39*$EM$35 -> 0 | EN39: =EL39*EM39 -> 0 | EP39: =EL39*$EP$35 -> 0 | EQ39: =EM39*$EQ$35 -> 0 | ER39: =EP39*EQ39 -> 0 | ET39: =EP39*$ET$35 -> 0 | EU39: =EQ39*$EU$35 -> 0 | EV39: =ET39*EU39 -> 0 | EX39: =ET39*$EX$35 -> 0 | EY39: =EU39*$EY$35 -> 0 | EZ39: =EX39*EY39 -> 0 | FB39: =EX39*$FB$35 -> 0 | FC39: =EY39*$FC$35 -> 0 | FD39: =FB39*FC39 -> 0 | FF39: =FB39*$FF$35 -> 0 | FG39: =FC39*$FG$35 -> 0 | FH39: =FF39*FG39 -> 0 | FJ39: =FF39*$FJ$35 -> 0 | FK39: =FG39*$FK$35 -> 0 | FL39: =FJ39*FK39 -> 0 | FN39: =FJ39*$FN$35 -> 0 | FO39: =FK39*$FO$35 -> 0 | FP39: =FN39*FO39 -> 0 | FR39: =FN39*$FR$35 -> 0 | FS39: =FO39*$FS$35 -> 0 | FT39: =FR39*FS39 -> 0 | FV39: =FR39*$FV$35 -> 0 | FW39: =FS39*$FW$35 -> 0 | FX39: =FV39*FW39 -> 0 | FZ39: =FV39*$FZ$35 -> 0 | GA39: =FW39*$GA$35 -> 0 | GB39: =FZ39*GA39 -> 0 | GD39: =FZ39*$GD$35 -> 0 | GE39: =GA39*$GE$35 -> 0 | GF39: =GD39*GE39 -> 0 | GH39: =GD39*$GH$35 -> 0 | GI39: =GE39*$GI$35 -> 0 | GJ39: =GH39*GI39 -> 0 | GL39: =GH39*$GL$35 -> 0 | GM39: =GI39*$GM$35 -> 0 | GN39: =GL39*GM39 -> 0 | GP39: =GL39*$GP$35 -> 0 | GQ39: =GM39*$GQ$35 -> 0 | GR39: =GP39*GQ39 -> 0 | GT39: =GP39*$GT$35 -> 0 | GU39: =GQ39*$GU$35 -> 0 | GV39: =GT39*GU39 -> 0 | GX39: =GT39*$GX$35 -> 0 | GY39: =GU39*$GY$35 -> 0 | GZ39: =GX39*GY39 -> 0 | HB39: =GX39*$HB$35 -> 0 | HC39: =GY39*$HC$35 -> 0 | HD39: =HB39*HC39 -> 0 | HF39: =HB39*$HF$35 -> 0 | HG39: =HC39*$HG$35 -> 0 | HH39: =HF39*HG39 -> 0 | HJ39: =HF39*$HJ$35 -> 0 | HK39: =HG39*$HK$35 -> 0 | HL39: =HJ39*HK39 -> 0 | HN39: =HJ39*$HN$35 -> 0 | HO39: =HK39*$HO$35 -> 0 | HP39: =HN39*HO39 -> 0 | HR39: =HN39*$HR$35 -> 0 | HS39: =HO39*$HS$35 -> 0 | HT39: =HR39*HS39 -> 0 | HV39: =HR39*$HV$35 -> 0 | HW39: =HS39*$HW$35 -> 0 | HX39: =HV39*HW39 -> 0 | HZ39: =HV39*$HZ$35 -> 0 | IA39: =HW39*$IA$35 -> 0 | IB39: =HZ39*IA39 -> 0 | ID39: =HZ39*$ID$35 -> 0 | IE39: =IA39*$IE$35 -> 0 | IF39: =ID39*IE39 -> 0 | IH39: =ID39*$IH$35 -> 0 | II39: =IE39*$II$35 -> 0 | IJ39: =IH39*II39 -> 0 | IL39: =SUMIFS($F39:$IK39,$F$3:$IK$3,IL$5,$F$6:$IK$6,IL$6) -> 0 | IM39: 0 | IN39: =SUMIFS($F39:$IK39,$F$3:$IK$3,IL$5,$F$6:$IK$6,IN$6) -> 0 | IP39: =SUMIFS($F39:$IK39,$F$3:$IK$3,IP$5,$F$6:$IK$6,IP$6) -> 0 | IQ39: 0 | IR39: =SUMIFS($F39:$IK39,$F$3:$IK$3,IP$5,$F$6:$IK$6,IR$6) -> 0 | IT39: =SUMIFS($F39:$IK39,$F$3:$IK$3,IT$5,$F$6:$IK$6,IT$6) -> 0 | IU39: 0 | IV39: =SUMIFS($F39:$IK39,$F$3:$IK$3,IT$5,$F$6:$IK$6,IV$6) -> 0 | IX39: =SUMIFS($F39:$IK39,$F$3:$IK$3,IX$5,$F$6:$IK$6,IX$6) -> 0 | IY39: 0 | IZ39: =SUMIFS($F39:$IK39,$F$3:$IK$3,IX$5,$F$6:$IK$6,IZ$6) -> 0 | JB39: =SUMIFS($F39:$IK39,$F$3:$IK$3,JB$5,$F$6:$IK$6,JB$6) -> 0 | JC39: 0 | JD39: =SUMIFS($F39:$IK39,$F$3:$IK$3,JB$5,$F$6:$IK$6,JD$6) -> 0 | JF39: =SUMIFS($F39:$IK39,$F$3:$IK$3,JF$5,$F$6:$IK$6,JF$6) -> 0 | JG39: 0 | JH39: =SUMIFS($F39:$IK39,$F$3:$IK$3,JF$5,$F$6:$IK$6,JH$6) -> 0
B40: 4d | D40: ='A.I Revenue Streams - P1'!E40 -> 0 | F40: ='A.I Revenue Streams - P1'!G40 -> 0 | G40: ='A.I Revenue Streams - P1'!I40 -> 0 | H40: =F40*G40 -> 0 | J40: =F40*$J$35 -> 0 | K40: =G40*$K$35 -> 0 | L40: =J40*K40 -> 0 | N40: =J40*$N$35 -> 0 | O40: =K40*$O$35 -> 0 | P40: =N40*O40 -> 0 | R40: =N40*$R$35 -> 0 | S40: =O40*$S$35 -> 0 | T40: =R40*S40 -> 0 | V40: =R40*$V$35 -> 0 | W40: =S40*$W$35 -> 0 | X40: =V40*W40 -> 0 | Z40: =V40*$Z$35 -> 0 | AA40: =W40*$AA$35 -> 0 | AB40: =Z40*AA40 -> 0 | AD40: =Z40*$AD$35 -> 0 | AE40: =AA40*$AE$35 -> 0 | AF40: =AD40*AE40 -> 0 | AH40: =AD40*$AH$35 -> 0 | AI40: =AE40*$AI$35 -> 0 | AJ40: =AH40*AI40 -> 0 | AL40: =AH40*$AL$35 -> 0 | AM40: =AI40*$AM$35 -> 0 | AN40: =AL40*AM40 -> 0 | AP40: =AL40*$AP$35 -> 0 | AQ40: =AM40*$AQ$35 -> 0 | AR40: =AP40*AQ40 -> 0 | AT40: =AP40*$AT$35 -> 0 | AU40: =AQ40*$AU$35 -> 0 | AV40: =AT40*AU40 -> 0 | AX40: =AT40*$AX$35 -> 0 | AY40: =AU40*$AY$35 -> 0 | AZ40: =AX40*AY40 -> 0 | BB40: =AX40*$BB$35 -> 0 | BC40: =AY40*$BC$35 -> 0 | BD40: =BB40*BC40 -> 0 | BF40: =BB40*$BF$35 -> 0 | BG40: =BC40*$BG$35 -> 0 | BH40: =BF40*BG40 -> 0 | BJ40: =BF40*$BJ$35 -> 0 | BK40: =BG40*$BK$35 -> 0 | BL40: =BJ40*BK40 -> 0 | BN40: =BJ40*$BN$35 -> 0 | BO40: =BK40*$BO$35 -> 0 | BP40: =BN40*BO40 -> 0 | BR40: =BN40*$BR$35 -> 0 | BS40: =BO40*$BS$35 -> 0 | BT40: =BR40*BS40 -> 0 | BV40: =BR40*$BV$35 -> 0 | BW40: =BS40*$BW$35 -> 0 | BX40: =BV40*BW40 -> 0 | BZ40: =BV40*$BZ$35 -> 0 | CA40: =BW40*$CA$35 -> 0 | CB40: =BZ40*CA40 -> 0 | CD40: =BZ40*$CD$35 -> 0 | CE40: =CA40*$CE$35 -> 0 | CF40: =CD40*CE40 -> 0 | CH40: =CD40*$CH$35 -> 0 | CI40: =CE40*$CI$35 -> 0 | CJ40: =CH40*CI40 -> 0 | CL40: =CH40*$CL$35 -> 0 | CM40: =CI40*$CM$35 -> 0 | CN40: =CL40*CM40 -> 0 | CP40: =CL40*$CP$35 -> 0 | CQ40: =CM40*$CQ$35 -> 0 | CR40: =CP40*CQ40 -> 0 | CT40: =CP40*$CT$35 -> 0 | CU40: =CQ40*$CU$35 -> 0 | CV40: =CT40*CU40 -> 0 | CX40: =CT40*$CX$35 -> 0 | CY40: =CU40*$CY$35 -> 0 | CZ40: =CX40*CY40 -> 0 | DB40: =CX40*$DB$35 -> 0 | DC40: =CY40*$DC$35 -> 0 | DD40: =DB40*DC40 -> 0 | DF40: =DB40*$DF$35 -> 0 | DG40: =DC40*$DG$35 -> 0 | DH40: =DF40*DG40 -> 0 | DJ40: =DF40*$DJ$35 -> 0 | DK40: =DG40*$DK$35 -> 0 | DL40: =DJ40*DK40 -> 0 | DN40: =DJ40*$DN$35 -> 0 | DO40: =DK40*$DO$35 -> 0 | DP40: =DN40*DO40 -> 0 | DR40: =DN40*$DR$35 -> 0 | DS40: =DO40*$DS$35 -> 0 | DT40: =DR40*DS40 -> 0 | DV40: =DR40*$DV$35 -> 0 | DW40: =DS40*$DW$35 -> 0 | DX40: =DV40*DW40 -> 0 | DZ40: =DV40*$DZ$35 -> 0 | EA40: =DW40*$EA$35 -> 0 | EB40: =DZ40*EA40 -> 0 | ED40: =DZ40*$ED$35 -> 0 | EE40: =EA40*$EE$35 -> 0 | EF40: =ED40*EE40 -> 0 | EH40: =ED40*$EH$35 -> 0 | EI40: =EE40*$EI$35 -> 0 | EJ40: =EH40*EI40 -> 0 | EL40: =EH40*$EL$35 -> 0 | EM40: =EI40*$EM$35 -> 0 | EN40: =EL40*EM40 -> 0 | EP40: =EL40*$EP$35 -> 0 | EQ40: =EM40*$EQ$35 -> 0 | ER40: =EP40*EQ40 -> 0 | ET40: =EP40*$ET$35 -> 0 | EU40: =EQ40*$EU$35 -> 0 | EV40: =ET40*EU40 -> 0 | EX40: =ET40*$EX$35 -> 0 | EY40: =EU40*$EY$35 -> 0 | EZ40: =EX40*EY40 -> 0 | FB40: =EX40*$FB$35 -> 0 | FC40: =EY40*$FC$35 -> 0 | FD40: =FB40*FC40 -> 0 | FF40: =FB40*$FF$35 -> 0 | FG40: =FC40*$FG$35 -> 0 | FH40: =FF40*FG40 -> 0 | FJ40: =FF40*$FJ$35 -> 0 | FK40: =FG40*$FK$35 -> 0 | FL40: =FJ40*FK40 -> 0 | FN40: =FJ40*$FN$35 -> 0 | FO40: =FK40*$FO$35 -> 0 | FP40: =FN40*FO40 -> 0 | FR40: =FN40*$FR$35 -> 0 | FS40: =FO40*$FS$35 -> 0 | FT40: =FR40*FS40 -> 0 | FV40: =FR40*$FV$35 -> 0 | FW40: =FS40*$FW$35 -> 0 | FX40: =FV40*FW40 -> 0 | FZ40: =FV40*$FZ$35 -> 0 | GA40: =FW40*$GA$35 -> 0 | GB40: =FZ40*GA40 -> 0 | GD40: =FZ40*$GD$35 -> 0 | GE40: =GA40*$GE$35 -> 0 | GF40: =GD40*GE40 -> 0 | GH40: =GD40*$GH$35 -> 0 | GI40: =GE40*$GI$35 -> 0 | GJ40: =GH40*GI40 -> 0 | GL40: =GH40*$GL$35 -> 0 | GM40: =GI40*$GM$35 -> 0 | GN40: =GL40*GM40 -> 0 | GP40: =GL40*$GP$35 -> 0 | GQ40: =GM40*$GQ$35 -> 0 | GR40: =GP40*GQ40 -> 0 | GT40: =GP40*$GT$35 -> 0 | GU40: =GQ40*$GU$35 -> 0 | GV40: =GT40*GU40 -> 0 | GX40: =GT40*$GX$35 -> 0 | GY40: =GU40*$GY$35 -> 0 | GZ40: =GX40*GY40 -> 0 | HB40: =GX40*$HB$35 -> 0 | HC40: =GY40*$HC$35 -> 0 | HD40: =HB40*HC40 -> 0 | HF40: =HB40*$HF$35 -> 0 | HG40: =HC40*$HG$35 -> 0 | HH40: =HF40*HG40 -> 0 | HJ40: =HF40*$HJ$35 -> 0 | HK40: =HG40*$HK$35 -> 0 | HL40: =HJ40*HK40 -> 0 | HN40: =HJ40*$HN$35 -> 0 | HO40: =HK40*$HO$35 -> 0 | HP40: =HN40*HO40 -> 0 | HR40: =HN40*$HR$35 -> 0 | HS40: =HO40*$HS$35 -> 0 | HT40: =HR40*HS40 -> 0 | HV40: =HR40*$HV$35 -> 0 | HW40: =HS40*$HW$35 -> 0 | HX40: =HV40*HW40 -> 0 | HZ40: =HV40*$HZ$35 -> 0 | IA40: =HW40*$IA$35 -> 0 | IB40: =HZ40*IA40 -> 0 | ID40: =HZ40*$ID$35 -> 0 | IE40: =IA40*$IE$35 -> 0 | IF40: =ID40*IE40 -> 0 | IH40: =ID40*$IH$35 -> 0 | II40: =IE40*$II$35 -> 0 | IJ40: =IH40*II40 -> 0 | IL40: =SUMIFS($F40:$IK40,$F$3:$IK$3,IL$5,$F$6:$IK$6,IL$6) -> 0 | IM40: 0 | IN40: =SUMIFS($F40:$IK40,$F$3:$IK$3,IL$5,$F$6:$IK$6,IN$6) -> 0 | IP40: =SUMIFS($F40:$IK40,$F$3:$IK$3,IP$5,$F$6:$IK$6,IP$6) -> 0 | IQ40: 0 | IR40: =SUMIFS($F40:$IK40,$F$3:$IK$3,IP$5,$F$6:$IK$6,IR$6) -> 0 | IT40: =SUMIFS($F40:$IK40,$F$3:$IK$3,IT$5,$F$6:$IK$6,IT$6) -> 0 | IU40: 0 | IV40: =SUMIFS($F40:$IK40,$F$3:$IK$3,IT$5,$F$6:$IK$6,IV$6) -> 0 | IX40: =SUMIFS($F40:$IK40,$F$3:$IK$3,IX$5,$F$6:$IK$6,IX$6) -> 0 | IY40: 0 | IZ40: =SUMIFS($F40:$IK40,$F$3:$IK$3,IX$5,$F$6:$IK$6,IZ$6) -> 0 | JB40: =SUMIFS($F40:$IK40,$F$3:$IK$3,JB$5,$F$6:$IK$6,JB$6) -> 0 | JC40: 0 | JD40: =SUMIFS($F40:$IK40,$F$3:$IK$3,JB$5,$F$6:$IK$6,JD$6) -> 0 | JF40: =SUMIFS($F40:$IK40,$F$3:$IK$3,JF$5,$F$6:$IK$6,JF$6) -> 0 | JG40: 0 | JH40: =SUMIFS($F40:$IK40,$F$3:$IK$3,JF$5,$F$6:$IK$6,JH$6) -> 0
B41: 4e | D41: ='A.I Revenue Streams - P1'!E41 -> 0 | F41: ='A.I Revenue Streams - P1'!G41 -> 0 | G41: ='A.I Revenue Streams - P1'!I41 -> 0 | H41: =F41*G41 -> 0 | J41: =F41*$J$35 -> 0 | K41: =G41*$K$35 -> 0 | L41: =J41*K41 -> 0 | N41: =J41*$N$35 -> 0 | O41: =K41*$O$35 -> 0 | P41: =N41*O41 -> 0 | R41: =N41*$R$35 -> 0 | S41: =O41*$S$35 -> 0 | T41: =R41*S41 -> 0 | V41: =R41*$V$35 -> 0 | W41: =S41*$W$35 -> 0 | X41: =V41*W41 -> 0 | Z41: =V41*$Z$35 -> 0 | AA41: =W41*$AA$35 -> 0 | AB41: =Z41*AA41 -> 0 | AD41: =Z41*$AD$35 -> 0 | AE41: =AA41*$AE$35 -> 0 | AF41: =AD41*AE41 -> 0 | AH41: =AD41*$AH$35 -> 0 | AI41: =AE41*$AI$35 -> 0 | AJ41: =AH41*AI41 -> 0 | AL41: =AH41*$AL$35 -> 0 | AM41: =AI41*$AM$35 -> 0 | AN41: =AL41*AM41 -> 0 | AP41: =AL41*$AP$35 -> 0 | AQ41: =AM41*$AQ$35 -> 0 | AR41: =AP41*AQ41 -> 0 | AT41: =AP41*$AT$35 -> 0 | AU41: =AQ41*$AU$35 -> 0 | AV41: =AT41*AU41 -> 0 | AX41: =AT41*$AX$35 -> 0 | AY41: =AU41*$AY$35 -> 0 | AZ41: =AX41*AY41 -> 0 | BB41: =AX41*$BB$35 -> 0 | BC41: =AY41*$BC$35 -> 0 | BD41: =BB41*BC41 -> 0 | BF41: =BB41*$BF$35 -> 0 | BG41: =BC41*$BG$35 -> 0 | BH41: =BF41*BG41 -> 0 | BJ41: =BF41*$BJ$35 -> 0 | BK41: =BG41*$BK$35 -> 0 | BL41: =BJ41*BK41 -> 0 | BN41: =BJ41*$BN$35 -> 0 | BO41: =BK41*$BO$35 -> 0 | BP41: =BN41*BO41 -> 0 | BR41: =BN41*$BR$35 -> 0 | BS41: =BO41*$BS$35 -> 0 | BT41: =BR41*BS41 -> 0 | BV41: =BR41*$BV$35 -> 0 | BW41: =BS41*$BW$35 -> 0 | BX41: =BV41*BW41 -> 0 | BZ41: =BV41*$BZ$35 -> 0 | CA41: =BW41*$CA$35 -> 0 | CB41: =BZ41*CA41 -> 0 | CD41: =BZ41*$CD$35 -> 0 | CE41: =CA41*$CE$35 -> 0 | CF41: =CD41*CE41 -> 0 | CH41: =CD41*$CH$35 -> 0 | CI41: =CE41*$CI$35 -> 0 | CJ41: =CH41*CI41 -> 0 | CL41: =CH41*$CL$35 -> 0 | CM41: =CI41*$CM$35 -> 0 | CN41: =CL41*CM41 -> 0 | CP41: =CL41*$CP$35 -> 0 | CQ41: =CM41*$CQ$35 -> 0 | CR41: =CP41*CQ41 -> 0 | CT41: =CP41*$CT$35 -> 0 | CU41: =CQ41*$CU$35 -> 0 | CV41: =CT41*CU41 -> 0 | CX41: =CT41*$CX$35 -> 0 | CY41: =CU41*$CY$35 -> 0 | CZ41: =CX41*CY41 -> 0 | DB41: =CX41*$DB$35 -> 0 | DC41: =CY41*$DC$35 -> 0 | DD41: =DB41*DC41 -> 0 | DF41: =DB41*$DF$35 -> 0 | DG41: =DC41*$DG$35 -> 0 | DH41: =DF41*DG41 -> 0 | DJ41: =DF41*$DJ$35 -> 0 | DK41: =DG41*$DK$35 -> 0 | DL41: =DJ41*DK41 -> 0 | DN41: =DJ41*$DN$35 -> 0 | DO41: =DK41*$DO$35 -> 0 | DP41: =DN41*DO41 -> 0 | DR41: =DN41*$DR$35 -> 0 | DS41: =DO41*$DS$35 -> 0 | DT41: =DR41*DS41 -> 0 | DV41: =DR41*$DV$35 -> 0 | DW41: =DS41*$DW$35 -> 0 | DX41: =DV41*DW41 -> 0 | DZ41: =DV41*$DZ$35 -> 0 | EA41: =DW41*$EA$35 -> 0 | EB41: =DZ41*EA41 -> 0 | ED41: =DZ41*$ED$35 -> 0 | EE41: =EA41*$EE$35 -> 0 | EF41: =ED41*EE41 -> 0 | EH41: =ED41*$EH$35 -> 0 | EI41: =EE41*$EI$35 -> 0 | EJ41: =EH41*EI41 -> 0 | EL41: =EH41*$EL$35 -> 0 | EM41: =EI41*$EM$35 -> 0 | EN41: =EL41*EM41 -> 0 | EP41: =EL41*$EP$35 -> 0 | EQ41: =EM41*$EQ$35 -> 0 | ER41: =EP41*EQ41 -> 0 | ET41: =EP41*$ET$35 -> 0 | EU41: =EQ41*$EU$35 -> 0 | EV41: =ET41*EU41 -> 0 | EX41: =ET41*$EX$35 -> 0 | EY41: =EU41*$EY$35 -> 0 | EZ41: =EX41*EY41 -> 0 | FB41: =EX41*$FB$35 -> 0 | FC41: =EY41*$FC$35 -> 0 | FD41: =FB41*FC41 -> 0 | FF41: =FB41*$FF$35 -> 0 | FG41: =FC41*$FG$35 -> 0 | FH41: =FF41*FG41 -> 0 | FJ41: =FF41*$FJ$35 -> 0 | FK41: =FG41*$FK$35 -> 0 | FL41: =FJ41*FK41 -> 0 | FN41: =FJ41*$FN$35 -> 0 | FO41: =FK41*$FO$35 -> 0 | FP41: =FN41*FO41 -> 0 | FR41: =FN41*$FR$35 -> 0 | FS41: =FO41*$FS$35 -> 0 | FT41: =FR41*FS41 -> 0 | FV41: =FR41*$FV$35 -> 0 | FW41: =FS41*$FW$35 -> 0 | FX41: =FV41*FW41 -> 0 | FZ41: =FV41*$FZ$35 -> 0 | GA41: =FW41*$GA$35 -> 0 | GB41: =FZ41*GA41 -> 0 | GD41: =FZ41*$GD$35 -> 0 | GE41: =GA41*$GE$35 -> 0 | GF41: =GD41*GE41 -> 0 | GH41: =GD41*$GH$35 -> 0 | GI41: =GE41*$GI$35 -> 0 | GJ41: =GH41*GI41 -> 0 | GL41: =GH41*$GL$35 -> 0 | GM41: =GI41*$GM$35 -> 0 | GN41: =GL41*GM41 -> 0 | GP41: =GL41*$GP$35 -> 0 | GQ41: =GM41*$GQ$35 -> 0 | GR41: =GP41*GQ41 -> 0 | GT41: =GP41*$GT$35 -> 0 | GU41: =GQ41*$GU$35 -> 0 | GV41: =GT41*GU41 -> 0 | GX41: =GT41*$GX$35 -> 0 | GY41: =GU41*$GY$35 -> 0 | GZ41: =GX41*GY41 -> 0 | HB41: =GX41*$HB$35 -> 0 | HC41: =GY41*$HC$35 -> 0 | HD41: =HB41*HC41 -> 0 | HF41: =HB41*$HF$35 -> 0 | HG41: =HC41*$HG$35 -> 0 | HH41: =HF41*HG41 -> 0 | HJ41: =HF41*$HJ$35 -> 0 | HK41: =HG41*$HK$35 -> 0 | HL41: =HJ41*HK41 -> 0 | HN41: =HJ41*$HN$35 -> 0 | HO41: =HK41*$HO$35 -> 0 | HP41: =HN41*HO41 -> 0 | HR41: =HN41*$HR$35 -> 0 | HS41: =HO41*$HS$35 -> 0 | HT41: =HR41*HS41 -> 0 | HV41: =HR41*$HV$35 -> 0 | HW41: =HS41*$HW$35 -> 0 | HX41: =HV41*HW41 -> 0 | HZ41: =HV41*$HZ$35 -> 0 | IA41: =HW41*$IA$35 -> 0 | IB41: =HZ41*IA41 -> 0 | ID41: =HZ41*$ID$35 -> 0 | IE41: =IA41*$IE$35 -> 0 | IF41: =ID41*IE41 -> 0 | IH41: =ID41*$IH$35 -> 0 | II41: =IE41*$II$35 -> 0 | IJ41: =IH41*II41 -> 0 | IL41: =SUMIFS($F41:$IK41,$F$3:$IK$3,IL$5,$F$6:$IK$6,IL$6) -> 0 | IM41: 0 | IN41: =SUMIFS($F41:$IK41,$F$3:$IK$3,IL$5,$F$6:$IK$6,IN$6) -> 0 | IP41: =SUMIFS($F41:$IK41,$F$3:$IK$3,IP$5,$F$6:$IK$6,IP$6) -> 0 | IQ41: 0 | IR41: =SUMIFS($F41:$IK41,$F$3:$IK$3,IP$5,$F$6:$IK$6,IR$6) -> 0 | IT41: =SUMIFS($F41:$IK41,$F$3:$IK$3,IT$5,$F$6:$IK$6,IT$6) -> 0 | IU41: 0 | IV41: =SUMIFS($F41:$IK41,$F$3:$IK$3,IT$5,$F$6:$IK$6,IV$6) -> 0 | IX41: =SUMIFS($F41:$IK41,$F$3:$IK$3,IX$5,$F$6:$IK$6,IX$6) -> 0 | IY41: 0 | IZ41: =SUMIFS($F41:$IK41,$F$3:$IK$3,IX$5,$F$6:$IK$6,IZ$6) -> 0 | JB41: =SUMIFS($F41:$IK41,$F$3:$IK$3,JB$5,$F$6:$IK$6,JB$6) -> 0 | JC41: 0 | JD41: =SUMIFS($F41:$IK41,$F$3:$IK$3,JB$5,$F$6:$IK$6,JD$6) -> 0 | JF41: =SUMIFS($F41:$IK41,$F$3:$IK$3,JF$5,$F$6:$IK$6,JF$6) -> 0 | JG41: 0 | JH41: =SUMIFS($F41:$IK41,$F$3:$IK$3,JF$5,$F$6:$IK$6,JH$6) -> 0
B42: Grand Total | F42: =SUM(F37:F41) -> 0 | H42: =SUM(H37:H41) -> 0 | J42: =SUM(J37:J41) -> 0 | L42: =SUM(L37:L41) -> 0 | N42: =SUM(N37:N41) -> 0 | P42: =SUM(P37:P41) -> 0 | R42: =SUM(R37:R41) -> 0 | T42: =SUM(T37:T41) -> 0 | V42: =SUM(V37:V41) -> 0 | X42: =SUM(X37:X41) -> 0 | Z42: =SUM(Z37:Z41) -> 0 | AB42: =SUM(AB37:AB41) -> 0 | AD42: =SUM(AD37:AD41) -> 0 | AF42: =SUM(AF37:AF41) -> 0 | AH42: =SUM(AH37:AH41) -> 0 | AJ42: =SUM(AJ37:AJ41) -> 0 | AL42: =SUM(AL37:AL41) -> 0 | AN42: =SUM(AN37:AN41) -> 0 | AP42: =SUM(AP37:AP41) -> 0 | AR42: =SUM(AR37:AR41) -> 0 | AT42: =SUM(AT37:AT41) -> 0 | AV42: =SUM(AV37:AV41) -> 0 | AX42: =SUM(AX37:AX41) -> 0 | AZ42: =SUM(AZ37:AZ41) -> 0 | BB42: =SUM(BB37:BB41) -> 0 | BD42: =SUM(BD37:BD41) -> 0 | BF42: =SUM(BF37:BF41) -> 0 | BH42: =SUM(BH37:BH41) -> 0 | BJ42: =SUM(BJ37:BJ41) -> 0 | BL42: =SUM(BL37:BL41) -> 0 | BN42: =SUM(BN37:BN41) -> 0 | BP42: =SUM(BP37:BP41) -> 0 | BR42: =SUM(BR37:BR41) -> 0 | BT42: =SUM(BT37:BT41) -> 0 | BV42: =SUM(BV37:BV41) -> 0 | BX42: =SUM(BX37:BX41) -> 0 | BZ42: =SUM(BZ37:BZ41) -> 0 | CB42: =SUM(CB37:CB41) -> 0 | CD42: =SUM(CD37:CD41) -> 0 | CF42: =SUM(CF37:CF41) -> 0 | CH42: =SUM(CH37:CH41) -> 0 | CJ42: =SUM(CJ37:CJ41) -> 0 | CL42: =SUM(CL37:CL41) -> 0 | CN42: =SUM(CN37:CN41) -> 0 | CP42: =SUM(CP37:CP41) -> 0 | CR42: =SUM(CR37:CR41) -> 0 | CT42: =SUM(CT37:CT41) -> 0 | CV42: =SUM(CV37:CV41) -> 0 | CX42: =SUM(CX37:CX41) -> 0 | CZ42: =SUM(CZ37:CZ41) -> 0 | DB42: =SUM(DB37:DB41) -> 0 | DD42: =SUM(DD37:DD41) -> 0 | DF42: =SUM(DF37:DF41) -> 0 | DH42: =SUM(DH37:DH41) -> 0 | DJ42: =SUM(DJ37:DJ41) -> 0 | DL42: =SUM(DL37:DL41) -> 0 | DN42: =SUM(DN37:DN41) -> 0 | DP42: =SUM(DP37:DP41) -> 0 | DR42: =SUM(DR37:DR41) -> 0 | DT42: =SUM(DT37:DT41) -> 0 | DV42: =SUM(DV37:DV41) -> 0 | DX42: =SUM(DX37:DX41) -> 0 | DZ42: =SUM(DZ37:DZ41) -> 0 | EB42: =SUM(EB37:EB41) -> 0 | ED42: =SUM(ED37:ED41) -> 0 | EF42: =SUM(EF37:EF41) -> 0 | EH42: =SUM(EH37:EH41) -> 0 | EJ42: =SUM(EJ37:EJ41) -> 0 | EL42: =SUM(EL37:EL41) -> 0 | EN42: =SUM(EN37:EN41) -> 0 | EP42: =SUM(EP37:EP41) -> 0 | ER42: =SUM(ER37:ER41) -> 0 | ET42: =SUM(ET37:ET41) -> 0 | EV42: =SUM(EV37:EV41) -> 0 | EX42: =SUM(EX37:EX41) -> 0 | EZ42: =SUM(EZ37:EZ41) -> 0 | FB42: =SUM(FB37:FB41) -> 0 | FD42: =SUM(FD37:FD41) -> 0 | FF42: =SUM(FF37:FF41) -> 0 | FH42: =SUM(FH37:FH41) -> 0 | FJ42: =SUM(FJ37:FJ41) -> 0 | FL42: =SUM(FL37:FL41) -> 0 | FN42: =SUM(FN37:FN41) -> 0 | FP42: =SUM(FP37:FP41) -> 0 | FR42: =SUM(FR37:FR41) -> 0 | FT42: =SUM(FT37:FT41) -> 0 | FV42: =SUM(FV37:FV41) -> 0 | FX42: =SUM(FX37:FX41) -> 0 | FZ42: =SUM(FZ37:FZ41) -> 0 | GB42: =SUM(GB37:GB41) -> 0 | GD42: =SUM(GD37:GD41) -> 0 | GF42: =SUM(GF37:GF41) -> 0 | GH42: =SUM(GH37:GH41) -> 0 | GJ42: =SUM(GJ37:GJ41) -> 0 | GL42: =SUM(GL37:GL41) -> 0 | GN42: =SUM(GN37:GN41) -> 0 | GP42: =SUM(GP37:GP41) -> 0 | GR42: =SUM(GR37:GR41) -> 0 | GT42: =SUM(GT37:GT41) -> 0 | GV42: =SUM(GV37:GV41) -> 0 | GX42: =SUM(GX37:GX41) -> 0 | GZ42: =SUM(GZ37:GZ41) -> 0 | HB42: =SUM(HB37:HB41) -> 0 | HD42: =SUM(HD37:HD41) -> 0 | HF42: =SUM(HF37:HF41) -> 0 | HH42: =SUM(HH37:HH41) -> 0 | HJ42: =SUM(HJ37:HJ41) -> 0 | HL42: =SUM(HL37:HL41) -> 0 | HN42: =SUM(HN37:HN41) -> 0 | HP42: =SUM(HP37:HP41) -> 0 | HR42: =SUM(HR37:HR41) -> 0 | HT42: =SUM(HT37:HT41) -> 0 | HV42: =SUM(HV37:HV41) -> 0 | HX42: =SUM(HX37:HX41) -> 0 | HZ42: =SUM(HZ37:HZ41) -> 0 | IB42: =SUM(IB37:IB41) -> 0 | ID42: =SUM(ID37:ID41) -> 0 | IF42: =SUM(IF37:IF41) -> 0 | IH42: =SUM(IH37:IH41) -> 0 | IJ42: =SUM(IJ37:IJ41) -> 0 | IL42: =SUM(IL37:IL41) -> 0 | IN42: =SUM(IN37:IN41) -> 0 | IP42: =SUM(IP37:IP41) -> 0 | IR42: =SUM(IR37:IR41) -> 0 | IT42: =SUM(IT37:IT41) -> 0 | IV42: =SUM(IV37:IV41) -> 0 | IX42: =SUM(IX37:IX41) -> 0 | IZ42: =SUM(IZ37:IZ41) -> 0 | JB42: =SUM(JB37:JB41) -> 0 | JD42: =SUM(JD37:JD41) -> 0 | JF42: =SUM(JF37:JF41) -> 0 | JH42: =SUM(JH37:JH41) -> 0
J44: ='A.I Revenue Streams - P1'!K46+100% -> 1 | K44: =$K$8 -> 1 | N44: 1 | O44: 1 | R44: =N44 -> 1 | S44: 1 | V44: =R44 -> 1 | W44: 1 | Z44: =V44 -> 1 | AA44: 1 | AD44: =Z44 -> 1 | AE44: 1 | AH44: =AD44 -> 1 | AI44: 1 | AL44: =AH44 -> 1 | AM44: 1 | AP44: 1 | AQ44: 1 | AT44: =AP44 -> 1 | AU44: 1 | AX44: =AT44 -> 1 | AY44: 1 | BB44: ='A.I Revenue Streams - P1'!M46+100% -> 1 | BC44: 1 | BF44: 1 | BG44: 1 | BJ44: =BF44 -> 1 | BK44: 1 | BN44: =BJ44 -> 1 | BO44: 1 | BR44: =BN44 -> 1 | BS44: 1 | BV44: =BR44 -> 1 | BW44: 1 | BZ44: =BV44 -> 1 | CA44: 1 | CD44: =BZ44 -> 1 | CE44: 1 | CH44: =CD44 -> 1 | CI44: 1 | CL44: 1 | CM44: 1 | CP44: 1 | CQ44: 1 | CT44: =CP44 -> 1 | CU44: 1 | CX44: ='A.I Revenue Streams - P1'!O46+100% -> 2.23 | CY44: 1 | DB44: 1 | DC44: 1 | DF44: =DB44 -> 1 | DG44: 1 | DJ44: =DF44 -> 1 | DK44: 1 | DN44: =DJ44 -> 1 | DO44: 1 | DR44: =DN44 -> 1 | DS44: 1 | DV44: =DR44 -> 1 | DW44: 1 | DZ44: =DV44 -> 1 | EA44: 1 | ED44: =DZ44 -> 1 | EE44: 1 | EH44: 1 | EI44: 1 | EL44: 1 | EM44: 1 | EP44: =EL44 -> 1 | EQ44: 1 | ET44: ='A.I Revenue Streams - P1'!Q46+100% -> 2.23 | EU44: 1 | EX44: 1 | EY44: 1 | FB44: =EX44 -> 1 | FC44: 1 | FF44: =FB44 -> 1 | FG44: 1 | FJ44: =FF44 -> 1 | FK44: 1 | FN44: =FJ44 -> 1 | FO44: 1 | FR44: =FN44 -> 1 | FS44: 1 | FV44: =FR44 -> 1 | FW44: 1 | FZ44: =FV44 -> 1 | GA44: 1 | GD44: 1 | GE44: 1 | GH44: 1 | GI44: 1 | GL44: =GH44 -> 1 | GM44: 1 | GP44: ='A.I Revenue Streams - P1'!S46+100% -> 1 | GQ44: 1 | GT44: 1 | GU44: 1 | GX44: =GT44 -> 1 | GY44: 1 | HB44: =GX44 -> 1 | HC44: 1 | HF44: =HB44 -> 1 | HG44: 1 | HJ44: =HF44 -> 1 | HK44: 1 | HN44: =HJ44 -> 1 | HO44: 1 | HR44: =HN44 -> 1 | HS44: 1 | HV44: =HR44 -> 1 | HW44: 1 | HZ44: 1 | IA44: 1 | ID44: 1 | IE44: 1 | IH44: =ID44 -> 1 | II44: 1 | IL44: ='A.I Revenue Streams - P2'!DI46+100% -> 1 | IM44: 1 | IP44: ='A.I Revenue Streams - P2'!DM46+100% -> 1 | IQ44: 1 | IT44: ='A.I Revenue Streams - P2'!DQ46+100% -> 1 | IU44: 1 | IX44: ='A.I Revenue Streams - P2'!DU46+100% -> 1 | IY44: 1 | JB44: ='A.I Revenue Streams - P2'!DY46+100% -> 1 | JC44: 1 | JF44: ='A.I Revenue Streams - P2'!EC46+100% -> 1 | JG44: 1
B45: 5 | C45: ='A.I Revenue Streams - P1'!D45 -> 0
B46: 5a | D46: ='A.I Revenue Streams - P1'!E46 -> 0 | F46: ='A.I Revenue Streams - P1'!G46 -> 0 | G46: ='A.I Revenue Streams - P1'!I46 -> 0 | H46: =F46*G46 -> 0 | J46: =F46*$J$44 -> 0 | K46: =G46*$K$44 -> 0 | L46: =J46*K46 -> 0 | N46: =J46*$N$44 -> 0 | O46: =K46*$O$44 -> 0 | P46: =N46*O46 -> 0 | R46: =N46*$R$44 -> 0 | S46: =O46*$S$44 -> 0 | T46: =R46*S46 -> 0 | V46: =R46*$V$44 -> 0 | W46: =S46*$W$44 -> 0 | X46: =V46*W46 -> 0 | Z46: =V46*$Z$44 -> 0 | AA46: =W46*$AA$44 -> 0 | AB46: =Z46*AA46 -> 0 | AD46: =Z46*$AD$44 -> 0 | AE46: =AA46*$AE$44 -> 0 | AF46: =AD46*AE46 -> 0 | AH46: =AD46*$AH$44 -> 0 | AI46: =AE46*$AI$44 -> 0 | AJ46: =AH46*AI46 -> 0 | AL46: =AH46*$AL$44 -> 0 | AM46: =AI46*$AM$44 -> 0 | AN46: =AL46*AM46 -> 0 | AP46: =AL46*$AP$44 -> 0 | AQ46: =AM46*$AQ$44 -> 0 | AR46: =AP46*AQ46 -> 0 | AT46: =AP46*$AT$44 -> 0 | AU46: =AQ46*$AU$44 -> 0 | AV46: =AT46*AU46 -> 0 | AX46: =AT46*$AX$44 -> 0 | AY46: =AU46*$AY$44 -> 0 | AZ46: =AX46*AY46 -> 0 | BB46: =AX46*$BB$44 -> 0 | BC46: =AY46*$BC$44 -> 0 | BD46: =BB46*BC46 -> 0 | BF46: =BB46*$BF$44 -> 0 | BG46: =BC46*$BG$44 -> 0 | BH46: =BF46*BG46 -> 0 | BJ46: =BF46*$BJ$44 -> 0 | BK46: =BG46*$BK$44 -> 0 | BL46: =BJ46*BK46 -> 0 | BN46: =BJ46*$BN$44 -> 0 | BO46: =BK46*$BO$44 -> 0 | BP46: =BN46*BO46 -> 0 | BR46: =BN46*$BR$44 -> 0 | BS46: =BO46*$BS$44 -> 0 | BT46: =BR46*BS46 -> 0 | BV46: =BR46*$BV$44 -> 0 | BW46: =BS46*$BW$44 -> 0 | BX46: =BV46*BW46 -> 0 | BZ46: =BV46*$BZ$44 -> 0 | CA46: =BW46*$CA$44 -> 0 | CB46: =BZ46*CA46 -> 0 | CD46: =BZ46*$CD$44 -> 0 | CE46: =CA46*$CE$44 -> 0 | CF46: =CD46*CE46 -> 0 | CH46: =CD46*$CH$44 -> 0 | CI46: =CE46*$CI$44 -> 0 | CJ46: =CH46*CI46 -> 0 | CL46: =CH46*$CL$44 -> 0 | CM46: =CI46*$CM$44 -> 0 | CN46: =CL46*CM46 -> 0 | CP46: =CL46*$CP$44 -> 0 | CQ46: =CM46*$CQ$44 -> 0 | CR46: =CP46*CQ46 -> 0 | CT46: =CP46*$CT$44 -> 0 | CU46: =CQ46*$CU$44 -> 0 | CV46: =CT46*CU46 -> 0 | CX46: =CT46*$CX$44 -> 0 | CY46: =CU46*$CY$44 -> 0 | CZ46: =CX46*CY46 -> 0 | DB46: =CX46*$DB$44 -> 0 | DC46: =CY46*$DC$44 -> 0 | DD46: =DB46*DC46 -> 0 | DF46: =DB46*$DF$44 -> 0 | DG46: =DC46*$DG$44 -> 0 | DH46: =DF46*DG46 -> 0 | DJ46: =DF46*$DJ$44 -> 0 | DK46: =DG46*$DK$44 -> 0 | DL46: =DJ46*DK46 -> 0 | DN46: =DJ46*$DN$44 -> 0 | DO46: =DK46*$DO$44 -> 0 | DP46: =DN46*DO46 -> 0 | DR46: =DN46*$DR$44 -> 0 | DS46: =DO46*$DS$44 -> 0 | DT46: =DR46*DS46 -> 0 | DV46: =DR46*$DV$44 -> 0 | DW46: =DS46*$DW$44 -> 0 | DX46: =DV46*DW46 -> 0 | DZ46: =DV46*$DZ$44 -> 0 | EA46: =DW46*$EA$44 -> 0 | EB46: =DZ46*EA46 -> 0 | ED46: =DZ46*$ED$44 -> 0 | EE46: =EA46*$EE$44 -> 0 | EF46: =ED46*EE46 -> 0 | EH46: =ED46*$EH$44 -> 0 | EI46: =EE46*$EI$44 -> 0 | EJ46: =EH46*EI46 -> 0 | EL46: =EH46*$EL$44 -> 0 | EM46: =EI46*$EM$44 -> 0 | EN46: =EL46*EM46 -> 0 | EP46: =EL46*$EP$44 -> 0 | EQ46: =EM46*$EQ$44 -> 0 | ER46: =EP46*EQ46 -> 0 | ET46: =EP46*$ET$44 -> 0 | EU46: =EQ46*$EU$44 -> 0 | EV46: =ET46*EU46 -> 0 | EX46: =ET46*$EX$44 -> 0 | EY46: =EU46*$EY$44 -> 0 | EZ46: =EX46*EY46 -> 0 | FB46: =EX46*$FB$44 -> 0 | FC46: =EY46*$FC$44 -> 0 | FD46: =FB46*FC46 -> 0 | FF46: =FB46*$FF$44 -> 0 | FG46: =FC46*$FG$44 -> 0 | FH46: =FF46*FG46 -> 0 | FJ46: =FF46*$FJ$44 -> 0 | FK46: =FG46*$FK$44 -> 0 | FL46: =FJ46*FK46 -> 0 | FN46: =FJ46*$FN$44 -> 0 | FO46: =FK46*$FO$44 -> 0 | FP46: =FN46*FO46 -> 0 | FR46: =FN46*$FR$44 -> 0 | FS46: =FO46*$FS$44 -> 0 | FT46: =FR46*FS46 -> 0 | FV46: =FR46*$FV$44 -> 0 | FW46: =FS46*$FW$44 -> 0 | FX46: =FV46*FW46 -> 0 | FZ46: =FV46*$FZ$44 -> 0 | GA46: =FW46*$GA$44 -> 0 | GB46: =FZ46*GA46 -> 0 | GD46: =FZ46*$GD$44 -> 0 | GE46: =GA46*$GE$44 -> 0 | GF46: =GD46*GE46 -> 0 | GH46: =GD46*$GH$44 -> 0 | GI46: =GE46*$GI$44 -> 0 | GJ46: =GH46*GI46 -> 0 | GL46: =GH46*$GL$44 -> 0 | GM46: =GI46*$GM$44 -> 0 | GN46: =GL46*GM46 -> 0 | GP46: =GL46*$GP$44 -> 0 | GQ46: =GM46*$GQ$44 -> 0 | GR46: =GP46*GQ46 -> 0 | GT46: =GP46*$GT$44 -> 0 | GU46: =GQ46*$GU$44 -> 0 | GV46: =GT46*GU46 -> 0 | GX46: =GT46*$GX$44 -> 0 | GY46: =GU46*$GY$44 -> 0 | GZ46: =GX46*GY46 -> 0 | HB46: =GX46*$HB$44 -> 0 | HC46: =GY46*$HC$44 -> 0 | HD46: =HB46*HC46 -> 0 | HF46: =HB46*$HF$44 -> 0 | HG46: =HC46*$HG$44 -> 0 | HH46: =HF46*HG46 -> 0 | HJ46: =HF46*$HJ$44 -> 0 | HK46: =HG46*$HK$44 -> 0 | HL46: =HJ46*HK46 -> 0 | HN46: =HJ46*$HN$44 -> 0 | HO46: =HK46*$HO$44 -> 0 | HP46: =HN46*HO46 -> 0 | HR46: =HN46*$HR$44 -> 0 | HS46: =HO46*$HS$44 -> 0 | HT46: =HR46*HS46 -> 0 | HV46: =HR46*$HV$44 -> 0 | HW46: =HS46*$HW$44 -> 0 | HX46: =HV46*HW46 -> 0 | HZ46: =HV46*$HZ$44 -> 0 | IA46: =HW46*$IA$44 -> 0 | IB46: =HZ46*IA46 -> 0 | ID46: =HZ46*$ID$44 -> 0 | IE46: =IA46*$IE$44 -> 0 | IF46: =ID46*IE46 -> 0 | IH46: =ID46*$IH$44 -> 0 | II46: =IE46*$II$44 -> 0 | IJ46: =IH46*II46 -> 0 | IL46: =SUMIFS($F46:$IK46,$F$3:$IK$3,IL$5,$F$6:$IK$6,IL$6) -> 0 | IM46: 0 | IN46: =SUMIFS($F46:$IK46,$F$3:$IK$3,IL$5,$F$6:$IK$6,IN$6) -> 0 | IP46: =SUMIFS($F46:$IK46,$F$3:$IK$3,IP$5,$F$6:$IK$6,IP$6) -> 0 | IQ46: 0 | IR46: =SUMIFS($F46:$IK46,$F$3:$IK$3,IP$5,$F$6:$IK$6,IR$6) -> 0 | IT46: =SUMIFS($F46:$IK46,$F$3:$IK$3,IT$5,$F$6:$IK$6,IT$6) -> 0 | IU46: 0 | IV46: =SUMIFS($F46:$IK46,$F$3:$IK$3,IT$5,$F$6:$IK$6,IV$6) -> 0 | IX46: =SUMIFS($F46:$IK46,$F$3:$IK$3,IX$5,$F$6:$IK$6,IX$6) -> 0 | IY46: 0 | IZ46: =SUMIFS($F46:$IK46,$F$3:$IK$3,IX$5,$F$6:$IK$6,IZ$6) -> 0 | JB46: =SUMIFS($F46:$IK46,$F$3:$IK$3,JB$5,$F$6:$IK$6,JB$6) -> 0 | JC46: 0 | JD46: =SUMIFS($F46:$IK46,$F$3:$IK$3,JB$5,$F$6:$IK$6,JD$6) -> 0 | JF46: =SUMIFS($F46:$IK46,$F$3:$IK$3,JF$5,$F$6:$IK$6,JF$6) -> 0 | JG46: 0 | JH46: =SUMIFS($F46:$IK46,$F$3:$IK$3,JF$5,$F$6:$IK$6,JH$6) -> 0
B47: 5b | D47: ='A.I Revenue Streams - P1'!E47 -> 0 | F47: ='A.I Revenue Streams - P1'!G47 -> 0 | G47: ='A.I Revenue Streams - P1'!I47 -> 0 | H47: =F47*G47 -> 0 | J47: =F47*$J$44 -> 0 | K47: =G47*$K$44 -> 0 | L47: =J47*K47 -> 0 | N47: =J47*$N$44 -> 0 | O47: =K47*$O$44 -> 0 | P47: =N47*O47 -> 0 | R47: =N47*$R$44 -> 0 | S47: =O47*$S$44 -> 0 | T47: =R47*S47 -> 0 | V47: =R47*$V$44 -> 0 | W47: =S47*$W$44 -> 0 | X47: =V47*W47 -> 0 | Z47: =V47*$Z$44 -> 0 | AA47: =W47*$AA$44 -> 0 | AB47: =Z47*AA47 -> 0 | AD47: =Z47*$AD$44 -> 0 | AE47: =AA47*$AE$44 -> 0 | AF47: =AD47*AE47 -> 0 | AH47: =AD47*$AH$44 -> 0 | AI47: =AE47*$AI$44 -> 0 | AJ47: =AH47*AI47 -> 0 | AL47: =AH47*$AL$44 -> 0 | AM47: =AI47*$AM$44 -> 0 | AN47: =AL47*AM47 -> 0 | AP47: =AL47*$AP$44 -> 0 | AQ47: =AM47*$AQ$44 -> 0 | AR47: =AP47*AQ47 -> 0 | AT47: =AP47*$AT$44 -> 0 | AU47: =AQ47*$AU$44 -> 0 | AV47: =AT47*AU47 -> 0 | AX47: =AT47*$AX$44 -> 0 | AY47: =AU47*$AY$44 -> 0 | AZ47: =AX47*AY47 -> 0 | BB47: =AX47*$BB$44 -> 0 | BC47: =AY47*$BC$44 -> 0 | BD47: =BB47*BC47 -> 0 | BF47: =BB47*$BF$44 -> 0 | BG47: =BC47*$BG$44 -> 0 | BH47: =BF47*BG47 -> 0 | BJ47: =BF47*$BJ$44 -> 0 | BK47: =BG47*$BK$44 -> 0 | BL47: =BJ47*BK47 -> 0 | BN47: =BJ47*$BN$44 -> 0 | BO47: =BK47*$BO$44 -> 0 | BP47: =BN47*BO47 -> 0 | BR47: =BN47*$BR$44 -> 0 | BS47: =BO47*$BS$44 -> 0 | BT47: =BR47*BS47 -> 0 | BV47: =BR47*$BV$44 -> 0 | BW47: =BS47*$BW$44 -> 0 | BX47: =BV47*BW47 -> 0 | BZ47: =BV47*$BZ$44 -> 0 | CA47: =BW47*$CA$44 -> 0 | CB47: =BZ47*CA47 -> 0 | CD47: =BZ47*$CD$44 -> 0 | CE47: =CA47*$CE$44 -> 0 | CF47: =CD47*CE47 -> 0 | CH47: =CD47*$CH$44 -> 0 | CI47: =CE47*$CI$44 -> 0 | CJ47: =CH47*CI47 -> 0 | CL47: =CH47*$CL$44 -> 0 | CM47: =CI47*$CM$44 -> 0 | CN47: =CL47*CM47 -> 0 | CP47: =CL47*$CP$44 -> 0 | CQ47: =CM47*$CQ$44 -> 0 | CR47: =CP47*CQ47 -> 0 | CT47: =CP47*$CT$44 -> 0 | CU47: =CQ47*$CU$44 -> 0 | CV47: =CT47*CU47 -> 0 | CX47: =CT47*$CX$44 -> 0 | CY47: =CU47*$CY$44 -> 0 | CZ47: =CX47*CY47 -> 0 | DB47: =CX47*$DB$44 -> 0 | DC47: =CY47*$DC$44 -> 0 | DD47: =DB47*DC47 -> 0 | DF47: =DB47*$DF$44 -> 0 | DG47: =DC47*$DG$44 -> 0 | DH47: =DF47*DG47 -> 0 | DJ47: =DF47*$DJ$44 -> 0 | DK47: =DG47*$DK$44 -> 0 | DL47: =DJ47*DK47 -> 0 | DN47: =DJ47*$DN$44 -> 0 | DO47: =DK47*$DO$44 -> 0 | DP47: =DN47*DO47 -> 0 | DR47: =DN47*$DR$44 -> 0 | DS47: =DO47*$DS$44 -> 0 | DT47: =DR47*DS47 -> 0 | DV47: =DR47*$DV$44 -> 0 | DW47: =DS47*$DW$44 -> 0 | DX47: =DV47*DW47 -> 0 | DZ47: =DV47*$DZ$44 -> 0 | EA47: =DW47*$EA$44 -> 0 | EB47: =DZ47*EA47 -> 0 | ED47: =DZ47*$ED$44 -> 0 | EE47: =EA47*$EE$44 -> 0 | EF47: =ED47*EE47 -> 0 | EH47: =ED47*$EH$44 -> 0 | EI47: =EE47*$EI$44 -> 0 | EJ47: =EH47*EI47 -> 0 | EL47: =EH47*$EL$44 -> 0 | EM47: =EI47*$EM$44 -> 0 | EN47: =EL47*EM47 -> 0 | EP47: =EL47*$EP$44 -> 0 | EQ47: =EM47*$EQ$44 -> 0 | ER47: =EP47*EQ47 -> 0 | ET47: =EP47*$ET$44 -> 0 | EU47: =EQ47*$EU$44 -> 0 | EV47: =ET47*EU47 -> 0 | EX47: =ET47*$EX$44 -> 0 | EY47: =EU47*$EY$44 -> 0 | EZ47: =EX47*EY47 -> 0 | FB47: =EX47*$FB$44 -> 0 | FC47: =EY47*$FC$44 -> 0 | FD47: =FB47*FC47 -> 0 | FF47: =FB47*$FF$44 -> 0 | FG47: =FC47*$FG$44 -> 0 | FH47: =FF47*FG47 -> 0 | FJ47: =FF47*$FJ$44 -> 0 | FK47: =FG47*$FK$44 -> 0 | FL47: =FJ47*FK47 -> 0 | FN47: =FJ47*$FN$44 -> 0 | FO47: =FK47*$FO$44 -> 0 | FP47: =FN47*FO47 -> 0 | FR47: =FN47*$FR$44 -> 0 | FS47: =FO47*$FS$44 -> 0 | FT47: =FR47*FS47 -> 0 | FV47: =FR47*$FV$44 -> 0 | FW47: =FS47*$FW$44 -> 0 | FX47: =FV47*FW47 -> 0 | FZ47: =FV47*$FZ$44 -> 0 | GA47: =FW47*$GA$44 -> 0 | GB47: =FZ47*GA47 -> 0 | GD47: =FZ47*$GD$44 -> 0 | GE47: =GA47*$GE$44 -> 0 | GF47: =GD47*GE47 -> 0 | GH47: =GD47*$GH$44 -> 0 | GI47: =GE47*$GI$44 -> 0 | GJ47: =GH47*GI47 -> 0 | GL47: =GH47*$GL$44 -> 0 | GM47: =GI47*$GM$44 -> 0 | GN47: =GL47*GM47 -> 0 | GP47: =GL47*$GP$44 -> 0 | GQ47: =GM47*$GQ$44 -> 0 | GR47: =GP47*GQ47 -> 0 | GT47: =GP47*$GT$44 -> 0 | GU47: =GQ47*$GU$44 -> 0 | GV47: =GT47*GU47 -> 0 | GX47: =GT47*$GX$44 -> 0 | GY47: =GU47*$GY$44 -> 0 | GZ47: =GX47*GY47 -> 0 | HB47: =GX47*$HB$44 -> 0 | HC47: =GY47*$HC$44 -> 0 | HD47: =HB47*HC47 -> 0 | HF47: =HB47*$HF$44 -> 0 | HG47: =HC47*$HG$44 -> 0 | HH47: =HF47*HG47 -> 0 | HJ47: =HF47*$HJ$44 -> 0 | HK47: =HG47*$HK$44 -> 0 | HL47: =HJ47*HK47 -> 0 | HN47: =HJ47*$HN$44 -> 0 | HO47: =HK47*$HO$44 -> 0 | HP47: =HN47*HO47 -> 0 | HR47: =HN47*$HR$44 -> 0 | HS47: =HO47*$HS$44 -> 0 | HT47: =HR47*HS47 -> 0 | HV47: =HR47*$HV$44 -> 0 | HW47: =HS47*$HW$44 -> 0 | HX47: =HV47*HW47 -> 0 | HZ47: =HV47*$HZ$44 -> 0 | IA47: =HW47*$IA$44 -> 0 | IB47: =HZ47*IA47 -> 0 | ID47: =HZ47*$ID$44 -> 0 | IE47: =IA47*$IE$44 -> 0 | IF47: =ID47*IE47 -> 0 | IH47: =ID47*$IH$44 -> 0 | II47: =IE47*$II$44 -> 0 | IJ47: =IH47*II47 -> 0 | IL47: =SUMIFS($F47:$IK47,$F$3:$IK$3,IL$5,$F$6:$IK$6,IL$6) -> 0 | IM47: 0 | IN47: =SUMIFS($F47:$IK47,$F$3:$IK$3,IL$5,$F$6:$IK$6,IN$6) -> 0 | IP47: =SUMIFS($F47:$IK47,$F$3:$IK$3,IP$5,$F$6:$IK$6,IP$6) -> 0 | IQ47: 0 | IR47: =SUMIFS($F47:$IK47,$F$3:$IK$3,IP$5,$F$6:$IK$6,IR$6) -> 0 | IT47: =SUMIFS($F47:$IK47,$F$3:$IK$3,IT$5,$F$6:$IK$6,IT$6) -> 0 | IU47: 0 | IV47: =SUMIFS($F47:$IK47,$F$3:$IK$3,IT$5,$F$6:$IK$6,IV$6) -> 0 | IX47: =SUMIFS($F47:$IK47,$F$3:$IK$3,IX$5,$F$6:$IK$6,IX$6) -> 0 | IY47: 0 | IZ47: =SUMIFS($F47:$IK47,$F$3:$IK$3,IX$5,$F$6:$IK$6,IZ$6) -> 0 | JB47: =SUMIFS($F47:$IK47,$F$3:$IK$3,JB$5,$F$6:$IK$6,JB$6) -> 0 | JC47: 0 | JD47: =SUMIFS($F47:$IK47,$F$3:$IK$3,JB$5,$F$6:$IK$6,JD$6) -> 0 | JF47: =SUMIFS($F47:$IK47,$F$3:$IK$3,JF$5,$F$6:$IK$6,JF$6) -> 0 | JG47: 0 | JH47: =SUMIFS($F47:$IK47,$F$3:$IK$3,JF$5,$F$6:$IK$6,JH$6) -> 0
B48: 5c | D48: ='A.I Revenue Streams - P1'!E48 -> 0 | F48: ='A.I Revenue Streams - P1'!G48 -> 0 | G48: ='A.I Revenue Streams - P1'!I48 -> 0 | H48: =F48*G48 -> 0 | J48: =F48*$J$44 -> 0 | K48: =G48*$K$44 -> 0 | L48: =J48*K48 -> 0 | N48: =J48*$N$44 -> 0 | O48: =K48*$O$44 -> 0 | P48: =N48*O48 -> 0 | R48: =N48*$R$44 -> 0 | S48: =O48*$S$44 -> 0 | T48: =R48*S48 -> 0 | V48: =R48*$V$44 -> 0 | W48: =S48*$W$44 -> 0 | X48: =V48*W48 -> 0 | Z48: =V48*$Z$44 -> 0 | AA48: =W48*$AA$44 -> 0 | AB48: =Z48*AA48 -> 0 | AD48: =Z48*$AD$44 -> 0 | AE48: =AA48*$AE$44 -> 0 | AF48: =AD48*AE48 -> 0 | AH48: =AD48*$AH$44 -> 0 | AI48: =AE48*$AI$44 -> 0 | AJ48: =AH48*AI48 -> 0 | AL48: =AH48*$AL$44 -> 0 | AM48: =AI48*$AM$44 -> 0 | AN48: =AL48*AM48 -> 0 | AP48: =AL48*$AP$44 -> 0 | AQ48: =AM48*$AQ$44 -> 0 | AR48: =AP48*AQ48 -> 0 | AT48: =AP48*$AT$44 -> 0 | AU48: =AQ48*$AU$44 -> 0 | AV48: =AT48*AU48 -> 0 | AX48: =AT48*$AX$44 -> 0 | AY48: =AU48*$AY$44 -> 0 | AZ48: =AX48*AY48 -> 0 | BB48: =AX48*$BB$44 -> 0 | BC48: =AY48*$BC$44 -> 0 | BD48: =BB48*BC48 -> 0 | BF48: =BB48*$BF$44 -> 0 | BG48: =BC48*$BG$44 -> 0 | BH48: =BF48*BG48 -> 0 | BJ48: =BF48*$BJ$44 -> 0 | BK48: =BG48*$BK$44 -> 0 | BL48: =BJ48*BK48 -> 0 | BN48: =BJ48*$BN$44 -> 0 | BO48: =BK48*$BO$44 -> 0 | BP48: =BN48*BO48 -> 0 | BR48: =BN48*$BR$44 -> 0 | BS48: =BO48*$BS$44 -> 0 | BT48: =BR48*BS48 -> 0 | BV48: =BR48*$BV$44 -> 0 | BW48: =BS48*$BW$44 -> 0 | BX48: =BV48*BW48 -> 0 | BZ48: =BV48*$BZ$44 -> 0 | CA48: =BW48*$CA$44 -> 0 | CB48: =BZ48*CA48 -> 0 | CD48: =BZ48*$CD$44 -> 0 | CE48: =CA48*$CE$44 -> 0 | CF48: =CD48*CE48 -> 0 | CH48: =CD48*$CH$44 -> 0 | CI48: =CE48*$CI$44 -> 0 | CJ48: =CH48*CI48 -> 0 | CL48: =CH48*$CL$44 -> 0 | CM48: =CI48*$CM$44 -> 0 | CN48: =CL48*CM48 -> 0 | CP48: =CL48*$CP$44 -> 0 | CQ48: =CM48*$CQ$44 -> 0 | CR48: =CP48*CQ48 -> 0 | CT48: =CP48*$CT$44 -> 0 | CU48: =CQ48*$CU$44 -> 0 | CV48: =CT48*CU48 -> 0 | CX48: =CT48*$CX$44 -> 0 | CY48: =CU48*$CY$44 -> 0 | CZ48: =CX48*CY48 -> 0 | DB48: =CX48*$DB$44 -> 0 | DC48: =CY48*$DC$44 -> 0 | DD48: =DB48*DC48 -> 0 | DF48: =DB48*$DF$44 -> 0 | DG48: =DC48*$DG$44 -> 0 | DH48: =DF48*DG48 -> 0 | DJ48: =DF48*$DJ$44 -> 0 | DK48: =DG48*$DK$44 -> 0 | DL48: =DJ48*DK48 -> 0 | DN48: =DJ48*$DN$44 -> 0 | DO48: =DK48*$DO$44 -> 0 | DP48: =DN48*DO48 -> 0 | DR48: =DN48*$DR$44 -> 0 | DS48: =DO48*$DS$44 -> 0 | DT48: =DR48*DS48 -> 0 | DV48: =DR48*$DV$44 -> 0 | DW48: =DS48*$DW$44 -> 0 | DX48: =DV48*DW48 -> 0 | DZ48: =DV48*$DZ$44 -> 0 | EA48: =DW48*$EA$44 -> 0 | EB48: =DZ48*EA48 -> 0 | ED48: =DZ48*$ED$44 -> 0 | EE48: =EA48*$EE$44 -> 0 | EF48: =ED48*EE48 -> 0 | EH48: =ED48*$EH$44 -> 0 | EI48: =EE48*$EI$44 -> 0 | EJ48: =EH48*EI48 -> 0 | EL48: =EH48*$EL$44 -> 0 | EM48: =EI48*$EM$44 -> 0 | EN48: =EL48*EM48 -> 0 | EP48: =EL48*$EP$44 -> 0 | EQ48: =EM48*$EQ$44 -> 0 | ER48: =EP48*EQ48 -> 0 | ET48: =EP48*$ET$44 -> 0 | EU48: =EQ48*$EU$44 -> 0 | EV48: =ET48*EU48 -> 0 | EX48: =ET48*$EX$44 -> 0 | EY48: =EU48*$EY$44 -> 0 | EZ48: =EX48*EY48 -> 0 | FB48: =EX48*$FB$44 -> 0 | FC48: =EY48*$FC$44 -> 0 | FD48: =FB48*FC48 -> 0 | FF48: =FB48*$FF$44 -> 0 | FG48: =FC48*$FG$44 -> 0 | FH48: =FF48*FG48 -> 0 | FJ48: =FF48*$FJ$44 -> 0 | FK48: =FG48*$FK$44 -> 0 | FL48: =FJ48*FK48 -> 0 | FN48: =FJ48*$FN$44 -> 0 | FO48: =FK48*$FO$44 -> 0 | FP48: =FN48*FO48 -> 0 | FR48: =FN48*$FR$44 -> 0 | FS48: =FO48*$FS$44 -> 0 | FT48: =FR48*FS48 -> 0 | FV48: =FR48*$FV$44 -> 0 | FW48: =FS48*$FW$44 -> 0 | FX48: =FV48*FW48 -> 0 | FZ48: =FV48*$FZ$44 -> 0 | GA48: =FW48*$GA$44 -> 0 | GB48: =FZ48*GA48 -> 0 | GD48: =FZ48*$GD$44 -> 0 | GE48: =GA48*$GE$44 -> 0 | GF48: =GD48*GE48 -> 0 | GH48: =GD48*$GH$44 -> 0 | GI48: =GE48*$GI$44 -> 0 | GJ48: =GH48*GI48 -> 0 | GL48: =GH48*$GL$44 -> 0 | GM48: =GI48*$GM$44 -> 0 | GN48: =GL48*GM48 -> 0 | GP48: =GL48*$GP$44 -> 0 | GQ48: =GM48*$GQ$44 -> 0 | GR48: =GP48*GQ48 -> 0 | GT48: =GP48*$GT$44 -> 0 | GU48: =GQ48*$GU$44 -> 0 | GV48: =GT48*GU48 -> 0 | GX48: =GT48*$GX$44 -> 0 | GY48: =GU48*$GY$44 -> 0 | GZ48: =GX48*GY48 -> 0 | HB48: =GX48*$HB$44 -> 0 | HC48: =GY48*$HC$44 -> 0 | HD48: =HB48*HC48 -> 0 | HF48: =HB48*$HF$44 -> 0 | HG48: =HC48*$HG$44 -> 0 | HH48: =HF48*HG48 -> 0 | HJ48: =HF48*$HJ$44 -> 0 | HK48: =HG48*$HK$44 -> 0 | HL48: =HJ48*HK48 -> 0 | HN48: =HJ48*$HN$44 -> 0 | HO48: =HK48*$HO$44 -> 0 | HP48: =HN48*HO48 -> 0 | HR48: =HN48*$HR$44 -> 0 | HS48: =HO48*$HS$44 -> 0 | HT48: =HR48*HS48 -> 0 | HV48: =HR48*$HV$44 -> 0 | HW48: =HS48*$HW$44 -> 0 | HX48: =HV48*HW48 -> 0 | HZ48: =HV48*$HZ$44 -> 0 | IA48: =HW48*$IA$44 -> 0 | IB48: =HZ48*IA48 -> 0 | ID48: =HZ48*$ID$44 -> 0 | IE48: =IA48*$IE$44 -> 0 | IF48: =ID48*IE48 -> 0 | IH48: =ID48*$IH$44 -> 0 | II48: =IE48*$II$44 -> 0 | IJ48: =IH48*II48 -> 0 | IL48: =SUMIFS($F48:$IK48,$F$3:$IK$3,IL$5,$F$6:$IK$6,IL$6) -> 0 | IM48: 0 | IN48: =SUMIFS($F48:$IK48,$F$3:$IK$3,IL$5,$F$6:$IK$6,IN$6) -> 0 | IP48: =SUMIFS($F48:$IK48,$F$3:$IK$3,IP$5,$F$6:$IK$6,IP$6) -> 0 | IQ48: 0 | IR48: =SUMIFS($F48:$IK48,$F$3:$IK$3,IP$5,$F$6:$IK$6,IR$6) -> 0 | IT48: =SUMIFS($F48:$IK48,$F$3:$IK$3,IT$5,$F$6:$IK$6,IT$6) -> 0 | IU48: 0 | IV48: =SUMIFS($F48:$IK48,$F$3:$IK$3,IT$5,$F$6:$IK$6,IV$6) -> 0 | IX48: =SUMIFS($F48:$IK48,$F$3:$IK$3,IX$5,$F$6:$IK$6,IX$6) -> 0 | IY48: 0 | IZ48: =SUMIFS($F48:$IK48,$F$3:$IK$3,IX$5,$F$6:$IK$6,IZ$6) -> 0 | JB48: =SUMIFS($F48:$IK48,$F$3:$IK$3,JB$5,$F$6:$IK$6,JB$6) -> 0 | JC48: 0 | JD48: =SUMIFS($F48:$IK48,$F$3:$IK$3,JB$5,$F$6:$IK$6,JD$6) -> 0 | JF48: =SUMIFS($F48:$IK48,$F$3:$IK$3,JF$5,$F$6:$IK$6,JF$6) -> 0 | JG48: 0 | JH48: =SUMIFS($F48:$IK48,$F$3:$IK$3,JF$5,$F$6:$IK$6,JH$6) -> 0
B49: 5d | D49: ='A.I Revenue Streams - P1'!E49 -> 0 | F49: ='A.I Revenue Streams - P1'!G49 -> 0 | G49: ='A.I Revenue Streams - P1'!I49 -> 0 | H49: =F49*G49 -> 0 | J49: =F49*$J$44 -> 0 | K49: =G49*$K$44 -> 0 | L49: =J49*K49 -> 0 | N49: =J49*$N$44 -> 0 | O49: =K49*$O$44 -> 0 | P49: =N49*O49 -> 0 | R49: =N49*$R$44 -> 0 | S49: =O49*$S$44 -> 0 | T49: =R49*S49 -> 0 | V49: =R49*$V$44 -> 0 | W49: =S49*$W$44 -> 0 | X49: =V49*W49 -> 0 | Z49: =V49*$Z$44 -> 0 | AA49: =W49*$AA$44 -> 0 | AB49: =Z49*AA49 -> 0 | AD49: =Z49*$AD$44 -> 0 | AE49: =AA49*$AE$44 -> 0 | AF49: =AD49*AE49 -> 0 | AH49: =AD49*$AH$44 -> 0 | AI49: =AE49*$AI$44 -> 0 | AJ49: =AH49*AI49 -> 0 | AL49: =AH49*$AL$44 -> 0 | AM49: =AI49*$AM$44 -> 0 | AN49: =AL49*AM49 -> 0 | AP49: =AL49*$AP$44 -> 0 | AQ49: =AM49*$AQ$44 -> 0 | AR49: =AP49*AQ49 -> 0 | AT49: =AP49*$AT$44 -> 0 | AU49: =AQ49*$AU$44 -> 0 | AV49: =AT49*AU49 -> 0 | AX49: =AT49*$AX$44 -> 0 | AY49: =AU49*$AY$44 -> 0 | AZ49: =AX49*AY49 -> 0 | BB49: =AX49*$BB$44 -> 0 | BC49: =AY49*$BC$44 -> 0 | BD49: =BB49*BC49 -> 0 | BF49: =BB49*$BF$44 -> 0 | BG49: =BC49*$BG$44 -> 0 | BH49: =BF49*BG49 -> 0 | BJ49: =BF49*$BJ$44 -> 0 | BK49: =BG49*$BK$44 -> 0 | BL49: =BJ49*BK49 -> 0 | BN49: =BJ49*$BN$44 -> 0 | BO49: =BK49*$BO$44 -> 0 | BP49: =BN49*BO49 -> 0 | BR49: =BN49*$BR$44 -> 0 | BS49: =BO49*$BS$44 -> 0 | BT49: =BR49*BS49 -> 0 | BV49: =BR49*$BV$44 -> 0 | BW49: =BS49*$BW$44 -> 0 | BX49: =BV49*BW49 -> 0 | BZ49: =BV49*$BZ$44 -> 0 | CA49: =BW49*$CA$44 -> 0 | CB49: =BZ49*CA49 -> 0 | CD49: =BZ49*$CD$44 -> 0 | CE49: =CA49*$CE$44 -> 0 | CF49: =CD49*CE49 -> 0 | CH49: =CD49*$CH$44 -> 0 | CI49: =CE49*$CI$44 -> 0 | CJ49: =CH49*CI49 -> 0 | CL49: =CH49*$CL$44 -> 0 | CM49: =CI49*$CM$44 -> 0 | CN49: =CL49*CM49 -> 0 | CP49: =CL49*$CP$44 -> 0 | CQ49: =CM49*$CQ$44 -> 0 | CR49: =CP49*CQ49 -> 0 | CT49: =CP49*$CT$44 -> 0 | CU49: =CQ49*$CU$44 -> 0 | CV49: =CT49*CU49 -> 0 | CX49: =CT49*$CX$44 -> 0 | CY49: =CU49*$CY$44 -> 0 | CZ49: =CX49*CY49 -> 0 | DB49: =CX49*$DB$44 -> 0 | DC49: =CY49*$DC$44 -> 0 | DD49: =DB49*DC49 -> 0 | DF49: =DB49*$DF$44 -> 0 | DG49: =DC49*$DG$44 -> 0 | DH49: =DF49*DG49 -> 0 | DJ49: =DF49*$DJ$44 -> 0 | DK49: =DG49*$DK$44 -> 0 | DL49: =DJ49*DK49 -> 0 | DN49: =DJ49*$DN$44 -> 0 | DO49: =DK49*$DO$44 -> 0 | DP49: =DN49*DO49 -> 0 | DR49: =DN49*$DR$44 -> 0 | DS49: =DO49*$DS$44 -> 0 | DT49: =DR49*DS49 -> 0 | DV49: =DR49*$DV$44 -> 0 | DW49: =DS49*$DW$44 -> 0 | DX49: =DV49*DW49 -> 0 | DZ49: =DV49*$DZ$44 -> 0 | EA49: =DW49*$EA$44 -> 0 | EB49: =DZ49*EA49 -> 0 | ED49: =DZ49*$ED$44 -> 0 | EE49: =EA49*$EE$44 -> 0 | EF49: =ED49*EE49 -> 0 | EH49: =ED49*$EH$44 -> 0 | EI49: =EE49*$EI$44 -> 0 | EJ49: =EH49*EI49 -> 0 | EL49: =EH49*$EL$44 -> 0 | EM49: =EI49*$EM$44 -> 0 | EN49: =EL49*EM49 -> 0 | EP49: =EL49*$EP$44 -> 0 | EQ49: =EM49*$EQ$44 -> 0 | ER49: =EP49*EQ49 -> 0 | ET49: =EP49*$ET$44 -> 0 | EU49: =EQ49*$EU$44 -> 0 | EV49: =ET49*EU49 -> 0 | EX49: =ET49*$EX$44 -> 0 | EY49: =EU49*$EY$44 -> 0 | EZ49: =EX49*EY49 -> 0 | FB49: =EX49*$FB$44 -> 0 | FC49: =EY49*$FC$44 -> 0 | FD49: =FB49*FC49 -> 0 | FF49: =FB49*$FF$44 -> 0 | FG49: =FC49*$FG$44 -> 0 | FH49: =FF49*FG49 -> 0 | FJ49: =FF49*$FJ$44 -> 0 | FK49: =FG49*$FK$44 -> 0 | FL49: =FJ49*FK49 -> 0 | FN49: =FJ49*$FN$44 -> 0 | FO49: =FK49*$FO$44 -> 0 | FP49: =FN49*FO49 -> 0 | FR49: =FN49*$FR$44 -> 0 | FS49: =FO49*$FS$44 -> 0 | FT49: =FR49*FS49 -> 0 | FV49: =FR49*$FV$44 -> 0 | FW49: =FS49*$FW$44 -> 0 | FX49: =FV49*FW49 -> 0 | FZ49: =FV49*$FZ$44 -> 0 | GA49: =FW49*$GA$44 -> 0 | GB49: =FZ49*GA49 -> 0 | GD49: =FZ49*$GD$44 -> 0 | GE49: =GA49*$GE$44 -> 0 | GF49: =GD49*GE49 -> 0 | GH49: =GD49*$GH$44 -> 0 | GI49: =GE49*$GI$44 -> 0 | GJ49: =GH49*GI49 -> 0 | GL49: =GH49*$GL$44 -> 0 | GM49: =GI49*$GM$44 -> 0 | GN49: =GL49*GM49 -> 0 | GP49: =GL49*$GP$44 -> 0 | GQ49: =GM49*$GQ$44 -> 0 | GR49: =GP49*GQ49 -> 0 | GT49: =GP49*$GT$44 -> 0 | GU49: =GQ49*$GU$44 -> 0 | GV49: =GT49*GU49 -> 0 | GX49: =GT49*$GX$44 -> 0 | GY49: =GU49*$GY$44 -> 0 | GZ49: =GX49*GY49 -> 0 | HB49: =GX49*$HB$44 -> 0 | HC49: =GY49*$HC$44 -> 0 | HD49: =HB49*HC49 -> 0 | HF49: =HB49*$HF$44 -> 0 | HG49: =HC49*$HG$44 -> 0 | HH49: =HF49*HG49 -> 0 | HJ49: =HF49*$HJ$44 -> 0 | HK49: =HG49*$HK$44 -> 0 | HL49: =HJ49*HK49 -> 0 | HN49: =HJ49*$HN$44 -> 0 | HO49: =HK49*$HO$44 -> 0 | HP49: =HN49*HO49 -> 0 | HR49: =HN49*$HR$44 -> 0 | HS49: =HO49*$HS$44 -> 0 | HT49: =HR49*HS49 -> 0 | HV49: =HR49*$HV$44 -> 0 | HW49: =HS49*$HW$44 -> 0 | HX49: =HV49*HW49 -> 0 | HZ49: =HV49*$HZ$44 -> 0 | IA49: =HW49*$IA$44 -> 0 | IB49: =HZ49*IA49 -> 0 | ID49: =HZ49*$ID$44 -> 0 | IE49: =IA49*$IE$44 -> 0 | IF49: =ID49*IE49 -> 0 | IH49: =ID49*$IH$44 -> 0 | II49: =IE49*$II$44 -> 0 | IJ49: =IH49*II49 -> 0 | IL49: =SUMIFS($F49:$IK49,$F$3:$IK$3,IL$5,$F$6:$IK$6,IL$6) -> 0 | IM49: 0 | IN49: =SUMIFS($F49:$IK49,$F$3:$IK$3,IL$5,$F$6:$IK$6,IN$6) -> 0 | IP49: =SUMIFS($F49:$IK49,$F$3:$IK$3,IP$5,$F$6:$IK$6,IP$6) -> 0 | IQ49: 0 | IR49: =SUMIFS($F49:$IK49,$F$3:$IK$3,IP$5,$F$6:$IK$6,IR$6) -> 0 | IT49: =SUMIFS($F49:$IK49,$F$3:$IK$3,IT$5,$F$6:$IK$6,IT$6) -> 0 | IU49: 0 | IV49: =SUMIFS($F49:$IK49,$F$3:$IK$3,IT$5,$F$6:$IK$6,IV$6) -> 0 | IX49: =SUMIFS($F49:$IK49,$F$3:$IK$3,IX$5,$F$6:$IK$6,IX$6) -> 0 | IY49: 0 | IZ49: =SUMIFS($F49:$IK49,$F$3:$IK$3,IX$5,$F$6:$IK$6,IZ$6) -> 0 | JB49: =SUMIFS($F49:$IK49,$F$3:$IK$3,JB$5,$F$6:$IK$6,JB$6) -> 0 | JC49: 0 | JD49: =SUMIFS($F49:$IK49,$F$3:$IK$3,JB$5,$F$6:$IK$6,JD$6) -> 0 | JF49: =SUMIFS($F49:$IK49,$F$3:$IK$3,JF$5,$F$6:$IK$6,JF$6) -> 0 | JG49: 0 | JH49: =SUMIFS($F49:$IK49,$F$3:$IK$3,JF$5,$F$6:$IK$6,JH$6) -> 0
